Workbook

Sheet 报名明细
A1: 岗位数量 | B1: 企业名称 | C1: 企业简介 | D1: 招聘岗位 | E1: 招聘人数 | F1: 学历 | G1: 岗位职责 | H1: 薪资情况 | I1: 标题拼接 | J1: 岗位长度 | K1: 岗位长度要求 | L1: 岗位长度截取 | M1: 专业 | N1: 专业字数 | O1: 专业个数
A2: =COUNTIF(B:B,B2) -> 4 | B2: 上海光通信有限公司 | C2: 上海光通信有限公司（英文名ShanghaiGTXSemiconductorCo.,Ltd，下称“GTX”），成立于1988年，于2022年初转型进入集成电路制造领域。 | D2: 仓储助理专员 | E2: 10 | F2: 大专 | G2: 工作职责1)根据规程，执行公司各种物资运输安排、管理及监控；2)执行物资仓储管理，保证物资有序账目清晰。任职要求1)大专及以上学历，物流、仓储等相关专业；2)具备良好的沟通能力和团队合作精神，具备独立工作、分析和解决问题的能力，良好的中英文读写说能力。 | H2: 月薪：5K-7K | I2: =_xlfn.CONCAT(D2,"（学历：",F2," 专业要求：",IF(ISBLANK(M2),"无",M2),"）") -> 仓储助理专员（学历：大专 专业要求：无） | J2: =LEN(G2) -> 126 | K2: =_xlfn.XLOOKUP(A2,长度要求!A:A,长度要求!E:E) -> 500 | L2: =IF(J2<K2,G2,LEFT(G2,K2)&"……") -> 工作职责1)根据规程，执行公司各种物资运输安排、管理及监控；2)执行物资仓储管理，保证物资有序账目清晰。任职要求1)大专及以上学历，物流、仓储等相关专业；2)具备良好的沟通能力和团队合作精神，具备独立工作、分析和解决问题的能力，良好的中英文读写说能力。 | N2: =LEN(M2) -> 0 | O2: =IF(ISBLANK(M2),0,COUNTA(_xlfn.TEXTSPLIT(M2,","))) -> 0
A3: =COUNTIF(B:B,B3) -> 6 | B3: 上海新皋实业有限公司 | C3: 新皋实业成立于2013年初，总部位于上海虹桥机场毗邻的明谷科技园，公司在智能家居领域率先投入智能家居控制系统的项目研发、生产及销售。获得软件专利著作权十多项，企业获得国家商标局认证商标：《新皋》《XINGAO》《艾登堡》《ATNBO》等品牌，并推出真正适合国内外用户的智能影音系列产品。自主研发新皋XINGAO智能影院中控系统及艾登堡ATNBO家庭影院系列产品,深受行业专业人士好评。新皋实业是上海闵行区就业促进中心审核认定的大学生实习基地，常年招收在校大学生实习实践，上海闵行地区户籍大学生或闵行地区高校学生优先录取，实习享受上海市闵行区人社局补贴。 | D3: 设计，UI设计，效果图设计 | E3: 5 | F3: 大专 | G3: 工作内容：企业设计类工作，主要内容协助领导UI设计工作。招聘条件：有相关工作经验者优先；1、熟悉办公软件操作，具备良好的文字表达能力；2、熟练UI设计软件。公司从事智能家居及智能私人影院技术研发及硬件生产，招聘在校大学生实习实践，对智能家居，私人影院设备产品感兴趣者，实习生学员公司各岗位培养。实习期间成绩优秀者，毕业学年转正为企业员工，签定劳动合同，享受企业员工一切待遇。上海新皋实业有限公司是上海闵行区人社局及财政局审核认定的大学生实习实训基地。 | H3: 日薪：80-180/天 | I3: =_xlfn.CONCAT(D3,"（学历：",F3," 专业要求：",IF(ISBLANK(M3),"无",M3),"）") -> 设计，UI设计，效果图设计（学历：大专 专业要求：无） | J3: =LEN(G3) -> 225 | K3: =_xlfn.XLOOKUP(A3,长度要求!A:A,长度要求!E:E) -> 500 | L3: =IF(J3<K3,G3,LEFT(G3,K3)&"……") -> 工作内容：企业设计类工作，主要内容协助领导UI设计工作。招聘条件：有相关工作经验者优先；1、熟悉办公软件操作，具备良好的文字表达能力；2、熟练UI设计软件。公司从事智能家居及智能私人影院技术研发及硬件生产，招聘在校大学生实习实践，对智能家居，私人影院设备产品感兴趣者，实习生学员公司各岗位培养。实习期间成绩优秀者，毕业学年转正为企业员工，签定劳动合同，享受企业员工一切待遇。上海新皋实业有限公司是上海闵行区人社局及财政局审核认定的大学生实习实训基地。 | N3: =LEN(M3) -> 0 | O3: =IF(ISBLANK(M3),0,COUNTA(_xlfn.TEXTSPLIT(M3,","))) -> 0
A4: =COUNTIF(B:B,B4) -> 6 | B4: 上海新皋实业有限公司 | C4: 新皋实业成立于2013年初，总部位于上海虹桥机场毗邻的明谷科技园，公司在智能家居领域率先投入智能家居控制系统的项目研发、生产及销售。获得软件专利著作权十多项，企业获得国家商标局认证商标：《新皋》《XINGAO》《艾登堡》《ATNBO》等品牌，并推出真正适合国内外用户的智能影音系列产品。自主研发新皋XINGAO智能影院中控系统及艾登堡ATNBO家庭影院系列产品,深受行业专业人士好评。新皋实业是上海闵行区就业促进中心审核认定的大学生实习基地，常年招收在校大学生实习实践，上海闵行地区户籍大学生或闵行地区高校学生优先录取，实习享受上海市闵行区人社局补贴。 | D4: 物联网技术助理 | E4: 3 | F4: 初中及以下 | G4: 我司是上海市人社局批准大学生实习基地，闵行区户籍实习生可以享受政府津贴，名额有限。公司从事智能家居及智能私人影院技术研发及硬件设备调试，招聘智能家居行业相关专业的在校大学生实习实践，要求物联网技术或电子及机电专业学生，具备弱电接线动手能力，对智能家居，私人影院设备安装调试感兴趣者，实习生学员公司提供技术培训。实习期间成绩优秀者，毕业学年转正为企业员工，签定劳动合同，享受企业员工一切待遇。优秀学员企业另外增加岗位津贴。面试证件：身份证；学信网个人资料；公司地址：上海市闵行区中春路7001号（明谷科技园）B栋415。公交路线：地铁9号线中春路站（2号口）出来沿着中春路骑行（10分钟）到达明谷科技园东大门，公司在东门左边进口处。 | H4: 日薪：80-150/天 | I4: =_xlfn.CONCAT(D4,"（学历：",F4," 专业要求：",IF(ISBLANK(M4),"无",M4),"）") -> 物联网技术助理（学历：初中及以下 专业要求：微电子技术,微电子学与固体电子学,微电子科学与工程） | J4: =LEN(G4) -> 315 | K4: =_xlfn.XLOOKUP(A4,长度要求!A:A,长度要求!E:E) -> 500 | L4: =IF(J4<K4,G4,LEFT(G4,K4)&"……") -> 我司是上海市人社局批准大学生实习基地，闵行区户籍实习生可以享受政府津贴，名额有限。公司从事智能家居及智能私人影院技术研发及硬件设备调试，招聘智能家居行业相关专业的在校大学生实习实践，要求物联网技术或电子及机电专业学生，具备弱电接线动手能力，对智能家居，私人影院设备安装调试感兴趣者，实习生学员公司提供技术培训。实习期间成绩优秀者，毕业学年转正为企业员工，签定劳动合同，享受企业员工一切待遇。优秀学员企业另外增加岗位津贴。面试证件：身份证；学信网个人资料；公司地址：上海市闵行区中春路7001号（明谷科技园）B栋415。公交路线：地铁9号线中春路站（2号口）出来沿着中春路骑行（10分钟）到达明谷科技园东大门，公司在东门左边进口处。 | M4: 微电子技术,微电子学与固体电子学,微电子科学与工程 | N4: =LEN(M4) -> 25 | O4: =IF(ISBLANK(M4),0,COUNTA(_xlfn.TEXTSPLIT(M4,","))) -> 3
A5: =COUNTIF(B:B,B5) -> 2 | B5: 上海德辰汽车销售有限公司 | C5: 上海德辰汽车销售公司是北方一大型汽车经销商集团在上海新投资创立的一汽大众奥迪品牌4S店。超越了传统豪华汽车4S店的概念，实际具备品牌体验、车型展示、新车销售、售后服务、二手车置换等多种功能，完备的设施以及周到的服务一应俱全，体现出国际豪华品牌全球统一的服务水准。该城市展厅坐落于闵行区颛桥地区（颛兴东路1280弄3号）。地铁、轻轨均可到达，交通便捷。地址：颛兴东路1280弄3号。总占地面积11455平方米。上下共有三层，展厅面积4168平方米，销售展示分两层，有超过多个标准汽车展位，大厅设有人性化的自动扶梯；屋顶设置顶楼停车厂，日接待能力超过100台。简洁明快的建筑风格，落地玻璃和透明天窗的结合使整个展厅最大限度地充满阳光和自然气息，充分体现了人性与科技的完美结合，展现奥迪品牌的超凡卓越和豪华尊贵，修理车间面积7287平方米，共有多个汽车维修工位，技术人员有40人，分为机修、电工、钣金、喷漆区，布局合理，设备先进。突出强调“买车修车到德辰，诚信舒心更放心”的服务理念。也是每个德辰员工的座右铭。我们以完善的硬件设施、周到的人性化服务迎接您的光临。背景介绍上海德辰的股东旗下共拥有多家4S店，其中在长春、嘉兴、宁波销售一汽奥迪、一汽马自达、一汽丰田等知名品牌汽车。企业文化上海德辰奉行“务实、诚信、进取、激情、团队精神、服务意识”的企业文化；在选人、用人、育人上：以具竞争力的薪酬吸引人才、以完善的培训体系培养人才，以强烈的业绩导向、快速的晋升和广阔的发展空间开发人才。 | D5: 机电实习生 | E5: 2 | F5: 中专/技校 | G5: 具有一定的汽车理论知识和汽车维修知识，具有较强的动手能力、语言表达能力、独立解决问题的能力、汽车工艺学习及钻研能力 | H5: 日薪：80-150/天 | I5: =_xlfn.CONCAT(D5,"（学历：",F5," 专业要求：",IF(ISBLANK(M5),"无",M5),"）") -> 机电实习生（学历：中专/技校 专业要求：汽车检测与维修技术,新能源汽车技术,汽车运用与维修技术,汽车车身维修技术,新能源汽车运用与维修,汽车制造类,汽车服务工程,汽车维修工程教育,新能源汽车工程） | J5: =LEN(G5) -> 57 | K5: =_xlfn.XLOOKUP(A5,长度要求!A:A,长度要求!E:E) -> 500 | L5: =IF(J5<K5,G5,LEFT(G5,K5)&"……") -> 具有一定的汽车理论知识和汽车维修知识，具有较强的动手能力、语言表达能力、独立解决问题的能力、汽车工艺学习及钻研能力 | M5: 汽车检测与维修技术,新能源汽车技术,汽车运用与维修技术,汽车车身维修技术,新能源汽车运用与维修,汽车制造类,汽车服务工程,汽车维修工程教育,新能源汽车工程 | N5: =LEN(M5) -> 77 | O5: =IF(ISBLANK(M5),0,COUNTA(_xlfn.TEXTSPLIT(M5,","))) -> 9
A6: =COUNTIF(B:B,B6) -> 1 | B6: 上海市黄浦区西凌第一幼儿园 | C6: 西凌第一幼儿园是一所上海市示范性幼儿园、上海市文明单位。地处黄浦区西藏南路，园内幼儿活动场地充裕，环境优美，四季绿化常青，阳光充足，是“上海市花园单位”。我园积极探索围棋与游戏融合的探索，秉持“以人为本，民主和谐，快乐发展”办园宗旨和“以棋养德、以棋怡情、以棋明理、以棋启智”的教育理念，深受幼儿与家长的喜欢。西凌第一幼儿园已成为孩子们游戏、学习、生活的乐园。 | D6: 保育员 | E6: 5 | F6: 初中及以下 | G6: 具有良好师德，爱孩子，有正确的儿童观具备保育专业知识与技能 | H6: 月薪：3K-5K | I6: =_xlfn.CONCAT(D6,"（学历：",F6," 专业要求：",IF(ISBLANK(M6),"无",M6),"）") -> 保育员（学历：初中及以下 专业要求：学前教育,卫生教育） | J6: =LEN(G6) -> 29 | K6: =_xlfn.XLOOKUP(A6,长度要求!A:A,长度要求!E:E) -> 500 | L6: =IF(J6<K6,G6,LEFT(G6,K6)&"……") -> 具有良好师德，爱孩子，有正确的儿童观具备保育专业知识与技能 | M6: 学前教育,卫生教育 | N6: =LEN(M6) -> 9 | O6: =IF(ISBLANK(M6),0,COUNTA(_xlfn.TEXTSPLIT(M6,","))) -> 2
A7: =COUNTIF(B:B,B7) -> 6 | B7: 上海新皋实业有限公司 | C7: 新皋实业成立于2013年初，总部位于上海虹桥机场毗邻的明谷科技园，公司在智能家居领域率先投入智能家居控制系统的项目研发、生产及销售。获得软件专利著作权十多项，企业获得国家商标局认证商标：《新皋》《XINGAO》《艾登堡》《ATNBO》等品牌，并推出真正适合国内外用户的智能影音系列产品。自主研发新皋XINGAO智能影院中控系统及艾登堡ATNBO家庭影院系列产品,深受行业专业人士好评。新皋实业是上海闵行区就业促进中心审核认定的大学生实习基地，常年招收在校大学生实习实践，上海闵行地区户籍大学生或闵行地区高校学生优先录取，实习享受上海市闵行区人社局补贴。 | D7: 新媒体运营 | E7: 4 | F7: 初中及以下 | G7: 工作内容负责公司多媒体渠道（包括但不限于微信公众号、抖音、微博等）的运营管理和内容策划。通过策划和执行，提升公司多媒体渠道的曝光度和用户粘性。主要职责：1、负责公司多媒体渠道的运营管理和内容策划，包括但不限于制定并执行渠道内容计划、跟踪和优化渠道运营效果、策划并执行创意等；2、撰写、编辑、发布公司公众号多媒体内容，提升内容质量和创意，以满足用户需求和公司需求；3、根据公司业务需求，制定并执行多媒体渠道的定期更新和升级策略，提升公司多媒体品牌形象和用户黏性；4、定期汇报公司多媒体渠道运营效果，提供数据驱动的改进建议，以优化公司多媒体运营策略；5、与其他部门的沟通和协作，包括但不限于与视频拍摄团队、设计师等合作，提升公司多媒体内容质量和用户体验。招聘条件多媒体运营专业，大专及以上学历，具备较强的项目管理能力和团队协作能力；1、熟悉新媒体渠道，具有一定的内容策划和创意能力，善于分析数据驱动问题；2、具有较强的沟通协调能力，能够与不同部门进行有效沟通和协作；3、具有较强的逻辑思维能力，能够独立思考和解决问题；4、熟练掌握公司多媒体运营流程和方法，了解公司业务需求。具有视频拍摄剪辑编辑能力。熟练OFFICE和PS、PR软件。上海闵行地区户籍大学生；或上海：交大、华师大、电机学院、东海大学大专院校学生享受本地区政策补贴扶持。闵行区大学生投递简历优先录用。公司地址：上海闵行区中春路7001号明谷科技园B栋415 | H7: 日薪：80-180/天 | I7: =_xlfn.CONCAT(D7,"（学历：",F7," 专业要求：",IF(ISBLANK(M7),"无",M7),"）") -> 新媒体运营（学历：初中及以下 专业要求：无） | J7: =LEN(G7) -> 608 | K7: =_xlfn.XLOOKUP(A7,长度要求!A:A,长度要求!E:E) -> 500 | L7: =IF(J7<K7,G7,LEFT(G7,K7)&"……") -> 工作内容负责公司多媒体渠道（包括但不限于微信公众号、抖音、微博等）的运营管理和内容策划。通过策划和执行，提升公司多媒体渠道的曝光度和用户粘性。主要职责：1、负责公司多媒体渠道的运营管理和内容策划，包括但不限于制定并执行渠道内容计划、跟踪和优化渠道运营效果、策划并执行创意等；2、撰写、编辑、发布公司公众号多媒体内容，提升内容质量和创意，以满足用户需求和公司需求；3、根据公司业务需求，制定并执行多媒体渠道的定期更新和升级策略，提升公司多媒体品牌形象和用户黏性；4、定期汇报公司多媒体渠道运营效果，提供数据驱动的改进建议，以优化公司多媒体运营策略；5、与其他部门的沟通和协作，包括但不限于与视频拍摄团队、设计师等合作，提升公司多媒体内容质量和用户体验。招聘条件多媒体运营专业，大专及以上学历，具备较强的项目管理能力和团队协作能力；1、熟悉新媒体渠道，具有一定的内容策划和创意能力，善于分析数据驱动问题；2、具有较强的沟通协调能力，能够与不同部门进行有效沟通和协作；3、具有较强的逻辑思维能力，能够独立思考和解决问题；4、熟练掌握公司多媒体运营流程和方法，了解公司业务需求。具有视频拍摄剪辑编辑能力。熟练…… | N7: =LEN(M7) -> 0 | O7: =IF(ISBLANK(M7),0,COUNTA(_xlfn.TEXTSPLIT(M7,","))) -> 0
A8: =COUNTIF(B:B,B8) -> 6 | B8: 上海新皋实业有限公司 | C8: 新皋实业成立于2013年初，总部位于上海虹桥机场毗邻的明谷科技园，公司在智能家居领域率先投入智能家居控制系统的项目研发、生产及销售。获得软件专利著作权十多项，企业获得国家商标局认证商标：《新皋》《XINGAO》《艾登堡》《ATNBO》等品牌，并推出真正适合国内外用户的智能影音系列产品。自主研发新皋XINGAO智能影院中控系统及艾登堡ATNBO家庭影院系列产品,深受行业专业人士好评。新皋实业是上海闵行区就业促进中心审核认定的大学生实习基地，常年招收在校大学生实习实践，上海闵行地区户籍大学生或闵行地区高校学生优先录取，实习享受上海市闵行区人社局补贴。 | D8: 技术调试普工 | E8: 3 | F8: 大专 | G8: 工作内容负责生产电子产品组装+装配+测试等简单工作。1.通过岗位技能培训后，对电子元器件进行装配；2.对产品进行外观方面的品质检查；3.每日下班前，保持台面和工具的清洁；招聘条件：文化程度：中专及以上学历；机电电子专业、物联网专业或微电子专业；有电子产品组装能力；能手工焊接工，会使用小型电动工具设备，熟练的动手能力。身体健康、工作认真负责，吃苦耐劳。 | H8: 日薪：80-150/天 | I8: =_xlfn.CONCAT(D8,"（学历：",F8," 专业要求：",IF(ISBLANK(M8),"无",M8),"）") -> 技术调试普工（学历：大专 专业要求：无） | J8: =LEN(G8) -> 176 | K8: =_xlfn.XLOOKUP(A8,长度要求!A:A,长度要求!E:E) -> 500 | L8: =IF(J8<K8,G8,LEFT(G8,K8)&"……") -> 工作内容负责生产电子产品组装+装配+测试等简单工作。1.通过岗位技能培训后，对电子元器件进行装配；2.对产品进行外观方面的品质检查；3.每日下班前，保持台面和工具的清洁；招聘条件：文化程度：中专及以上学历；机电电子专业、物联网专业或微电子专业；有电子产品组装能力；能手工焊接工，会使用小型电动工具设备，熟练的动手能力。身体健康、工作认真负责，吃苦耐劳。 | N8: =LEN(M8) -> 0 | O8: =IF(ISBLANK(M8),0,COUNTA(_xlfn.TEXTSPLIT(M8,","))) -> 0
A9: =COUNTIF(B:B,B9) -> 6 | B9: 上海新皋实业有限公司 | C9: 新皋实业成立于2013年初，总部位于上海虹桥机场毗邻的明谷科技园，公司在智能家居领域率先投入智能家居控制系统的项目研发、生产及销售。获得软件专利著作权十多项，企业获得国家商标局认证商标：《新皋》《XINGAO》《艾登堡》《ATNBO》等品牌，并推出真正适合国内外用户的智能影音系列产品。自主研发新皋XINGAO智能影院中控系统及艾登堡ATNBO家庭影院系列产品,深受行业专业人士好评。新皋实业是上海闵行区就业促进中心审核认定的大学生实习基地，常年招收在校大学生实习实践，上海闵行地区户籍大学生或闵行地区高校学生优先录取，实习享受上海市闵行区人社局补贴。 | D9: 办公室文员(人事助理） | E9: 2 | F9: 大专 | G9: 工作内容：负责办公室日常运营和维护，处理各类文件及档案，负责公司会议前准备工作：负责协助部门负责人完成人事行政辅助类工作，包括但不限于来客来访接待、整理文件等；招聘条件：不限工作经验，有相关工作经验者优先；1、熟悉办公软件操作，具备良好的文字表达能力；2、具备良好的组织协调能力和团队合作意识；3、具有较强的沟通能力和抗压能力，能够适应工作中的挑战；4、有较强的责任心和事业心， | H9: 日薪：80-150/天 | I9: =_xlfn.CONCAT(D9,"（学历：",F9," 专业要求：",IF(ISBLANK(M9),"无",M9),"）") -> 办公室文员(人事助理）（学历：大专 专业要求：无） | J9: =LEN(G9) -> 189 | K9: =_xlfn.XLOOKUP(A9,长度要求!A:A,长度要求!E:E) -> 500 | L9: =IF(J9<K9,G9,LEFT(G9,K9)&"……") -> 工作内容：负责办公室日常运营和维护，处理各类文件及档案，负责公司会议前准备工作：负责协助部门负责人完成人事行政辅助类工作，包括但不限于来客来访接待、整理文件等；招聘条件：不限工作经验，有相关工作经验者优先；1、熟悉办公软件操作，具备良好的文字表达能力；2、具备良好的组织协调能力和团队合作意识；3、具有较强的沟通能力和抗压能力，能够适应工作中的挑战；4、有较强的责任心和事业心， | N9: =LEN(M9) -> 0 | O9: =IF(ISBLANK(M9),0,COUNTA(_xlfn.TEXTSPLIT(M9,","))) -> 0
A10: =COUNTIF(B:B,B10) -> 6 | B10: 上海新皋实业有限公司 | C10: 新皋实业成立于2013年初，总部位于上海虹桥机场毗邻的明谷科技园，公司在智能家居领域率先投入智能家居控制系统的项目研发、生产及销售。获得软件专利著作权十多项，企业获得国家商标局认证商标：《新皋》《XINGAO》《艾登堡》《ATNBO》等品牌，并推出真正适合国内外用户的智能影音系列产品。自主研发新皋XINGAO智能影院中控系统及艾登堡ATNBO家庭影院系列产品,深受行业专业人士好评。新皋实业是上海闵行区就业促进中心审核认定的大学生实习基地，常年招收在校大学生实习实践，上海闵行地区户籍大学生或闵行地区高校学生优先录取，实习享受上海市闵行区人社局补贴。 | D10: 电商运营 (电商客服) | E10: 5 | F10: 大专 | G10: 工作内容：1、负责店铺日常运营，包括商品上架、售后处理、物流跟踪等；日常产品标题优化、主图和详情页优化、评价维护、站内外推广、活动策划及提报等运营工作；招聘条件：具有较强的责任心和耐心，对电商领域有浓厚的兴趣和学习意愿；-熟练掌握淘宝、天猫等电商平台运营规则，了解各种推广工具的使用；-有良好的沟通能力和团队协作精神，善于与上级和同事进行有效沟通。熟练OFFICE和PS、PR软件。待遇：基本新资+提成 | H10: 日薪：80-150/天 | I10: =_xlfn.CONCAT(D10,"（学历：",F10," 专业要求：",IF(ISBLANK(M10),"无",M10),"）") -> 电商运营 (电商客服)（学历：大专 专业要求：无） | J10: =LEN(G10) -> 201 | K10: =_xlfn.XLOOKUP(A10,长度要求!A:A,长度要求!E:E) -> 500 | L10: =IF(J10<K10,G10,LEFT(G10,K10)&"……") -> 工作内容：1、负责店铺日常运营，包括商品上架、售后处理、物流跟踪等；日常产品标题优化、主图和详情页优化、评价维护、站内外推广、活动策划及提报等运营工作；招聘条件：具有较强的责任心和耐心，对电商领域有浓厚的兴趣和学习意愿；-熟练掌握淘宝、天猫等电商平台运营规则，了解各种推广工具的使用；-有良好的沟通能力和团队协作精神，善于与上级和同事进行有效沟通。熟练OFFICE和PS、PR软件。待遇：基本新资+提成 | N10: =LEN(M10) -> 0 | O10: =IF(ISBLANK(M10),0,COUNTA(_xlfn.TEXTSPLIT(M10,","))) -> 0
A11: =COUNTIF(B:B,B11) -> 2 | B11: 上海网鱼酒店管理有限公司 | C11: 网鱼创始于1998年，从诞生之初就秉承不断创新的理念，致力于打造多人游戏空间。截至2020年12月31日，网鱼全球会员数超2000万，服务覆盖国内外106个城市。全球拥有超1000家门店，年服务人次超3000万，iG战队倾情代言，是深受全球玩家喜爱的聚玩圣地。2021年推出“网鱼电竞酒店”，正式进军电竞酒店行业，打造跨品类、跨业态、跨平台的综合娱乐型品牌，践行“给用户美好的体验”。 | D11: 门店管培生 | E11: 50 | F11: 大专 | G11: 公司简介：网鱼创始于1998年，起源于上海松江，2015年获得上海市著名商标荣誉称号。作为国内电竞连锁的代表，从诞生之初就秉承不断创新的理念，致力于全球第一电竞社区的打造，为全球电竞玩家提供优质的电竞休闲娱乐服务。截至2021年12月31日，网鱼全球会员数超2000万，服务覆盖国内外82个城市，在美国、英国、加拿大、澳大利亚、新加坡等多个国家开设门店，全球拥有900多家门店，年服务人次超4000万。2021年，网鱼品牌创新升级为“网鱼电竞”，打造游戏玩家的电竞基地；探索多业态，推出“网鱼电竞酒店”，正式进军电竞酒店行业，打造跨品类、跨业态、跨平台的综合娱乐型品牌，践行“给用户美好的体验”。截至2023年12月，网鱼电竞酒店覆盖全国26个主要城市，在营门店数量超过200家。岗位介绍门店管培生（储备店长）：50名工作地点：全国（全国1700家门店，可根据意向城市分配工作城市）。工作职责:1、经营管理：从基层店员历练开始，协助酒店店长进行门店的运营管理，管理门店资产设备、现金、账务，薪资录入，奖金核算；2、学习管理：跟随导师学习门店人员的岗位落实及日常管理；3、品质管理：保证门店卫生品质，逐步掌握处理店铺突发事件；4、参与店铺全岗位知识学习，按照计划参与岗位晋升培训，稳步晋升协助店长管理店面日常及销售管理工作，达成店面销售目标；要求：1、大专学历，2025年或2026年毕业；2、专业不限，连锁经营管理、经管专业等优先，其他专业优秀同学也可；3、仪容仪表端正，良好的沟通表达能力，思路清晰，适应能力强。各阶段岗位薪酬：1、综合月薪：入职后的前4个月4000-5000元左右，第5个月-7个月5000-6000元左右，第8个月晋升店长后，月薪8000元及以上（不同城市薪资略有差异）2、福利：包住宿 | H11: 月薪：5K-10K | I11: =_xlfn.CONCAT(D11,"（学历：",F11," 专业要求：",IF(ISBLANK(M11),"无",M11),"）") -> 门店管培生（学历：大专 专业要求：无） | J11: =LEN(G11) -> 754 | K11: =_xlfn.XLOOKUP(A11,长度要求!A:A,长度要求!E:E) -> 500 | L11: =IF(J11<K11,G11,LEFT(G11,K11)&"……") -> 公司简介：网鱼创始于1998年，起源于上海松江，2015年获得上海市著名商标荣誉称号。作为国内电竞连锁的代表，从诞生之初就秉承不断创新的理念，致力于全球第一电竞社区的打造，为全球电竞玩家提供优质的电竞休闲娱乐服务。截至2021年12月31日，网鱼全球会员数超2000万，服务覆盖国内外82个城市，在美国、英国、加拿大、澳大利亚、新加坡等多个国家开设门店，全球拥有900多家门店，年服务人次超4000万。2021年，网鱼品牌创新升级为“网鱼电竞”，打造游戏玩家的电竞基地；探索多业态，推出“网鱼电竞酒店”，正式进军电竞酒店行业，打造跨品类、跨业态、跨平台的综合娱乐型品牌，践行“给用户美好的体验”。截至2023年12月，网鱼电竞酒店覆盖全国26个主要城市，在营门店数量超过200家。岗位介绍门店管培生（储备店长）：50名工作地点：全国（全国1700家门店，可根据意向城市分配工作城市）。工作职责:1、经营管理：从基层店员历练开始，协助酒店店长进行门店的运营管理，管理门店资产设备、现金、账务，薪资录入，奖金核算；2、学习管理：跟随导师学习门店人员的岗位落实及日常管理；3、品质管理：保证门店卫生品质，逐…… | N11: =LEN(M11) -> 0 | O11: =IF(ISBLANK(M11),0,COUNTA(_xlfn.TEXTSPLIT(M11,","))) -> 0
A12: =COUNTIF(B:B,B12) -> 2 | B12: 上海网鱼酒店管理有限公司 | C12: 网鱼创始于1998年，从诞生之初就秉承不断创新的理念，致力于打造多人游戏空间。截至2020年12月31日，网鱼全球会员数超2000万，服务覆盖国内外106个城市。全球拥有超1000家门店，年服务人次超3000万，iG战队倾情代言，是深受全球玩家喜爱的聚玩圣地。2021年推出“网鱼电竞酒店”，正式进军电竞酒店行业，打造跨品类、跨业态、跨平台的综合娱乐型品牌，践行“给用户美好的体验”。 | D12: 客户经理 | E12: 30 | F12: 大专 | G12: 职责：1、导座服务：①严格执行门店导座SOP标准，提升顾客满意度；②主动观察顾客消费习惯，提供个性化服务；③工作时间需着JK制服，并保持整洁得体的妆容及精神面貌；2、抖音直播：①每日在门店非上客高峰期，使用门店抖音账号，完成2小时直播；②负责直播间的秩序维护和用户互动，积极解答用户问题；③发掘直播间内意向用户，吸引用户到店，提升门店新会员数量；④每日24点前，完成一条抖音视频发布。3、会员运营：①完成企业微信社群搭建、成员邀请及日常维护；②每日回访新客，定期收集top100顾客反馈建议；③每日邀请老顾客到店上网，并为顾客线上订座；4、线上平台维护：①每周按照店长要求，完成高德/百度/腾讯地图/美团平台的优质好评数。②100%邀请团购用户消费后评价。要求：1、性别：女2、年龄：18-24周岁3、学历：大专及以上学历4、形象：身高160CM以上，形象气质佳5、性格特质：活泼开朗，有服务意识，擅沟通喜交流6、经验能力：会端游、有直播或者游戏教练经验者优先薪资待遇1、薪资：月薪5000+；2、福利：每月免费上网时长60小时，免费饮品10杯，简餐半价券42张，其他福利均同门店其他员工；3、销售提成另计，包含但不限于鱼乐卡销售提成 | H12: 月薪：5K-7K | I12: =_xlfn.CONCAT(D12,"（学历：",F12," 专业要求：",IF(ISBLANK(M12),"无",M12),"）") -> 客户经理（学历：大专 专业要求：无） | J12: =LEN(G12) -> 517 | K12: =_xlfn.XLOOKUP(A12,长度要求!A:A,长度要求!E:E) -> 500 | L12: =IF(J12<K12,G12,LEFT(G12,K12)&"……") -> 职责：1、导座服务：①严格执行门店导座SOP标准，提升顾客满意度；②主动观察顾客消费习惯，提供个性化服务；③工作时间需着JK制服，并保持整洁得体的妆容及精神面貌；2、抖音直播：①每日在门店非上客高峰期，使用门店抖音账号，完成2小时直播；②负责直播间的秩序维护和用户互动，积极解答用户问题；③发掘直播间内意向用户，吸引用户到店，提升门店新会员数量；④每日24点前，完成一条抖音视频发布。3、会员运营：①完成企业微信社群搭建、成员邀请及日常维护；②每日回访新客，定期收集top100顾客反馈建议；③每日邀请老顾客到店上网，并为顾客线上订座；4、线上平台维护：①每周按照店长要求，完成高德/百度/腾讯地图/美团平台的优质好评数。②100%邀请团购用户消费后评价。要求：1、性别：女2、年龄：18-24周岁3、学历：大专及以上学历4、形象：身高160CM以上，形象气质佳5、性格特质：活泼开朗，有服务意识，擅沟通喜交流6、经验能力：会端游、有直播或者游戏教练经验者优先薪资待遇1、薪资：月薪5000+；2、福利：每月免费上网时长60小时，免费饮品10杯，简餐半价券42张，其他福利均同门店其他员工；3、销售提…… | N12: =LEN(M12) -> 0 | O12: =IF(ISBLANK(M12),0,COUNTA(_xlfn.TEXTSPLIT(M12,","))) -> 0
A13: =COUNTIF(B:B,B13) -> 4 | B13: 珍岛信息技术（上海）股份有限公司 | C13: 珍岛信息技术（上海）股份有限公司（简称珍岛集团，股票代码02556.HK）是中国最大的营销及销售SaaS公司，也是最早推出T-force营销领域大模型的公司，最早推出AI-Agentforce中台的公司，聚焦数字化与智能化，基于人工智能、大数据技术，是专注数字化智能营销的SaaS服务提供商，于2024年在香港上市。 | D13: 校企合作经理 | E13: 3 | F13: 大专 | G13: 岗位职责：1、负责面向全国本科、高职、中职、技师院校进行数字营销实训软件的销售工作；2、制定区域销售计划并保障计划有效完成，进行系统化成本风控；3、完成区域业务团队组建、培养和绩效管理；4、建立院校业务多元化合作伙伴架构和体系。任职要求：1、不限专业，金融、网络营销、电子商务为佳；2、做事严谨细致，有耐心，有责任心，具有优秀的表达能力与团队协作能力3、具备良好的学习力、承压能力及高度责任心。4、能接受出差 | H13: 月薪：6K-9K | I13: =_xlfn.CONCAT(D13,"（学历：",F13," 专业要求：",IF(ISBLANK(M13),"无",M13),"）") -> 校企合作经理（学历：大专 专业要求：无） | J13: =LEN(G13) -> 204 | K13: =_xlfn.XLOOKUP(A13,长度要求!A:A,长度要求!E:E) -> 500 | L13: =IF(J13<K13,G13,LEFT(G13,K13)&"……") -> 岗位职责：1、负责面向全国本科、高职、中职、技师院校进行数字营销实训软件的销售工作；2、制定区域销售计划并保障计划有效完成，进行系统化成本风控；3、完成区域业务团队组建、培养和绩效管理；4、建立院校业务多元化合作伙伴架构和体系。任职要求：1、不限专业，金融、网络营销、电子商务为佳；2、做事严谨细致，有耐心，有责任心，具有优秀的表达能力与团队协作能力3、具备良好的学习力、承压能力及高度责任心。4、能接受出差 | N13: =LEN(M13) -> 0 | O13: =IF(ISBLANK(M13),0,COUNTA(_xlfn.TEXTSPLIT(M13,","))) -> 0
A14: =COUNTIF(B:B,B14) -> 5 | B14: 宁波革力物流有限公司上海分公司 | C14: 革力物流有限公司总部设在上海,并在深圳,广州,佛山,中山,以及宁波设有分公司,在华北地区也有较好的代理网络。公司网址为：www.gclchina.net公司的代理网络覆盖100多个国家,优势航线为欧洲,地中海,中东印巴,以及澳洲新西兰和东南亚国家除基本海运空运以外，公司还致力于发展进出口代理、清关、仓储、供应链管理等多元化主体化的国际物流服务。主要合作船公司有:MAERSK、APL、EVERGREEN、NORASIA、PIL、HAPAGLIOYD、MSC、COSCO、CSCL、CMA、WANHAI、YANGMING、OOCL；主要合作的航空公司有联邦快递、联合包裹、美国航空、新加坡航空、加拿大航空、新西兰航空、马来西亚航空、以色列航空、法国航空、德国汉莎、奥地利航空、英航、国泰、阿联酋航空等。我们诚邀你的加入，让我们共同致力于打造美好的明天！我们公司全体员工满怀信心，愿以一流的服务、良好的信誉面向世界，竭诚希望与世界各国、全国各地的代理和货主建立良好的合作关系！ | D14: 会计助理（实习生） | E14: 2 | F14: 大专 | G14: 开票基础凭证录入及时完成领导交办的其他事项岗位要求：会计或财务相关专业工作认真、仔细、负责欢迎应届毕业生 | H14: 日薪：120-150/天 | I14: =_xlfn.CONCAT(D14,"（学历：",F14," 专业要求：",IF(ISBLANK(M14),"无",M14),"）") -> 会计助理（实习生）（学历：大专 专业要求：无） | J14: =LEN(G14) -> 52 | K14: =_xlfn.XLOOKUP(A14,长度要求!A:A,长度要求!E:E) -> 500 | L14: =IF(J14<K14,G14,LEFT(G14,K14)&"……") -> 开票基础凭证录入及时完成领导交办的其他事项岗位要求：会计或财务相关专业工作认真、仔细、负责欢迎应届毕业生 | N14: =LEN(M14) -> 0 | O14: =IF(ISBLANK(M14),0,COUNTA(_xlfn.TEXTSPLIT(M14,","))) -> 0
A15: =COUNTIF(B:B,B15) -> 4 | B15: 上海光通信有限公司 | C15: 上海光通信有限公司（英文名ShanghaiGTXSemiconductorCo.,Ltd，下称“GTX”），成立于1988年，于2022年初转型进入集成电路制造领域。 | D15: 良率提升助理技术员 | E15: 5 | F15: 大专 | G15: 岗位描述：1）负责支持在线缺陷监控，处理产线检测的产品、设备，保证产品正常生产，设备正常运行。2）负责监控并处理检测及复检机台的异常运行状况，保证机台正常运行。3）协同工程师进行缺陷改善，建立合格的检测程式和复检程式，发现并通知产生缺陷的制程，减少缺陷的影响范围。4）负责简单的缺陷切片制样，跟进切片结果。任职要求：1）大专及以上学历，专业不限。2）具备良好的沟通能力，具备团队意识。3）倒班工作模式，接受无尘室工作环境。 | H15: 月薪：6K-8K | I15: =_xlfn.CONCAT(D15,"（学历：",F15," 专业要求：",IF(ISBLANK(M15),"无",M15),"）") -> 良率提升助理技术员（学历：大专 专业要求：无） | J15: =LEN(G15) -> 211 | K15: =_xlfn.XLOOKUP(A15,长度要求!A:A,长度要求!E:E) -> 500 | L15: =IF(J15<K15,G15,LEFT(G15,K15)&"……") -> 岗位描述：1）负责支持在线缺陷监控，处理产线检测的产品、设备，保证产品正常生产，设备正常运行。2）负责监控并处理检测及复检机台的异常运行状况，保证机台正常运行。3）协同工程师进行缺陷改善，建立合格的检测程式和复检程式，发现并通知产生缺陷的制程，减少缺陷的影响范围。4）负责简单的缺陷切片制样，跟进切片结果。任职要求：1）大专及以上学历，专业不限。2）具备良好的沟通能力，具备团队意识。3）倒班工作模式，接受无尘室工作环境。 | N15: =LEN(M15) -> 0 | O15: =IF(ISBLANK(M15),0,COUNTA(_xlfn.TEXTSPLIT(M15,","))) -> 0
A16: =COUNTIF(B:B,B16) -> 4 | B16: 上海光通信有限公司 | C16: 上海光通信有限公司（英文名ShanghaiGTXSemiconductorCo.,Ltd，下称“GTX”），成立于1988年，于2022年初转型进入集成电路制造领域。 | D16: 实验室技术员 | E16: 20 | F16: 大专 | G16: 岗位描述：1）按照规程和作业指导书，执行失效分析实验室/可靠性实验室/化学实验室内相关仪器的操作并按照求完成具体失效分析工作。2）按照规程和作业指导书，执行失效分析实验室/可靠性实验室/化学实验室的日常点检，协助处理机台的日常维护工作。任职要求：1）大专以上学历，理工科相关专业。2）接受倒班工作模式，接受无尘室工作环境。3）具备良好的沟通能力和团队合作精神，具备独立工作、分析和解决问题的能力，良好的中英文读写说能力。 | H16: 月薪：6K-8K | I16: =_xlfn.CONCAT(D16,"（学历：",F16," 专业要求：",IF(ISBLANK(M16),"无",M16),"）") -> 实验室技术员（学历：大专 专业要求：无） | J16: =LEN(G16) -> 210 | K16: =_xlfn.XLOOKUP(A16,长度要求!A:A,长度要求!E:E) -> 500 | L16: =IF(J16<K16,G16,LEFT(G16,K16)&"……") -> 岗位描述：1）按照规程和作业指导书，执行失效分析实验室/可靠性实验室/化学实验室内相关仪器的操作并按照求完成具体失效分析工作。2）按照规程和作业指导书，执行失效分析实验室/可靠性实验室/化学实验室的日常点检，协助处理机台的日常维护工作。任职要求：1）大专以上学历，理工科相关专业。2）接受倒班工作模式，接受无尘室工作环境。3）具备良好的沟通能力和团队合作精神，具备独立工作、分析和解决问题的能力，良好的中英文读写说能力。 | N16: =LEN(M16) -> 0 | O16: =IF(ISBLANK(M16),0,COUNTA(_xlfn.TEXTSPLIT(M16,","))) -> 0
A17: =COUNTIF(B:B,B17) -> 7 | B17: 上海地矿物业管理有限公司 | C17: 上海地矿物业管理有限公司隶属于上市市规划和自然资源局。上海地矿物业管理有限公司城市规划展示馆项目。上海城市规划展示馆市国内售价以展示城市规划与发展为主题专业性场馆。 | D17: 展区管理员 | E17: 10 | F17: 大专 | G17: 要求：（1）五官端正、形象气质号，女性165cm，男性175cm以上，年龄30岁以下。（2）语言表达能力强、善于沟通。普通话水平二级乙等以上或具备同等水平。（3）有较强的组织协调能力，团队协作能力，反应敏捷、能妥善处理游客的突发状况，且具备熟练的电脑操作知识。（4）具有一定的英语口语能力，能与外宾简单交流。薪资待遇：5000-6000元/月其他福利：早中餐、高温费、年终奖、大礼包等实习生3000元+500元全勤奖，国企，提供完善的培训，实习表现优秀者毕业后优先录用。录用后缴纳四金，提供年终奖、高温费、大礼包，详情面谈。 | H17: 月薪：5K-6K | I17: =_xlfn.CONCAT(D17,"（学历：",F17," 专业要求：",IF(ISBLANK(M17),"无",M17),"）") -> 展区管理员（学历：大专 专业要求：无） | J17: =LEN(G17) -> 262 | K17: =_xlfn.XLOOKUP(A17,长度要求!A:A,长度要求!E:E) -> 500 | L17: =IF(J17<K17,G17,LEFT(G17,K17)&"……") -> 要求：（1）五官端正、形象气质号，女性165cm，男性175cm以上，年龄30岁以下。（2）语言表达能力强、善于沟通。普通话水平二级乙等以上或具备同等水平。（3）有较强的组织协调能力，团队协作能力，反应敏捷、能妥善处理游客的突发状况，且具备熟练的电脑操作知识。（4）具有一定的英语口语能力，能与外宾简单交流。薪资待遇：5000-6000元/月其他福利：早中餐、高温费、年终奖、大礼包等实习生3000元+500元全勤奖，国企，提供完善的培训，实习表现优秀者毕业后优先录用。录用后缴纳四金，提供年终奖、高温费、大礼包，详情面谈。 | N17: =LEN(M17) -> 0 | O17: =IF(ISBLANK(M17),0,COUNTA(_xlfn.TEXTSPLIT(M17,","))) -> 0
A18: =COUNTIF(B:B,B18) -> 6 | B18: 上海点晴信息科技有限公司 | C18: 上海点晴信息科技有限公司(ALCHEMYInformationtech-nologyCo.,Ltd)成立于2013年，是一家集独立游戏开发、高品质游戏美术制作服务及游戏美术赛事运营为一体的移动互联网公司。获高新技术企业，专精特新企业、科技小巨人企业、徐汇区企业技术中心、上海市设计创新中心等荣誉。作为腾讯，网易，育碧，米哈游，拳头，电魂，英雄互娱等知名研发公司的核心供应商，点晴参与制作了刺客信条、王者荣耀、原神、绝地求生、阴阳师、第五人格、狐妖小红娘、蛋仔派对等国内外各类型最前沿的主流游戏，致力于为全球市场提供自主研发的高品质游戏娱乐产品。公司旗下教育品牌【第九联盟】专注于CG行业人才储备及校企产学研项目;【GGAC数字艺术平台】集CG领域作品发布及赛事运营于一体。 | D18: 3D模型师/3D建模师 | E18: 20 | F18: 大专 | G18: 负责制作游戏内相关道具场景的建模，熟练使用3Dmax，ps，maya，zb等软件，熟悉次世代制作流程者优先。 | H18: 月薪：5K-8K | I18: =_xlfn.CONCAT(D18,"（学历：",F18," 专业要求：",IF(ISBLANK(M18),"无",M18),"）") -> 3D模型师/3D建模师（学历：大专 专业要求：无） | J18: =LEN(G18) -> 54 | K18: =_xlfn.XLOOKUP(A18,长度要求!A:A,长度要求!E:E) -> 500 | L18: =IF(J18<K18,G18,LEFT(G18,K18)&"……") -> 负责制作游戏内相关道具场景的建模，熟练使用3Dmax，ps，maya，zb等软件，熟悉次世代制作流程者优先。 | N18: =LEN(M18) -> 0 | O18: =IF(ISBLANK(M18),0,COUNTA(_xlfn.TEXTSPLIT(M18,","))) -> 0
A19: =COUNTIF(B:B,B19) -> 5 | B19: 上海汇珏科技集团股份有限公司 | C19: 汇珏集团成立于2002年，是一家集能源系统集成解决方案与智能网络通信设备服务型制造的高新技术企业，公司致力于成为通信及能源行业的领跑者。总部位于上海自贸区临港新片区，注册资金10778万元，目前在全国拥有6家全资子公司。在上海奉贤、江苏海安建立了3大生产基地，总占地面积超20万余平方米，拥有员工超数千人，销售和服务网点遍布全国各个城市，产品远销欧洲、北美、东南亚等多个国家和地区。汇珏网络先后获得了“高新技术企业”、“服务型制造示范”、“国家知识产权优势企业”、“上海专利示范企业”、“上海市企业技术中心”、“上海市著名商标”、“上海名牌产品”等众多荣誉。经过20多年的发展创新，产品及服务覆盖智慧ICT网络解决方案、数据中心解决方案、智慧能源解决方案、智慧移动通信解决方案、智慧建筑一体化解决方案、智慧城市一站式服务六大方向，产品广泛应用于通信、电力、新能源、交通、建筑、医疗等多个行业，实现了产品的多元化创新和商务模式向服务型制造升级。企业竞争力和市场地位不断提升，其中最新研发的智慧能源解决方案已应用市政、交通、教育、运营商等国内外多个行业，同时在国际市场中崭露锋芒。公司发展历程：2002-2004公司成立，引进先进技术；2005-2006办公厂房落成，公司商标注册；2007-2010开发“光进铜退室外机柜”，中标中国电信；2011-2012“PLC分路器”开发成功，中标三大运营商，新建生产基地；2013-2014投建江苏100亩光器件产业园，成立汇珏智能软件公司，开发网优软件产品，填补国内空白，签约中国电信；2015-2016集团信息化平台应用提升专业化管理。产品智能化升级，研发IODN等产品，推动智能化制造，连续中标国内三大运营商。公司秉承“汇当凌珏顶，一览众山小”的企业精神，先后获得上海市“高新技术企业”，“上海市著名商标”，“科技小巨人企业（培育）”，“专精特新企业”，“创新型企业”，等荣誉，多个产品获得了“上海市高新技术成果转化项目”。 | D19: 外贸业务助理 | E19: 5 | F19: 大专 | G19: 1.英语大学四级及以上，书面英语读写无障碍，口语交流流利。2.优秀的沟通表达能力与亲和力，有出色的组织协调能力与执行力。3.工作积极主动、认真负责，责任心强。4.善于组织策划活动，有服务意识。5.持有有效驾照，驾驶技术熟练者优先。(因工作经常会涉及到海外客户接待需求)。 | H19: 日薪：120-150/天 | I19: =_xlfn.CONCAT(D19,"（学历：",F19," 专业要求：",IF(ISBLANK(M19),"无",M19),"）") -> 外贸业务助理（学历：大专 专业要求：国际经济与贸易,国际贸易学,贸易经济） | J19: =LEN(G19) -> 135 | K19: =_xlfn.XLOOKUP(A19,长度要求!A:A,长度要求!E:E) -> 500 | L19: =IF(J19<K19,G19,LEFT(G19,K19)&"……") -> 1.英语大学四级及以上，书面英语读写无障碍，口语交流流利。2.优秀的沟通表达能力与亲和力，有出色的组织协调能力与执行力。3.工作积极主动、认真负责，责任心强。4.善于组织策划活动，有服务意识。5.持有有效驾照，驾驶技术熟练者优先。(因工作经常会涉及到海外客户接待需求)。 | M19: 国际经济与贸易,国际贸易学,贸易经济 | N19: =LEN(M19) -> 18 | O19: =IF(ISBLANK(M19),0,COUNTA(_xlfn.TEXTSPLIT(M19,","))) -> 3
A20: =COUNTIF(B:B,B20) -> 1 | B20: 上海世博中心有限公司 | C20: 上海世博中心，作为上海市机关事务管理局下属国有企业，同样具备了举办展览、会议、活动以及房屋租赁的功能，与上展中心在浦江两岸形成东西呼应的两座上海标志性建筑。上海世博中心以成为世界级的会议中心为目标。世博会期间，其承担了庆典、交流、贵宾接待、新闻发布和指挥运营等重要任务。世博会后，已转型成为大型高规格国际会议的重要场所，一方面承担政务服务功能，成为上海市“两会”及其他政务性会议的重要举办场所；另一方面还要承载社会功能，对市场和社会开放，以其会议、展览、活动（宴会）等专业功能形成核心竞争力，充分展示上海国际大都会形象，提升上海城市的综合竞争力。 | D20: 会展接待服务 | E20: 4 | F20: 初中及以下 | G20: 1.女：身高1.65米以上，专业不限；2.品貌端正、无纹身、对工作有责任心，能吃苦耐劳；3.按照客户要求布置好会场，做好会前的准备工作；4.做好会中接待工作，确保会议有序进行；5.本岗位可招收实习生；6.完成上级安排的其他工作。 | H20: 月薪：5K-9K | I20: =_xlfn.CONCAT(D20,"（学历：",F20," 专业要求：",IF(ISBLANK(M20),"无",M20),"）") -> 会展接待服务（学历：初中及以下 专业要求：无） | J20: =LEN(G20) -> 114 | K20: =_xlfn.XLOOKUP(A20,长度要求!A:A,长度要求!E:E) -> 500 | L20: =IF(J20<K20,G20,LEFT(G20,K20)&"……") -> 1.女：身高1.65米以上，专业不限；2.品貌端正、无纹身、对工作有责任心，能吃苦耐劳；3.按照客户要求布置好会场，做好会前的准备工作；4.做好会中接待工作，确保会议有序进行；5.本岗位可招收实习生；6.完成上级安排的其他工作。 | N20: =LEN(M20) -> 0 | O20: =IF(ISBLANK(M20),0,COUNTA(_xlfn.TEXTSPLIT(M20,","))) -> 0
A21: =COUNTIF(B:B,B21) -> 2 | B21: 上海万厦建筑装饰加固工程有限公司 | C21: 上海万厦建筑装饰加固工程有限公司是一家装饰加固的专业公司，影院建设的集成单位。公司专业配套、工种齐全。具有工艺设计、建声设计、装修设计、结构设计、机电设计以及工程管理与各施工项目经理部。在长期的工程实践中已取得了丰富的经验，形成了设计施工一体化的操作模式，取得了丰硕的业绩。公司自上世纪九十年代至今已先后设计和施工了影剧院、演剧场、文化馆等几百项文化设施项目及公共商业设施项目，取得了良好的社会信誉和业主好评。 | D21: 软件开发设计师 | E21: 2 | F21: 大专 | G21: 技术基础：掌握前端基础技术，包括HTML/CSS/JavaScript，了解ES6及以上语法；熟悉或初步了解小程序开发技术栈（WXML/WXSS），有使用微信开发者工具的基础经验；了解Vue、React等前端框架，或Python、Java等任一后端语言者优先。3.工具与能力：能使用微信开发者工具完成简单代码编写、调试与预览；具备基础的逻辑思维和问题排查能力，能理解简单业务需求并配合完成代码辅助工作；会使用Git等版本控制工具（如GitHub、GitLab）者加分。 | H21: 日薪：150-200/天 | I21: =_xlfn.CONCAT(D21,"（学历：",F21," 专业要求：",IF(ISBLANK(M21),"无",M21),"）") -> 软件开发设计师（学历：大专 专业要求：无） | J21: =LEN(G21) -> 234 | K21: =_xlfn.XLOOKUP(A21,长度要求!A:A,长度要求!E:E) -> 500 | L21: =IF(J21<K21,G21,LEFT(G21,K21)&"……") -> 技术基础：掌握前端基础技术，包括HTML/CSS/JavaScript，了解ES6及以上语法；熟悉或初步了解小程序开发技术栈（WXML/WXSS），有使用微信开发者工具的基础经验；了解Vue、React等前端框架，或Python、Java等任一后端语言者优先。3.工具与能力：能使用微信开发者工具完成简单代码编写、调试与预览；具备基础的逻辑思维和问题排查能力，能理解简单业务需求并配合完成代码辅助工作；会使用Git等版本控制工具（如GitHub、GitLab）者加分。 | N21: =LEN(M21) -> 0 | O21: =IF(ISBLANK(M21),0,COUNTA(_xlfn.TEXTSPLIT(M21,","))) -> 0
A22: =COUNTIF(B:B,B22) -> 2 | B22: 上海万厦建筑装饰加固工程有限公司 | C22: 上海万厦建筑装饰加固工程有限公司是一家装饰加固的专业公司，影院建设的集成单位。公司专业配套、工种齐全。具有工艺设计、建声设计、装修设计、结构设计、机电设计以及工程管理与各施工项目经理部。在长期的工程实践中已取得了丰富的经验，形成了设计施工一体化的操作模式，取得了丰硕的业绩。公司自上世纪九十年代至今已先后设计和施工了影剧院、演剧场、文化馆等几百项文化设施项目及公共商业设施项目，取得了良好的社会信誉和业主好评。 | D22: 装饰设计 | E22: 5 | F22: 大专 | G22: 软件技能：熟练使用CAD（绘制平面图、施工图）、SketchUp（基础建模），掌握3DMax/Blender（建模）、Photoshop（效果图后期）者优先。具备基础的空间布局、色彩搭配审美；了解常见装饰材料（如板材、涂料）、施工工艺基础知识者。 | H22: 日薪：150-200/天 | I22: =_xlfn.CONCAT(D22,"（学历：",F22," 专业要求：",IF(ISBLANK(M22),"无",M22),"）") -> 装饰设计（学历：大专 专业要求：无） | J22: =LEN(G22) -> 123 | K22: =_xlfn.XLOOKUP(A22,长度要求!A:A,长度要求!E:E) -> 500 | L22: =IF(J22<K22,G22,LEFT(G22,K22)&"……") -> 软件技能：熟练使用CAD（绘制平面图、施工图）、SketchUp（基础建模），掌握3DMax/Blender（建模）、Photoshop（效果图后期）者优先。具备基础的空间布局、色彩搭配审美；了解常见装饰材料（如板材、涂料）、施工工艺基础知识者。 | N22: =LEN(M22) -> 0 | O22: =IF(ISBLANK(M22),0,COUNTA(_xlfn.TEXTSPLIT(M22,","))) -> 0
A23: =COUNTIF(B:B,B23) -> 3 | B23: 上海云众名远信息技术有限公司 | C23: 上海云众专注于移动互联网整合营销，汇集了全国数家移动媒体，是360在上海地区的优秀代理商。为客户提供全渠道“一对一”顾问式的定制服务方案，利用深度数据分析挖掘工具、可视化报表处理功能、高精度的实时用户画像，先进的搜索引擎技术实施精准投放广告，从广告主企业实际需求的出发，实现企业网络营销效果，提高广告转化效果。基于360AI大模型，提供元宇宙定制、AI数字人智能化业务定制服务，致力于通过前沿科技为企业提供数字化营销管理专属解决方案，助力企业获客提效。 | D23: 广告运营专员 | E23: 3 | F23: 大专 | G23: 岗位职责：1、与客户沟通，及时了解客户需求和广告投放计划；2、根据客户产品制定投放策略，指导客户有效执行；3、对广告投放进行效果监控，及时反馈，并定期制定数据分析报告；4、跟进续费事宜，维护客户关系，确保客户长期合作；5、定期拜访客户，了解需求和效果，以便做账户优化和调整。任职要求：1、专业不限，积极主动，执行力强，踏实稳定，有强烈责任心和沟通能力；2、能熟练运用excel、PPT等办公软件；3、实习生可免费提供住宿，可转正。 | H23: 月薪：4K-6K | I23: =_xlfn.CONCAT(D23,"（学历：",F23," 专业要求：",IF(ISBLANK(M23),"无",M23),"）") -> 广告运营专员（学历：大专 专业要求：无） | J23: =LEN(G23) -> 215 | K23: =_xlfn.XLOOKUP(A23,长度要求!A:A,长度要求!E:E) -> 500 | L23: =IF(J23<K23,G23,LEFT(G23,K23)&"……") -> 岗位职责：1、与客户沟通，及时了解客户需求和广告投放计划；2、根据客户产品制定投放策略，指导客户有效执行；3、对广告投放进行效果监控，及时反馈，并定期制定数据分析报告；4、跟进续费事宜，维护客户关系，确保客户长期合作；5、定期拜访客户，了解需求和效果，以便做账户优化和调整。任职要求：1、专业不限，积极主动，执行力强，踏实稳定，有强烈责任心和沟通能力；2、能熟练运用excel、PPT等办公软件；3、实习生可免费提供住宿，可转正。 | N23: =LEN(M23) -> 0 | O23: =IF(ISBLANK(M23),0,COUNTA(_xlfn.TEXTSPLIT(M23,","))) -> 0
A24: =COUNTIF(B:B,B24) -> 3 | B24: 上海三客友文化传播有限公司 | C24: 公司成立于2021年04月01日，其创始人以及各合伙人均在本行业耕耘十余年，具有相当的专业能力以及行业分析力。现主营业务为全国各大行业展会行业头部展商展台的现场运营和各大知名品牌的线下推广活动以及国企央企等上市企业宣传片拍摄、短视频制作及新媒体运营等。服务企业有中国铁路局上海工务段、中粮集团、龙湖地产、奔驰、北汽、吉利、极狐、松下、尼康、三菱电机、丰收日集团、花嫁丽舍、沙田物业、上海婚庆行业协会等等。现由于公司业务扩张，望有意向的同行业有志青年及对广告会展行业有兴趣的小伙伴加入团队。 | D24: 会展项目执行及管理 | E24: 2 | F24: 大专 | G24: 1.项目策划与执行：参与展会项目的策划，包括但不限于确定展会主题、制定展会流程、安排展会时间表等，确保项目从策划到执行的顺利进行。2.沟通协调：与各部门、参展商、供应商等建立有效的沟通机制，确保信息的准确传达和项目的顺利推进。3.现场管理：在展会期间，负责现场的协调与管理工作，确保展会现场的秩序和安全。4.数据分析与报告：收集展会相关数据，进行分析并撰写报告，为公司的决策提供有力支持。岗位要求：展会现场执行、并辅助项目经理做好向下内部管理工作，例如：各类人员招募、礼品物料整理、了解基础搭建及制作知识，简单制作统计表等；具有一定的社交能力。 | H24: 月薪：5K-8K | I24: =_xlfn.CONCAT(D24,"（学历：",F24," 专业要求：",IF(ISBLANK(M24),"无",M24),"）") -> 会展项目执行及管理（学历：大专 专业要求：无） | J24: =LEN(G24) -> 272 | K24: =_xlfn.XLOOKUP(A24,长度要求!A:A,长度要求!E:E) -> 500 | L24: =IF(J24<K24,G24,LEFT(G24,K24)&"……") -> 1.项目策划与执行：参与展会项目的策划，包括但不限于确定展会主题、制定展会流程、安排展会时间表等，确保项目从策划到执行的顺利进行。2.沟通协调：与各部门、参展商、供应商等建立有效的沟通机制，确保信息的准确传达和项目的顺利推进。3.现场管理：在展会期间，负责现场的协调与管理工作，确保展会现场的秩序和安全。4.数据分析与报告：收集展会相关数据，进行分析并撰写报告，为公司的决策提供有力支持。岗位要求：展会现场执行、并辅助项目经理做好向下内部管理工作，例如：各类人员招募、礼品物料整理、了解基础搭建及制作知识，简单制作统计表等；具有一定的社交能力。 | N24: =LEN(M24) -> 0 | O24: =IF(ISBLANK(M24),0,COUNTA(_xlfn.TEXTSPLIT(M24,","))) -> 0
A25: =COUNTIF(B:B,B25) -> 3 | B25: 上海明华智慧城市运营管理有限公司 | C25: 上海明华智慧城市运营管理有限公司（简称明华）成立于1992年8月，为上海市最早获得国家物业管理一级资质企业之一。近三十年来，明华始终秉承“快乐服务，追求卓越”的服务理念，不走寻常路，差异发展、创新经营，先人一步走出了一条“公众物业管理”的探索之路；在个性化、人性化、国际化理念的指引下，通过量身定制的服务研发和产品输出，成为物业行业中公众物业管理领域的领先者。在公众物业管理领域，明华在上海乃至国内外具有影响力的主要项目如下：公众展览场馆——中华艺术宫、上海科技馆、上海自然博物馆、上海历史博物馆等公众演艺场馆——上海交响乐团、上海京剧院乐团、上海京剧院传习馆等公众体育场馆——上海网球中心公众交通枢纽——磁浮列车龙阳路站公众绿地公园——上海辰山植物园、上海动物园金融园区——中国人寿保险数据中心大学校园——上海交通大学、华东理工大学闵行校区高端写字楼——航汇大厦 | D25: 展馆管理 | E25: 10 | F25: 大专 | G25: 岗位职责1.学习了解场馆内容主题，整理讲解词，向游客进行解说工作；2.负责场馆内指引接待工作，维护参观秩序；3.协助做好团队的其他工作。任职资格1.有亲和力，形象气质佳；2.有较强的语言表达能力，普通话标准；3.熟练掌握办公软件操作能力。 | H25: 月薪：4K-5K | I25: =_xlfn.CONCAT(D25,"（学历：",F25," 专业要求：",IF(ISBLANK(M25),"无",M25),"）") -> 展馆管理（学历：大专 专业要求：无） | J25: =LEN(G25) -> 119 | K25: =_xlfn.XLOOKUP(A25,长度要求!A:A,长度要求!E:E) -> 500 | L25: =IF(J25<K25,G25,LEFT(G25,K25)&"……") -> 岗位职责1.学习了解场馆内容主题，整理讲解词，向游客进行解说工作；2.负责场馆内指引接待工作，维护参观秩序；3.协助做好团队的其他工作。任职资格1.有亲和力，形象气质佳；2.有较强的语言表达能力，普通话标准；3.熟练掌握办公软件操作能力。 | N25: =LEN(M25) -> 0 | O25: =IF(ISBLANK(M25),0,COUNTA(_xlfn.TEXTSPLIT(M25,","))) -> 0
A26: =COUNTIF(B:B,B26) -> 2 | B26: 予童家庭服务（上海）有限公司 | C26: 予童家庭服务（BabyNanny），以“重塑美好育儿生态”为使命，专注为高净值家庭提供育婴照护、婴儿早教、孩童陪伴等服务。作为高标准母婴护理及高质量家庭服务的坚定笃行者，予童为同样追求育儿品质的家庭，定制集育婴护理、入户指导和社群体验“三维一体”的婴童成长呵护方案，让育儿回归优雅和从容。以“百里挑一”的严苛标准遴选育婴师，打造迎合高端家庭需求的培塑实训，冀期予童的每一名育婴师，都能成为宝宝的温情暖手、宝妈的得力助手、家庭的坚实帮手。 | D26: 家庭育婴师 | E26: 10 | F26: 大专 | G26: 一、工作地点上海全市二、岗位职责-全面负责新生儿的生活照料，涵盖喂养、洗澡、抚触、更换尿布等环节，保障宝宝的清洁与舒适。-密切留意宝宝的生长发育状况，诸如身高、体重、睡眠、大小便等方面，一旦察觉异常立即向家长或医生反馈。-依据宝宝的年龄及发展阶段，精心制定科学合理的喂养计划与作息时间表，悉心培养宝宝良好的生活习惯。-开展早期教育与启蒙工作，借助游戏、互动等多种方式，推动宝宝的认知、语言、运动以及社交能力的发展。-承担宝宝衣物、用品的清洗与消毒工作，确保宝宝生活环境的整洁与卫生。-与家长保持高效且良好的沟通，深入了解家长的需求与关注重点，给予专业的育婴建议和指导。-协助家长妥善处理宝宝的其他相关事务，像就医、接种疫苗等。三、任职要求需要会做饭。持有专业的育婴师资格证书，例如育婴员职业资格证书等优先。具有早教中心、托育园、幼儿园实习经验者优先。对婴幼儿事业充满热爱，拥有爱心、耐心和责任心，具备良好的职业道德和素养。具备出色的沟通能力和团队协作精神，能够与家长及其他工作人员构建起良好的关系。身体健康，拥有良好的心理素质和抗压能力。具有一定的学习和创新能力，能够持续更新育婴知识和技能。 | H26: 日薪：80-150/天 | I26: =_xlfn.CONCAT(D26,"（学历：",F26," 专业要求：",IF(ISBLANK(M26),"无",M26),"）") -> 家庭育婴师（学历：大专 专业要求：护理,学前教育,助产） | J26: =LEN(G26) -> 496 | K26: =_xlfn.XLOOKUP(A26,长度要求!A:A,长度要求!E:E) -> 500 | L26: =IF(J26<K26,G26,LEFT(G26,K26)&"……") -> 一、工作地点上海全市二、岗位职责-全面负责新生儿的生活照料，涵盖喂养、洗澡、抚触、更换尿布等环节，保障宝宝的清洁与舒适。-密切留意宝宝的生长发育状况，诸如身高、体重、睡眠、大小便等方面，一旦察觉异常立即向家长或医生反馈。-依据宝宝的年龄及发展阶段，精心制定科学合理的喂养计划与作息时间表，悉心培养宝宝良好的生活习惯。-开展早期教育与启蒙工作，借助游戏、互动等多种方式，推动宝宝的认知、语言、运动以及社交能力的发展。-承担宝宝衣物、用品的清洗与消毒工作，确保宝宝生活环境的整洁与卫生。-与家长保持高效且良好的沟通，深入了解家长的需求与关注重点，给予专业的育婴建议和指导。-协助家长妥善处理宝宝的其他相关事务，像就医、接种疫苗等。三、任职要求需要会做饭。持有专业的育婴师资格证书，例如育婴员职业资格证书等优先。具有早教中心、托育园、幼儿园实习经验者优先。对婴幼儿事业充满热爱，拥有爱心、耐心和责任心，具备良好的职业道德和素养。具备出色的沟通能力和团队协作精神，能够与家长及其他工作人员构建起良好的关系。身体健康，拥有良好的心理素质和抗压能力。具有一定的学习和创新能力，能够持续更新育婴知识和技能。 | M26: 护理,学前教育,助产 | N26: =LEN(M26) -> 10 | O26: =IF(ISBLANK(M26),0,COUNTA(_xlfn.TEXTSPLIT(M26,","))) -> 3
A27: =COUNTIF(B:B,B27) -> 3 | B27: 上海明华智慧城市运营管理有限公司 | C27: 上海明华智慧城市运营管理有限公司（简称明华）成立于1992年8月，为上海市最早获得国家物业管理一级资质企业之一。近三十年来，明华始终秉承“快乐服务，追求卓越”的服务理念，不走寻常路，差异发展、创新经营，先人一步走出了一条“公众物业管理”的探索之路；在个性化、人性化、国际化理念的指引下，通过量身定制的服务研发和产品输出，成为物业行业中公众物业管理领域的领先者。在公众物业管理领域，明华在上海乃至国内外具有影响力的主要项目如下：公众展览场馆——中华艺术宫、上海科技馆、上海自然博物馆、上海历史博物馆等公众演艺场馆——上海交响乐团、上海京剧院乐团、上海京剧院传习馆等公众体育场馆——上海网球中心公众交通枢纽——磁浮列车龙阳路站公众绿地公园——上海辰山植物园、上海动物园金融园区——中国人寿保险数据中心大学校园——上海交通大学、华东理工大学闵行校区高端写字楼——航汇大厦 | D27: 行政助理 | E27: 2 | F27: 大专 | G27: 岗位职责在带教人指导下，协助完成日常行政事务、文档处理、信息整理及基础沟通协调工作，同时熟悉办公流程与职场规范，提升基础办公技能。1.文档处理与资料管理-协助进行文档的录入、排版、打印、复印与装订，确保文档格式规范、内容准确。-参与资料的整理与归档，2.日常行政事务协助-负责办公区域的基础后勤支持，如整理办公环境、补充办公用品（笔、纸、打印机耗材等）、登记领用情况。-协助接待来访人员，做好引导、登记，通知相关同事对接；3.信息整理与数据统计-协助收集、整理各类基础信息，按照要求进行简单的分类与汇总。-及时更新基础信息台账，保证信息的时效性。4.沟通协调与事务跟进-协助在部门内部或跨部门间传递文件、传达简单通知，确保信息传递及时。-跟进简单事务的进展（如待办事项、任务反馈等），并向带教人或上级汇报进度。任职资格1.仔细认真，沟通协调能力较强；2.办公软件熟练；3.有意向在物业行业长期发展者优先。 | H27: 月薪：5K-6K | I27: =_xlfn.CONCAT(D27,"（学历：",F27," 专业要求：",IF(ISBLANK(M27),"无",M27),"）") -> 行政助理（学历：大专 专业要求：无） | J27: =LEN(G27) -> 402 | K27: =_xlfn.XLOOKUP(A27,长度要求!A:A,长度要求!E:E) -> 500 | L27: =IF(J27<K27,G27,LEFT(G27,K27)&"……") -> 岗位职责在带教人指导下，协助完成日常行政事务、文档处理、信息整理及基础沟通协调工作，同时熟悉办公流程与职场规范，提升基础办公技能。1.文档处理与资料管理-协助进行文档的录入、排版、打印、复印与装订，确保文档格式规范、内容准确。-参与资料的整理与归档，2.日常行政事务协助-负责办公区域的基础后勤支持，如整理办公环境、补充办公用品（笔、纸、打印机耗材等）、登记领用情况。-协助接待来访人员，做好引导、登记，通知相关同事对接；3.信息整理与数据统计-协助收集、整理各类基础信息，按照要求进行简单的分类与汇总。-及时更新基础信息台账，保证信息的时效性。4.沟通协调与事务跟进-协助在部门内部或跨部门间传递文件、传达简单通知，确保信息传递及时。-跟进简单事务的进展（如待办事项、任务反馈等），并向带教人或上级汇报进度。任职资格1.仔细认真，沟通协调能力较强；2.办公软件熟练；3.有意向在物业行业长期发展者优先。 | N27: =LEN(M27) -> 0 | O27: =IF(ISBLANK(M27),0,COUNTA(_xlfn.TEXTSPLIT(M27,","))) -> 0
A28: =COUNTIF(B:B,B28) -> 2 | B28: 中国电信股份有限公司上海莘闵电信局 | C28: 中国电信股份有限公司上海莘闵电信局坐落于闵行区莘东路199号，简称莘闵电信局。前身为上海市电话局莘闵区局。2000年7月1日，中国电信集团上海市电信公司成立后，更名为上海市电信公司莘闵电信局；2008年3月，更名为中国电信股份有限公司上海莘闵电信局。中国电信股份有限公司上海莘闵电信局提供固定电话、移动通信、宽带互联网接入、互联网电视、卫星通信、信息化应用等泛在网络和综合智能信息服务能力，服务闵行区内各类客户，始终保持区域内通信市场的领先地位。莘闵电信局以党的建设统领企业发展全局，以改革创新为动力，加快推进"网络智能化、业务生态化和运营智慧化"，积极构建"五大业务"生态圈，努力做领先的综合智能信息服务运营商,为闵行区经济发展和网络强国建设做出更大贡献，助推闵行区信息化及经济高速增长。 | D28: 门店经理见习生 | E28: 30 | F28: 大专 | G28: 电信门店的整体运营与业绩达成，核心涵盖经营指标、团队管理、客户服务、营销与渠道协同、合规与风险控制等关键模块。 | H28: 日薪：80-150/天 | I28: =_xlfn.CONCAT(D28,"（学历：",F28," 专业要求：",IF(ISBLANK(M28),"无",M28),"）") -> 门店经理见习生（学历：大专 专业要求：无） | J28: =LEN(G28) -> 55 | K28: =_xlfn.XLOOKUP(A28,长度要求!A:A,长度要求!E:E) -> 500 | L28: =IF(J28<K28,G28,LEFT(G28,K28)&"……") -> 电信门店的整体运营与业绩达成，核心涵盖经营指标、团队管理、客户服务、营销与渠道协同、合规与风险控制等关键模块。 | N28: =LEN(M28) -> 0 | O28: =IF(ISBLANK(M28),0,COUNTA(_xlfn.TEXTSPLIT(M28,","))) -> 0
A29: =COUNTIF(B:B,B29) -> 4 | B29: 上海樱帆望文化传媒有限公司 | C29: 樱帆电竞成立于2015年8月，以电竞赛事组织策划执行和直转播节目制作为业务核心。赛事组织板块已经完成过2018年雅加达亚运会、2018-2019年WESG全球总决赛、2019-2024OPL职业联赛等各类国内外高级别比赛的赛事组织工作，时至今日樱帆电竞已经完成超过500个游戏项目赛事组织执行工作。2021年公司成立直转播节目制作业务板块，完成了征途全民争霸赛总决赛暨年终盛典、三届永劫无间高校总决赛、剑网3竞技群英赛、DCDC冠军联赛、实况足球世总赛、影之诗联赛、漫威争锋冠军杯、SCS年度总决赛、蛋仔派对高校总决赛、剑网3竞技大师赛等在内的上百个大型项目的直转播节目制作工作。目前在上海拥有包括1个制播中心及5套演播棚在内的1500平专业节目制播场地以及一个技术中心、一个创意中心，专业服务于各类电竞赛事及泛娱乐节目制作。 | D29: 电竞赛事直转播播控岗位实习生 | E29: 2 | F29: 大专 | G29: 一、职位概述参与电竞赛事直转播工作，协助专业团队确保赛事直播的顺利进行。二、主要职责1.直播协助●深度参与电竞赛事直转播过程中的播控操作工作，包括但不限于设备的开启与关闭、信号切换、画面调整等。●密切监控直播信号，及时发现并反馈直播中的异常情况，确保直播质量。2.学习提升●学习电竞赛事直转播的流程和技术，熟悉各类播控设备的使用。●参加内部培训，提升专业技能和对电竞行业的认知。3.资料整理●整理电竞赛事直转播相关的技术资料和数据记录。●协助撰写简单的直播报告。4.播控任务●完成上级交办的其他与电竞赛事直转播播控相关的工作。内容包含但不限于导播切台、VCR、字幕机等。三、任职要求1.专业背景●传媒、广播电视、数字媒体技术、电子竞技等相关专业优先。2.技能要求●具备一定的计算机操作能力，熟悉常用办公软件。●对电竞有浓厚兴趣，了解电竞赛事直播特点，需要有一定的相关经验(社团、兼职等均可)。3.态度品质●工作认真负责，细心耐心，有较强的学习能力和团队合作精神。4.学历要求●大专以上学历，26届27届毕业生优先。 | H29: 日薪：150-200/天 | I29: =_xlfn.CONCAT(D29,"（学历：",F29," 专业要求：",IF(ISBLANK(M29),"无",M29),"）") -> 电竞赛事直转播播控岗位实习生（学历：大专 专业要求：广播电视学,广播电视,广播影视节目制作,广播电视编导） | J29: =LEN(G29) -> 457 | K29: =_xlfn.XLOOKUP(A29,长度要求!A:A,长度要求!E:E) -> 500 | L29: =IF(J29<K29,G29,LEFT(G29,K29)&"……") -> 一、职位概述参与电竞赛事直转播工作，协助专业团队确保赛事直播的顺利进行。二、主要职责1.直播协助●深度参与电竞赛事直转播过程中的播控操作工作，包括但不限于设备的开启与关闭、信号切换、画面调整等。●密切监控直播信号，及时发现并反馈直播中的异常情况，确保直播质量。2.学习提升●学习电竞赛事直转播的流程和技术，熟悉各类播控设备的使用。●参加内部培训，提升专业技能和对电竞行业的认知。3.资料整理●整理电竞赛事直转播相关的技术资料和数据记录。●协助撰写简单的直播报告。4.播控任务●完成上级交办的其他与电竞赛事直转播播控相关的工作。内容包含但不限于导播切台、VCR、字幕机等。三、任职要求1.专业背景●传媒、广播电视、数字媒体技术、电子竞技等相关专业优先。2.技能要求●具备一定的计算机操作能力，熟悉常用办公软件。●对电竞有浓厚兴趣，了解电竞赛事直播特点，需要有一定的相关经验(社团、兼职等均可)。3.态度品质●工作认真负责，细心耐心，有较强的学习能力和团队合作精神。4.学历要求●大专以上学历，26届27届毕业生优先。 | M29: 广播电视学,广播电视,广播影视节目制作,广播电视编导 | N29: =LEN(M29) -> 26 | O29: =IF(ISBLANK(M29),0,COUNTA(_xlfn.TEXTSPLIT(M29,","))) -> 4
A30: =COUNTIF(B:B,B30) -> 4 | B30: 上海樱帆望文化传媒有限公司 | C30: 樱帆电竞成立于2015年8月，以电竞赛事组织策划执行和直转播节目制作为业务核心。赛事组织板块已经完成过2018年雅加达亚运会、2018-2019年WESG全球总决赛、2019-2024OPL职业联赛等各类国内外高级别比赛的赛事组织工作，时至今日樱帆电竞已经完成超过500个游戏项目赛事组织执行工作。2021年公司成立直转播节目制作业务板块，完成了征途全民争霸赛总决赛暨年终盛典、三届永劫无间高校总决赛、剑网3竞技群英赛、DCDC冠军联赛、实况足球世总赛、影之诗联赛、漫威争锋冠军杯、SCS年度总决赛、蛋仔派对高校总决赛、剑网3竞技大师赛等在内的上百个大型项目的直转播节目制作工作。目前在上海拥有包括1个制播中心及5套演播棚在内的1500平专业节目制播场地以及一个技术中心、一个创意中心，专业服务于各类电竞赛事及泛娱乐节目制作。 | D30: 电竞赛事实习导演 | E30: 2 | F30: 大专 | G30: 岗位概述：作为公司导演及创意方向的核心管培生，你将参与到行业细分领域最头部的各项电竞赛事及内容节目的全流程导演工作中。我们希望你具备自主学习、钻研创新、吃苦耐劳的优秀品质和能力，对游戏和电竞内容抱有浓厚兴趣与较高审美。公司会针对管培安排包含培训、考核、轮岗等多样化的培养计划，并对表现优秀者优先招聘录用。一、岗位职责：1.【创意策划】：协助总导演对接产品相关的线上线下活动的前期创意策划，能够根据客户的需求，协助分析赛事或活动举办的底层逻辑；2.【筹备推进】：根据策划方案，协助总导演深化产出流程RD、视觉包装设计等创意落地方案，协助并确保各项产出匹配预期规划，保证项目顺利完成；3.【沟通协作】：协助总导演做好内外部的沟通管理与协调工作。在跨部门协作中，能够帮助总导演做到及时高效精准的信息沟通，保持各部门之间良好持久的协作关系，有效帮助工作推进。熟练掌握英/日/韩等外语书面及口语沟通能力者加分；4.【落地执行】：赛事/活动执行的彩排与直播期间，协助总导演完成现场的执行导演工作；5【复盘总结】：协助总导演对完成项目进行总结复盘，系统化整理与分享经验。二、任职要求:1.大专及以上学历，影视编导、新闻传播、电竞赛事等相关专业优先；2.热爱电子竞技，了解电竞产业，对某一类游戏产品及主流电竞赛事有较深理解，游戏高段位或游戏高时长将为加分项；3.具有较好的时间管理及多任务规划能力，拥有敏锐的洞察力能对市场和客户做出一定判断；4.思维活跃、创意十足、善于表达、逻辑思考能力强、有较好的审美及文案能力，抗压性好，具备平面三维设计、视频后期剪辑能力，熟练AI工具使用者优先；5.实习期间将重点参与格斗类赛道最头部产品的全球顶级赛事筹备和全流程制作。 | H30: 日薪：150-200/天 | I30: =_xlfn.CONCAT(D30,"（学历：",F30," 专业要求：",IF(ISBLANK(M30),"无",M30),"）") -> 电竞赛事实习导演（学历：大专 专业要求：影视编导,新闻传播学类,新闻与传播,新闻传播学） | J30: =LEN(G30) -> 722 | K30: =_xlfn.XLOOKUP(A30,长度要求!A:A,长度要求!E:E) -> 500 | L30: =IF(J30<K30,G30,LEFT(G30,K30)&"……") -> 岗位概述：作为公司导演及创意方向的核心管培生，你将参与到行业细分领域最头部的各项电竞赛事及内容节目的全流程导演工作中。我们希望你具备自主学习、钻研创新、吃苦耐劳的优秀品质和能力，对游戏和电竞内容抱有浓厚兴趣与较高审美。公司会针对管培安排包含培训、考核、轮岗等多样化的培养计划，并对表现优秀者优先招聘录用。一、岗位职责：1.【创意策划】：协助总导演对接产品相关的线上线下活动的前期创意策划，能够根据客户的需求，协助分析赛事或活动举办的底层逻辑；2.【筹备推进】：根据策划方案，协助总导演深化产出流程RD、视觉包装设计等创意落地方案，协助并确保各项产出匹配预期规划，保证项目顺利完成；3.【沟通协作】：协助总导演做好内外部的沟通管理与协调工作。在跨部门协作中，能够帮助总导演做到及时高效精准的信息沟通，保持各部门之间良好持久的协作关系，有效帮助工作推进。熟练掌握英/日/韩等外语书面及口语沟通能力者加分；4.【落地执行】：赛事/活动执行的彩排与直播期间，协助总导演完成现场的执行导演工作；5【复盘总结】：协助总导演对完成项目进行总结复盘，系统化整理与分享经验。二、任职要求:1.大专及以上学历，影视编导、…… | M30: 影视编导,新闻传播学类,新闻与传播,新闻传播学 | N30: =LEN(M30) -> 23 | O30: =IF(ISBLANK(M30),0,COUNTA(_xlfn.TEXTSPLIT(M30,","))) -> 4
A31: =COUNTIF(B:B,B31) -> 2 | B31: 中国电信股份有限公司上海莘闵电信局 | C31: 中国电信股份有限公司上海莘闵电信局坐落于闵行区莘东路199号，简称莘闵电信局。前身为上海市电话局莘闵区局。2000年7月1日，中国电信集团上海市电信公司成立后，更名为上海市电信公司莘闵电信局；2008年3月，更名为中国电信股份有限公司上海莘闵电信局。中国电信股份有限公司上海莘闵电信局提供固定电话、移动通信、宽带互联网接入、互联网电视、卫星通信、信息化应用等泛在网络和综合智能信息服务能力，服务闵行区内各类客户，始终保持区域内通信市场的领先地位。莘闵电信局以党的建设统领企业发展全局，以改革创新为动力，加快推进"网络智能化、业务生态化和运营智慧化"，积极构建"五大业务"生态圈，努力做领先的综合智能信息服务运营商,为闵行区经济发展和网络强国建设做出更大贡献，助推闵行区信息化及经济高速增长。 | D31: 装维见习生 | E31: 30 | F31: 大专 | G31: 电信宽带、固定电话、IPTV等电信业务的安装与故障维修，同时承担客户沟通与网络简单维护任务。 | H31: 日薪：80-150/天 | I31: =_xlfn.CONCAT(D31,"（学历：",F31," 专业要求：",IF(ISBLANK(M31),"无",M31),"）") -> 装维见习生（学历：大专 专业要求：无） | J31: =LEN(G31) -> 46 | K31: =_xlfn.XLOOKUP(A31,长度要求!A:A,长度要求!E:E) -> 500 | L31: =IF(J31<K31,G31,LEFT(G31,K31)&"……") -> 电信宽带、固定电话、IPTV等电信业务的安装与故障维修，同时承担客户沟通与网络简单维护任务。 | N31: =LEN(M31) -> 0 | O31: =IF(ISBLANK(M31),0,COUNTA(_xlfn.TEXTSPLIT(M31,","))) -> 0
A32: =COUNTIF(B:B,B32) -> 4 | B32: 上海樱帆望文化传媒有限公司 | C32: 樱帆电竞成立于2015年8月，以电竞赛事组织策划执行和直转播节目制作为业务核心。赛事组织板块已经完成过2018年雅加达亚运会、2018-2019年WESG全球总决赛、2019-2024OPL职业联赛等各类国内外高级别比赛的赛事组织工作，时至今日樱帆电竞已经完成超过500个游戏项目赛事组织执行工作。2021年公司成立直转播节目制作业务板块，完成了征途全民争霸赛总决赛暨年终盛典、三届永劫无间高校总决赛、剑网3竞技群英赛、DCDC冠军联赛、实况足球世总赛、影之诗联赛、漫威争锋冠军杯、SCS年度总决赛、蛋仔派对高校总决赛、剑网3竞技大师赛等在内的上百个大型项目的直转播节目制作工作。目前在上海拥有包括1个制播中心及5套演播棚在内的1500平专业节目制播场地以及一个技术中心、一个创意中心，专业服务于各类电竞赛事及泛娱乐节目制作。 | D32: 电竞赛事执行 | E32: 2 | F32: 大专 | G32: 一、游戏硬性要求：包括但不限于以下两款游戏，可接受入职之后再熟悉拳皇KOF全系列【1、拳皇KOF全系列（97-15均可），街霸6，铁拳等游戏，以上游戏单产品游戏时长50小时以上】【2、瓦罗兰特，游戏段位要求达到超凡】二、岗位要求：1、有拳皇系列&街霸6等格斗游戏经验的优先；2、有国内城市办赛经验者优先；3、熟练excel、word、PPT等日常办公软件；4、熟悉市场主流游戏的游戏机制和赛事规则；5、具有一定沟通、抗压能力，擅长对接及协助工作；三、任职要求1.专业背景●传媒、广播电视、数字媒体技术、电子竞技等相关专业优先。2.技能要求●具备一定的计算机操作能力，熟悉常用办公软件。●对电竞有浓厚兴趣，了解电竞赛事直播特点。3.态度品质●工作认真负责，细心耐心，有较强的学习能力和团队合作精神。4.学历要求●大专以上学历，26届27届毕业生优先。小贴士：公司比较看重岗位匹配度，同时也致力于挖掘每一位求职者的潜在能力，让大家能在最适合的岗位上发光发热。 | H32: 日薪：150-200/天 | I32: =_xlfn.CONCAT(D32,"（学历：",F32," 专业要求：",IF(ISBLANK(M32),"无",M32),"）") -> 电竞赛事执行（学历：大专 专业要求：体育学类,广播影视节目制作,文化服务类,广告学） | J32: =LEN(G32) -> 427 | K32: =_xlfn.XLOOKUP(A32,长度要求!A:A,长度要求!E:E) -> 500 | L32: =IF(J32<K32,G32,LEFT(G32,K32)&"……") -> 一、游戏硬性要求：包括但不限于以下两款游戏，可接受入职之后再熟悉拳皇KOF全系列【1、拳皇KOF全系列（97-15均可），街霸6，铁拳等游戏，以上游戏单产品游戏时长50小时以上】【2、瓦罗兰特，游戏段位要求达到超凡】二、岗位要求：1、有拳皇系列&街霸6等格斗游戏经验的优先；2、有国内城市办赛经验者优先；3、熟练excel、word、PPT等日常办公软件；4、熟悉市场主流游戏的游戏机制和赛事规则；5、具有一定沟通、抗压能力，擅长对接及协助工作；三、任职要求1.专业背景●传媒、广播电视、数字媒体技术、电子竞技等相关专业优先。2.技能要求●具备一定的计算机操作能力，熟悉常用办公软件。●对电竞有浓厚兴趣，了解电竞赛事直播特点。3.态度品质●工作认真负责，细心耐心，有较强的学习能力和团队合作精神。4.学历要求●大专以上学历，26届27届毕业生优先。小贴士：公司比较看重岗位匹配度，同时也致力于挖掘每一位求职者的潜在能力，让大家能在最适合的岗位上发光发热。 | M32: 体育学类,广播影视节目制作,文化服务类,广告学 | N32: =LEN(M32) -> 23 | O32: =IF(ISBLANK(M32),0,COUNTA(_xlfn.TEXTSPLIT(M32,","))) -> 4
A33: =COUNTIF(B:B,B33) -> 4 | B33: 上海樱帆望文化传媒有限公司 | C33: 樱帆电竞成立于2015年8月，以电竞赛事组织策划执行和直转播节目制作为业务核心。赛事组织板块已经完成过2018年雅加达亚运会、2018-2019年WESG全球总决赛、2019-2024OPL职业联赛等各类国内外高级别比赛的赛事组织工作，时至今日樱帆电竞已经完成超过500个游戏项目赛事组织执行工作。2021年公司成立直转播节目制作业务板块，完成了征途全民争霸赛总决赛暨年终盛典、三届永劫无间高校总决赛、剑网3竞技群英赛、DCDC冠军联赛、实况足球世总赛、影之诗联赛、漫威争锋冠军杯、SCS年度总决赛、蛋仔派对高校总决赛、剑网3竞技大师赛等在内的上百个大型项目的直转播节目制作工作。目前在上海拥有包括1个制播中心及5套演播棚在内的1500平专业节目制播场地以及一个技术中心、一个创意中心，专业服务于各类电竞赛事及泛娱乐节目制作。 | D33: 制片助理 | E33: 2 | F33: 大专 | G33: 任职要求​1、专业不限，对影视、广告等行业的制片工作有兴趣者优先；​2、具备清晰的逻辑思维能力，能够有条理地处理多项事务；​3、做事缜密细致，注重细节，有较强的责任心和执行力；​4、具备良好的沟通表达能力，能与团队成员及外部供应商有效协作；​5、熟练使用办公软件（如Word、Excel等），有一定的数据整理能力。岗位职责​1、制片事务执行：协助制片完成项目中与“吃喝住行”相关的各项预定及执行工作，包括但不限于预订拍摄期间的餐饮、住宿、交通等，确保各项安排准确无误，保障项目顺利推进。​2、验收与记录：负责对项目所需物资、服务等进行验收，并按要求进行拍照记录，确保相关资料的完整性和准确性，为后续工作提供可靠依据。​3、辅助结案制作：在项目结案阶段，积极配合团队完成相关资料的整理、汇总等辅助工作，助力顺利产出制作成果。​4、供应商沟通：与各类供应商保持良好沟通，及时传达需求、反馈问题，协调解决合作过程中的相关事宜，维护稳定的合作关系。​5、报销收集整理：负责收集项目相关的各类报销凭证，按照公司规定进行整理、核对，确保报销信息准确、完整。 | H33: 日薪：150-200/天 | I33: =_xlfn.CONCAT(D33,"（学历：",F33," 专业要求：",IF(ISBLANK(M33),"无",M33),"）") -> 制片助理（学历：大专 专业要求：竞赛组织,新闻与传播,项目管理,文化服务类,广播影视类,广播影视节目制作,广告策划与营销） | J33: =LEN(G33) -> 472 | K33: =_xlfn.XLOOKUP(A33,长度要求!A:A,长度要求!E:E) -> 500 | L33: =IF(J33<K33,G33,LEFT(G33,K33)&"……") -> 任职要求​1、专业不限，对影视、广告等行业的制片工作有兴趣者优先；​2、具备清晰的逻辑思维能力，能够有条理地处理多项事务；​3、做事缜密细致，注重细节，有较强的责任心和执行力；​4、具备良好的沟通表达能力，能与团队成员及外部供应商有效协作；​5、熟练使用办公软件（如Word、Excel等），有一定的数据整理能力。岗位职责​1、制片事务执行：协助制片完成项目中与“吃喝住行”相关的各项预定及执行工作，包括但不限于预订拍摄期间的餐饮、住宿、交通等，确保各项安排准确无误，保障项目顺利推进。​2、验收与记录：负责对项目所需物资、服务等进行验收，并按要求进行拍照记录，确保相关资料的完整性和准确性，为后续工作提供可靠依据。​3、辅助结案制作：在项目结案阶段，积极配合团队完成相关资料的整理、汇总等辅助工作，助力顺利产出制作成果。​4、供应商沟通：与各类供应商保持良好沟通，及时传达需求、反馈问题，协调解决合作过程中的相关事宜，维护稳定的合作关系。​5、报销收集整理：负责收集项目相关的各类报销凭证，按照公司规定进行整理、核对，确保报销信息准确、完整。 | M33: 竞赛组织,新闻与传播,项目管理,文化服务类,广播影视类,广播影视节目制作,广告策划与营销 | N33: =LEN(M33) -> 44 | O33: =IF(ISBLANK(M33),0,COUNTA(_xlfn.TEXTSPLIT(M33,","))) -> 7
A34: =COUNTIF(B:B,B34) -> 2 | B34: 上海羊鑫布艺有限公司 | C34: 上海羊鑫布艺有限公司是海派旗袍与新中式文化创新的时尚企业作为上海海派旗袍文化促进会副会长单位,公司以"致知青花"系列为代表,融合传统制衣工艺与现代设计,打造独具东方韵味的高级定制服饰。产品屡获长三角旗袍设计大赛银奖等殊荣,创始人杨玉娟女士获“东方时尚工匠”称号。公司通过时尚闪秀、文化展览等多元化形式,致力于传承和发展海派旗袍文化,推动传统服饰艺术的现代表达与创新发展。 | D34: 打样纸板师 | E34: 1 | F34: 大专 | G34: 【岗位职责】负责服装款式的打板与制版工作：根据设计师提供的效果图、设计稿或样衣，精准制作纸样（含裁剪版、工艺版），确保版型符合设计风格与人体工学。样衣跟进与调整：配合样衣车间完成首件样衣制作，参与样衣试穿评审，根据试穿反馈（如尺寸偏差、版型舒适度）优化纸样，直至样衣合格。工艺文件输出：整理打板数据，制定详细的制版工艺说明（如缝份、缩率、面料特性适配方案），为生产车间提供清晰的技术指导。版型库管理：建立并维护公司版型数据库，分类归档不同款式、尺码的纸样文件，便于后续款式复用与优化。跨部门协作：与设计师、采购部（确认面料特性）、生产部（解决生产中的版型问题）高效配合，确保打板-制版-生产流程顺畅。【任职要求】学历与经验：中专及以上学历，服装相关专业（如服装工程、服装设计），1-3年及以上服装打板/制版经验（应届生可投递助理岗，需熟悉基础打板逻辑）。核心技能：熟练掌握手工打板技巧，能独立完成从净版到毛版的制作；精通制版软件（如富怡、ET、格柏Gerber等），可高效进行数字化制版与纸样修改；了解不同面料特性（如棉、丝、针织、弹力面料）对版型的影响，能针对性调整打板方案；熟悉服装号型标准（如GB/T1335、欧码、美码等），可根据目标市场适配尺码版型。能力素质：细节敏感度强，能精准把控版型尺寸误差（如±0.5cm内）；沟通能力佳，能清晰理解设计需求并反馈技术可行性；有责任心，能按时完成打板任务，配合紧急款式的开发需求 | H34: 月薪：5K-6K | I34: =_xlfn.CONCAT(D34,"（学历：",F34," 专业要求：",IF(ISBLANK(M34),"无",M34),"）") -> 打样纸板师（学历：大专 专业要求：无） | J34: =LEN(G34) -> 614 | K34: =_xlfn.XLOOKUP(A34,长度要求!A:A,长度要求!E:E) -> 500 | L34: =IF(J34<K34,G34,LEFT(G34,K34)&"……") -> 【岗位职责】负责服装款式的打板与制版工作：根据设计师提供的效果图、设计稿或样衣，精准制作纸样（含裁剪版、工艺版），确保版型符合设计风格与人体工学。样衣跟进与调整：配合样衣车间完成首件样衣制作，参与样衣试穿评审，根据试穿反馈（如尺寸偏差、版型舒适度）优化纸样，直至样衣合格。工艺文件输出：整理打板数据，制定详细的制版工艺说明（如缝份、缩率、面料特性适配方案），为生产车间提供清晰的技术指导。版型库管理：建立并维护公司版型数据库，分类归档不同款式、尺码的纸样文件，便于后续款式复用与优化。跨部门协作：与设计师、采购部（确认面料特性）、生产部（解决生产中的版型问题）高效配合，确保打板-制版-生产流程顺畅。【任职要求】学历与经验：中专及以上学历，服装相关专业（如服装工程、服装设计），1-3年及以上服装打板/制版经验（应届生可投递助理岗，需熟悉基础打板逻辑）。核心技能：熟练掌握手工打板技巧，能独立完成从净版到毛版的制作；精通制版软件（如富怡、ET、格柏Gerber等），可高效进行数字化制版与纸样修改；了解不同面料特性（如棉、丝、针织、弹力面料）对版型的影响，能针对性调整打板方案；熟悉服装号型标准（如G…… | N34: =LEN(M34) -> 0 | O34: =IF(ISBLANK(M34),0,COUNTA(_xlfn.TEXTSPLIT(M34,","))) -> 0
A35: =COUNTIF(B:B,B35) -> 4 | B35: 上海天安轴承有限公司 | C35: 上海天安轴承有限公司为上海电气集团旗下上海集优机械有限公司的全资企业，位于上海市闵行区莘庄工业园区银都路4399号，具有60多年的生产历史。公司专业生产具有高精度、高转速、高灵敏度、低噪音、长寿命的微型轴承，并对轴承产品进行技术开发和产品售后服务。产品广泛运用于航空航天、工业装备、汽车医疗等行业，性能达到国际领先水平。近几年公司大力支持国家航天事业，已为“天宫一号”、“神舟五号”、“神州六号”、“神舟七号”、“神州八号”和“绕月探测工程”成功配套，获得了国家有关部门的多次嘉奖。 | D35: 数控操作 | E35: 2 | F35: 大专 | G35: 1、按作业指导书及设备操作规程，正确操作和保养数控机床2、对数控机床进行加工编程、线切割3、做好加工零件的自查，确保加工产品合格率 | H35: 月薪：5K-7K | I35: =_xlfn.CONCAT(D35,"（学历：",F35," 专业要求：",IF(ISBLANK(M35),"无",M35),"）") -> 数控操作（学历：大专 专业要求：无） | J35: =LEN(G35) -> 65 | K35: =_xlfn.XLOOKUP(A35,长度要求!A:A,长度要求!E:E) -> 500 | L35: =IF(J35<K35,G35,LEFT(G35,K35)&"……") -> 1、按作业指导书及设备操作规程，正确操作和保养数控机床2、对数控机床进行加工编程、线切割3、做好加工零件的自查，确保加工产品合格率 | N35: =LEN(M35) -> 0 | O35: =IF(ISBLANK(M35),0,COUNTA(_xlfn.TEXTSPLIT(M35,","))) -> 0
A36: =COUNTIF(B:B,B36) -> 1 | B36: 上海特金信息科技有限公司 | C36: 上海特金创立于2003年，是国家级高新技术企业、国家级专精特新“小巨人”企业、上海市“专精特新”企业，20余年深耕无线电感知和频谱大数据分析技术，致力于提供可信赖的低空安全管控解决方案，在无人机预案、预警、识别、定位、追踪及处置方面处于业界领军地位，是国内将TDOA网格化无人机管控技术进行产品化和大规模商用的发起者。特金拥有一百多项核心知识产权，深度参与国标、行标、团标的标准制定，荣获国际电联ITUTelecomWorld全球最佳创新奖。特金无人机探测定位管制系统服务于建党百周年庆及70周年国庆首都核心区，杭州亚运会、成都大运会、央视春晚等大型活动低空安全保障，被誉为“低空防御专家，家国和平卫士”。 | D36: 助理产品工程师 | E36: 7 | F36: 大专 | G36: 岗位职责：1、通过相关培训能够快速适应生产作业，保证每个产品都是按照工艺要求生产；2、经过培训严格按照工艺要求熟练掌握产品组装、调试、测试；3、严格执行上级领导指派的工作任务；4、严格执行生产安全管理制度；5、遵守6S现场规章制度，保持生产线标准化工作环境；6、负责日常设备问题排查维修并输出维修报告。任职资格：1、机械，机电，电子，电气，通讯，无线电专业等工学专业；2、要求大专学历，应届毕业生或实习生；3、掌握基础电路、机械、钳工专业知识，会简单编程，熟练使用办公软件；4、能够接受不定时加班、户外测试，有驾驶证优先；5、有机械证书或者电工证优先；6、为人正直有较强的团队协助精神、勤奋好学、积极向上、有敬业精神，无不良嗜好。7、能尽快上岗者优先。 | H36: 月薪：5K-8K | I36: =_xlfn.CONCAT(D36,"（学历：",F36," 专业要求：",IF(ISBLANK(M36),"无",M36),"）") -> 助理产品工程师（学历：大专 专业要求：无） | J36: =LEN(G36) -> 326 | K36: =_xlfn.XLOOKUP(A36,长度要求!A:A,长度要求!E:E) -> 500 | L36: =IF(J36<K36,G36,LEFT(G36,K36)&"……") -> 岗位职责：1、通过相关培训能够快速适应生产作业，保证每个产品都是按照工艺要求生产；2、经过培训严格按照工艺要求熟练掌握产品组装、调试、测试；3、严格执行上级领导指派的工作任务；4、严格执行生产安全管理制度；5、遵守6S现场规章制度，保持生产线标准化工作环境；6、负责日常设备问题排查维修并输出维修报告。任职资格：1、机械，机电，电子，电气，通讯，无线电专业等工学专业；2、要求大专学历，应届毕业生或实习生；3、掌握基础电路、机械、钳工专业知识，会简单编程，熟练使用办公软件；4、能够接受不定时加班、户外测试，有驾驶证优先；5、有机械证书或者电工证优先；6、为人正直有较强的团队协助精神、勤奋好学、积极向上、有敬业精神，无不良嗜好。7、能尽快上岗者优先。 | N36: =LEN(M36) -> 0 | O36: =IF(ISBLANK(M36),0,COUNTA(_xlfn.TEXTSPLIT(M36,","))) -> 0
A37: =COUNTIF(B:B,B37) -> 4 | B37: 上海天安轴承有限公司 | C37: 上海天安轴承有限公司为上海电气集团旗下上海集优机械有限公司的全资企业，位于上海市闵行区莘庄工业园区银都路4399号，具有60多年的生产历史。公司专业生产具有高精度、高转速、高灵敏度、低噪音、长寿命的微型轴承，并对轴承产品进行技术开发和产品售后服务。产品广泛运用于航空航天、工业装备、汽车医疗等行业，性能达到国际领先水平。近几年公司大力支持国家航天事业，已为“天宫一号”、“神舟五号”、“神州六号”、“神舟七号”、“神州八号”和“绕月探测工程”成功配套，获得了国家有关部门的多次嘉奖。 | D37: 电气维修 | E37: 2 | F37: 大专 | G37: 负责公司电气故障的排除；对公司内用电的分配、设计及用电管理工作；监督检查变电所管理制度的执行情况及备件管理工作 | H37: 月薪：5K-7K | I37: =_xlfn.CONCAT(D37,"（学历：",F37," 专业要求：",IF(ISBLANK(M37),"无",M37),"）") -> 电气维修（学历：大专 专业要求：无） | J37: =LEN(G37) -> 55 | K37: =_xlfn.XLOOKUP(A37,长度要求!A:A,长度要求!E:E) -> 500 | L37: =IF(J37<K37,G37,LEFT(G37,K37)&"……") -> 负责公司电气故障的排除；对公司内用电的分配、设计及用电管理工作；监督检查变电所管理制度的执行情况及备件管理工作 | N37: =LEN(M37) -> 0 | O37: =IF(ISBLANK(M37),0,COUNTA(_xlfn.TEXTSPLIT(M37,","))) -> 0
A38: =COUNTIF(B:B,B38) -> 2 | B38: 上海科瑞物业管理发展有限公司 | C38: “和我们共创无限可能的未来”上海科瑞物业管理发展有限公司，成立于2002年1月18日，注册资金5000万元。公司致力于成为“成为现代物业服务专业管家”品牌企业，服务于超高层建筑、城市综合体、办公楼、大型住宅、公众项目；以及提供大中小学校区管理、酒店管理和物业顾问等服务。科瑞物业崇尚现代物业管理理念，坚持以人为本、生态平衡的管理服务本质，追求高标准管理、细节化服务、规范化收费、可持续发展，以“一切围绕和谐、创造和谐而奋斗！”作为企业口号既企业管理方针，维护社会、业主、企业三方利益。我们的实力：1）上海市物业管理协会副会长单位；2）上海市物业服务综合百强企业排名第三3）上海市物业管理数量领先企业、物业管理面积领先企业（住宅类、非居类、办公类、学校类）TOP104）进入（外）城市个数领先企业、营业收入领先企业、轨道交通收入领先企业、净利润领先企业、员工总数领先企业TOP105）上市公司的成员企业，从东北长春吉林到南部广东佛山，从西北内蒙古到东部上海都有我们科瑞的足迹你有梦想吗？即使面临现实的社会，残酷的生活，你想在此情形下继续维持梦想吗？你想在繁重的工作之余还有诗和远方吗？你想拥有自由的发展空间吗？加入我们，我们能提供你想要的，你梦想的，与科瑞共同创造未来。 | D38: 智能建筑工程实习生 | E38: 10 | F38: 大专 | G38: 通过参与智能建筑工程全流程（设计辅助、现场实施、调试配合、文档整理等）工作，帮助实习生掌握智能建筑系统（如楼宇自控、安防监控、综合布线等）的基本原理与实际应用，熟悉工程现场管理流程，培养工程实践能力与问题解决意识，为未来从事智能建筑相关工作奠定基础。 | H38: 日薪：80-150/天 | I38: =_xlfn.CONCAT(D38,"（学历：",F38," 专业要求：",IF(ISBLANK(M38),"无",M38),"）") -> 智能建筑工程实习生（学历：大专 专业要求：建筑智能化工程技术） | J38: =LEN(G38) -> 125 | K38: =_xlfn.XLOOKUP(A38,长度要求!A:A,长度要求!E:E) -> 500 | L38: =IF(J38<K38,G38,LEFT(G38,K38)&"……") -> 通过参与智能建筑工程全流程（设计辅助、现场实施、调试配合、文档整理等）工作，帮助实习生掌握智能建筑系统（如楼宇自控、安防监控、综合布线等）的基本原理与实际应用，熟悉工程现场管理流程，培养工程实践能力与问题解决意识，为未来从事智能建筑相关工作奠定基础。 | M38: 建筑智能化工程技术 | N38: =LEN(M38) -> 9 | O38: =IF(ISBLANK(M38),0,COUNTA(_xlfn.TEXTSPLIT(M38,","))) -> 1
A39: =COUNTIF(B:B,B39) -> 4 | B39: 上海天安轴承有限公司 | C39: 上海天安轴承有限公司为上海电气集团旗下上海集优机械有限公司的全资企业，位于上海市闵行区莘庄工业园区银都路4399号，具有60多年的生产历史。公司专业生产具有高精度、高转速、高灵敏度、低噪音、长寿命的微型轴承，并对轴承产品进行技术开发和产品售后服务。产品广泛运用于航空航天、工业装备、汽车医疗等行业，性能达到国际领先水平。近几年公司大力支持国家航天事业，已为“天宫一号”、“神舟五号”、“神州六号”、“神舟七号”、“神州八号”和“绕月探测工程”成功配套，获得了国家有关部门的多次嘉奖。 | D39: 设备维修 | E39: 2 | F39: 大专 | G39: 对设备的机械、液压、气动系统的故障、磨损进行维修，确保生产；对设备进行点检、保养工作负责设备的日常报表填写 | H39: 月薪：5K-7K | I39: =_xlfn.CONCAT(D39,"（学历：",F39," 专业要求：",IF(ISBLANK(M39),"无",M39),"）") -> 设备维修（学历：大专 专业要求：无） | J39: =LEN(G39) -> 53 | K39: =_xlfn.XLOOKUP(A39,长度要求!A:A,长度要求!E:E) -> 500 | L39: =IF(J39<K39,G39,LEFT(G39,K39)&"……") -> 对设备的机械、液压、气动系统的故障、磨损进行维修，确保生产；对设备进行点检、保养工作负责设备的日常报表填写 | N39: =LEN(M39) -> 0 | O39: =IF(ISBLANK(M39),0,COUNTA(_xlfn.TEXTSPLIT(M39,","))) -> 0
A40: =COUNTIF(B:B,B40) -> 2 | B40: 图萌（上海）科技有限公司 | C40: 图萌（上海）科技有限公司倡导“科技融合，创新共赢”的理念，专注于新媒体+XR领域的数字技术和内容研发，在人工智能时代背景下，致力于AIGC内容生成式人才的培养，涵盖虚拟现实、数字媒体技术、动漫设计、广播电视编导、节目制作、新闻采编与制作、新媒体艺术、艺术设计、广告学、计算机等领域。作为长三角文旅产业联盟会员单位、教育部职教工场项目白名单企业，图萌科技拥有计算机软件著作权登记证书、上海电影电视技术学会会员单位、上海高等职业学校校企合作联盟单位等资质，并具备AIGC课程研发与授课实战经验，以及上海多媒体行业产教融合专委会成员单位身份。取得高新科技企业、双软企业资质，并通过ISO9001质量管理体系认证，重合同守信用企业、科技型中小企业、专精特新企业资质。图萌科技提供面向AIGC+专业条件下的教育解决方案，基于图智AIGC教学资源平台和云端AIGC工具平台，落地人才培养方案、课程建设实施、实验实训建设、师资培训服务、教辅教材开发、赛事指导支持和职业证书认证等服务。 | D40: 平面设计 | E40: 2 | F40: 大专 | G40: 岗位职责1、负责公司宣传材料、册页等的设计与整合。2、精通PS、AI等设计软件。3、参与设计讨论，和业务团队共同创建用户界面，跟踪设计效果，提出设计优化方案。4、良好的团队精神，工作踏实稳定。岗位要求1、全日制大专或以上学历，艺术设计类相关专业毕业。2、有实习经验者优先，能独立完成设计方案。3、会使用CAD做平面布局图者优先。4、会渲染三维效果图者优先。 | H40: 日薪：80-200/天 | I40: =_xlfn.CONCAT(D40,"（学历：",F40," 专业要求：",IF(ISBLANK(M40),"无",M40),"）") -> 平面设计（学历：大专 专业要求：视觉传达设计） | J40: =LEN(G40) -> 178 | K40: =_xlfn.XLOOKUP(A40,长度要求!A:A,长度要求!E:E) -> 500 | L40: =IF(J40<K40,G40,LEFT(G40,K40)&"……") -> 岗位职责1、负责公司宣传材料、册页等的设计与整合。2、精通PS、AI等设计软件。3、参与设计讨论，和业务团队共同创建用户界面，跟踪设计效果，提出设计优化方案。4、良好的团队精神，工作踏实稳定。岗位要求1、全日制大专或以上学历，艺术设计类相关专业毕业。2、有实习经验者优先，能独立完成设计方案。3、会使用CAD做平面布局图者优先。4、会渲染三维效果图者优先。 | M40: 视觉传达设计 | N40: =LEN(M40) -> 6 | O40: =IF(ISBLANK(M40),0,COUNTA(_xlfn.TEXTSPLIT(M40,","))) -> 1
A41: =COUNTIF(B:B,B41) -> 4 | B41: 上海天安轴承有限公司 | C41: 上海天安轴承有限公司为上海电气集团旗下上海集优机械有限公司的全资企业，位于上海市闵行区莘庄工业园区银都路4399号，具有60多年的生产历史。公司专业生产具有高精度、高转速、高灵敏度、低噪音、长寿命的微型轴承，并对轴承产品进行技术开发和产品售后服务。产品广泛运用于航空航天、工业装备、汽车医疗等行业，性能达到国际领先水平。近几年公司大力支持国家航天事业，已为“天宫一号”、“神舟五号”、“神州六号”、“神舟七号”、“神州八号”和“绕月探测工程”成功配套，获得了国家有关部门的多次嘉奖。 | D41: 质量检验员 | E41: 2 | F41: 大专 | G41: 1、做好检验状态的表示，按规定放置各类产品技师处理废品2、按检验规程做好产品首检、巡检、工艺纪律监督工作并对检验过程中发现的不合格现象、违反工艺的情况技师通知操作者纠正3、按照工艺规程、检验规程实施完工检，发现异常情况及时向有关人员反馈，保证不合格品不转序4、当天产品当天清，即将产品及时检验 | H41: 月薪：5K-7K | I41: =_xlfn.CONCAT(D41,"（学历：",F41," 专业要求：",IF(ISBLANK(M41),"无",M41),"）") -> 质量检验员（学历：大专 专业要求：无） | J41: =LEN(G41) -> 146 | K41: =_xlfn.XLOOKUP(A41,长度要求!A:A,长度要求!E:E) -> 500 | L41: =IF(J41<K41,G41,LEFT(G41,K41)&"……") -> 1、做好检验状态的表示，按规定放置各类产品技师处理废品2、按检验规程做好产品首检、巡检、工艺纪律监督工作并对检验过程中发现的不合格现象、违反工艺的情况技师通知操作者纠正3、按照工艺规程、检验规程实施完工检，发现异常情况及时向有关人员反馈，保证不合格品不转序4、当天产品当天清，即将产品及时检验 | N41: =LEN(M41) -> 0 | O41: =IF(ISBLANK(M41),0,COUNTA(_xlfn.TEXTSPLIT(M41,","))) -> 0
A42: =COUNTIF(B:B,B42) -> 2 | B42: 图萌（上海）科技有限公司 | C42: 图萌（上海）科技有限公司倡导“科技融合，创新共赢”的理念，专注于新媒体+XR领域的数字技术和内容研发，在人工智能时代背景下，致力于AIGC内容生成式人才的培养，涵盖虚拟现实、数字媒体技术、动漫设计、广播电视编导、节目制作、新闻采编与制作、新媒体艺术、艺术设计、广告学、计算机等领域。作为长三角文旅产业联盟会员单位、教育部职教工场项目白名单企业，图萌科技拥有计算机软件著作权登记证书、上海电影电视技术学会会员单位、上海高等职业学校校企合作联盟单位等资质，并具备AIGC课程研发与授课实战经验，以及上海多媒体行业产教融合专委会成员单位身份。取得高新科技企业、双软企业资质，并通过ISO9001质量管理体系认证，重合同守信用企业、科技型中小企业、专精特新企业资质。图萌科技提供面向AIGC+专业条件下的教育解决方案，基于图智AIGC教学资源平台和云端AIGC工具平台，落地人才培养方案、课程建设实施、实验实训建设、师资培训服务、教辅教材开发、赛事指导支持和职业证书认证等服务。 | D42: AI虚拟数字人拍摄制作专员 | E42: 2 | F42: 大专 | G42: 岗位职责:1、负责AI虚拟数字人的形象设计、动态捕捉及视频拍摄全流程制作，包括前期策划、场景搭建、灯光调试等。2、使用动作捕捉设备(如光学/惯性动捕系统)、面部表情捕捉技术等，完成数字人的高精度动作与表情数据采集。3、配合A|算法团队，优化数字人的语音、表情、肢体动作的同步性与自然度提升拟真效果。4、负责虚拟拍摄现场的设备调试(如摄像机追踪、虚拟引擎实时渲染等)，确保拍摄效率与质量。5、跟踪行业技术趋势，探索A数字人在直播、短视频、影视等领域的创新应用场景。岗位要求:1、熟悉虚拟制作流程，有动作捕捉(如Vicon、OptiTrack)、面部捕捉(如Faceware、iPhoneARKit)或影视拍摄经验。2、掌握至少一款3D制作工具(如Blender、Maya、UnrealEngine、Unity)能完成基础模型调整与场景搭建。3、了解A|数字人相关技术(如语音合成、TTS、NLP)，有AI工具(如D-D、Synthesia)使用经验者优先。4、具备良好的镜头语言和审美能力，能独立完成脚本分镜设计及后期剪辑(熟悉Premiere、DaVinci等)。 | H42: 日薪：80-200/天 | I42: =_xlfn.CONCAT(D42,"（学历：",F42," 专业要求：",IF(ISBLANK(M42),"无",M42),"）") -> AI虚拟数字人拍摄制作专员（学历：大专 专业要求：无） | J42: =LEN(G42) -> 482 | K42: =_xlfn.XLOOKUP(A42,长度要求!A:A,长度要求!E:E) -> 500 | L42: =IF(J42<K42,G42,LEFT(G42,K42)&"……") -> 岗位职责:1、负责AI虚拟数字人的形象设计、动态捕捉及视频拍摄全流程制作，包括前期策划、场景搭建、灯光调试等。2、使用动作捕捉设备(如光学/惯性动捕系统)、面部表情捕捉技术等，完成数字人的高精度动作与表情数据采集。3、配合A|算法团队，优化数字人的语音、表情、肢体动作的同步性与自然度提升拟真效果。4、负责虚拟拍摄现场的设备调试(如摄像机追踪、虚拟引擎实时渲染等)，确保拍摄效率与质量。5、跟踪行业技术趋势，探索A数字人在直播、短视频、影视等领域的创新应用场景。岗位要求:1、熟悉虚拟制作流程，有动作捕捉(如Vicon、OptiTrack)、面部捕捉(如Faceware、iPhoneARKit)或影视拍摄经验。2、掌握至少一款3D制作工具(如Blender、Maya、UnrealEngine、Unity)能完成基础模型调整与场景搭建。3、了解A|数字人相关技术(如语音合成、TTS、NLP)，有AI工具(如D-D、Synthesia)使用经验者优先。4、具备良好的镜头语言和审美能力，能独立完成脚本分镜设计及后期剪辑(熟悉Premiere、DaVinci等)。 | N42: =LEN(M42) -> 0 | O42: =IF(ISBLANK(M42),0,COUNTA(_xlfn.TEXTSPLIT(M42,","))) -> 0
A43: =COUNTIF(B:B,B43) -> 1 | B43: 上海积千理网络科技有限公司 | C43: 上海积千理网络科技有限公司成立于2019年9月23日，是一家专注游戏直播领域的小微企业，公司位于上海市闵行区禾谷文创园A213号，目前处于开业状态。公司经营范围广泛，涵盖数字文化创意内容应用、互联网数据服务、个人互联网直播服务等。自成立以来，公司凭借专业的团队和创新的理念，在游戏直播领域崭露头角，致力于为观众呈现精彩的游戏直播内容，为游戏爱好者搭建互动交流平台，在竞争激烈的游戏直播市场中逐步站稳脚跟。 | D43: 弹幕游戏互动主播 | E43: 10 | F43: 初中及以下 | G43: 年满18岁，接受无经验从业者，新手小白，弹幕游戏就是抖音最新直播间弹幕游戏玩法，直播间可以不露脸露不露脸看自己个人意愿，主要就是烘托直播间PK赛况的气氛，拉动观众互动率，不用会玩游戏，不需要你上手操作，解说游戏赛况实时即可。岗位职责:1.负责直播抖音平台弹幕实时互动类游戏，直播游戏玩法2.正常上手后，开播六小时。配合公司运营下播复盘3.运营团队跟播，每日下播复盘，成熟话术提供，打造专属你个人的弹幕游戏直播间4.不需要你去维护大哥大姐，抖音平台自动分流，对新人流量扶持极大5.无任何培训费用，接受新手小白0经验，能快速上手6.公司提供专业电脑以及声卡设备，老人带播任职要求：1.公司可接受新手小白0经验新人从业者，应届生，在校大学生，有无经验均可，有直播行业从业经验优先考虑。2.零基础操作，无需懂太多游戏操作，只要你敢开口说话，性格外向活泼开朗，善于沟通，情商高。3.无任何形象上的要求，不需要才艺，年龄没有限制，学历没有要求，只需要你情商高会说话，敢说话，胆子大月入过万不再是梦想工作时间：每日工作六小时不加班，不需要一直坐班，稳定后可以自己挑选时间段播可以居家办公，节假日正常放假。薪资待遇：保底6000-8000（面试定薪）+平台返佣提成+抖音新人奖+全勤奖，稳定综合月收入1.5w以上，公司施行阶梯制激励政策，突破一点上一台阶。没有封顶，只有新高。付出努力与收入成正比，婉拒只想混底薪的。员工福利：公司定期员工团建，下午茶福利，业绩达标奖励，现金红包奖励等，我们是一个年轻且活泼的公司，不积跬步无以至千里，期待更多小伙伴加入我们的团队，共创辉煌！ | H43: 月薪：6K-20K | I43: =_xlfn.CONCAT(D43,"（学历：",F43," 专业要求：",IF(ISBLANK(M43),"无",M43),"）") -> 弹幕游戏互动主播（学历：初中及以下 专业要求：无） | J43: =LEN(G43) -> 679 | K43: =_xlfn.XLOOKUP(A43,长度要求!A:A,长度要求!E:E) -> 500 | L43: =IF(J43<K43,G43,LEFT(G43,K43)&"……") -> 年满18岁，接受无经验从业者，新手小白，弹幕游戏就是抖音最新直播间弹幕游戏玩法，直播间可以不露脸露不露脸看自己个人意愿，主要就是烘托直播间PK赛况的气氛，拉动观众互动率，不用会玩游戏，不需要你上手操作，解说游戏赛况实时即可。岗位职责:1.负责直播抖音平台弹幕实时互动类游戏，直播游戏玩法2.正常上手后，开播六小时。配合公司运营下播复盘3.运营团队跟播，每日下播复盘，成熟话术提供，打造专属你个人的弹幕游戏直播间4.不需要你去维护大哥大姐，抖音平台自动分流，对新人流量扶持极大5.无任何培训费用，接受新手小白0经验，能快速上手6.公司提供专业电脑以及声卡设备，老人带播任职要求：1.公司可接受新手小白0经验新人从业者，应届生，在校大学生，有无经验均可，有直播行业从业经验优先考虑。2.零基础操作，无需懂太多游戏操作，只要你敢开口说话，性格外向活泼开朗，善于沟通，情商高。3.无任何形象上的要求，不需要才艺，年龄没有限制，学历没有要求，只需要你情商高会说话，敢说话，胆子大月入过万不再是梦想工作时间：每日工作六小时不加班，不需要一直坐班，稳定后可以自己挑选时间段播可以居家办公，节假日正常放假。薪资待遇：…… | N43: =LEN(M43) -> 0 | O43: =IF(ISBLANK(M43),0,COUNTA(_xlfn.TEXTSPLIT(M43,","))) -> 0
A44: =COUNTIF(B:B,B44) -> 2 | B44: 予童家庭服务（上海）有限公司 | C44: 予童家庭服务（BabyNanny），以“重塑美好育儿生态”为使命，专注为高净值家庭提供育婴照护、婴儿早教、孩童陪伴等服务。作为高标准母婴护理及高质量家庭服务的坚定笃行者，予童为同样追求育儿品质的家庭，定制集育婴护理、入户指导和社群体验“三维一体”的婴童成长呵护方案，让育儿回归优雅和从容。以“百里挑一”的严苛标准遴选育婴师，打造迎合高端家庭需求的培塑实训，冀期予童的每一名育婴师，都能成为宝宝的温情暖手、宝妈的得力助手、家庭的坚实帮手。 | D44: 家庭育婴师 | E44: 20 | F44: 初中及以下 | G44: 可选择白班或住家1.全面负责新生儿的生活照料，涵盖喂养、洗澡、抚触、更换尿布等环节，保障宝宝的清洁与舒适。2.密切留意宝宝的生长发育状况，诸如身高、体重、睡眠、大小便等方面，一旦察觉异常立即向家长或医生反馈。3.依据宝宝的年龄及发展阶段，精心制定科学合理的喂养计划与作息时间表，悉心培养宝宝良好的生活习惯。4.开展早期教育与启蒙工作，借助游戏、互动等多种方式，推动宝宝的认知、语言、运动以及社交能力的发展。5.承担宝宝衣物、用品的清洗与消毒工作，确保宝宝生活环境的整洁与卫生。6.与家长保持高效且良好的沟通，深入了解家长的需求与关注重点，给予专业的育婴建议和指导。7.协助家长妥善处理宝宝的其他相关事务，像就医、接种疫苗等。任职要求对婴幼儿事业充满热爱，拥有爱心、耐心和责任心，具备良好的职业道德和素养。具备出色的沟通能力和团队协作精神，能够与家长及其他工作人员构建起良好的关系。身体健康，无传染性疾病，拥有良好的心理素质和抗压能力。具有一定的学习和创新能力，能够持续更新育婴知识和技能。有相关从业经验、实习经验者优先；护理专业、学前教育专业、婴幼儿托育专业优先；有乐器、舞蹈、声乐、英语、绘画等特长优先；有相关职业技能证书优先（如育婴师证书、教师资格证等） | H44: 月薪：6K-7K | I44: =_xlfn.CONCAT(D44,"（学历：",F44," 专业要求：",IF(ISBLANK(M44),"无",M44),"）") -> 家庭育婴师（学历：初中及以下 专业要求：学前教育,学前教育学,护理学,护理,护理学类,护理类,卫生教育,儿科学,妇幼保健医学,预防医学） | J44: =LEN(G44) -> 529 | K44: =_xlfn.XLOOKUP(A44,长度要求!A:A,长度要求!E:E) -> 500 | L44: =IF(J44<K44,G44,LEFT(G44,K44)&"……") -> 可选择白班或住家1.全面负责新生儿的生活照料，涵盖喂养、洗澡、抚触、更换尿布等环节，保障宝宝的清洁与舒适。2.密切留意宝宝的生长发育状况，诸如身高、体重、睡眠、大小便等方面，一旦察觉异常立即向家长或医生反馈。3.依据宝宝的年龄及发展阶段，精心制定科学合理的喂养计划与作息时间表，悉心培养宝宝良好的生活习惯。4.开展早期教育与启蒙工作，借助游戏、互动等多种方式，推动宝宝的认知、语言、运动以及社交能力的发展。5.承担宝宝衣物、用品的清洗与消毒工作，确保宝宝生活环境的整洁与卫生。6.与家长保持高效且良好的沟通，深入了解家长的需求与关注重点，给予专业的育婴建议和指导。7.协助家长妥善处理宝宝的其他相关事务，像就医、接种疫苗等。任职要求对婴幼儿事业充满热爱，拥有爱心、耐心和责任心，具备良好的职业道德和素养。具备出色的沟通能力和团队协作精神，能够与家长及其他工作人员构建起良好的关系。身体健康，无传染性疾病，拥有良好的心理素质和抗压能力。具有一定的学习和创新能力，能够持续更新育婴知识和技能。有相关从业经验、实习经验者优先；护理专业、学前教育专业、婴幼儿托育专业优先；有乐器、舞蹈、声乐、英语、绘画等特长…… | M44: 学前教育,学前教育学,护理学,护理,护理学类,护理类,卫生教育,儿科学,妇幼保健医学,预防医学 | N44: =LEN(M44) -> 47 | O44: =IF(ISBLANK(M44),0,COUNTA(_xlfn.TEXTSPLIT(M44,","))) -> 10
A45: =COUNTIF(B:B,B45) -> 5 | B45: 上海加行自动化科技有限公司 | C45: 上海加行自动化科技有限公司总部位于紫竹科学园区。基于对洁净室技术在现代社会发展中日益凸显的重要作用的认识，缘硕自创立至今，始终专注于洁净室技术及其广阔的应用领域，保持着与国内知名高校和科研机构以及美国、德国、加拿大等先进工业化国家知名企业的良好合作，密切跟踪国内外洁净室技术的最新发展并适时予以吸收和应用，使得缘硕始终保有充沛的技术活力，并以其鲜明的技术特色服务于国内外广大客户。加行为医疗机构、科研机构提供全面的设备、设施整体解决方案。量身定制集成式、模块化的设备和设施，提供专业维护、保养服务，满足专业化、多元化的需求。今天，加行已成为一家创新活力的现代企业。加行通过引入各类国际体系认证使得企业管理日益规范与成熟，被闵行区人力资源和社会保障局认定为区级大学生社会实践基地。而与此同时，对于企业诚信文化建设和团队建设的关注，赋予了缘硕前进所需的品格、力量与激情。 | D45: 安装维护 | E45: 5 | F45: 大专 | G45: 支持公司安装维护相关工作我司是闵行区大学生社会实践基地，具有闵行区户籍的普通高等学校毕业前两年内的全日制学生（不含研究生）和闵行区内的普通高等学校毕业前两年内的全日制学生（不含研究生）来我司实习可额外申请闵行区补贴（每月补贴标准为本市当年城镇职工月最低工资标准的80%）。投递简历 | H45: 月薪：4K-8K | I45: =_xlfn.CONCAT(D45,"（学历：",F45," 专业要求：",IF(ISBLANK(M45),"无",M45),"）") -> 安装维护（学历：大专 专业要求：无） | J45: =LEN(G45) -> 140 | K45: =_xlfn.XLOOKUP(A45,长度要求!A:A,长度要求!E:E) -> 500 | L45: =IF(J45<K45,G45,LEFT(G45,K45)&"……") -> 支持公司安装维护相关工作我司是闵行区大学生社会实践基地，具有闵行区户籍的普通高等学校毕业前两年内的全日制学生（不含研究生）和闵行区内的普通高等学校毕业前两年内的全日制学生（不含研究生）来我司实习可额外申请闵行区补贴（每月补贴标准为本市当年城镇职工月最低工资标准的80%）。投递简历 | N45: =LEN(M45) -> 0 | O45: =IF(ISBLANK(M45),0,COUNTA(_xlfn.TEXTSPLIT(M45,","))) -> 0
A46: =COUNTIF(B:B,B46) -> 5 | B46: 上海加行自动化科技有限公司 | C46: 上海加行自动化科技有限公司总部位于紫竹科学园区。基于对洁净室技术在现代社会发展中日益凸显的重要作用的认识，缘硕自创立至今，始终专注于洁净室技术及其广阔的应用领域，保持着与国内知名高校和科研机构以及美国、德国、加拿大等先进工业化国家知名企业的良好合作，密切跟踪国内外洁净室技术的最新发展并适时予以吸收和应用，使得缘硕始终保有充沛的技术活力，并以其鲜明的技术特色服务于国内外广大客户。加行为医疗机构、科研机构提供全面的设备、设施整体解决方案。量身定制集成式、模块化的设备和设施，提供专业维护、保养服务，满足专业化、多元化的需求。今天，加行已成为一家创新活力的现代企业。加行通过引入各类国际体系认证使得企业管理日益规范与成熟，被闵行区人力资源和社会保障局认定为区级大学生社会实践基地。而与此同时，对于企业诚信文化建设和团队建设的关注，赋予了缘硕前进所需的品格、力量与激情。 | D46: 销售助理 | E46: 5 | F46: 大专 | G46: 协助公司销售相关工作我司是闵行区大学生社会实践基地，具有闵行区户籍的普通高等学校毕业前两年内的全日制学生（不含研究生）和闵行区内的普通高等学校毕业前两年内的全日制学生（不含研究生）来我司实习可额外申请闵行区补贴（每月补贴标准为本市当年城镇职工月最低工资标准的80%）。 | H46: 月薪：4K-8K | I46: =_xlfn.CONCAT(D46,"（学历：",F46," 专业要求：",IF(ISBLANK(M46),"无",M46),"）") -> 销售助理（学历：大专 专业要求：无） | J46: =LEN(G46) -> 134 | K46: =_xlfn.XLOOKUP(A46,长度要求!A:A,长度要求!E:E) -> 500 | L46: =IF(J46<K46,G46,LEFT(G46,K46)&"……") -> 协助公司销售相关工作我司是闵行区大学生社会实践基地，具有闵行区户籍的普通高等学校毕业前两年内的全日制学生（不含研究生）和闵行区内的普通高等学校毕业前两年内的全日制学生（不含研究生）来我司实习可额外申请闵行区补贴（每月补贴标准为本市当年城镇职工月最低工资标准的80%）。 | N46: =LEN(M46) -> 0 | O46: =IF(ISBLANK(M46),0,COUNTA(_xlfn.TEXTSPLIT(M46,","))) -> 0
A47: =COUNTIF(B:B,B47) -> 5 | B47: 上海加行自动化科技有限公司 | C47: 上海加行自动化科技有限公司总部位于紫竹科学园区。基于对洁净室技术在现代社会发展中日益凸显的重要作用的认识，缘硕自创立至今，始终专注于洁净室技术及其广阔的应用领域，保持着与国内知名高校和科研机构以及美国、德国、加拿大等先进工业化国家知名企业的良好合作，密切跟踪国内外洁净室技术的最新发展并适时予以吸收和应用，使得缘硕始终保有充沛的技术活力，并以其鲜明的技术特色服务于国内外广大客户。加行为医疗机构、科研机构提供全面的设备、设施整体解决方案。量身定制集成式、模块化的设备和设施，提供专业维护、保养服务，满足专业化、多元化的需求。今天，加行已成为一家创新活力的现代企业。加行通过引入各类国际体系认证使得企业管理日益规范与成熟，被闵行区人力资源和社会保障局认定为区级大学生社会实践基地。而与此同时，对于企业诚信文化建设和团队建设的关注，赋予了缘硕前进所需的品格、力量与激情。 | D47: 技术支持 | E47: 5 | F47: 大专 | G47: 支持公司技术支持相关工作。我司是闵行区大学生社会实践基地，具有闵行区户籍的普通高等学校毕业前两年内的全日制学生（不含研究生）和闵行区内的普通高等学校毕业前两年内的全日制学生（不含研究生）来我司实习可额外申请闵行区补贴（每月补贴标准为本市当年城镇职工月最低工资标准的80%）。 | H47: 月薪：4K-8K | I47: =_xlfn.CONCAT(D47,"（学历：",F47," 专业要求：",IF(ISBLANK(M47),"无",M47),"）") -> 技术支持（学历：大专 专业要求：无） | J47: =LEN(G47) -> 137 | K47: =_xlfn.XLOOKUP(A47,长度要求!A:A,长度要求!E:E) -> 500 | L47: =IF(J47<K47,G47,LEFT(G47,K47)&"……") -> 支持公司技术支持相关工作。我司是闵行区大学生社会实践基地，具有闵行区户籍的普通高等学校毕业前两年内的全日制学生（不含研究生）和闵行区内的普通高等学校毕业前两年内的全日制学生（不含研究生）来我司实习可额外申请闵行区补贴（每月补贴标准为本市当年城镇职工月最低工资标准的80%）。 | N47: =LEN(M47) -> 0 | O47: =IF(ISBLANK(M47),0,COUNTA(_xlfn.TEXTSPLIT(M47,","))) -> 0
A48: =COUNTIF(B:B,B48) -> 5 | B48: 上海置道液压控制技术有限公司 | C48: 上海置道液压控制技术有限公司自2005年成立以来，致力于拥有自主知识产权和行业核心竞争力的专业液压控制系统集成供应商，是国家高新技术企业，上海市专精特新重点企业，创新型科技企业。公司集“研发、设计、生产、销售及系统工程服务”于一体，主要业务涉及电力、新能源、化工、钢铁、船舶等领域，现正积极研究和拓展智能化电液系统集成业务。公司技术和管理人员主要来自国际知名大公司及国内著名大型企业，具有强大的设计研发能力和工程经验,公司（含子公司）拥有包括博士、硕士、本科学历的相关专业人员100多人，大专以上学历员工占工厂总员工70%以上。目前，在电力液压系统设备领域，上海置道已发展为市场占有率稳居第一的行业领军企业，是同行业中唯一一家与国内主流大、中主机厂均有长期配套关系的公司，同时，已与三菱日立、艾默生等跨国公司建立了稳定的供货合作关系。四川德阳生产基地主要负责西南地区业务，并在乌鲁木齐设立了检修分公司，便于新疆地区电厂的设备检修及备件供应。顺应“中国制造2025”的步伐，置道公司将积极引进人才，努力引领行业先进技术，势将继续保持行业领先水平。 | D48: 质检员 | E48: 3 | F48: 本科 | G48: 任职及岗位要求：1.较强的学习、交流、沟通能力，具有团队合作精神2.为人诚信，工作认真负责，高度敬业精神,服从团队工作安排。3.熟练办公自动化软件（word,excel,PPT等）工作地点：上海或外派办事处 | H48: 月薪：6K-8K | I48: =_xlfn.CONCAT(D48,"（学历：",F48," 专业要求：",IF(ISBLANK(M48),"无",M48),"）") -> 质检员（学历：本科 专业要求：无） | J48: =LEN(G48) -> 103 | K48: =_xlfn.XLOOKUP(A48,长度要求!A:A,长度要求!E:E) -> 500 | L48: =IF(J48<K48,G48,LEFT(G48,K48)&"……") -> 任职及岗位要求：1.较强的学习、交流、沟通能力，具有团队合作精神2.为人诚信，工作认真负责，高度敬业精神,服从团队工作安排。3.熟练办公自动化软件（word,excel,PPT等）工作地点：上海或外派办事处 | N48: =LEN(M48) -> 0 | O48: =IF(ISBLANK(M48),0,COUNTA(_xlfn.TEXTSPLIT(M48,","))) -> 0
A49: =COUNTIF(B:B,B49) -> 4 | B49: 澳康达（上海）车辆销售有限公司 | C49: 澳康达，创立于1999年，澳康达名车广场（深圳）获吉尼斯认证为——“全球最大二手车交易展厅”。作为最早一批专注二手车经营的行业先行者，澳康达追求卓越发展，致力于为客户提供专业性更强、诚信度更高的服务模式，从二手车企业中脱颖而出，成为中国二手车行业领军者。迄今为止，澳康达发展成为一个全球知名的二手车独立经销商。2013年投入使用的深圳澳康达名车广场，首创了自有品牌+自建物业+自主经营的二手车发展之路，占地1万㎡，建筑面积12万㎡，12层全空调全玻璃幕墙立体展厅，集名车交易、汽车精品商城、维修保养中心、汽车文化生活、车管所、金融机构、高级会所为一体。澳康达秉承“优质、实惠、尊贵”的服务理念，打造以消费者为中心的服务模式；给消费者不仅带来了名车海洋般的丰富选择，也让二手车消费更加时尚，更值得信赖。澳康达摈弃了租赁经营方式，也不做单一的平台经营或中间服务商，而是深耕二手车行业，从售前、售中到售后的每一个环节，为客户提供全方位、精细化的尊贵服务、客户重复购买率超过60%。作为行业创新先行者，澳康达不仅铸就了行业美誉度第一的实体二手车品牌，同时也搭建了多维度的互联网服务平台，将线下展厅与线上实现无缝对接，连接起全国各地的名车爱好者，远程享受澳康达优质服务。 | D49: 汽车学徒 | E49: 5 | F49: 中专/技校 | G49: 1、严格依照标准化操作流程进行对车辆全车抛光、打蜡工作/钣金/轮胎2、施工结束后对施工结果进行自检，保证施工质量3、维护好本车间的环境卫生，保持车间整洁，保管好施工设备和施工工具4、服从公司调度及上级领导安排 | H49: 月薪：4K-8K | I49: =_xlfn.CONCAT(D49,"（学历：",F49," 专业要求：",IF(ISBLANK(M49),"无",M49),"）") -> 汽车学徒（学历：中专/技校 专业要求：无） | J49: =LEN(G49) -> 104 | K49: =_xlfn.XLOOKUP(A49,长度要求!A:A,长度要求!E:E) -> 500 | L49: =IF(J49<K49,G49,LEFT(G49,K49)&"……") -> 1、严格依照标准化操作流程进行对车辆全车抛光、打蜡工作/钣金/轮胎2、施工结束后对施工结果进行自检，保证施工质量3、维护好本车间的环境卫生，保持车间整洁，保管好施工设备和施工工具4、服从公司调度及上级领导安排 | N49: =LEN(M49) -> 0 | O49: =IF(ISBLANK(M49),0,COUNTA(_xlfn.TEXTSPLIT(M49,","))) -> 0
A50: =COUNTIF(B:B,B50) -> 5 | B50: 上海置道液压控制技术有限公司 | C50: 上海置道液压控制技术有限公司自2005年成立以来，致力于拥有自主知识产权和行业核心竞争力的专业液压控制系统集成供应商，是国家高新技术企业，上海市专精特新重点企业，创新型科技企业。公司集“研发、设计、生产、销售及系统工程服务”于一体，主要业务涉及电力、新能源、化工、钢铁、船舶等领域，现正积极研究和拓展智能化电液系统集成业务。公司技术和管理人员主要来自国际知名大公司及国内著名大型企业，具有强大的设计研发能力和工程经验,公司（含子公司）拥有包括博士、硕士、本科学历的相关专业人员100多人，大专以上学历员工占工厂总员工70%以上。目前，在电力液压系统设备领域，上海置道已发展为市场占有率稳居第一的行业领军企业，是同行业中唯一一家与国内主流大、中主机厂均有长期配套关系的公司，同时，已与三菱日立、艾默生等跨国公司建立了稳定的供货合作关系。四川德阳生产基地主要负责西南地区业务，并在乌鲁木齐设立了检修分公司，便于新疆地区电厂的设备检修及备件供应。顺应“中国制造2025”的步伐，置道公司将积极引进人才，努力引领行业先进技术，势将继续保持行业领先水平。 | D50: 行政助理 | E50: 3 | F50: 本科 | G50: 任职及岗位要求：1.为人诚信，工作认真负责，高度敬业精神。2.协助管理层内部行政沟通协调及文档管理，文字功底较好。3.协助并陪同公司高层接待和拜访公司重要客户。4.管理层培训与拓展的策划和安排。5.社会公益等非经营性活动的参与安排。6.本岗位优先考虑女性。工作地点：上海 | H50: 月薪：6K-8K | I50: =_xlfn.CONCAT(D50,"（学历：",F50," 专业要求：",IF(ISBLANK(M50),"无",M50),"）") -> 行政助理（学历：本科 专业要求：行政管理,人力资源管理,文秘类） | J50: =LEN(G50) -> 135 | K50: =_xlfn.XLOOKUP(A50,长度要求!A:A,长度要求!E:E) -> 500 | L50: =IF(J50<K50,G50,LEFT(G50,K50)&"……") -> 任职及岗位要求：1.为人诚信，工作认真负责，高度敬业精神。2.协助管理层内部行政沟通协调及文档管理，文字功底较好。3.协助并陪同公司高层接待和拜访公司重要客户。4.管理层培训与拓展的策划和安排。5.社会公益等非经营性活动的参与安排。6.本岗位优先考虑女性。工作地点：上海 | M50: 行政管理,人力资源管理,文秘类 | N50: =LEN(M50) -> 15 | O50: =IF(ISBLANK(M50),0,COUNTA(_xlfn.TEXTSPLIT(M50,","))) -> 3
A51: =COUNTIF(B:B,B51) -> 5 | B51: 上海置道液压控制技术有限公司 | C51: 上海置道液压控制技术有限公司自2005年成立以来，致力于拥有自主知识产权和行业核心竞争力的专业液压控制系统集成供应商，是国家高新技术企业，上海市专精特新重点企业，创新型科技企业。公司集“研发、设计、生产、销售及系统工程服务”于一体，主要业务涉及电力、新能源、化工、钢铁、船舶等领域，现正积极研究和拓展智能化电液系统集成业务。公司技术和管理人员主要来自国际知名大公司及国内著名大型企业，具有强大的设计研发能力和工程经验,公司（含子公司）拥有包括博士、硕士、本科学历的相关专业人员100多人，大专以上学历员工占工厂总员工70%以上。目前，在电力液压系统设备领域，上海置道已发展为市场占有率稳居第一的行业领军企业，是同行业中唯一一家与国内主流大、中主机厂均有长期配套关系的公司，同时，已与三菱日立、艾默生等跨国公司建立了稳定的供货合作关系。四川德阳生产基地主要负责西南地区业务，并在乌鲁木齐设立了检修分公司，便于新疆地区电厂的设备检修及备件供应。顺应“中国制造2025”的步伐，置道公司将积极引进人才，努力引领行业先进技术，势将继续保持行业领先水平。 | D51: 调试及服务人员 | E51: 10 | F51: 大专 | G51: 任职及岗位要求:1.职高及以上文凭（机电一体化或机械自动化优先）2.勤奋肯学，善于同现场客户沟通，为人正直。3.通过短时间培训，能够看懂机械液压设备的装配图、系统原理图、管路图等，根据图纸完成厂内机械液压设备装配、调试。4.通过短时间培训可以根据图纸的技术要求完成机械液压设备调试5.根据电气图纸进行简单的查线，端子图接线，会简单电脑操作6.胜任在厂内及现场对液压设备的安装和调试工作进行指导。工作地点：上海或外派办事处 | H51: 月薪：6K-8K | I51: =_xlfn.CONCAT(D51,"（学历：",F51," 专业要求：",IF(ISBLANK(M51),"无",M51),"）") -> 调试及服务人员（学历：大专 专业要求：机械工程,机械设计制造及其自动化,机械制造及其自动化,机械设计及理论,机械设计与制造,机械制造与自动化,机械装备制造技术,船舶机械工程技术,机械类,机械） | J51: =LEN(G51) -> 210 | K51: =_xlfn.XLOOKUP(A51,长度要求!A:A,长度要求!E:E) -> 500 | L51: =IF(J51<K51,G51,LEFT(G51,K51)&"……") -> 任职及岗位要求:1.职高及以上文凭（机电一体化或机械自动化优先）2.勤奋肯学，善于同现场客户沟通，为人正直。3.通过短时间培训，能够看懂机械液压设备的装配图、系统原理图、管路图等，根据图纸完成厂内机械液压设备装配、调试。4.通过短时间培训可以根据图纸的技术要求完成机械液压设备调试5.根据电气图纸进行简单的查线，端子图接线，会简单电脑操作6.胜任在厂内及现场对液压设备的安装和调试工作进行指导。工作地点：上海或外派办事处 | M51: 机械工程,机械设计制造及其自动化,机械制造及其自动化,机械设计及理论,机械设计与制造,机械制造与自动化,机械装备制造技术,船舶机械工程技术,机械类,机械 | N51: =LEN(M51) -> 76 | O51: =IF(ISBLANK(M51),0,COUNTA(_xlfn.TEXTSPLIT(M51,","))) -> 10
A52: =COUNTIF(B:B,B52) -> 5 | B52: 上海置道液压控制技术有限公司 | C52: 上海置道液压控制技术有限公司自2005年成立以来，致力于拥有自主知识产权和行业核心竞争力的专业液压控制系统集成供应商，是国家高新技术企业，上海市专精特新重点企业，创新型科技企业。公司集“研发、设计、生产、销售及系统工程服务”于一体，主要业务涉及电力、新能源、化工、钢铁、船舶等领域，现正积极研究和拓展智能化电液系统集成业务。公司技术和管理人员主要来自国际知名大公司及国内著名大型企业，具有强大的设计研发能力和工程经验,公司（含子公司）拥有包括博士、硕士、本科学历的相关专业人员100多人，大专以上学历员工占工厂总员工70%以上。目前，在电力液压系统设备领域，上海置道已发展为市场占有率稳居第一的行业领军企业，是同行业中唯一一家与国内主流大、中主机厂均有长期配套关系的公司，同时，已与三菱日立、艾默生等跨国公司建立了稳定的供货合作关系。四川德阳生产基地主要负责西南地区业务，并在乌鲁木齐设立了检修分公司，便于新疆地区电厂的设备检修及备件供应。顺应“中国制造2025”的步伐，置道公司将积极引进人才，努力引领行业先进技术，势将继续保持行业领先水平。 | D52: 机械电气工程师 | E52: 5 | F52: 本科 | G52: 任职及岗位要求:1.为人诚信，工作认真负责，高度敬业精神。2.较强的学习、交流、沟通能力，具有团队合作精神。3.基本的机械液压相关知识，专业课程学分良好。4.熟练使用工程相关绘图软件，主要负责机械液压配套电气设计工作，机电一体化尤佳。工作地点：上海或外派办事处 | H52: 月薪：8K-12K | I52: =_xlfn.CONCAT(D52,"（学历：",F52," 专业要求：",IF(ISBLANK(M52),"无",M52),"）") -> 机械电气工程师（学历：本科 专业要求：机械工程,机械设计制造及其自动化,机械制造及其自动化,机械设计及理论,机械设计与制造,船舶机械工程技术,工程机械运用技术,机械类,机械,机械设计制造类） | J52: =LEN(G52) -> 130 | K52: =_xlfn.XLOOKUP(A52,长度要求!A:A,长度要求!E:E) -> 500 | L52: =IF(J52<K52,G52,LEFT(G52,K52)&"……") -> 任职及岗位要求:1.为人诚信，工作认真负责，高度敬业精神。2.较强的学习、交流、沟通能力，具有团队合作精神。3.基本的机械液压相关知识，专业课程学分良好。4.熟练使用工程相关绘图软件，主要负责机械液压配套电气设计工作，机电一体化尤佳。工作地点：上海或外派办事处 | M52: 机械工程,机械设计制造及其自动化,机械制造及其自动化,机械设计及理论,机械设计与制造,船舶机械工程技术,工程机械运用技术,机械类,机械,机械设计制造类 | N52: =LEN(M52) -> 75 | O52: =IF(ISBLANK(M52),0,COUNTA(_xlfn.TEXTSPLIT(M52,","))) -> 10
A53: =COUNTIF(B:B,B53) -> 1 | B53: 上海霈赞国际物流有限公司 | C53: 公司集国际货物贸易、报关、报检、货物运输代理等一体，主要承办货物的国际贸易代理、海运、空运进出口货物的国际运输及代理业务，是中国海关AEO高级认证企业，是诸多一线国际品牌合作伙伴。 | D53: 物流单证报关实习生 | E53: 6 | F53: 大专 | G53: 物流单证报关实习生（浦东机场/双休/早9晚5）岗位职责：1、关务单证的收取、录入、整理、登记等；2、进出口报关输单、制单；3、操作文档的整理归档等；4、完成上级布置的其他任务。岗位要求：1、大专及以上学历，2026年毕业生；2、国际贸易、报关、物流管理专业优先；3、良好的学习能力，沟通能力，性格开朗，主动性强；4、word、excel软件操作熟练；5、家住上海浦东机场或祝桥镇周边地区。实习周期：周一—周五，结业完毕后依据实习期考核，表现优异者，进行正式录用及建立劳动关系；团队介绍：年轻活力的团队，专业资深的导师，舒适明亮的办公室；实习福利：实习160元/天，外加20元/天餐补。地址：浦东新区闻居路1333号A座608室闵行区莲花南路2288号杨浦区大连路688号 | H53: 日薪：0-150/天 | I53: =_xlfn.CONCAT(D53,"（学历：",F53," 专业要求：",IF(ISBLANK(M53),"无",M53),"）") -> 物流单证报关实习生（学历：大专 专业要求：物流管理,报关与国际货运,国际贸易实务） | J53: =LEN(G53) -> 335 | K53: =_xlfn.XLOOKUP(A53,长度要求!A:A,长度要求!E:E) -> 500 | L53: =IF(J53<K53,G53,LEFT(G53,K53)&"……") -> 物流单证报关实习生（浦东机场/双休/早9晚5）岗位职责：1、关务单证的收取、录入、整理、登记等；2、进出口报关输单、制单；3、操作文档的整理归档等；4、完成上级布置的其他任务。岗位要求：1、大专及以上学历，2026年毕业生；2、国际贸易、报关、物流管理专业优先；3、良好的学习能力，沟通能力，性格开朗，主动性强；4、word、excel软件操作熟练；5、家住上海浦东机场或祝桥镇周边地区。实习周期：周一—周五，结业完毕后依据实习期考核，表现优异者，进行正式录用及建立劳动关系；团队介绍：年轻活力的团队，专业资深的导师，舒适明亮的办公室；实习福利：实习160元/天，外加20元/天餐补。地址：浦东新区闻居路1333号A座608室闵行区莲花南路2288号杨浦区大连路688号 | M53: 物流管理,报关与国际货运,国际贸易实务 | N53: =LEN(M53) -> 19 | O53: =IF(ISBLANK(M53),0,COUNTA(_xlfn.TEXTSPLIT(M53,","))) -> 3
A54: =COUNTIF(B:B,B54) -> 1 | B54: 上海新致致远智能技术有限公司 | C54: 新致软件成立于1994年，总部坐落于上海，在北京、深圳、大连、重庆、成都、贵安、武汉、东京等多地设立了分支机构。新致软件专注于向保险公司、银行等金融机构及电信、汽车、医疗等其他行业终端客户提供IT解决方案、IT运维服务，以及向一级软件承包商提供软件项目分包服务。上海新致致远智能公司致力于云计算、人工智能产品与解决方案。 | D54: 云计算与AI算力运维工程师 | E54: 3 | F54: 大专 | G54: 1.云架构设计与实施：参与设计高可用、高并发、可扩展的云基础架构方案（主要为IOT相关系统），参与人工智能算力架构设计，并负责将其落地实施。2.云计算与人工智能算力资源管理：管理和维护公司在公有云（如AWS、华为云、阿里云等）上的计算、存储、网络和安全资源。3.运维与监控：建立和完善监控、告警和日志系统，确保云上应用的稳定运行，并能快速定位并给出长期解决方案；对于中间件设定参数的确认，是否合理或者根据相关指标能及时调整。4.成本优化：监控和分析云资源使用情况，提出并实施成本优化方案，控制云支出。5.安全与合规：实施云安全最佳实践，负责网络访问控制、安全组策略、数据加密等，确保基础设施符合安全与合规要求。 | H54: 月薪：6K-12K | I54: =_xlfn.CONCAT(D54,"（学历：",F54," 专业要求：",IF(ISBLANK(M54),"无",M54),"）") -> 云计算与AI算力运维工程师（学历：大专 专业要求：云计算技术与应用,人工智能技术服务） | J54: =LEN(G54) -> 305 | K54: =_xlfn.XLOOKUP(A54,长度要求!A:A,长度要求!E:E) -> 500 | L54: =IF(J54<K54,G54,LEFT(G54,K54)&"……") -> 1.云架构设计与实施：参与设计高可用、高并发、可扩展的云基础架构方案（主要为IOT相关系统），参与人工智能算力架构设计，并负责将其落地实施。2.云计算与人工智能算力资源管理：管理和维护公司在公有云（如AWS、华为云、阿里云等）上的计算、存储、网络和安全资源。3.运维与监控：建立和完善监控、告警和日志系统，确保云上应用的稳定运行，并能快速定位并给出长期解决方案；对于中间件设定参数的确认，是否合理或者根据相关指标能及时调整。4.成本优化：监控和分析云资源使用情况，提出并实施成本优化方案，控制云支出。5.安全与合规：实施云安全最佳实践，负责网络访问控制、安全组策略、数据加密等，确保基础设施符合安全与合规要求。 | M54: 云计算技术与应用,人工智能技术服务 | N54: =LEN(M54) -> 17 | O54: =IF(ISBLANK(M54),0,COUNTA(_xlfn.TEXTSPLIT(M54,","))) -> 2
A55: =COUNTIF(B:B,B55) -> 5 | B55: 上海无线电设备研究所 | C55: 八O二所，是我国从事精确制导、光电近程探测、空间探测与遥感、数据通信、电磁散射辐射与环境效应、智能交通与探测、智能制造、智慧安防等领域技术研究、产品研制试验与生产的国家重点科研单位。经过五十余年的发展，八O二所在专业发展、科研任务、科研基础条件、人才队伍和企业文化等各方面取得了瞩目的成绩，目前拥有一个国家级重点实验室、两个上海市级重点实验室和工程技术中心以及集团公司精确制导研发中心、交通感知雷达技术研发中心、八院激光探测技术研发中心等优势科研平台，并与国内外多所高校、研究机构建立了联合实验室，科研实力、科研基础条件、科研成果处于国内领先，致力发展成为具有国际竞争力、科研生产智慧化的小型产业集团和国内领先、国际一流专业研究所。现有职工1300余人，其中各类专业技术人才近900人，博士、硕士超700人，拥有国家百千万人才工程专家、政府特殊津贴专家、省部级学术技术带头人、高级工程师以上高层次技术人才350余人，先后承担数百项国家级、省部级重点科研项目研制和生产任务，荣获省部级以上科技成果200余项，拥有专利560余项。先后荣获全国五一劳动奖状、全国五四红旗团委、全国模范职工之家、上海市职工最满意企业称号、国资委深化人才发展体制机制改革示范企业，蝉联上海市、集团公司文明单位、上海市高新技术企业。秉承弘扬“勤勉、专业、激情、包容”的企业文化，构建良好的工作环境、文化氛围，热诚欢迎广大优秀人才与我们并肩前行，携手共创祖国航天事业美好未来！ | D55: 无线电调试岗 | E55: 5 | F55: 大专 | G55: 机械、电子类相关专业，有仪器、仪表使用经验者优先。 | H55: 日薪：80-200/天 | I55: =_xlfn.CONCAT(D55,"（学历：",F55," 专业要求：",IF(ISBLANK(M55),"无",M55),"）") -> 无线电调试岗（学历：大专 专业要求：无） | J55: =LEN(G55) -> 25 | K55: =_xlfn.XLOOKUP(A55,长度要求!A:A,长度要求!E:E) -> 500 | L55: =IF(J55<K55,G55,LEFT(G55,K55)&"……") -> 机械、电子类相关专业，有仪器、仪表使用经验者优先。 | N55: =LEN(M55) -> 0 | O55: =IF(ISBLANK(M55),0,COUNTA(_xlfn.TEXTSPLIT(M55,","))) -> 0
A56: =COUNTIF(B:B,B56) -> 5 | B56: 上海无线电设备研究所 | C56: 八O二所，是我国从事精确制导、光电近程探测、空间探测与遥感、数据通信、电磁散射辐射与环境效应、智能交通与探测、智能制造、智慧安防等领域技术研究、产品研制试验与生产的国家重点科研单位。经过五十余年的发展，八O二所在专业发展、科研任务、科研基础条件、人才队伍和企业文化等各方面取得了瞩目的成绩，目前拥有一个国家级重点实验室、两个上海市级重点实验室和工程技术中心以及集团公司精确制导研发中心、交通感知雷达技术研发中心、八院激光探测技术研发中心等优势科研平台，并与国内外多所高校、研究机构建立了联合实验室，科研实力、科研基础条件、科研成果处于国内领先，致力发展成为具有国际竞争力、科研生产智慧化的小型产业集团和国内领先、国际一流专业研究所。现有职工1300余人，其中各类专业技术人才近900人，博士、硕士超700人，拥有国家百千万人才工程专家、政府特殊津贴专家、省部级学术技术带头人、高级工程师以上高层次技术人才350余人，先后承担数百项国家级、省部级重点科研项目研制和生产任务，荣获省部级以上科技成果200余项，拥有专利560余项。先后荣获全国五一劳动奖状、全国五四红旗团委、全国模范职工之家、上海市职工最满意企业称号、国资委深化人才发展体制机制改革示范企业，蝉联上海市、集团公司文明单位、上海市高新技术企业。秉承弘扬“勤勉、专业、激情、包容”的企业文化，构建良好的工作环境、文化氛围，热诚欢迎广大优秀人才与我们并肩前行，携手共创祖国航天事业美好未来！ | D56: 机械装配岗 | E56: 3 | F56: 大专 | G56: 结构与机构装配岗，有技能等级证书者优先。 | H56: 日薪：80-200/天 | I56: =_xlfn.CONCAT(D56,"（学历：",F56," 专业要求：",IF(ISBLANK(M56),"无",M56),"）") -> 机械装配岗（学历：大专 专业要求：无） | J56: =LEN(G56) -> 20 | K56: =_xlfn.XLOOKUP(A56,长度要求!A:A,长度要求!E:E) -> 500 | L56: =IF(J56<K56,G56,LEFT(G56,K56)&"……") -> 结构与机构装配岗，有技能等级证书者优先。 | N56: =LEN(M56) -> 0 | O56: =IF(ISBLANK(M56),0,COUNTA(_xlfn.TEXTSPLIT(M56,","))) -> 0
A57: =COUNTIF(B:B,B57) -> 1 | B57: 上海率震档案信息技术有限公司 | C57: 上海率震档案信息技术有限公司是一家专业为律师、律所、政法机关等提供现代化档案信息服务的科技型公司。现主营业务为档案软件开发，档案5A数字化建设、档案大规模扫描服务、文档追溯管理、档案图像识别、图像优化、档案寄存等。2024年3月1日，《中华人民共和国档案法实施条例》正式施行。相较于此前的《档案法实施办法》，本次施行的《中华人民共和国档案法实施条例》无论是条款数量还是具体内容都有较大变化，内容更加符合当下时代发展，反映时代特点，能够与1991年司法部、国家档案局颁布的《律师业务档案立卷归档办法》和《律师业务档案管理办法》紧密结合，为律师业务档案管理工作提供明确的法律依据和路线指导。上海率震档案信息技术有限公司公司秉承专业、可靠、高效的宗旨，为将律师及律师事务所从律师业务档案的繁重工作中彻底解放出来。现提供律师业务档案的整理、装订、数字化及保管等全流程的服务。 | D57: 档案信息采集员 | E57: 10 | F57: 大专 | G57: 岗位名称及职责：整理员：将单位档案资料整理清楚，页码连贯、目录对应。扫描员：将单位档案资料通过扫描仪进行扫描处理，形成电子格式文档。质检员：检查扫描图像是否合格，并加以更正修改。录入员：将单位档案的封面信息、当事人信息、目录信息通过录入软件输入系统内。装订员：将数字化处理完的档案进行三孔一线的装订。岗位要求：1、大专及以上学历，专业不限；2、扫描员、质检员、录入员必须懂得电脑基本操作，熟练掌握OFFICE等办公软件。年龄18~35周岁，男女不限。扫描员要求动作迅速麻利，质检员要求认真仔细，录入员要求打字速度较快，五笔拼音皆可。整理员、装订员无需使用电脑，要求认真仔细，吃苦耐劳。3、入职需签署保密协议、提供无犯罪记录证明。4、着装得体，遵守单位和公司纪律。 | H57: 日薪：120-150/天 | I57: =_xlfn.CONCAT(D57,"（学历：",F57," 专业要求：",IF(ISBLANK(M57),"无",M57),"）") -> 档案信息采集员（学历：大专 专业要求：档案学,图书档案管理） | J57: =LEN(G57) -> 331 | K57: =_xlfn.XLOOKUP(A57,长度要求!A:A,长度要求!E:E) -> 500 | L57: =IF(J57<K57,G57,LEFT(G57,K57)&"……") -> 岗位名称及职责：整理员：将单位档案资料整理清楚，页码连贯、目录对应。扫描员：将单位档案资料通过扫描仪进行扫描处理，形成电子格式文档。质检员：检查扫描图像是否合格，并加以更正修改。录入员：将单位档案的封面信息、当事人信息、目录信息通过录入软件输入系统内。装订员：将数字化处理完的档案进行三孔一线的装订。岗位要求：1、大专及以上学历，专业不限；2、扫描员、质检员、录入员必须懂得电脑基本操作，熟练掌握OFFICE等办公软件。年龄18~35周岁，男女不限。扫描员要求动作迅速麻利，质检员要求认真仔细，录入员要求打字速度较快，五笔拼音皆可。整理员、装订员无需使用电脑，要求认真仔细，吃苦耐劳。3、入职需签署保密协议、提供无犯罪记录证明。4、着装得体，遵守单位和公司纪律。 | M57: 档案学,图书档案管理 | N57: =LEN(M57) -> 10 | O57: =IF(ISBLANK(M57),0,COUNTA(_xlfn.TEXTSPLIT(M57,","))) -> 2
A58: =COUNTIF(B:B,B58) -> 1 | B58: 上海久事公共交通集团有限公司 | C58: 上海久事公共交通集团有限公司是沪上大型城市公共交通国有企业。久事公交下属企业分为公交企业板块、保障类企业板块，及综合类企业板块。其中公交运营板块，主要负责上海浦西中心城区的公交运营以及相关车辆维修保障等工作。该板块由五家公交营运公司组成（上海巴士第一公共交通有限公司、上海巴士第二公共交通有限公司、上海巴士第三公共交通有限公司、上海巴士第四公共交通有限公司、上海巴士第五公共交通有限公司）久事公交共有员工2.5万人左右。 | D58: 公交车定向培训驾驶员 | E58: 5 | F58: 大专 | G58: 1、具有本市户籍的，大专或以上应届毕业生。2、无不良社会记录，如拘留、劳改、判刑、吸毒史等。3、身体健康，有良好的反应能力及沟通能力。4、经用人单位面试、政审、体检合格后，签订“三方”（企业、驾校、个人）培训协议书（自费26000元），参加企业驾驶员定向培训。作为城市的名片及服务的窗口，公交车驾驶员需以热情饱满的精神面貌，良好的服务素养，独立担任线路车辆的营运，根据相关规定的线路与班式，保障公众出行的安全与便利。安全驾驶，维护公交车辆的车貌与车况，为广大乘客提供优质的服务。 | H58: 月薪：3K-9K | I58: =_xlfn.CONCAT(D58,"（学历：",F58," 专业要求：",IF(ISBLANK(M58),"无",M58),"）") -> 公交车定向培训驾驶员（学历：大专 专业要求：交通运输类） | J58: =LEN(G58) -> 239 | K58: =_xlfn.XLOOKUP(A58,长度要求!A:A,长度要求!E:E) -> 500 | L58: =IF(J58<K58,G58,LEFT(G58,K58)&"……") -> 1、具有本市户籍的，大专或以上应届毕业生。2、无不良社会记录，如拘留、劳改、判刑、吸毒史等。3、身体健康，有良好的反应能力及沟通能力。4、经用人单位面试、政审、体检合格后，签订“三方”（企业、驾校、个人）培训协议书（自费26000元），参加企业驾驶员定向培训。作为城市的名片及服务的窗口，公交车驾驶员需以热情饱满的精神面貌，良好的服务素养，独立担任线路车辆的营运，根据相关规定的线路与班式，保障公众出行的安全与便利。安全驾驶，维护公交车辆的车貌与车况，为广大乘客提供优质的服务。 | M58: 交通运输类 | N58: =LEN(M58) -> 5 | O58: =IF(ISBLANK(M58),0,COUNTA(_xlfn.TEXTSPLIT(M58,","))) -> 1
A59: =COUNTIF(B:B,B59) -> 5 | B59: 宁波革力物流有限公司上海分公司 | C59: 革力物流有限公司总部设在上海,并在深圳,广州,佛山,中山,以及宁波设有分公司,在华北地区也有较好的代理网络。公司网址为：www.gclchina.net公司的代理网络覆盖100多个国家,优势航线为欧洲,地中海,中东印巴,以及澳洲新西兰和东南亚国家除基本海运空运以外，公司还致力于发展进出口代理、清关、仓储、供应链管理等多元化主体化的国际物流服务。主要合作船公司有:MAERSK、APL、EVERGREEN、NORASIA、PIL、HAPAGLIOYD、MSC、COSCO、CSCL、CMA、WANHAI、YANGMING、OOCL；主要合作的航空公司有联邦快递、联合包裹、美国航空、新加坡航空、加拿大航空、新西兰航空、马来西亚航空、以色列航空、法国航空、德国汉莎、奥地利航空、英航、国泰、阿联酋航空等。我们诚邀你的加入，让我们共同致力于打造美好的明天！我们公司全体员工满怀信心，愿以一流的服务、良好的信誉面向世界，竭诚希望与世界各国、全国各地的代理和货主建立良好的合作关系！ | D59: 单证员 | E59: 5 | F59: 大专 | G59: 负责托书准确的录入负责MBL&HOUSEBILL的核对、更改、申领及签发；熟悉各个船公司、各航线的制单要求；负责费用的录入及确认工作；负责VGM的审核确认及系统导入工作；做好单证及文件的整理和归档任职要求：具有中专以上学历，同行业三个月以上工作经验；能熟练使用电脑，中英文打字速度快，能熟练运用OFFICE操作软件。较强的学习能力，肯吃苦耐劳，对本职工作有着强烈的责任心，耐心、细致、谨慎地对待日常单证工作；有良好的语言表达能力，善于沟通、交流，具有团队合作的精神； | H59: 日薪：120-150/天 | I59: =_xlfn.CONCAT(D59,"（学历：",F59," 专业要求：",IF(ISBLANK(M59),"无",M59),"）") -> 单证员（学历：大专 专业要求：无） | J59: =LEN(G59) -> 233 | K59: =_xlfn.XLOOKUP(A59,长度要求!A:A,长度要求!E:E) -> 500 | L59: =IF(J59<K59,G59,LEFT(G59,K59)&"……") -> 负责托书准确的录入负责MBL&HOUSEBILL的核对、更改、申领及签发；熟悉各个船公司、各航线的制单要求；负责费用的录入及确认工作；负责VGM的审核确认及系统导入工作；做好单证及文件的整理和归档任职要求：具有中专以上学历，同行业三个月以上工作经验；能熟练使用电脑，中英文打字速度快，能熟练运用OFFICE操作软件。较强的学习能力，肯吃苦耐劳，对本职工作有着强烈的责任心，耐心、细致、谨慎地对待日常单证工作；有良好的语言表达能力，善于沟通、交流，具有团队合作的精神； | N59: =LEN(M59) -> 0 | O59: =IF(ISBLANK(M59),0,COUNTA(_xlfn.TEXTSPLIT(M59,","))) -> 0
A60: =COUNTIF(B:B,B60) -> 2 | B60: 上海味捷智朗科技发展有限公司 | C60: 上海味捷智朗科技发展有限公司是熙香科技集团重要子公司之一。集团始创于2014年，是国内领先的人工智能科技企业，国内首家落地的生活服务机器人系统解决方案的服务商，公司致力于借助人工智能、物联网、大数据等技术，激发出更具交互性、智能化和安全的生活服务新业态，通过将物AI+技术应用于生活服务领域，建立智能服务一体化、作业机械无人化、需求定制自动化的“两化一体”模式，实现数据驱动的的精细化运营。公司相关智能产品具备智能感知、智能认知、自主决策、自控执行等功能，是人工智能应用场景的优秀实践和数字化转型的有益探索，大幅加快了行业数字化、智慧化转型。目前，已成长为国内知名的生活服务机器人以及智能制造解决方案提供商，专注、专业打造全系列机器人产品以及跨行业智能制造解决方案。近三年公司员工规模稳重有进，随着公司大量客户案例的成功落地，市场对公司产品的认可度也在快速提高，公司目前在生活服务机器人领域处于国内领先地位。凭借雄厚的先进技术积累和市场领先地位，公司得到了产业资本的高度青睐，先后收到了来自浙江金控、中金资本等多家知名企业的多轮融资。目前，公司在推进C轮融资和后续IPO筹备工作。在发展过程中，公司也获得了各界政府领导的支持和指导，公司主导产品之一深度应用场景—智慧AI食堂获得了习近平主席和李强总理的莅临考察指导，为企业的未来发展提供了强大的信心。 | D60: 机械电工 | E60: 5 | F60: 大专 | G60: 本岗位要求:1、3年以上非标自动化设备电气装配，有低压电工证，2、能看懂图纸3、会布线排线，会对点4、熟悉电气控制柜排布、电气元器件功能;5、熟练掌握电工的基本操作技能和工具6、能接受加班，能接受短期、临时出差 | H60: 月薪：10K-12K | I60: =_xlfn.CONCAT(D60,"（学历：",F60," 专业要求：",IF(ISBLANK(M60),"无",M60),"）") -> 机械电工（学历：大专 专业要求：机械工程,机械设计制造及其自动化,机械制造及其自动化,机械电子工程） | J60: =LEN(G60) -> 105 | K60: =_xlfn.XLOOKUP(A60,长度要求!A:A,长度要求!E:E) -> 500 | L60: =IF(J60<K60,G60,LEFT(G60,K60)&"……") -> 本岗位要求:1、3年以上非标自动化设备电气装配，有低压电工证，2、能看懂图纸3、会布线排线，会对点4、熟悉电气控制柜排布、电气元器件功能;5、熟练掌握电工的基本操作技能和工具6、能接受加班，能接受短期、临时出差 | M60: 机械工程,机械设计制造及其自动化,机械制造及其自动化,机械电子工程 | N60: =LEN(M60) -> 33 | O60: =IF(ISBLANK(M60),0,COUNTA(_xlfn.TEXTSPLIT(M60,","))) -> 4
A61: =COUNTIF(B:B,B61) -> 2 | B61: 上海味捷智朗科技发展有限公司 | C61: 上海味捷智朗科技发展有限公司是熙香科技集团重要子公司之一。集团始创于2014年，是国内领先的人工智能科技企业，国内首家落地的生活服务机器人系统解决方案的服务商，公司致力于借助人工智能、物联网、大数据等技术，激发出更具交互性、智能化和安全的生活服务新业态，通过将物AI+技术应用于生活服务领域，建立智能服务一体化、作业机械无人化、需求定制自动化的“两化一体”模式，实现数据驱动的的精细化运营。公司相关智能产品具备智能感知、智能认知、自主决策、自控执行等功能，是人工智能应用场景的优秀实践和数字化转型的有益探索，大幅加快了行业数字化、智慧化转型。目前，已成长为国内知名的生活服务机器人以及智能制造解决方案提供商，专注、专业打造全系列机器人产品以及跨行业智能制造解决方案。近三年公司员工规模稳重有进，随着公司大量客户案例的成功落地，市场对公司产品的认可度也在快速提高，公司目前在生活服务机器人领域处于国内领先地位。凭借雄厚的先进技术积累和市场领先地位，公司得到了产业资本的高度青睐，先后收到了来自浙江金控、中金资本等多家知名企业的多轮融资。目前，公司在推进C轮融资和后续IPO筹备工作。在发展过程中，公司也获得了各界政府领导的支持和指导，公司主导产品之一深度应用场景—智慧AI食堂获得了习近平主席和李强总理的莅临考察指导，为企业的未来发展提供了强大的信心。 | D61: 高级java开发工程师 | E61: 5 | F61: 大专 | G61: 岗位职责1.参与公司产品或项目的需求分析、设计与开发，根据业务需求完成高质量代码编写，实现系统功能模块；2.负责后端系统的架构设计、搭建与优化，确保系统的稳定性、性能和可扩展性，保障系统高效稳定运行；3.与前端开发团队紧密协作，定义数据接口规范，完成前后端数据交互开发，确保项目整体功能的完整性和流畅性；4.进行数据库设计、优化和维护，熟练编写SQL语句，处理复杂的数据操作和事务管理，保障数据的准确性和安全性；5.编写详细准确的技术文档，包括设计文档、接口文档、使用说明等，为团队协作和系统维护提供支持6.独立解决和处理所负责的项目的运维和监控，及时处理生产环境中的故障和问题，保障系统的可用性和稳定性；7.持续关注行业技术发展趋势，引入新技术、新工具，优化现有技术方案和开发流程，提升团队技术水平和开发效率。任职要求1.专科及以上学历，计算机科学与技术、软件工程、机械、自动化等相关专业优先。2.具有5年以上Java开发经验，有完整的项目开发经验，能够独立承担模块开发任务3.扎实的Java基础知识，熟悉常用设计模式，对多线程、并发编程、JVM原理及调优有深入理解。4.熟练掌握Spring、SpringBoot、SpringCloud等主流开发框架，熟悉其原理和应用场景，能够进行高效开发。5.熟练使用MyBatis、Hibernate等持久层框架，熟悉数据库设计和优化，精通MySQL等关系型数据库6.熟悉常用类库及消息中间件，如Redis、RabbitMQ、Kafka等，了解其基本原理和应用场景，能够进行配置和使用。7.熟悉Linux操作系统，掌握常用命令，能够进行服务器部署、调试和运维工作。8.具备良好的沟通能力和团队协作精神，工作认真负责，有较强的学习能力和解决问题的能力 | H61: 月薪：15K-20K | I61: =_xlfn.CONCAT(D61,"（学历：",F61," 专业要求：",IF(ISBLANK(M61),"无",M61),"）") -> 高级java开发工程师（学历：大专 专业要求：计算机科学与技术,电子与计算机工程,计算机网络技术,计算机应用技术,计算机应用工程） | J61: =LEN(G61) -> 745 | K61: =_xlfn.XLOOKUP(A61,长度要求!A:A,长度要求!E:E) -> 500 | L61: =IF(J61<K61,G61,LEFT(G61,K61)&"……") -> 岗位职责1.参与公司产品或项目的需求分析、设计与开发，根据业务需求完成高质量代码编写，实现系统功能模块；2.负责后端系统的架构设计、搭建与优化，确保系统的稳定性、性能和可扩展性，保障系统高效稳定运行；3.与前端开发团队紧密协作，定义数据接口规范，完成前后端数据交互开发，确保项目整体功能的完整性和流畅性；4.进行数据库设计、优化和维护，熟练编写SQL语句，处理复杂的数据操作和事务管理，保障数据的准确性和安全性；5.编写详细准确的技术文档，包括设计文档、接口文档、使用说明等，为团队协作和系统维护提供支持6.独立解决和处理所负责的项目的运维和监控，及时处理生产环境中的故障和问题，保障系统的可用性和稳定性；7.持续关注行业技术发展趋势，引入新技术、新工具，优化现有技术方案和开发流程，提升团队技术水平和开发效率。任职要求1.专科及以上学历，计算机科学与技术、软件工程、机械、自动化等相关专业优先。2.具有5年以上Java开发经验，有完整的项目开发经验，能够独立承担模块开发任务3.扎实的Java基础知识，熟悉常用设计模式，对多线程、并发编程、JVM原理及调优有深入理解。4.熟练掌握Spring、Sp…… | M61: 计算机科学与技术,电子与计算机工程,计算机网络技术,计算机应用技术,计算机应用工程 | N61: =LEN(M61) -> 41 | O61: =IF(ISBLANK(M61),0,COUNTA(_xlfn.TEXTSPLIT(M61,","))) -> 5
A62: =COUNTIF(B:B,B62) -> 3 | B62: 上海鲸鱼机器人科技有限公司 | C62: 鲸鱼机器人专注于青少年人工智能与教育机器人领域，是集机器人软硬件的设计、研发、生产、销售为一体的高科技公司。 | D62: 科技馆店员 | E62: 5 | F62: 大专 | G62: 岗位职责:1、服务引导：承担游客的引导、与游玩提供基础服务2、活动与执行人员：负责组织场馆内活动、及其他互动项目，提升游客的参与感和体验感，同时配合其他部门完成临时性工作3、设备维护人员：负责场馆内展品及设备的日常维护与检修，确保展品功能正常，为游客提供良好的互动体验4、安全与秩序管理人员：负责维护场馆内外的秩序，确保游客环境安全，并处理突发情况，如人员疏散或紧急救援5、其他辅助人员：根据实际需求，配合其他部门完成临时性工作，如场馆清洁、车辆协调等任职要求:1、有1年以上儿童乐园、亲子场馆工作经验优先2、有良好的服务意识，亲善友好，能主动为顾客解决问题3、较强的口头沟通能力 | H62: 日薪：120/天 | I62: =_xlfn.CONCAT(D62,"（学历：",F62," 专业要求：",IF(ISBLANK(M62),"无",M62),"）") -> 科技馆店员（学历：大专 专业要求：无） | J62: =LEN(G62) -> 290 | K62: =_xlfn.XLOOKUP(A62,长度要求!A:A,长度要求!E:E) -> 500 | L62: =IF(J62<K62,G62,LEFT(G62,K62)&"……") -> 岗位职责:1、服务引导：承担游客的引导、与游玩提供基础服务2、活动与执行人员：负责组织场馆内活动、及其他互动项目，提升游客的参与感和体验感，同时配合其他部门完成临时性工作3、设备维护人员：负责场馆内展品及设备的日常维护与检修，确保展品功能正常，为游客提供良好的互动体验4、安全与秩序管理人员：负责维护场馆内外的秩序，确保游客环境安全，并处理突发情况，如人员疏散或紧急救援5、其他辅助人员：根据实际需求，配合其他部门完成临时性工作，如场馆清洁、车辆协调等任职要求:1、有1年以上儿童乐园、亲子场馆工作经验优先2、有良好的服务意识，亲善友好，能主动为顾客解决问题3、较强的口头沟通能力 | N62: =LEN(M62) -> 0 | O62: =IF(ISBLANK(M62),0,COUNTA(_xlfn.TEXTSPLIT(M62,","))) -> 0
A63: =COUNTIF(B:B,B63) -> 3 | B63: 上海鲸鱼机器人科技有限公司 | C63: 鲸鱼机器人专注于青少年人工智能与教育机器人领域，是集机器人软硬件的设计、研发、生产、销售为一体的高科技公司。 | D63: 技术服务实习生 | E63: 2 | F63: 大专 | G63: 工作职责1、处理用户咨询与反馈，提供专业、及时的解答；2、协助分析客户诉求，推动问题高效解决；3、记录并整理客诉数据，为产品优化提供支持；4、团队协作，共同提升用户满意度。任职要求1、本科及以上学历，专业不限，有客服或机构教育经验者优先；2、具备优秀的沟通能力和同理心，能耐心应对各种用户场景；3、逻辑清晰，善于总结，对数据敏感；4、积极主动，有责任心和团队精神；5、对教育科技、机器人行业感兴趣者加分！ | H63: 日薪：120/天 | I63: =_xlfn.CONCAT(D63,"（学历：",F63," 专业要求：",IF(ISBLANK(M63),"无",M63),"）") -> 技术服务实习生（学历：大专 专业要求：无） | J63: =LEN(G63) -> 202 | K63: =_xlfn.XLOOKUP(A63,长度要求!A:A,长度要求!E:E) -> 500 | L63: =IF(J63<K63,G63,LEFT(G63,K63)&"……") -> 工作职责1、处理用户咨询与反馈，提供专业、及时的解答；2、协助分析客户诉求，推动问题高效解决；3、记录并整理客诉数据，为产品优化提供支持；4、团队协作，共同提升用户满意度。任职要求1、本科及以上学历，专业不限，有客服或机构教育经验者优先；2、具备优秀的沟通能力和同理心，能耐心应对各种用户场景；3、逻辑清晰，善于总结，对数据敏感；4、积极主动，有责任心和团队精神；5、对教育科技、机器人行业感兴趣者加分！ | N63: =LEN(M63) -> 0 | O63: =IF(ISBLANK(M63),0,COUNTA(_xlfn.TEXTSPLIT(M63,","))) -> 0
A64: =COUNTIF(B:B,B64) -> 3 | B64: 上海鲸鱼机器人科技有限公司 | C64: 鲸鱼机器人专注于青少年人工智能与教育机器人领域，是集机器人软硬件的设计、研发、生产、销售为一体的高科技公司。 | D64: 研学交付实习生 | E64: 2 | F64: 大专 | G64: AI机器人幼儿中小学教育背景工作职责1．协助机器人研学活动前期物料、教具准备与检查工作；2．支持活动现场执行，辅助主讲导师完成教学任务；3．经过培训，可独立进行展厅/工厂等内容讲解，组织学生课程活动;4．负责活动现场照片、视频等素材拍摄及整理；5．参与活动后设备回收、物料清点、场地整理及反馈数据的收集与汇总；6．完成团队负责人安排的其他相关工作。任职要求1．专科及以上学历，理工科、教育类、学前教育相关专业背景优先。2．有机器人、编程、无人机经验者优先；3．具备较强的动手能力和沟通能力，乐于接触新科技产品；4．拥有出色的沟通表达和互动引导能力，喜欢孩子，有耐心和热情；5．责任心强，积极主动，注重细节，具备优秀的团队协作精神；6．根据活动需求，适应偶尔周末工作（有调休）。 | H64: 日薪：120/天 | I64: =_xlfn.CONCAT(D64,"（学历：",F64," 专业要求：",IF(ISBLANK(M64),"无",M64),"）") -> 研学交付实习生（学历：大专 专业要求：无） | J64: =LEN(G64) -> 338 | K64: =_xlfn.XLOOKUP(A64,长度要求!A:A,长度要求!E:E) -> 500 | L64: =IF(J64<K64,G64,LEFT(G64,K64)&"……") -> AI机器人幼儿中小学教育背景工作职责1．协助机器人研学活动前期物料、教具准备与检查工作；2．支持活动现场执行，辅助主讲导师完成教学任务；3．经过培训，可独立进行展厅/工厂等内容讲解，组织学生课程活动;4．负责活动现场照片、视频等素材拍摄及整理；5．参与活动后设备回收、物料清点、场地整理及反馈数据的收集与汇总；6．完成团队负责人安排的其他相关工作。任职要求1．专科及以上学历，理工科、教育类、学前教育相关专业背景优先。2．有机器人、编程、无人机经验者优先；3．具备较强的动手能力和沟通能力，乐于接触新科技产品；4．拥有出色的沟通表达和互动引导能力，喜欢孩子，有耐心和热情；5．责任心强，积极主动，注重细节，具备优秀的团队协作精神；6．根据活动需求，适应偶尔周末工作（有调休）。 | N64: =LEN(M64) -> 0 | O64: =IF(ISBLANK(M64),0,COUNTA(_xlfn.TEXTSPLIT(M64,","))) -> 0
A65: =COUNTIF(B:B,B65) -> 1 | B65: 上海慧之颜美容有限公司 | C65: 在上海市中心坐拥5家分店，主营品牌苗方清颜，主打祛痘及问题肌肤管理。开业14年以来，累计会员3000名以上。因为拓店需求，现招聘10名有工作经验的高级美容师及美容学徒，欢迎有志之士的加入。 | D65: 美容师 | E65: 5 | F65: 大专 | G65: 工作职责：1、为顾客提供皮肤护理、美容服务；2、安装美容仪器要求、程序、性能进行美容护理操作；3、保持工作环境的干净整洁；4、学习产品知识和专业技术，不断提高自身职业素质和技能。任职要求：1、形象好、气质佳，在20-40岁之间；2、有一年以上美容、仪器操作经验。有针清祛痘经验的优先3、沟通理解能力强、技术手法好，有服务意识；4、具有亲和力和团队精神，有上进心5、销售能力强的优先考虑薪资福利：1、试用期有保底工资2、转正后工资底薪+提成+奖金，具体详谈，薪资优厚，阶段性考核通过底薪提高3、提供宿舍4、完整的晋升通道：美容师-资深美容师-美容顾问-储备店长-店长5、带薪年假，生日福利，各种额外福利6、试用期过了享受员工福利价购买公司产品，以及免费做脱毛清洁等基础护理项目 | H65: 月薪：7K-13K | I65: =_xlfn.CONCAT(D65,"（学历：",F65," 专业要求：",IF(ISBLANK(M65),"无",M65),"）") -> 美容师（学历：大专 专业要求：无） | J65: =LEN(G65) -> 337 | K65: =_xlfn.XLOOKUP(A65,长度要求!A:A,长度要求!E:E) -> 500 | L65: =IF(J65<K65,G65,LEFT(G65,K65)&"……") -> 工作职责：1、为顾客提供皮肤护理、美容服务；2、安装美容仪器要求、程序、性能进行美容护理操作；3、保持工作环境的干净整洁；4、学习产品知识和专业技术，不断提高自身职业素质和技能。任职要求：1、形象好、气质佳，在20-40岁之间；2、有一年以上美容、仪器操作经验。有针清祛痘经验的优先3、沟通理解能力强、技术手法好，有服务意识；4、具有亲和力和团队精神，有上进心5、销售能力强的优先考虑薪资福利：1、试用期有保底工资2、转正后工资底薪+提成+奖金，具体详谈，薪资优厚，阶段性考核通过底薪提高3、提供宿舍4、完整的晋升通道：美容师-资深美容师-美容顾问-储备店长-店长5、带薪年假，生日福利，各种额外福利6、试用期过了享受员工福利价购买公司产品，以及免费做脱毛清洁等基础护理项目 | N65: =LEN(M65) -> 0 | O65: =IF(ISBLANK(M65),0,COUNTA(_xlfn.TEXTSPLIT(M65,","))) -> 0
A66: =COUNTIF(B:B,B66) -> 3 | B66: 上海虹艺空调工程有限公司 | C66: 上海虹艺空调工程有限公司成立于2006年，公司位于上海市闵行区吴中路1268号。本公司主要从事暖通工程项目，主营品牌为格力，是上海格力空调一级代理商和格力电器指定客户服务中心。是首家被格力总部命名的上海格力空调旗舰店，上海地区唯一《格力专卖店开拓贡献奖》获得者。2022年5月又被格力总部评选为全国《卓越工程商》。公司还是上海市“守合同重信用”单位；上海市诚信创建单位，上海市闵行区文明单位，同时也是中央政府采购指定供应商、上海市政府采购中心指定供应商。 | D66: 暖通设计师 | E66: 2 | F66: 大专 | G66: （一）岗位要求​学历与专业​本科及以上学历，建筑环境与能源应用工程、能源与动力工程（建筑环境方向）、土木工程（建筑设备方向）等相关专业。​成绩优良，核心课程（暖通空调、供热工程、通风工程、建筑节能技术等）无挂科记录。​知识与技能​掌握暖通系统设计基础理论，了解《民用建筑供暖通风与空气调节设计规范》等行业标准；​能熟练使用AutoCAD绘制暖通图纸，具备Revit、鸿业暖通等设计软件基础操作能力者优先；​了解BIM技术在暖通设计中的应用，有课程设计、毕业设计（如办公楼空调系统设计）经验者优先。​素质与能力​具备较强的逻辑思维与方案梳理能力，能清晰表达设计思路；​工作严谨细致，有责任心，具备团队协作意识；​主动学习行业新技术（如绿色建筑、智能暖通），适应项目型工作节奏。​其他​持有CAD工程师认证、BIM技能等级证书者优先；​参与过“人环奖”、高校暖通设计竞赛等赛事者优先。 | H66: 月薪：7K-12K | I66: =_xlfn.CONCAT(D66,"（学历：",F66," 专业要求：",IF(ISBLANK(M66),"无",M66),"）") -> 暖通设计师（学历：大专 专业要求：建筑环境与能源应用工程,能源与动力工程,供热通风与空调工程技术,环境工程,建筑设备工程技术,土木工程） | J66: =LEN(G66) -> 390 | K66: =_xlfn.XLOOKUP(A66,长度要求!A:A,长度要求!E:E) -> 500 | L66: =IF(J66<K66,G66,LEFT(G66,K66)&"……") -> （一）岗位要求​学历与专业​本科及以上学历，建筑环境与能源应用工程、能源与动力工程（建筑环境方向）、土木工程（建筑设备方向）等相关专业。​成绩优良，核心课程（暖通空调、供热工程、通风工程、建筑节能技术等）无挂科记录。​知识与技能​掌握暖通系统设计基础理论，了解《民用建筑供暖通风与空气调节设计规范》等行业标准；​能熟练使用AutoCAD绘制暖通图纸，具备Revit、鸿业暖通等设计软件基础操作能力者优先；​了解BIM技术在暖通设计中的应用，有课程设计、毕业设计（如办公楼空调系统设计）经验者优先。​素质与能力​具备较强的逻辑思维与方案梳理能力，能清晰表达设计思路；​工作严谨细致，有责任心，具备团队协作意识；​主动学习行业新技术（如绿色建筑、智能暖通），适应项目型工作节奏。​其他​持有CAD工程师认证、BIM技能等级证书者优先；​参与过“人环奖”、高校暖通设计竞赛等赛事者优先。 | M66: 建筑环境与能源应用工程,能源与动力工程,供热通风与空调工程技术,环境工程,建筑设备工程技术,土木工程 | N66: =LEN(M66) -> 50 | O66: =IF(ISBLANK(M66),0,COUNTA(_xlfn.TEXTSPLIT(M66,","))) -> 6
A67: =COUNTIF(B:B,B67) -> 3 | B67: 上海虹艺空调工程有限公司 | C67: 上海虹艺空调工程有限公司成立于2006年，公司位于上海市闵行区吴中路1268号。本公司主要从事暖通工程项目，主营品牌为格力，是上海格力空调一级代理商和格力电器指定客户服务中心。是首家被格力总部命名的上海格力空调旗舰店，上海地区唯一《格力专卖店开拓贡献奖》获得者。2022年5月又被格力总部评选为全国《卓越工程商》。公司还是上海市“守合同重信用”单位；上海市诚信创建单位，上海市闵行区文明单位，同时也是中央政府采购指定供应商、上海市政府采购中心指定供应商。 | D67: 中央空调维修技术员 | E67: 3 | F67: 大专 | G67: （一）岗位要求​学历与专业​大专及以上学历，供热通风与空调工程技术、机电一体化技术、建筑设备工程技术等相关专业。​知识与技能​掌握中央空调系统（水冷机组、风冷热泵、VRV多联机等）的工作原理与组成结构；​能使用万用表、钳形表等工具检测电气故障，了解制冷系统打压、抽真空、加氟等基础操作；​熟悉中央空调控制系统（如PLC、变频控制）基础原理者优先，有金工实习、设备拆装实训经验者优先。​素质与能力​动手能力强，能适应一定的现场作业（如机房巡检、设备维修）；​具备较强的问题排查能力与应急处理意识，能清晰记录维修过程；​吃苦耐劳，服从工作安排（部分项目需短途出差或轮班巡检）。​其他​持有制冷与空调作业特种作业操作证（低压电工证）者优先；​参与过高校机电设备维修竞赛、实习期间从事过中央空调运维工作者优先。 | H67: 月薪：7K-15K | I67: =_xlfn.CONCAT(D67,"（学历：",F67," 专业要求：",IF(ISBLANK(M67),"无",M67),"）") -> 中央空调维修技术员（学历：大专 专业要求：制冷与空调技术,供热通风与空调工程技术,机电设备安装技术,建筑智能化工程技术,机电一体化技术） | J67: =LEN(G67) -> 351 | K67: =_xlfn.XLOOKUP(A67,长度要求!A:A,长度要求!E:E) -> 500 | L67: =IF(J67<K67,G67,LEFT(G67,K67)&"……") -> （一）岗位要求​学历与专业​大专及以上学历，供热通风与空调工程技术、机电一体化技术、建筑设备工程技术等相关专业。​知识与技能​掌握中央空调系统（水冷机组、风冷热泵、VRV多联机等）的工作原理与组成结构；​能使用万用表、钳形表等工具检测电气故障，了解制冷系统打压、抽真空、加氟等基础操作；​熟悉中央空调控制系统（如PLC、变频控制）基础原理者优先，有金工实习、设备拆装实训经验者优先。​素质与能力​动手能力强，能适应一定的现场作业（如机房巡检、设备维修）；​具备较强的问题排查能力与应急处理意识，能清晰记录维修过程；​吃苦耐劳，服从工作安排（部分项目需短途出差或轮班巡检）。​其他​持有制冷与空调作业特种作业操作证（低压电工证）者优先；​参与过高校机电设备维修竞赛、实习期间从事过中央空调运维工作者优先。 | M67: 制冷与空调技术,供热通风与空调工程技术,机电设备安装技术,建筑智能化工程技术,机电一体化技术 | N67: =LEN(M67) -> 46 | O67: =IF(ISBLANK(M67),0,COUNTA(_xlfn.TEXTSPLIT(M67,","))) -> 5
A68: =COUNTIF(B:B,B68) -> 3 | B68: 上海虹艺空调工程有限公司 | C68: 上海虹艺空调工程有限公司成立于2006年，公司位于上海市闵行区吴中路1268号。本公司主要从事暖通工程项目，主营品牌为格力，是上海格力空调一级代理商和格力电器指定客户服务中心。是首家被格力总部命名的上海格力空调旗舰店，上海地区唯一《格力专卖店开拓贡献奖》获得者。2022年5月又被格力总部评选为全国《卓越工程商》。公司还是上海市“守合同重信用”单位；上海市诚信创建单位，上海市闵行区文明单位，同时也是中央政府采购指定供应商、上海市政府采购中心指定供应商。 | D68: 造价工程师 | E68: 2 | F68: 大专 | G68: （一）岗位要求​学历与专业​本科及以上学历，工程造价、建筑环境与能源应用工程、土木工程等相关专业。​熟悉暖通设备（空调机组、风机、散热器等）型号与市场价格者优先。​知识与技能​掌握工程造价基础理论，了解《建设工程工程量清单计价规范》，能识别暖通工程图纸；​能熟练使用广联达、鲁班等造价软件进行工程量计算与套价，有课程设计（如暖通工程预算编制）经验者优先；​了解暖通工程施工流程，能结合施工工艺分析造价组成。​素质与能力​具备较强的数据分析能力与细节把控能力，对数字敏感；​沟通表达清晰，能与设计、施工团队协同对接造价问题；​学习能力强，愿意主动了解建材市场价格波动与政策调整（如增值税率变化）。​其他​持有二级造价工程师（基础科目）合格证明者优先；​参与过高校工程造价竞赛、实习期间接触过暖通预算工作者优先 | H68: 月薪：8K-15K | I68: =_xlfn.CONCAT(D68,"（学历：",F68," 专业要求：",IF(ISBLANK(M68),"无",M68),"）") -> 造价工程师（学历：大专 专业要求：建筑环境与能源应用工程,工程造价,能源与动力工程,供热通风与空调工程技术,建设工程管理,建筑工程技术） | J68: =LEN(G68) -> 353 | K68: =_xlfn.XLOOKUP(A68,长度要求!A:A,长度要求!E:E) -> 500 | L68: =IF(J68<K68,G68,LEFT(G68,K68)&"……") -> （一）岗位要求​学历与专业​本科及以上学历，工程造价、建筑环境与能源应用工程、土木工程等相关专业。​熟悉暖通设备（空调机组、风机、散热器等）型号与市场价格者优先。​知识与技能​掌握工程造价基础理论，了解《建设工程工程量清单计价规范》，能识别暖通工程图纸；​能熟练使用广联达、鲁班等造价软件进行工程量计算与套价，有课程设计（如暖通工程预算编制）经验者优先；​了解暖通工程施工流程，能结合施工工艺分析造价组成。​素质与能力​具备较强的数据分析能力与细节把控能力，对数字敏感；​沟通表达清晰，能与设计、施工团队协同对接造价问题；​学习能力强，愿意主动了解建材市场价格波动与政策调整（如增值税率变化）。​其他​持有二级造价工程师（基础科目）合格证明者优先；​参与过高校工程造价竞赛、实习期间接触过暖通预算工作者优先 | M68: 建筑环境与能源应用工程,工程造价,能源与动力工程,供热通风与空调工程技术,建设工程管理,建筑工程技术 | N68: =LEN(M68) -> 50 | O68: =IF(ISBLANK(M68),0,COUNTA(_xlfn.TEXTSPLIT(M68,","))) -> 6
A69: =COUNTIF(B:B,B69) -> 5 | B69: 上海宝盖头家居科技有限公司 | C69: 宝盖头·启屋家居于上海2020年成立，是一群行业精英创立&综合性家居新零售体验中心，超4000平方米近30个当今流行趋势空间展示区，满足客户多种选择，设上下三层，配备咖啡洽谈区、儿童观影区、灯饰展示区、软装选材区、路演厅、设计师共享空间等，公司不但为消费者提供高质量性价比家居产品，且提供创新体验设计服务，为消费者建立一站式购物享受，设有星咖设平台为设计师提供全案及软装系统化专业赋能。我们搜集全球范围内家居最流行趋势，寻找有共鸣感的家居。直接、严选、自由是我们理想的经营方式。我们提供专业的全屋软装搭配服务，最大程度输出“追求有品质的个性化生活”理念。我们希望能有更多的人通过我们，享受到高品质的家居生活。 | D69: 新媒体运营-偏拍摄/剪辑文案 | E69: 2 | F69: 大专 | G69: 岗位职责：1、强摄影及修图能力，负责配合小红书平台运营的摄影摄像；2、负责抖音、视频号等公司各平台的信息流短视频拍摄、剪辑、画面包装、调色、声音处理、字幕、特效合成等；3、负责新媒体平台运营及文案撰写（微博、微信、公众号、抖音等）；4、负责新媒体平台的内容选取、编辑、发布；5、负责平台粉丝招募和维护；6、负责活动内容质量和传播度；7、负责新媒体产品挖掘与运营，及时掌握同行业新媒体动向，与现公司业务相结合，进行网络营销推广，及时反馈对公司的相关信息；8、参与视频创作团队完成视频内容创意策划。对素材进行整理和分类，优化与内容策划的协作流程，提高整体输出视频效率；建立并完善新媒体资源库；9、配合制作公司各类宣传海报、酷家乐软件渲然图片等工作；10、认真完成领导交代的其他工作。任职要求：1、强摄影摄像能力；2、熟悉新媒体平台（抖音、微信、微博、微信朋友圈、公众号等）文案；3、有文字功底，阅读能力，熟悉平面设计、摄影剪辑；4、参与短视频拍摄；5、有良好的沟通能力，和团队合作精神。工作时间：做六休一，早上9:30-下午18:30；工作地点：上海市闵行区颛桥镇光华路158号（宝盖头家居）；福利待遇：五险一金，生日红包（蛋糕），团建活动，节日礼品，带薪年假，每日还可享受现磨咖啡。 | H69: 月薪：6K-10K | I69: =_xlfn.CONCAT(D69,"（学历：",F69," 专业要求：",IF(ISBLANK(M69),"无",M69),"）") -> 新媒体运营-偏拍摄/剪辑文案（学历：大专 专业要求：电子信息科学与技术,数字媒体技术,电子与计算机工程） | J69: =LEN(G69) -> 540 | K69: =_xlfn.XLOOKUP(A69,长度要求!A:A,长度要求!E:E) -> 500 | L69: =IF(J69<K69,G69,LEFT(G69,K69)&"……") -> 岗位职责：1、强摄影及修图能力，负责配合小红书平台运营的摄影摄像；2、负责抖音、视频号等公司各平台的信息流短视频拍摄、剪辑、画面包装、调色、声音处理、字幕、特效合成等；3、负责新媒体平台运营及文案撰写（微博、微信、公众号、抖音等）；4、负责新媒体平台的内容选取、编辑、发布；5、负责平台粉丝招募和维护；6、负责活动内容质量和传播度；7、负责新媒体产品挖掘与运营，及时掌握同行业新媒体动向，与现公司业务相结合，进行网络营销推广，及时反馈对公司的相关信息；8、参与视频创作团队完成视频内容创意策划。对素材进行整理和分类，优化与内容策划的协作流程，提高整体输出视频效率；建立并完善新媒体资源库；9、配合制作公司各类宣传海报、酷家乐软件渲然图片等工作；10、认真完成领导交代的其他工作。任职要求：1、强摄影摄像能力；2、熟悉新媒体平台（抖音、微信、微博、微信朋友圈、公众号等）文案；3、有文字功底，阅读能力，熟悉平面设计、摄影剪辑；4、参与短视频拍摄；5、有良好的沟通能力，和团队合作精神。工作时间：做六休一，早上9:30-下午18:30；工作地点：上海市闵行区颛桥镇光华路158号（宝盖头家居）；福利待遇：…… | M69: 电子信息科学与技术,数字媒体技术,电子与计算机工程 | N69: =LEN(M69) -> 25 | O69: =IF(ISBLANK(M69),0,COUNTA(_xlfn.TEXTSPLIT(M69,","))) -> 3
A70: =COUNTIF(B:B,B70) -> 2 | B70: 上海市闵行区医疗急救中心 | C70: 上海市闵行区医疗急救中心隶属于上海市闵行区卫生健康委员会，是区内唯一从事院前急救专业的公立医疗卫生事业单位。承担了闵行区内272万人口的院前急救、危急重病症初步诊治与抢救护理。职责还包括急救临床教学、急救医学科研、急救卫生技术人员培训和区域重特大事故现场紧急救援以及大型赛事活动现场医疗保障等工作。 | D70: 院前急救辅助人员 | E70: 2 | F70: 大专 | G70: 1.协助急救医生做好现场医疗急救工作；2.承担病人的抬抱转运工作；3.协助急救驾驶员做好安全行车、车辆卫生及其他辅助性工作。 | H70: 月薪：4K-5K | I70: =_xlfn.CONCAT(D70,"（学历：",F70," 专业要求：",IF(ISBLANK(M70),"无",M70),"）") -> 院前急救辅助人员（学历：大专 专业要求：无） | J70: =LEN(G70) -> 62 | K70: =_xlfn.XLOOKUP(A70,长度要求!A:A,长度要求!E:E) -> 500 | L70: =IF(J70<K70,G70,LEFT(G70,K70)&"……") -> 1.协助急救医生做好现场医疗急救工作；2.承担病人的抬抱转运工作；3.协助急救驾驶员做好安全行车、车辆卫生及其他辅助性工作。 | N70: =LEN(M70) -> 0 | O70: =IF(ISBLANK(M70),0,COUNTA(_xlfn.TEXTSPLIT(M70,","))) -> 0
A71: =COUNTIF(B:B,B71) -> 2 | B71: 上海博赫尔科技集团有限公司 | C71: 博赫尔（POHIR）科技集团是一家全球智能化清洁清洗解决方案提供商和服务商，POHIR博赫尔品牌起源于上个世纪90年代的德国，经过近20多年的发展和不断创新，POHIR博赫尔在全球已覆盖了北美，欧洲，东南亚等全球50多个国家或地区，并为全球30万+客户提供清洁清洗设备解决方案。在欧洲，博赫尔（POHIR）分别在德国、法国等地设有2个仓储运营服务中心和1个产品设计研发中心。在北美，博赫尔（POHIR）分别和本土巨头沃尔玛Walmart和亚马逊AMAZON合作在纽约和洛杉矶、芝加哥等设有3个海外仓运营服务中心。在中国，博赫尔（POHIR）于2013年将总部设在中国上海，目前博赫尔（POHIR）科技集团在国内设立了1家产业研究院、2家产品研发中心、4大产业园和制造基地、600多家售后服务网点、5万㎡中心仓库。旗下运营公司拥有国家级专利30+，并于2021年由上海市科学技术委员会、上海市财政局、国家税务总局上海市分局联合认定为“高新技术企业”和“科技型企业”称号。目前公司的生产经营品类也从高压清洗机逐步拓展到商用扫地机，商用洗地机，工业吸尘器，扫雪机，疏通机，吹干机，抛光机，升降堆高设备，交通设备等，其主营产品在国内头部电商平台（天猫、京东等）销量连续多年位居热销TOP水平。博赫尔（POHIR）目前已经为家乐福，太太乐，新希望集团，中粮集团，国药集团，万科物业，上海仁济医院，碧桂园，海底捞，伊利集团及大型国央企，政府和军队提供产品和服务解决方案，建立了良好的合作关系。博赫尔（POHIR）集团秉承成为全球清洁清洗设备专家的企业愿景，始终着眼全球化视野，坚持务实，稳健，创新，环保的发展理念，且始终坚持客户至上，用心服务的原则不断前进！ | D71: 电商客服 | E71: 5 | F71: 大专 | G71: 岗位职责：1、通过聊天工具完成平台的售前客户咨询接待；2、负责跟进订单、异常件管理；3、服从安排，负责其它售后问题及突发事件。4、打字速度50字/分钟以上；岗位要求：1、经验不限；2、做6休1，国定假期正常放假。公司提供完善的培训、轮岗、转岗及晋升机会！ | H71: 日薪：120-200/天 | I71: =_xlfn.CONCAT(D71,"（学历：",F71," 专业要求：",IF(ISBLANK(M71),"无",M71),"）") -> 电商客服（学历：大专 专业要求：电子商务类） | J71: =LEN(G71) -> 127 | K71: =_xlfn.XLOOKUP(A71,长度要求!A:A,长度要求!E:E) -> 500 | L71: =IF(J71<K71,G71,LEFT(G71,K71)&"……") -> 岗位职责：1、通过聊天工具完成平台的售前客户咨询接待；2、负责跟进订单、异常件管理；3、服从安排，负责其它售后问题及突发事件。4、打字速度50字/分钟以上；岗位要求：1、经验不限；2、做6休1，国定假期正常放假。公司提供完善的培训、轮岗、转岗及晋升机会！ | M71: 电子商务类 | N71: =LEN(M71) -> 5 | O71: =IF(ISBLANK(M71),0,COUNTA(_xlfn.TEXTSPLIT(M71,","))) -> 1
A72: =COUNTIF(B:B,B72) -> 2 | B72: 上海博赫尔科技集团有限公司 | C72: 博赫尔（POHIR）科技集团是一家全球智能化清洁清洗解决方案提供商和服务商，POHIR博赫尔品牌起源于上个世纪90年代的德国，经过近20多年的发展和不断创新，POHIR博赫尔在全球已覆盖了北美，欧洲，东南亚等全球50多个国家或地区，并为全球30万+客户提供清洁清洗设备解决方案。在欧洲，博赫尔（POHIR）分别在德国、法国等地设有2个仓储运营服务中心和1个产品设计研发中心。在北美，博赫尔（POHIR）分别和本土巨头沃尔玛Walmart和亚马逊AMAZON合作在纽约和洛杉矶、芝加哥等设有3个海外仓运营服务中心。在中国，博赫尔（POHIR）于2013年将总部设在中国上海，目前博赫尔（POHIR）科技集团在国内设立了1家产业研究院、2家产品研发中心、4大产业园和制造基地、600多家售后服务网点、5万㎡中心仓库。旗下运营公司拥有国家级专利30+，并于2021年由上海市科学技术委员会、上海市财政局、国家税务总局上海市分局联合认定为“高新技术企业”和“科技型企业”称号。目前公司的生产经营品类也从高压清洗机逐步拓展到商用扫地机，商用洗地机，工业吸尘器，扫雪机，疏通机，吹干机，抛光机，升降堆高设备，交通设备等，其主营产品在国内头部电商平台（天猫、京东等）销量连续多年位居热销TOP水平。博赫尔（POHIR）目前已经为家乐福，太太乐，新希望集团，中粮集团，国药集团，万科物业，上海仁济医院，碧桂园，海底捞，伊利集团及大型国央企，政府和军队提供产品和服务解决方案，建立了良好的合作关系。博赫尔（POHIR）集团秉承成为全球清洁清洗设备专家的企业愿景，始终着眼全球化视野，坚持务实，稳健，创新，环保的发展理念，且始终坚持客户至上，用心服务的原则不断前进！ | D72: 跨境电商运营助理 | E72: 4 | F72: 本科 | G72: 岗位职责:1.参与跨境电商平台（亚马逊、eBay、独立站等）的运营活动，包括但不限于产品发布、活动策划与执行；2.进行市场数据分析，了解行业趋势，调整运营策略以满足市场需求；3.与团队协作，开发新的销售渠道，提升产品曝光率和销量；4.管理和优化产品列表，确保产品信息的准确性和吸引力；5.监控运营指标，及时调整运营计划以达到销售目标。任职要求：1.对跨境电商行业感兴趣，具备基本的市场分析能力；2.具备创新思维，能够不断提出和实施新的运营思路。3、大学本科在读学生，英语好. | H72: 日薪：150-200/天 | I72: =_xlfn.CONCAT(D72,"（学历：",F72," 专业要求：",IF(ISBLANK(M72),"无",M72),"）") -> 跨境电商运营助理（学历：本科 专业要求：跨境电子商务） | J72: =LEN(G72) -> 237 | K72: =_xlfn.XLOOKUP(A72,长度要求!A:A,长度要求!E:E) -> 500 | L72: =IF(J72<K72,G72,LEFT(G72,K72)&"……") -> 岗位职责:1.参与跨境电商平台（亚马逊、eBay、独立站等）的运营活动，包括但不限于产品发布、活动策划与执行；2.进行市场数据分析，了解行业趋势，调整运营策略以满足市场需求；3.与团队协作，开发新的销售渠道，提升产品曝光率和销量；4.管理和优化产品列表，确保产品信息的准确性和吸引力；5.监控运营指标，及时调整运营计划以达到销售目标。任职要求：1.对跨境电商行业感兴趣，具备基本的市场分析能力；2.具备创新思维，能够不断提出和实施新的运营思路。3、大学本科在读学生，英语好. | M72: 跨境电子商务 | N72: =LEN(M72) -> 6 | O72: =IF(ISBLANK(M72),0,COUNTA(_xlfn.TEXTSPLIT(M72,","))) -> 1
A73: =COUNTIF(B:B,B73) -> 5 | B73: 上海宝盖头家居科技有限公司 | C73: 宝盖头·启屋家居于上海2020年成立，是一群行业精英创立&综合性家居新零售体验中心，超4000平方米近30个当今流行趋势空间展示区，满足客户多种选择，设上下三层，配备咖啡洽谈区、儿童观影区、灯饰展示区、软装选材区、路演厅、设计师共享空间等，公司不但为消费者提供高质量性价比家居产品，且提供创新体验设计服务，为消费者建立一站式购物享受，设有星咖设平台为设计师提供全案及软装系统化专业赋能。我们搜集全球范围内家居最流行趋势，寻找有共鸣感的家居。直接、严选、自由是我们理想的经营方式。我们提供专业的全屋软装搭配服务，最大程度输出“追求有品质的个性化生活”理念。我们希望能有更多的人通过我们，享受到高品质的家居生活。 | D73: 全屋定制销售顾问 | E73: 2 | F73: 大专 | G73: 岗位职责：1、对家装有一定了解，为客户提供全屋定制及软装搭配服务；2、熟悉全屋定制全套流程，精准捕捉客户全屋定制需求；3、为客户提供专业的一对一服务，解决客户售前产品咨询，售中对接设计师服务，售后等各类问题反馈，衔接售后部的上门服务需求；4、意向客户的定期追踪维护，定期向部门负责人进行汇报，并转化客户需求及设计服务；5、具备对接客户需求，能独立上门测量，且能现场及时有效沟通反馈；6、能够清晰把握客户方向，并讲解设计方案，能为客户提供全屋定制设计方案对接；7、对接工厂，设计师及安装团队，跟踪订单生产进度，确保按时交付，能处理安装过程中的突发问题；8、交付后定期回访，收集满意度反馈，推动复购或转介绍；9、有操作酷家乐软件能力，优先考虑；10、完成领导交代的其他工作，以及团队间的项目配合。任职要求：1、20岁以上，男女不限，展厅接待，能独立完成产品介绍；2、1年以上全屋定制硬装销售经验者优先；3、日常事务的配合：巡场、盘点、维护展厅及优化展厅；4、能独立开单，实现个人业绩增长；5、工作细心，条理清晰，有一定的的沟通、协调能力，有良好的团结协作的精神。工作时间：做六休一，早上9:30-下午18:30；工作地点：上海市闵行区颛桥镇光华路158号（宝盖头家居）；福利待遇：五险一金，生日红包（蛋糕），团建活动，节日礼品，带薪年假，每日还可享受现磨咖啡。 | H73: 月薪：10K-16K | I73: =_xlfn.CONCAT(D73,"（学历：",F73," 专业要求：",IF(ISBLANK(M73),"无",M73),"）") -> 全屋定制销售顾问（学历：大专 专业要求：土木工程,建筑学,城市设计） | J73: =LEN(G73) -> 578 | K73: =_xlfn.XLOOKUP(A73,长度要求!A:A,长度要求!E:E) -> 500 | L73: =IF(J73<K73,G73,LEFT(G73,K73)&"……") -> 岗位职责：1、对家装有一定了解，为客户提供全屋定制及软装搭配服务；2、熟悉全屋定制全套流程，精准捕捉客户全屋定制需求；3、为客户提供专业的一对一服务，解决客户售前产品咨询，售中对接设计师服务，售后等各类问题反馈，衔接售后部的上门服务需求；4、意向客户的定期追踪维护，定期向部门负责人进行汇报，并转化客户需求及设计服务；5、具备对接客户需求，能独立上门测量，且能现场及时有效沟通反馈；6、能够清晰把握客户方向，并讲解设计方案，能为客户提供全屋定制设计方案对接；7、对接工厂，设计师及安装团队，跟踪订单生产进度，确保按时交付，能处理安装过程中的突发问题；8、交付后定期回访，收集满意度反馈，推动复购或转介绍；9、有操作酷家乐软件能力，优先考虑；10、完成领导交代的其他工作，以及团队间的项目配合。任职要求：1、20岁以上，男女不限，展厅接待，能独立完成产品介绍；2、1年以上全屋定制硬装销售经验者优先；3、日常事务的配合：巡场、盘点、维护展厅及优化展厅；4、能独立开单，实现个人业绩增长；5、工作细心，条理清晰，有一定的的沟通、协调能力，有良好的团结协作的精神。工作时间：做六休一，早上9:30-下午18…… | M73: 土木工程,建筑学,城市设计 | N73: =LEN(M73) -> 13 | O73: =IF(ISBLANK(M73),0,COUNTA(_xlfn.TEXTSPLIT(M73,","))) -> 3
A74: =COUNTIF(B:B,B74) -> 3 | B74: 尚众环保科技（上海）有限公司 | C74: 尚众环保科技（上海）有限公司，成立于2012年，下属公司有：上海家常工程技术服务有限公司、浙江余慈智能电气科技有限公司。公司具有相应的三体系认证，及施工资质：电子与智能化工程专业承包二级、城市及道路照明工程专业承包二级、市政公用工程施工总承包二级、建筑装修装饰工程专业承包二级等。公司主要业务：一、“三化”工程业务1.智能化工程及维保，含道闸、门禁、监控、LED显示屏、远程智能控制系统、预付费电表系统、图像识别系统、自动监测系统等工程业务;2.亮化工程及维保，城市及道路照明工程、建筑及市政景观亮化工程、厂区园区小区亮化工程等;3.绿化工程及绿化养护，市政园林、城市道路、小区社区绿化工程等。二、装饰装修业务厂房、员工宿舍楼、小区住宅、写字楼、酒店等。三、产品生产及购销1.灯具、配电柜、电器设备等；2.燃气智能井盖（泄露检测装置）；（浙江余慈，在嘉善）3.树木、小苗、花卉等;（在崇明、余姚有公司苗木基地) | D74: CAD制图员 | E74: 1 | F74: 大专 | G74: 熟练使用CAD软件，主要负责弱电、电气、绿化制图。 | H74: 月薪：5K-7K | I74: =_xlfn.CONCAT(D74,"（学历：",F74," 专业要求：",IF(ISBLANK(M74),"无",M74),"）") -> CAD制图员（学历：大专 专业要求：无） | J74: =LEN(G74) -> 25 | K74: =_xlfn.XLOOKUP(A74,长度要求!A:A,长度要求!E:E) -> 500 | L74: =IF(J74<K74,G74,LEFT(G74,K74)&"……") -> 熟练使用CAD软件，主要负责弱电、电气、绿化制图。 | N74: =LEN(M74) -> 0 | O74: =IF(ISBLANK(M74),0,COUNTA(_xlfn.TEXTSPLIT(M74,","))) -> 0
A75: =COUNTIF(B:B,B75) -> 3 | B75: 尚众环保科技（上海）有限公司 | C75: 尚众环保科技（上海）有限公司，成立于2012年，下属公司有：上海家常工程技术服务有限公司、浙江余慈智能电气科技有限公司。公司具有相应的三体系认证，及施工资质：电子与智能化工程专业承包二级、城市及道路照明工程专业承包二级、市政公用工程施工总承包二级、建筑装修装饰工程专业承包二级等。公司主要业务：一、“三化”工程业务1.智能化工程及维保，含道闸、门禁、监控、LED显示屏、远程智能控制系统、预付费电表系统、图像识别系统、自动监测系统等工程业务;2.亮化工程及维保，城市及道路照明工程、建筑及市政景观亮化工程、厂区园区小区亮化工程等;3.绿化工程及绿化养护，市政园林、城市道路、小区社区绿化工程等。二、装饰装修业务厂房、员工宿舍楼、小区住宅、写字楼、酒店等。三、产品生产及购销1.灯具、配电柜、电器设备等；2.燃气智能井盖（泄露检测装置）；（浙江余慈，在嘉善）3.树木、小苗、花卉等;（在崇明、余姚有公司苗木基地) | D75: 销售 | E75: 5 | F75: 大专 | G75: 1.具有想从事销售工作的愿望2.性格外向、胆大、心细、能坚持3恪守规则 | H75: 月薪：5K-8K | I75: =_xlfn.CONCAT(D75,"（学历：",F75," 专业要求：",IF(ISBLANK(M75),"无",M75),"）") -> 销售（学历：大专 专业要求：无） | J75: =LEN(G75) -> 35 | K75: =_xlfn.XLOOKUP(A75,长度要求!A:A,长度要求!E:E) -> 500 | L75: =IF(J75<K75,G75,LEFT(G75,K75)&"……") -> 1.具有想从事销售工作的愿望2.性格外向、胆大、心细、能坚持3恪守规则 | N75: =LEN(M75) -> 0 | O75: =IF(ISBLANK(M75),0,COUNTA(_xlfn.TEXTSPLIT(M75,","))) -> 0
A76: =COUNTIF(B:B,B76) -> 3 | B76: 尚众环保科技（上海）有限公司 | C76: 尚众环保科技（上海）有限公司，成立于2012年，下属公司有：上海家常工程技术服务有限公司、浙江余慈智能电气科技有限公司。公司具有相应的三体系认证，及施工资质：电子与智能化工程专业承包二级、城市及道路照明工程专业承包二级、市政公用工程施工总承包二级、建筑装修装饰工程专业承包二级等。公司主要业务：一、“三化”工程业务1.智能化工程及维保，含道闸、门禁、监控、LED显示屏、远程智能控制系统、预付费电表系统、图像识别系统、自动监测系统等工程业务;2.亮化工程及维保，城市及道路照明工程、建筑及市政景观亮化工程、厂区园区小区亮化工程等;3.绿化工程及绿化养护，市政园林、城市道路、小区社区绿化工程等。二、装饰装修业务厂房、员工宿舍楼、小区住宅、写字楼、酒店等。三、产品生产及购销1.灯具、配电柜、电器设备等；2.燃气智能井盖（泄露检测装置）；（浙江余慈，在嘉善）3.树木、小苗、花卉等;（在崇明、余姚有公司苗木基地) | D76: 技术员 | E76: 2 | F76: 本科 | G76: 1、本科以上学历；2、楼宇智能化、机电一体化等相关专业；3、有电子智能化或弱电行业的实习经验，熟悉智能化各子系统，能安装调试者优先；4、具有较强的工作责任心，上进心，吃苦耐劳。 | H76: 月薪：5K-6K | I76: =_xlfn.CONCAT(D76,"（学历：",F76," 专业要求：",IF(ISBLANK(M76),"无",M76),"）") -> 技术员（学历：本科 专业要求：无） | J76: =LEN(G76) -> 88 | K76: =_xlfn.XLOOKUP(A76,长度要求!A:A,长度要求!E:E) -> 500 | L76: =IF(J76<K76,G76,LEFT(G76,K76)&"……") -> 1、本科以上学历；2、楼宇智能化、机电一体化等相关专业；3、有电子智能化或弱电行业的实习经验，熟悉智能化各子系统，能安装调试者优先；4、具有较强的工作责任心，上进心，吃苦耐劳。 | N76: =LEN(M76) -> 0 | O76: =IF(ISBLANK(M76),0,COUNTA(_xlfn.TEXTSPLIT(M76,","))) -> 0
A77: =COUNTIF(B:B,B77) -> 1 | B77: 上海墨刻景观工程有限公司 | C77: 上海墨刻景观工程有限公司是集设计与施工为一体的全程化景观服务咨询公司，同时也是最具设计魅力和施工表现的中国本土景观设计公司之一。我们致力于探索中国当代景观设计，继承本土设计的精华，同时力求创造中西文化艺术交融，强调将独到的创意与地域特征结合在一起，为不同客户创造不同的景观场所。项目地点遍及上海、北京、天津、南京、成都、西安、银川、无锡、南昌、合肥、马鞍山、蚌埠、芜湖、武汉、大同，以及美国旧金山等。项目内容包括高档住宅社区、高档酒店及旅游度假区、都市公园、郊野公园与市政广场、旅游风景区及主题公园、开发区及高科技园区等。我们与许多地方政府以及发展商建立了良好的合作关系。在项目发展过程中，我们始终充分理解业主的需求与意图，并积极寻求业主的充分参与。项目地点遍及上海、北京、天津、南京、成都、西安、银川、无锡、南昌、合肥、马鞍山、蚌埠、芜湖、武汉、大同，以及美国旧金山等。项目内容包括高档住宅社区、高档酒店及旅游度假区、都市公园、郊野公园与市政广场、旅游风景区及主题公园、开发区及高科技园区等。我们与许多地方政府以及发展商建立了良好的合作关系。在项目发展过程中，我们始终充分理解业主的需求与意图，并积极寻求业主的充分参与。MEKELandscapeundertakelandscapeprojectsfromconcepttoconstructionstages.Ouruniquedesignpracticesandhigh-qualityconstructionsmakeitbecomeoneofthebestdesigncompaniesinChina.MEKEfocusoncontemporarylandscapedesignwiththecombinationofwesternlandscapeandtraditionalChinesegardening.WeprovidetheclientsaspecialconceptionwithgeographicalcharactersindifferentsitesMEKEcontainprojectsfromsuperiorresidentialcommunities,luxuryresorts,urbanparksandplazas,scenicspots,themeparks,economicandindustrialcommunities.OursitesspreadthroughoutChinaandSanFrancisco.MEKEhavemadeagoodrelationshipwithlocalcouncilandRealestateDeveloper.Wealwayspayfullattentiontoclients'needsandmakethembarticipateintheprojectsactivelyMEKEbelievein"Designmakesbetterlife"andcarrythroughalltheprojects.Ourgreatteammakesgreatservicefortheclientswithprofessionalandresponsibledesigners.Weworkincollaborationoninternationalandlocalprojects,whichareprospective.Asateam,wealsohaveconsultantswithextensiveexperiencetohelpusproducecreativedesignworks | D77: 设计助理 | E77: 3 | F77: 大专 | G77: 1、艺术设计类相关专业，具有深厚的美术功底，有较强的艺术修养；2、掌握CAD、Coreldraw、Photoshop、SketchUp等设计软件；3、具备独特的设计理念，思维开阔、善于创意，具备丰富的空间想象力及创新能力，熟知商业美陈设计、商业空间设计、展览、展示设计及工艺结构和运作流程，能独立完成各种设计方案和施工图的制作； | H77: 月薪：3K-5K | I77: =_xlfn.CONCAT(D77,"（学历：",F77," 专业要求：",IF(ISBLANK(M77),"无",M77),"）") -> 设计助理（学历：大专 专业要求：建筑室内设计） | J77: =LEN(G77) -> 164 | K77: =_xlfn.XLOOKUP(A77,长度要求!A:A,长度要求!E:E) -> 500 | L77: =IF(J77<K77,G77,LEFT(G77,K77)&"……") -> 1、艺术设计类相关专业，具有深厚的美术功底，有较强的艺术修养；2、掌握CAD、Coreldraw、Photoshop、SketchUp等设计软件；3、具备独特的设计理念，思维开阔、善于创意，具备丰富的空间想象力及创新能力，熟知商业美陈设计、商业空间设计、展览、展示设计及工艺结构和运作流程，能独立完成各种设计方案和施工图的制作； | M77: 建筑室内设计 | N77: =LEN(M77) -> 6 | O77: =IF(ISBLANK(M77),0,COUNTA(_xlfn.TEXTSPLIT(M77,","))) -> 1
A78: =COUNTIF(B:B,B78) -> 4 | B78: 上海飒智智能科技有限公司 | C78: 飒智智能作为前沿科技领域的开拓者，以底层技术驱动为核心、面向全球复杂场景赋能的国家级高新技术企业和国家级专精特新小巨人企业。公司致力于构建“手-眼-脚-脑”一体化的智能移动类人作业机器人，深度布局汽车零部件、电子半导体、新能源、生物医药、高端食品等战略领域，业务遍布全球100+国家和地区。飒智智能以上海为总部，在深圳、天津等重要城市设立子公司，并构建以欧洲、东南亚、北美为支点的全球业务辐射网络，实现技术、市场与服务的国际化布局，为全球客户提供高端、可靠、持续进化的智能作业解决方案，成为赋能人类迈向智能新纪元的世界级科技企业。 | D78: 大客户经理 | E78: 10 | F78: 大专 | G78: 岗位职责1.协助资深销售对接头部企业客户，参与客户需求调研、方案沟通与商务谈判，快速熟悉大客户销售全流程。2.负责客户信息整理与维护，建立客户档案，跟踪客户合作进度，辅助完成订单跟进与回款协助工作。3.参与市场竞品分析与行业动态收集，输出简易分析报告，为大客户销售策略制定提供数据支持。4.完成管培生专项培养计划，包括产品知识培训、销售技巧实战演练、跨部门轮岗（任职要求1.2026届全日制本科及以上学历，专业不限，市场营销、工商管理、国际贸易等相关专业优先。2.具备强烈的目标感与抗压能力，愿意挑战高薪，对ToB大客户销售工作有明确兴趣与热情。3.拥有优秀的沟通表达与逻辑思维能力，能清晰传递信息，快速理解客户需求，有校园社团管理、大型活动组织或销售相关实习经历者优先。4.学习能力强，具备团队协作意识，能快速适应快节奏工作环境 | H78: 月薪：7K-10K | I78: =_xlfn.CONCAT(D78,"（学历：",F78," 专业要求：",IF(ISBLANK(M78),"无",M78),"）") -> 大客户经理（学历：大专 专业要求：工商管理,市场营销,国际经济与贸易,国际贸易学） | J78: =LEN(G78) -> 365 | K78: =_xlfn.XLOOKUP(A78,长度要求!A:A,长度要求!E:E) -> 500 | L78: =IF(J78<K78,G78,LEFT(G78,K78)&"……") -> 岗位职责1.协助资深销售对接头部企业客户，参与客户需求调研、方案沟通与商务谈判，快速熟悉大客户销售全流程。2.负责客户信息整理与维护，建立客户档案，跟踪客户合作进度，辅助完成订单跟进与回款协助工作。3.参与市场竞品分析与行业动态收集，输出简易分析报告，为大客户销售策略制定提供数据支持。4.完成管培生专项培养计划，包括产品知识培训、销售技巧实战演练、跨部门轮岗（任职要求1.2026届全日制本科及以上学历，专业不限，市场营销、工商管理、国际贸易等相关专业优先。2.具备强烈的目标感与抗压能力，愿意挑战高薪，对ToB大客户销售工作有明确兴趣与热情。3.拥有优秀的沟通表达与逻辑思维能力，能清晰传递信息，快速理解客户需求，有校园社团管理、大型活动组织或销售相关实习经历者优先。4.学习能力强，具备团队协作意识，能快速适应快节奏工作环境 | M78: 工商管理,市场营销,国际经济与贸易,国际贸易学 | N78: =LEN(M78) -> 23 | O78: =IF(ISBLANK(M78),0,COUNTA(_xlfn.TEXTSPLIT(M78,","))) -> 4
A79: =COUNTIF(B:B,B79) -> 6 | B79: 上海三菱电梯有限公司安装维修分公司 | C79: 上海三菱电梯有限公司上海分公司（营业执照名称为：上海三菱电梯有限公司安装维修分公司，以下简称：公司）成立于1992年4月，隶属于上海三菱电梯有限公司，专业从事上海三菱电梯有限公司和日本三菱电机株式会社制造的各型号电梯、自动扶梯产品销售、安装、维修、改造、保养、备件销售等业务，具备国家特种设备安装改造维修A级资质。公司坐落于上海昌化路649号。通过30多年的发展，上海三菱电梯有限公司安装维分公司已实现年度销售、安装电梯达5000多台，保养电梯40000多台的业绩。 | D79: 电梯维修保养岗位 | E79: 15 | F79: 大专 | G79: 工作职责：代表公司与客户处理管辖区域内的电梯保养、维修施工中出现的各种问题；及时响应客户的需求，为客户提供可靠的技术诊断与维修支持。员工发展与工作环境：实习期工资2700元，每月享受交通及话费补贴200元，并根据考核发放年终奖，转正后工资平均月薪4000-8000元/月（税前），并根据绩效情况发放月度奖金，年底根据工作表现发放全勤奖及年终奖；每年参加岗位培训及评定，增长技能工资；一经录用缴纳相关社会保险；根据技能评定及工作表现岗位上升依次为为“检查调整岗”、“项目组长”、“站长助理”、“站长”等，并承担相关职责，享受相应升级待遇。工作区域：上海市各大电梯维保站点。岗位变动：工作表现优异者，可被推荐、被选拔至高阶岗位；也可转电梯安装岗（个别申请）。 | H79: 月薪：4K-15K | I79: =_xlfn.CONCAT(D79,"（学历：",F79," 专业要求：",IF(ISBLANK(M79),"无",M79),"）") -> 电梯维修保养岗位（学历：大专 专业要求：无） | J79: =LEN(G79) -> 327 | K79: =_xlfn.XLOOKUP(A79,长度要求!A:A,长度要求!E:E) -> 500 | L79: =IF(J79<K79,G79,LEFT(G79,K79)&"……") -> 工作职责：代表公司与客户处理管辖区域内的电梯保养、维修施工中出现的各种问题；及时响应客户的需求，为客户提供可靠的技术诊断与维修支持。员工发展与工作环境：实习期工资2700元，每月享受交通及话费补贴200元，并根据考核发放年终奖，转正后工资平均月薪4000-8000元/月（税前），并根据绩效情况发放月度奖金，年底根据工作表现发放全勤奖及年终奖；每年参加岗位培训及评定，增长技能工资；一经录用缴纳相关社会保险；根据技能评定及工作表现岗位上升依次为为“检查调整岗”、“项目组长”、“站长助理”、“站长”等，并承担相关职责，享受相应升级待遇。工作区域：上海市各大电梯维保站点。岗位变动：工作表现优异者，可被推荐、被选拔至高阶岗位；也可转电梯安装岗（个别申请）。 | N79: =LEN(M79) -> 0 | O79: =IF(ISBLANK(M79),0,COUNTA(_xlfn.TEXTSPLIT(M79,","))) -> 0
A80: =COUNTIF(B:B,B80) -> 5 | B80: 上海永达北沃汽车销售服务有限公司 | C80: 永达沃尔沃申江店是由永达汽车倾力全新打造的，依照沃尔沃全球新的VRE设计标准建成，将为客户提供沃尔沃全系车型新车销售、二手车评估置换、金融贷款、融资租赁、保险服务、汽车维修保养等一条龙服务。秉承沃尔沃汽车“以人为尊”的品牌理念和永达汽车“诚信，追求卓越”的服务理念，我们力求让每一位沃尔沃车主体验到“方便快捷、舒心贴心和北欧生活”这三大特色服务。 | D80: 市场助理 | E80: 1 | F80: 大专 | G80: 1.负责前台客流登记2.负责配合完成各项市场营销策划活动3.负责开发针对经销商与客户的季节性或主题性推广活动4.领导交代的其他工作 | H80: 日薪：120-150/天 | I80: =_xlfn.CONCAT(D80,"（学历：",F80," 专业要求：",IF(ISBLANK(M80),"无",M80),"）") -> 市场助理（学历：大专 专业要求：无） | J80: =LEN(G80) -> 65 | K80: =_xlfn.XLOOKUP(A80,长度要求!A:A,长度要求!E:E) -> 500 | L80: =IF(J80<K80,G80,LEFT(G80,K80)&"……") -> 1.负责前台客流登记2.负责配合完成各项市场营销策划活动3.负责开发针对经销商与客户的季节性或主题性推广活动4.领导交代的其他工作 | N80: =LEN(M80) -> 0 | O80: =IF(ISBLANK(M80),0,COUNTA(_xlfn.TEXTSPLIT(M80,","))) -> 0
A81: =COUNTIF(B:B,B81) -> 4 | B81: 上海卡倍亿新能源科技有限公司 | C81: 卡倍亿是一家汽车线缆产品专业制造商，始创于1986年8月，具有39年汽车线缆研发、生产、销售、服务的历史，公司注册地为浙江省宁波市宁海县，管理中心设立在上海市闵行区，目前在宁波、成都、本溪、上海、惠州、麻城、北美墨西哥7地设有生产基地，员工1000多人。2020年8月卡倍亿在深交所挂牌上市，股票代码300863，成为中国国内唯一一家汽车线缆A股上市公司，被誉为“中国汽车线缆第一股”。公司作为汽车供应链的二级供应商，长期供货和服务的线束客户有矢崎、安波福、住友、李尔、德科斯米尔、古河、莱尼、科世科等世界汽车线束十强中的八强。线缆产品被广泛使用于：大众、宝马、奔驰、通用、福特、沃尔沃、丰田、本田、荣威、吉利、特斯拉、比亚迪、蔚小理等知名品牌汽车上。公司大力开展汽车、储能和人工智能领域，打造多元化的产品。公司是ISO国际汽车线缆标准委员会成员，近年来多次参与了新能源高压电缆、铝电缆、以太网电缆等一系列重要的国际汽车线缆标准的制订。 | D81: 交付类管培生 | E81: 2 | F81: 大专 | G81: 该岗位未来方向为生产岗、研发岗、交付岗等，电线电缆、电子电气、机械工程及自动化、数学、统计学等专业优先，要求每周至少3天全天出勤任职资格：1、统招大学专科以上学历，电线电缆、电子电气、机械工程及自动化、数学、统计学等专业优先；2、有上进心，学习意愿较强，愿意从基础开始学起，能吃苦耐劳；3、学习成绩优异，专业排名靠前；4、熟悉常用办公软件。 | H81: 日薪：150-200/天 | I81: =_xlfn.CONCAT(D81,"（学历：",F81," 专业要求：",IF(ISBLANK(M81),"无",M81),"）") -> 交付类管培生（学历：大专 专业要求：电线电缆制造技术,机械设计制造及其自动化,数学,统计学） | J81: =LEN(G81) -> 170 | K81: =_xlfn.XLOOKUP(A81,长度要求!A:A,长度要求!E:E) -> 500 | L81: =IF(J81<K81,G81,LEFT(G81,K81)&"……") -> 该岗位未来方向为生产岗、研发岗、交付岗等，电线电缆、电子电气、机械工程及自动化、数学、统计学等专业优先，要求每周至少3天全天出勤任职资格：1、统招大学专科以上学历，电线电缆、电子电气、机械工程及自动化、数学、统计学等专业优先；2、有上进心，学习意愿较强，愿意从基础开始学起，能吃苦耐劳；3、学习成绩优异，专业排名靠前；4、熟悉常用办公软件。 | M81: 电线电缆制造技术,机械设计制造及其自动化,数学,统计学 | N81: =LEN(M81) -> 27 | O81: =IF(ISBLANK(M81),0,COUNTA(_xlfn.TEXTSPLIT(M81,","))) -> 4
A82: =COUNTIF(B:B,B82) -> 5 | B82: 上海宝盖头家居科技有限公司 | C82: 宝盖头·启屋家居于上海2020年成立，是一群行业精英创立&综合性家居新零售体验中心，超4000平方米近30个当今流行趋势空间展示区，满足客户多种选择，设上下三层，配备咖啡洽谈区、儿童观影区、灯饰展示区、软装选材区、路演厅、设计师共享空间等，公司不但为消费者提供高质量性价比家居产品，且提供创新体验设计服务，为消费者建立一站式购物享受，设有星咖设平台为设计师提供全案及软装系统化专业赋能。我们搜集全球范围内家居最流行趋势，寻找有共鸣感的家居。直接、严选、自由是我们理想的经营方式。我们提供专业的全屋软装搭配服务，最大程度输出“追求有品质的个性化生活”理念。我们希望能有更多的人通过我们，享受到高品质的家居生活。 | D82: 软装设计师 | E82: 2 | F82: 大专 | G82: 岗位职责：1、了解公司产品，热情的为客户提供专业的产品介绍，通过和客户耐心细致的交流与沟通，快速并精准了解客户个性及需求，捕捉客户置家需求；2、能熟练操作画图软件并运用软件完成客户洽谈与下单；3、为客户提供软装搭配方案，跟进及协调客户订单完成；4、按照公司销售服务标准为客户提供优质服务，提升品牌形象；5、了解客户对公司产品及各环节服务评价或期望并反馈给公司及上级，为提升客户消费体验提供改进方向；6、更新公司软装方案模板，为客户提供更多优质的设计选择；7、具备良好的团队合作精神，有责任心，进取心；8、遵纪守法，有职业道德，并遵守公司各规章制度；9、完成上级下达的各项工作指令。任职要求：1、20岁以上，男女不限；艺术设计类大专以上学历；2、1年以上软装设计工作经验，具备硬装设计经验优先考虑；3、具备较好的空间感、色彩搭配能力、较高的悟性，能熟练使用autocad、Photoshop、PPT、酷家乐等设计软件优先考虑；4、熟悉各种装饰风格，具有良好的艺术修养，对软装设计行业有较强敏感度及充满极大的热情；5、工作细心，有条理，效率高，沟通、协调能力强。工作时间：做六休一，早上9:30-下午18:30；工作地点：上海市闵行区颛桥镇光华路158号（宝盖头家居）；福利待遇：五险一金，生日红包（蛋糕），团建活动，节日礼品，带薪年假，每日还可享受现磨咖啡。 | H82: 月薪：9K-13K | I82: =_xlfn.CONCAT(D82,"（学历：",F82," 专业要求：",IF(ISBLANK(M82),"无",M82),"）") -> 软装设计师（学历：大专 专业要求：建筑设计及其理论,建筑设计,家具设计与制造） | J82: =LEN(G82) -> 578 | K82: =_xlfn.XLOOKUP(A82,长度要求!A:A,长度要求!E:E) -> 500 | L82: =IF(J82<K82,G82,LEFT(G82,K82)&"……") -> 岗位职责：1、了解公司产品，热情的为客户提供专业的产品介绍，通过和客户耐心细致的交流与沟通，快速并精准了解客户个性及需求，捕捉客户置家需求；2、能熟练操作画图软件并运用软件完成客户洽谈与下单；3、为客户提供软装搭配方案，跟进及协调客户订单完成；4、按照公司销售服务标准为客户提供优质服务，提升品牌形象；5、了解客户对公司产品及各环节服务评价或期望并反馈给公司及上级，为提升客户消费体验提供改进方向；6、更新公司软装方案模板，为客户提供更多优质的设计选择；7、具备良好的团队合作精神，有责任心，进取心；8、遵纪守法，有职业道德，并遵守公司各规章制度；9、完成上级下达的各项工作指令。任职要求：1、20岁以上，男女不限；艺术设计类大专以上学历；2、1年以上软装设计工作经验，具备硬装设计经验优先考虑；3、具备较好的空间感、色彩搭配能力、较高的悟性，能熟练使用autocad、Photoshop、PPT、酷家乐等设计软件优先考虑；4、熟悉各种装饰风格，具有良好的艺术修养，对软装设计行业有较强敏感度及充满极大的热情；5、工作细心，有条理，效率高，沟通、协调能力强。工作时间：做六休一，早上9:30-下午18…… | M82: 建筑设计及其理论,建筑设计,家具设计与制造 | N82: =LEN(M82) -> 21 | O82: =IF(ISBLANK(M82),0,COUNTA(_xlfn.TEXTSPLIT(M82,","))) -> 3
A83: =COUNTIF(B:B,B83) -> 1 | B83: 中移铁通有限公司上海闵行分公司 | C83: 中移铁通为中国移动下属专业子公司，公司定位为“属地装维营销专业化支撑者”和“数智工程服务市场化拓展者”，重点聚焦家庭宽带安装维护、政企客户项目交付、DICT系统集成和工程项目建设维护等业务。 | D83: 爱家工程师 | E83: 10 | F83: 大专 | G83: 宽带、互联网电视、智能家居产品的安装调试，用户故障处理，移动业务随销等。 | H83: 月薪：5K-15K | I83: =_xlfn.CONCAT(D83,"（学历：",F83," 专业要求：",IF(ISBLANK(M83),"无",M83),"）") -> 爱家工程师（学历：大专 专业要求：无） | J83: =LEN(G83) -> 36 | K83: =_xlfn.XLOOKUP(A83,长度要求!A:A,长度要求!E:E) -> 500 | L83: =IF(J83<K83,G83,LEFT(G83,K83)&"……") -> 宽带、互联网电视、智能家居产品的安装调试，用户故障处理，移动业务随销等。 | N83: =LEN(M83) -> 0 | O83: =IF(ISBLANK(M83),0,COUNTA(_xlfn.TEXTSPLIT(M83,","))) -> 0
A84: =COUNTIF(B:B,B84) -> 4 | B84: 上海卡倍亿新能源科技有限公司 | C84: 卡倍亿是一家汽车线缆产品专业制造商，始创于1986年8月，具有39年汽车线缆研发、生产、销售、服务的历史，公司注册地为浙江省宁波市宁海县，管理中心设立在上海市闵行区，目前在宁波、成都、本溪、上海、惠州、麻城、北美墨西哥7地设有生产基地，员工1000多人。2020年8月卡倍亿在深交所挂牌上市，股票代码300863，成为中国国内唯一一家汽车线缆A股上市公司，被誉为“中国汽车线缆第一股”。公司作为汽车供应链的二级供应商，长期供货和服务的线束客户有矢崎、安波福、住友、李尔、德科斯米尔、古河、莱尼、科世科等世界汽车线束十强中的八强。线缆产品被广泛使用于：大众、宝马、奔驰、通用、福特、沃尔沃、丰田、本田、荣威、吉利、特斯拉、比亚迪、蔚小理等知名品牌汽车上。公司大力开展汽车、储能和人工智能领域，打造多元化的产品。公司是ISO国际汽车线缆标准委员会成员，近年来多次参与了新能源高压电缆、铝电缆、以太网电缆等一系列重要的国际汽车线缆标准的制订。 | D84: 技术管培生 | E84: 2 | F84: 本科 | G84: 该岗位未来方向可分为研发岗、工艺岗等，电线电缆，高分子材料，计算机等专业优先，要求每周至少3天全天出勤。任职资格：1、统招大学专科以上学历，电线电缆或高分子材料相关专业毕业优先；2、有上进心，学习意愿较强，愿意从基础开始学起，能吃苦耐劳；3、学习成绩优异，专业排名靠前；4、熟悉常用办公软件。 | H84: 日薪：150-200/天 | I84: =_xlfn.CONCAT(D84,"（学历：",F84," 专业要求：",IF(ISBLANK(M84),"无",M84),"）") -> 技术管培生（学历：本科 专业要求：电线电缆制造技术,电气工程及其自动化,机械工程） | J84: =LEN(G84) -> 146 | K84: =_xlfn.XLOOKUP(A84,长度要求!A:A,长度要求!E:E) -> 500 | L84: =IF(J84<K84,G84,LEFT(G84,K84)&"……") -> 该岗位未来方向可分为研发岗、工艺岗等，电线电缆，高分子材料，计算机等专业优先，要求每周至少3天全天出勤。任职资格：1、统招大学专科以上学历，电线电缆或高分子材料相关专业毕业优先；2、有上进心，学习意愿较强，愿意从基础开始学起，能吃苦耐劳；3、学习成绩优异，专业排名靠前；4、熟悉常用办公软件。 | M84: 电线电缆制造技术,电气工程及其自动化,机械工程 | N84: =LEN(M84) -> 23 | O84: =IF(ISBLANK(M84),0,COUNTA(_xlfn.TEXTSPLIT(M84,","))) -> 3
A85: =COUNTIF(B:B,B85) -> 4 | B85: 上海卡倍亿新能源科技有限公司 | C85: 卡倍亿是一家汽车线缆产品专业制造商，始创于1986年8月，具有39年汽车线缆研发、生产、销售、服务的历史，公司注册地为浙江省宁波市宁海县，管理中心设立在上海市闵行区，目前在宁波、成都、本溪、上海、惠州、麻城、北美墨西哥7地设有生产基地，员工1000多人。2020年8月卡倍亿在深交所挂牌上市，股票代码300863，成为中国国内唯一一家汽车线缆A股上市公司，被誉为“中国汽车线缆第一股”。公司作为汽车供应链的二级供应商，长期供货和服务的线束客户有矢崎、安波福、住友、李尔、德科斯米尔、古河、莱尼、科世科等世界汽车线束十强中的八强。线缆产品被广泛使用于：大众、宝马、奔驰、通用、福特、沃尔沃、丰田、本田、荣威、吉利、特斯拉、比亚迪、蔚小理等知名品牌汽车上。公司大力开展汽车、储能和人工智能领域，打造多元化的产品。公司是ISO国际汽车线缆标准委员会成员，近年来多次参与了新能源高压电缆、铝电缆、以太网电缆等一系列重要的国际汽车线缆标准的制订。 | D85: 营销管培生 | E85: 2 | F85: 本科 | G85: 该岗位未来方向为外销岗位(日语，英语），要求市场营销，英语或者日语等相关专业，每周要求至少3天全天出勤任职资格：1、统招专科以上学历，市场营销、英语或者日语等专业毕业；2、性格外向，具有较强的沟通能力和语言表达能力，应变能力和谈判能力；3、（英语）或（日语）流利加分；会开车（开车熟练）；4、有汽车零配件行业销售经验加分；5、有上进心，学习意愿较强，愿意从基础开始学起，能吃苦耐劳；6、学习成绩优异，专业排名靠前；7、熟悉常用办公软件。 | H85: 日薪：150-200/天 | I85: =_xlfn.CONCAT(D85,"（学历：",F85," 专业要求：",IF(ISBLANK(M85),"无",M85),"）") -> 营销管培生（学历：本科 专业要求：日语,商务日语,应用日语,英语,商务英语,应用英语） | J85: =LEN(G85) -> 218 | K85: =_xlfn.XLOOKUP(A85,长度要求!A:A,长度要求!E:E) -> 500 | L85: =IF(J85<K85,G85,LEFT(G85,K85)&"……") -> 该岗位未来方向为外销岗位(日语，英语），要求市场营销，英语或者日语等相关专业，每周要求至少3天全天出勤任职资格：1、统招专科以上学历，市场营销、英语或者日语等专业毕业；2、性格外向，具有较强的沟通能力和语言表达能力，应变能力和谈判能力；3、（英语）或（日语）流利加分；会开车（开车熟练）；4、有汽车零配件行业销售经验加分；5、有上进心，学习意愿较强，愿意从基础开始学起，能吃苦耐劳；6、学习成绩优异，专业排名靠前；7、熟悉常用办公软件。 | M85: 日语,商务日语,应用日语,英语,商务英语,应用英语 | N85: =LEN(M85) -> 25 | O85: =IF(ISBLANK(M85),0,COUNTA(_xlfn.TEXTSPLIT(M85,","))) -> 6
A86: =COUNTIF(B:B,B86) -> 2 | B86: 上海上勤高级楼宇管理有限公司 | C86: 上海上勤高级楼宇管理有限公司，隶属于上海市机关事务管理局委托管理的国有独资企业，一直从事市人大和市政府等机关后勤服务保障工作。公司秉持“一流服务、领先水平”的服务理念，坚持“做优服务、做强保障、做实管理”的工作目标，坚持专业化、标准化、个性化、精细化的品质，形成了独特的服务理念以及管理模式。目前，公司在管项目服务总量占市级机关物业服务市场62%，并在服务过程中形成品牌效应，具有较高的认知度和美誉度。 | D86: 工程助理（物业维修电工） | E86: 1 | F86: 中专/技校 | G86: 机关项目，做五休二（晚间有轮流安排夜值班）岗位要求：1、年龄50岁以下，经验丰富者可适当放宽。2、至少须持有低压电工证、职业资格证书（维修电工初级/五级），能独立动手操作。3、须有高度的工作责任心、良好的沟通能力、有较强的团队意识。4、有酒店、办公楼等物业工作经验优先。 | H86: 月薪：6K-7K | I86: =_xlfn.CONCAT(D86,"（学历：",F86," 专业要求：",IF(ISBLANK(M86),"无",M86),"）") -> 工程助理（物业维修电工）（学历：中专/技校 专业要求：无） | J86: =LEN(G86) -> 135 | K86: =_xlfn.XLOOKUP(A86,长度要求!A:A,长度要求!E:E) -> 500 | L86: =IF(J86<K86,G86,LEFT(G86,K86)&"……") -> 机关项目，做五休二（晚间有轮流安排夜值班）岗位要求：1、年龄50岁以下，经验丰富者可适当放宽。2、至少须持有低压电工证、职业资格证书（维修电工初级/五级），能独立动手操作。3、须有高度的工作责任心、良好的沟通能力、有较强的团队意识。4、有酒店、办公楼等物业工作经验优先。 | N86: =LEN(M86) -> 0 | O86: =IF(ISBLANK(M86),0,COUNTA(_xlfn.TEXTSPLIT(M86,","))) -> 0
A87: =COUNTIF(B:B,B87) -> 1 | B87: 上海世界联合服装有限公司 | C87: 上海世界联合服装有限公司隶属ICCF之禾卡纷集团。ICCF之禾卡纷集团是着重于可持续发展的全业务连高端时尚集团，致力于为世界提供基于优质原料的环境友好时装。集团旗下目前的主要业务板块，包含中国品牌ICICLE之禾，法国品牌CARVEN卡纷，时装制造中心以及物流中心，从原料采购、产品开发、制造、销售和消费者体验的全业务连视角，寻求品牌发展与环境、社会的和谐共生。我们的团队年轻有活力，乐意带教新人。我们诚挚的欢迎阳光，积极，进取的你。我们秉承集团追求天然，舒适，环保的理念，为员工提供良好的工作环境和氛围。 | D87: 生产培训生（毛衫方向） | E87: 4 | F87: 大专 | G87: 招聘岗位：生产培训生（毛衫方向）培养方向：生产管理招聘人数：4人工作地点：上海市闵行区绿春路189号薪资：6000-8000元/月任职要求：1.专科及以上学历，服装相关专业（针织专业优先考虑）；2.应届毕业生或毕业三年以内；3.善于沟通表达；4.逻辑思维能力强，有进取心，职业发展规划清晰；5.热爱服装行业，愿意扎根工厂，热爱制造福利：包吃包住、带薪年假、节日福利、定期体检、六险一金（包含补充商业医疗保险）、交通补贴、团建活动。联系人：人事行政部 | H87: 月薪：6K-8K | I87: =_xlfn.CONCAT(D87,"（学历：",F87," 专业要求：",IF(ISBLANK(M87),"无",M87),"）") -> 生产培训生（毛衫方向）（学历：大专 专业要求：服装设计与工程,针织技术与针织服装,服装与服饰设计,服装设计与工艺,服装设计与工艺教育） | J87: =LEN(G87) -> 224 | K87: =_xlfn.XLOOKUP(A87,长度要求!A:A,长度要求!E:E) -> 500 | L87: =IF(J87<K87,G87,LEFT(G87,K87)&"……") -> 招聘岗位：生产培训生（毛衫方向）培养方向：生产管理招聘人数：4人工作地点：上海市闵行区绿春路189号薪资：6000-8000元/月任职要求：1.专科及以上学历，服装相关专业（针织专业优先考虑）；2.应届毕业生或毕业三年以内；3.善于沟通表达；4.逻辑思维能力强，有进取心，职业发展规划清晰；5.热爱服装行业，愿意扎根工厂，热爱制造福利：包吃包住、带薪年假、节日福利、定期体检、六险一金（包含补充商业医疗保险）、交通补贴、团建活动。联系人：人事行政部 | M87: 服装设计与工程,针织技术与针织服装,服装与服饰设计,服装设计与工艺,服装设计与工艺教育 | N87: =LEN(M87) -> 43 | O87: =IF(ISBLANK(M87),0,COUNTA(_xlfn.TEXTSPLIT(M87,","))) -> 5
A88: =COUNTIF(B:B,B88) -> 1 | B88: 闵行区吴泾第二幼儿园 | C88: 闵行区吴泾第二幼儿园位于闵行区吴泾地区的黄浦江边，创办于1992年，是一所公办幼儿园，园所占地面积为3208平方米，建筑面积1237平方米。绿化面积948平方米。园训：博学之本启蒙之所办园理念：伴着幼儿健康幸福地成长幼儿发展目标：习惯良好好奇探究文明乐群勇敢自信健康快乐。 | D88: 教师 | E88: 1 | F88: 本科 | G88: 学前教育专业，本科，有幼儿园教师资格证，身体健康，对待工作有责任心有爱心，有良好的团队合作精神。 | H88: 月薪：4K-6K | I88: =_xlfn.CONCAT(D88,"（学历：",F88," 专业要求：",IF(ISBLANK(M88),"无",M88),"）") -> 教师（学历：本科 专业要求：学前教育） | J88: =LEN(G88) -> 48 | K88: =_xlfn.XLOOKUP(A88,长度要求!A:A,长度要求!E:E) -> 500 | L88: =IF(J88<K88,G88,LEFT(G88,K88)&"……") -> 学前教育专业，本科，有幼儿园教师资格证，身体健康，对待工作有责任心有爱心，有良好的团队合作精神。 | M88: 学前教育 | N88: =LEN(M88) -> 4 | O88: =IF(ISBLANK(M88),0,COUNTA(_xlfn.TEXTSPLIT(M88,","))) -> 1
A89: =COUNTIF(B:B,B89) -> 1 | B89: 上海圆外物业集团有限公司 | C89: 上海圆外物业集团有限公司于2004年2月经国家工商行政管理局批准成立，注册资金500万。公司目前管理的物业面积有400余万平方米,包括：高层住宅、多层住宅、别墅、商业物业、办公楼、工业厂房、学校等各类物业的管理与服务。公司董事长李俊南先生，上海市闵行区政协常委，本科学历，工程师中级职称，专注物业管理服务15年，获得上海市物业管理行业协会首批物业管理专家、上海市物业行业协会优秀工作者、上海市房地局物业招投标评审专家、上海市物业管理超标准认证评审专家、上海市闵行区物业管理行业工会联合会工会主席等多种荣誉。公司自成立以来注重服务管理和服务质量，有完整的运营管理机制和全新的经营理念，有团结向上的团队精神、积极向上的工作作风、良好的服务信誉以及高标准的经营服务道德规范。公司始终坚持忠诚、务实、团结、守信的管理理念，坚持奉行“打破惯性、挑战自我、不断创新”的质量方针，坚持贯彻为您竭尽所能的服务口号！脚踏实地抓管理，精益求精创品牌。公司是上海市物业管理行业协会理事会理事单位。被上海市物业管理行业协会评为“上海市物业服务综合百强企业”以及“上海市物业服务综合能力四星级星级企业”。闵行区房管局应急抢修单位。物业服务行诚信承诺AAA级单位。公司设有八个部门：行政人事部、财务部、品质保障部、技术支持部、采购部、运营部、市场拓展部、公众事业部，拥有人数1000余人，具备专业经验的管理人才队伍和具备专业操作技能的服务队伍，能够为不同需求的业主提供细致、周到、规范和满意的服务。 | D89: 智能弱电工（实习-转正） | E89: 1 | F89: 大专 | G89: 1、负责弱电系统的日常运维、故障检修与基础调试，保障弱电系统稳定运行，支撑楼宇智能化服务落地。2、负责弱电系统的日常巡检，涵盖综合布线系统（网络、电话、光纤链路）、安防监控系统（摄像头、存储设备、监控平台）、出入口控制系统（门禁一体机、人脸识别设备、道闸联动）、楼宇对讲系统（室内分机、单元门口机、中心管理机）及停车场智能管理系统（车位引导屏、缴费终端、车牌识别设备）。3、协助完成弱电系统升级改造的现场配合工作（如综合布线扩容、旧监控设备替换）。4、配合弱电工程师完成弱电系统的基础调试，如新增门禁卡授权、监控摄像头角度调整、楼宇对讲系统室内分机注册，确保设备接入现有系统正常运行。5、建立个人负责区域的弱电设备台账，记录设备型号、安装位置、维保时间、故障历史，每月底汇总至部门负责人，确保台账信息准确更新。​6、响应业主关于弱电系统的基础咨询（如门禁卡补办流程、家中网络接口无法使用排查），跟踪问题解决进度。 | H89: 月薪：4K-8K | I89: =_xlfn.CONCAT(D89,"（学历：",F89," 专业要求：",IF(ISBLANK(M89),"无",M89),"）") -> 智能弱电工（实习-转正）（学历：大专 专业要求：建筑智能化工程技术） | J89: =LEN(G89) -> 406 | K89: =_xlfn.XLOOKUP(A89,长度要求!A:A,长度要求!E:E) -> 500 | L89: =IF(J89<K89,G89,LEFT(G89,K89)&"……") -> 1、负责弱电系统的日常运维、故障检修与基础调试，保障弱电系统稳定运行，支撑楼宇智能化服务落地。2、负责弱电系统的日常巡检，涵盖综合布线系统（网络、电话、光纤链路）、安防监控系统（摄像头、存储设备、监控平台）、出入口控制系统（门禁一体机、人脸识别设备、道闸联动）、楼宇对讲系统（室内分机、单元门口机、中心管理机）及停车场智能管理系统（车位引导屏、缴费终端、车牌识别设备）。3、协助完成弱电系统升级改造的现场配合工作（如综合布线扩容、旧监控设备替换）。4、配合弱电工程师完成弱电系统的基础调试，如新增门禁卡授权、监控摄像头角度调整、楼宇对讲系统室内分机注册，确保设备接入现有系统正常运行。5、建立个人负责区域的弱电设备台账，记录设备型号、安装位置、维保时间、故障历史，每月底汇总至部门负责人，确保台账信息准确更新。​6、响应业主关于弱电系统的基础咨询（如门禁卡补办流程、家中网络接口无法使用排查），跟踪问题解决进度。 | M89: 建筑智能化工程技术 | N89: =LEN(M89) -> 9 | O89: =IF(ISBLANK(M89),0,COUNTA(_xlfn.TEXTSPLIT(M89,","))) -> 1
A90: =COUNTIF(B:B,B90) -> 5 | B90: 上海永达北沃汽车销售服务有限公司 | C90: 永达沃尔沃申江店是由永达汽车倾力全新打造的，依照沃尔沃全球新的VRE设计标准建成，将为客户提供沃尔沃全系车型新车销售、二手车评估置换、金融贷款、融资租赁、保险服务、汽车维修保养等一条龙服务。秉承沃尔沃汽车“以人为尊”的品牌理念和永达汽车“诚信，追求卓越”的服务理念，我们力求让每一位沃尔沃车主体验到“方便快捷、舒心贴心和北欧生活”这三大特色服务。 | D90: 销售助理 | E90: 1 | F90: 大专 | G90: 工作内容及职责：1、根据厂方及公司的销售任务，负责汇总及统计相关销售数据2、对客户的订单进行汇总、整理、录入工作，并及时检查订单是否完整和准确3、定期将客户的市场反馈信息上报有关部门4、协助部门领导完成各类报表2026年应届毕业生，大专以上学历，文秘、电子商务或市场营销相关专业 | H90: 日薪：120/天 | I90: =_xlfn.CONCAT(D90,"（学历：",F90," 专业要求：",IF(ISBLANK(M90),"无",M90),"）") -> 销售助理（学历：大专 专业要求：无） | J90: =LEN(G90) -> 139 | K90: =_xlfn.XLOOKUP(A90,长度要求!A:A,长度要求!E:E) -> 500 | L90: =IF(J90<K90,G90,LEFT(G90,K90)&"……") -> 工作内容及职责：1、根据厂方及公司的销售任务，负责汇总及统计相关销售数据2、对客户的订单进行汇总、整理、录入工作，并及时检查订单是否完整和准确3、定期将客户的市场反馈信息上报有关部门4、协助部门领导完成各类报表2026年应届毕业生，大专以上学历，文秘、电子商务或市场营销相关专业 | N90: =LEN(M90) -> 0 | O90: =IF(ISBLANK(M90),0,COUNTA(_xlfn.TEXTSPLIT(M90,","))) -> 0
A91: =COUNTIF(B:B,B91) -> 1 | B91: 慈溪市公牛电器有限公司 | C91: 公牛集团股份有限公司创办于1995年，公司专注于以转换器、墙壁开关插座为核心的民用电工产品的研发、生产和销售，主要包括转换器（即延长线插座、移动式插座等）、墙壁开关插座、LED照明、数码配件等电源连接和用电延伸性产品，广泛应用于家庭、办公等用电场合。目前，公司拥有观海卫工业园东区、工业园西区、古窑、龙山等多个制造基地，员工总数超过1万人，建立了近100万家网点的线下实体营销网络和专业的线上电商营销网络。 | D91: 电商运维专员 | E91: 20 | F91: 大专 | G91: 岗位名称：电商运维专员薪资待遇：实习期4000元/月（工作期间每日12元餐补）,转正后：6000-12000，年终13薪，带薪年假工作时间：每天8小时，每周固定工作5天休息2天早班：9:00-18:00中间休息一小时晚班：13:00-22:00中间休息一小时（电商活动期间会有加班，平时基本没加班）工作内容：负责公牛电器天猫商城、京东商城在线运营，及售前、售中、售后服务（非电话形式），纯写字楼办公要求：大专及以上学历，打字速度快，专业不限，公司提供带薪培训一个月 | H91: 月薪：4K-12K | I91: =_xlfn.CONCAT(D91,"（学历：",F91," 专业要求：",IF(ISBLANK(M91),"无",M91),"）") -> 电商运维专员（学历：大专 专业要求：无） | J91: =LEN(G91) -> 232 | K91: =_xlfn.XLOOKUP(A91,长度要求!A:A,长度要求!E:E) -> 500 | L91: =IF(J91<K91,G91,LEFT(G91,K91)&"……") -> 岗位名称：电商运维专员薪资待遇：实习期4000元/月（工作期间每日12元餐补）,转正后：6000-12000，年终13薪，带薪年假工作时间：每天8小时，每周固定工作5天休息2天早班：9:00-18:00中间休息一小时晚班：13:00-22:00中间休息一小时（电商活动期间会有加班，平时基本没加班）工作内容：负责公牛电器天猫商城、京东商城在线运营，及售前、售中、售后服务（非电话形式），纯写字楼办公要求：大专及以上学历，打字速度快，专业不限，公司提供带薪培训一个月 | N91: =LEN(M91) -> 0 | O91: =IF(ISBLANK(M91),0,COUNTA(_xlfn.TEXTSPLIT(M91,","))) -> 0
A92: =COUNTIF(B:B,B92) -> 1 | B92: 上海励影文化传媒有限公司 | C92: 上海励影文化传媒有限公司，成立于2014年，是一家综合型专业公关活动影服务商。提供导播直播、摄影摄像、视频制作等活动影像技术解决方案。公司核心团队均为高校编导专业毕业，团队年总计近干场影像服务经验，其专业度获得客户高度认可。公司自有多套顶级4KEFP导播直播系统以及高端摄影摄像器材。管理上导入了绩效管理机制，励影传媒，凭借资深执行团队+自有高端影像设备+成熟管理机制三大优势，给客户带来最具性价比的服务。希望通过专业视频传播服务，效，高质呈现客户所需。为客户品牌带来最大商业价值! | D92: 助理 | E92: 4 | F92: 中专/技校 | G92: 培养目标：（直播转播活动摄像方向，平面和TVC发展方向的勿扰，）摄像师，导播，网络直播技术，摇臂手，项目经理，部门经理。*广阔的晋升空间；*可接触到业内先进设备；*过了试用期，签约后可以提供住宿；*会开车可优先考虑；岗位描述：1、配合摄像师进行日常拍摄，准备设备，搬运装配设备；2、协助直播导播完成工作，听从导播安排；3、对直播拍摄设备进行日常维护和保养；4、对拍摄素材进行归档整理和简单剪辑；5、负责项目现场内部花絮视频和照片的搜集工作；6、相关影视器材检查、整理，保养和维护。 | H92: 月薪：2K-4K | I92: =_xlfn.CONCAT(D92,"（学历：",F92," 专业要求：",IF(ISBLANK(M92),"无",M92),"）") -> 助理（学历：中专/技校 专业要求：广播电视编导） | J92: =LEN(G92) -> 240 | K92: =_xlfn.XLOOKUP(A92,长度要求!A:A,长度要求!E:E) -> 500 | L92: =IF(J92<K92,G92,LEFT(G92,K92)&"……") -> 培养目标：（直播转播活动摄像方向，平面和TVC发展方向的勿扰，）摄像师，导播，网络直播技术，摇臂手，项目经理，部门经理。*广阔的晋升空间；*可接触到业内先进设备；*过了试用期，签约后可以提供住宿；*会开车可优先考虑；岗位描述：1、配合摄像师进行日常拍摄，准备设备，搬运装配设备；2、协助直播导播完成工作，听从导播安排；3、对直播拍摄设备进行日常维护和保养；4、对拍摄素材进行归档整理和简单剪辑；5、负责项目现场内部花絮视频和照片的搜集工作；6、相关影视器材检查、整理，保养和维护。 | M92: 广播电视编导 | N92: =LEN(M92) -> 6 | O92: =IF(ISBLANK(M92),0,COUNTA(_xlfn.TEXTSPLIT(M92,","))) -> 1
A93: =COUNTIF(B:B,B93) -> 1 | B93: 中国福利会托儿所 | C93: 中国福利会托儿所，由新中国的缔造者之一、国家名誉主席、中国福利会创始人宋庆龄女士亲手创办于1950年。70多年来，遵循宋庆龄“愿小树苗健康成长”的教育期许和“把最宝贵的东西给予儿童”的工作要求，中国福利会托儿所积极探索营养膳食、科学育儿、婴幼儿教育教学的研究与实践，逐渐形成了以营养为特色，以保健为基础，保教结合，身心并举的健康教育模式，构建了1-6岁早期教育全程化的办学格局。 | D93: 保育员 | E93: 8 | F93: 大专 | G93: 1、应具备良好的师德、健康的身心，得体的仪表；2、充满爱心和童心，爱岗敬业，能吃苦耐劳；3、护理幼儿生活，做好班级日常生活工作、校园环境、班级卫生及各类设施清洁工作；4、协助配合带班教师做好幼儿教育教学等工作；5、服从单位安排的其他相关工作。 | H93: 月薪：6K-9K | I93: =_xlfn.CONCAT(D93,"（学历：",F93," 专业要求：",IF(ISBLANK(M93),"无",M93),"）") -> 保育员（学历：大专 专业要求：学前教育,幼儿发展与健康管理） | J93: =LEN(G93) -> 121 | K93: =_xlfn.XLOOKUP(A93,长度要求!A:A,长度要求!E:E) -> 500 | L93: =IF(J93<K93,G93,LEFT(G93,K93)&"……") -> 1、应具备良好的师德、健康的身心，得体的仪表；2、充满爱心和童心，爱岗敬业，能吃苦耐劳；3、护理幼儿生活，做好班级日常生活工作、校园环境、班级卫生及各类设施清洁工作；4、协助配合带班教师做好幼儿教育教学等工作；5、服从单位安排的其他相关工作。 | M93: 学前教育,幼儿发展与健康管理 | N93: =LEN(M93) -> 14 | O93: =IF(ISBLANK(M93),0,COUNTA(_xlfn.TEXTSPLIT(M93,","))) -> 2
A94: =COUNTIF(B:B,B94) -> 4 | B94: 上海永达新能源汽车集团有限公司 | C94: 集团简介永达集团成立于1992年，是一家在香港主板上市的大型集团企业（股票代码：HK03669），永达凭借专业的服务能力、强大的企业实力和优良的企业形象，得到了社会各界和行业专家的广泛认可，先后荣获了“中国企业500强”、“中国汽车销售服务十大企业集团”、“全国守合同重信用企业”、“全国文明单位”、“上海市文明单位”、“上海市著名商标”等荣誉称号。我们主要经营汽车销售服务、二手车、汽车金融、汽车租赁等产业，公司主要代理宾利、保时捷、捷豹路虎、阿斯顿马丁、宝马、奔驰、奥迪、林肯、英菲尼迪、凯迪拉克等多个国际知名豪华汽车品牌，服务网络主要分布在上海、北京、天津等3个直辖市和17个省的55个城市。率先在行业内形成学车、买车、卖车、租车、修车、验车等完整的汽车销售服务产业链，提供新车销售、汽车金融与保险、装潢用品、售后服务、平行进口汽车、二手车置换与销售、快修连锁、汽车零配件和养护品销售等服务，并通过互联网电商及新媒体平台，构建线上线下一体化全方位的汽车产业链生态圈，打造高效、便捷的汽车生活服务平台。永达新能源集团上海永达新能源汽车集团有限公司主要经营新能源汽车销售服务、新能源后市场服务及充换电等产业，公司主要代理小鹏、华为AITO、特斯拉、路特斯、SMART、上汽智己、福特新能源（野马）、欧拉、零跑等多个国内知名新势力新能源汽车品牌，服务网络持续扩大目前主要分布在上海、苏州、杭州、无锡、南京、丽水、常州、广州、南昌、合肥、绵阳等多个城市，运营规模及服务能力不断攀升。 | D94: 财务实习生 | E94: 1 | F94: 大专 | G94: [岗位职责]1、协助门店财务部门完成日常财务工作，如整理票据、会计凭证和财务资料等；2、协助部门同事完成维修工单的开票结算和新车整车的开票与开具出门单；3、根据业务发展需要，完成指定的其他工作。[任职资格]1、大专及以上学历，财会相关专业者优先；2、工作积极主动，细心，有责任心，执行能力强；3、善于思考，有较强的解决问题能力和抗压能力；4、有较强的沟通能力、学习能力和专注力。 | H94: 日薪：150/天 | I94: =_xlfn.CONCAT(D94,"（学历：",F94," 专业要求：",IF(ISBLANK(M94),"无",M94),"）") -> 财务实习生（学历：大专 专业要求：无） | J94: =LEN(G94) -> 189 | K94: =_xlfn.XLOOKUP(A94,长度要求!A:A,长度要求!E:E) -> 500 | L94: =IF(J94<K94,G94,LEFT(G94,K94)&"……") -> [岗位职责]1、协助门店财务部门完成日常财务工作，如整理票据、会计凭证和财务资料等；2、协助部门同事完成维修工单的开票结算和新车整车的开票与开具出门单；3、根据业务发展需要，完成指定的其他工作。[任职资格]1、大专及以上学历，财会相关专业者优先；2、工作积极主动，细心，有责任心，执行能力强；3、善于思考，有较强的解决问题能力和抗压能力；4、有较强的沟通能力、学习能力和专注力。 | N94: =LEN(M94) -> 0 | O94: =IF(ISBLANK(M94),0,COUNTA(_xlfn.TEXTSPLIT(M94,","))) -> 0
A95: =COUNTIF(B:B,B95) -> 4 | B95: 上海永达新能源汽车集团有限公司 | C95: 集团简介永达集团成立于1992年，是一家在香港主板上市的大型集团企业（股票代码：HK03669），永达凭借专业的服务能力、强大的企业实力和优良的企业形象，得到了社会各界和行业专家的广泛认可，先后荣获了“中国企业500强”、“中国汽车销售服务十大企业集团”、“全国守合同重信用企业”、“全国文明单位”、“上海市文明单位”、“上海市著名商标”等荣誉称号。我们主要经营汽车销售服务、二手车、汽车金融、汽车租赁等产业，公司主要代理宾利、保时捷、捷豹路虎、阿斯顿马丁、宝马、奔驰、奥迪、林肯、英菲尼迪、凯迪拉克等多个国际知名豪华汽车品牌，服务网络主要分布在上海、北京、天津等3个直辖市和17个省的55个城市。率先在行业内形成学车、买车、卖车、租车、修车、验车等完整的汽车销售服务产业链，提供新车销售、汽车金融与保险、装潢用品、售后服务、平行进口汽车、二手车置换与销售、快修连锁、汽车零配件和养护品销售等服务，并通过互联网电商及新媒体平台，构建线上线下一体化全方位的汽车产业链生态圈，打造高效、便捷的汽车生活服务平台。永达新能源集团上海永达新能源汽车集团有限公司主要经营新能源汽车销售服务、新能源后市场服务及充换电等产业，公司主要代理小鹏、华为AITO、特斯拉、路特斯、SMART、上汽智己、福特新能源（野马）、欧拉、零跑等多个国内知名新势力新能源汽车品牌，服务网络持续扩大目前主要分布在上海、苏州、杭州、无锡、南京、丽水、常州、广州、南昌、合肥、绵阳等多个城市，运营规模及服务能力不断攀升。 | D95: 服务顾问实习生 | E95: 3 | F95: 大专 | G95: [岗位职责]1.热情引导接待用户，沟通确认用户需求，根据需求给出专业的服务方案；2.熟悉车辆功能及使用，深刻理解公司服务理念，为用户提供专业的解答；3.跟踪车辆整体维修情况，确保维修时效质量、完工交付标准及维修服务体验；4.维护用户关系，保证每位用户都能得到专业且有温度的售后服务。[任职资格]1.大专或以上学历，汽车相关专业优先；2.做事认真仔细，责任心强，对待工作积极主动；3.具有良好的服务意识、营销意识和沟通协调能力；4.持有驾驶证并熟练驾驶汽车者优先。 | H95: 日薪：150/天 | I95: =_xlfn.CONCAT(D95,"（学历：",F95," 专业要求：",IF(ISBLANK(M95),"无",M95),"）") -> 服务顾问实习生（学历：大专 专业要求：无） | J95: =LEN(G95) -> 231 | K95: =_xlfn.XLOOKUP(A95,长度要求!A:A,长度要求!E:E) -> 500 | L95: =IF(J95<K95,G95,LEFT(G95,K95)&"……") -> [岗位职责]1.热情引导接待用户，沟通确认用户需求，根据需求给出专业的服务方案；2.熟悉车辆功能及使用，深刻理解公司服务理念，为用户提供专业的解答；3.跟踪车辆整体维修情况，确保维修时效质量、完工交付标准及维修服务体验；4.维护用户关系，保证每位用户都能得到专业且有温度的售后服务。[任职资格]1.大专或以上学历，汽车相关专业优先；2.做事认真仔细，责任心强，对待工作积极主动；3.具有良好的服务意识、营销意识和沟通协调能力；4.持有驾驶证并熟练驾驶汽车者优先。 | N95: =LEN(M95) -> 0 | O95: =IF(ISBLANK(M95),0,COUNTA(_xlfn.TEXTSPLIT(M95,","))) -> 0
A96: =COUNTIF(B:B,B96) -> 4 | B96: 上海永达新能源汽车集团有限公司 | C96: 集团简介永达集团成立于1992年，是一家在香港主板上市的大型集团企业（股票代码：HK03669），永达凭借专业的服务能力、强大的企业实力和优良的企业形象，得到了社会各界和行业专家的广泛认可，先后荣获了“中国企业500强”、“中国汽车销售服务十大企业集团”、“全国守合同重信用企业”、“全国文明单位”、“上海市文明单位”、“上海市著名商标”等荣誉称号。我们主要经营汽车销售服务、二手车、汽车金融、汽车租赁等产业，公司主要代理宾利、保时捷、捷豹路虎、阿斯顿马丁、宝马、奔驰、奥迪、林肯、英菲尼迪、凯迪拉克等多个国际知名豪华汽车品牌，服务网络主要分布在上海、北京、天津等3个直辖市和17个省的55个城市。率先在行业内形成学车、买车、卖车、租车、修车、验车等完整的汽车销售服务产业链，提供新车销售、汽车金融与保险、装潢用品、售后服务、平行进口汽车、二手车置换与销售、快修连锁、汽车零配件和养护品销售等服务，并通过互联网电商及新媒体平台，构建线上线下一体化全方位的汽车产业链生态圈，打造高效、便捷的汽车生活服务平台。永达新能源集团上海永达新能源汽车集团有限公司主要经营新能源汽车销售服务、新能源后市场服务及充换电等产业，公司主要代理小鹏、华为AITO、特斯拉、路特斯、SMART、上汽智己、福特新能源（野马）、欧拉、零跑等多个国内知名新势力新能源汽车品牌，服务网络持续扩大目前主要分布在上海、苏州、杭州、无锡、南京、丽水、常州、广州、南昌、合肥、绵阳等多个城市，运营规模及服务能力不断攀升。 | D96: 售后技术实习生 | E96: 3 | F96: 大专 | G96: [岗位职责]1.为用户提供规范、专业的新能源汽车保养、维修、装潢等售后服务；2.接受永达新能源所代理的品牌产品的专业知识与技术培训，完成各阶段成长任务；3.根据产品维修手册，规范使用工具设备，有效准确地进行车辆维修，并记录维修工单；4.熟练掌握车间的专用工具和诊断设备，定期对工具设备进行检查调整、保养或维修；5.在车间主管的带领下，认真执行车间5S，并与各分工部门保持紧密的合作与沟通。[任职资格]1.大专或以上学历，汽车相关专业；2.做事认真仔细，责任心强，对待工作积极主动；3.具备一定汽修知识以及相关证书；4.持有驾驶证并熟练驾驶汽车者优先。 | H96: 日薪：150/天 | I96: =_xlfn.CONCAT(D96,"（学历：",F96," 专业要求：",IF(ISBLANK(M96),"无",M96),"）") -> 售后技术实习生（学历：大专 专业要求：无） | J96: =LEN(G96) -> 275 | K96: =_xlfn.XLOOKUP(A96,长度要求!A:A,长度要求!E:E) -> 500 | L96: =IF(J96<K96,G96,LEFT(G96,K96)&"……") -> [岗位职责]1.为用户提供规范、专业的新能源汽车保养、维修、装潢等售后服务；2.接受永达新能源所代理的品牌产品的专业知识与技术培训，完成各阶段成长任务；3.根据产品维修手册，规范使用工具设备，有效准确地进行车辆维修，并记录维修工单；4.熟练掌握车间的专用工具和诊断设备，定期对工具设备进行检查调整、保养或维修；5.在车间主管的带领下，认真执行车间5S，并与各分工部门保持紧密的合作与沟通。[任职资格]1.大专或以上学历，汽车相关专业；2.做事认真仔细，责任心强，对待工作积极主动；3.具备一定汽修知识以及相关证书；4.持有驾驶证并熟练驾驶汽车者优先。 | N96: =LEN(M96) -> 0 | O96: =IF(ISBLANK(M96),0,COUNTA(_xlfn.TEXTSPLIT(M96,","))) -> 0
A97: =COUNTIF(B:B,B97) -> 4 | B97: 上海永达新能源汽车集团有限公司 | C97: 集团简介永达集团成立于1992年，是一家在香港主板上市的大型集团企业（股票代码：HK03669），永达凭借专业的服务能力、强大的企业实力和优良的企业形象，得到了社会各界和行业专家的广泛认可，先后荣获了“中国企业500强”、“中国汽车销售服务十大企业集团”、“全国守合同重信用企业”、“全国文明单位”、“上海市文明单位”、“上海市著名商标”等荣誉称号。我们主要经营汽车销售服务、二手车、汽车金融、汽车租赁等产业，公司主要代理宾利、保时捷、捷豹路虎、阿斯顿马丁、宝马、奔驰、奥迪、林肯、英菲尼迪、凯迪拉克等多个国际知名豪华汽车品牌，服务网络主要分布在上海、北京、天津等3个直辖市和17个省的55个城市。率先在行业内形成学车、买车、卖车、租车、修车、验车等完整的汽车销售服务产业链，提供新车销售、汽车金融与保险、装潢用品、售后服务、平行进口汽车、二手车置换与销售、快修连锁、汽车零配件和养护品销售等服务，并通过互联网电商及新媒体平台，构建线上线下一体化全方位的汽车产业链生态圈，打造高效、便捷的汽车生活服务平台。永达新能源集团上海永达新能源汽车集团有限公司主要经营新能源汽车销售服务、新能源后市场服务及充换电等产业，公司主要代理小鹏、华为AITO、特斯拉、路特斯、SMART、上汽智己、福特新能源（野马）、欧拉、零跑等多个国内知名新势力新能源汽车品牌，服务网络持续扩大目前主要分布在上海、苏州、杭州、无锡、南京、丽水、常州、广州、南昌、合肥、绵阳等多个城市，运营规模及服务能力不断攀升。 | D97: 新能源汽车产品专家 - 上海 | E97: 10 | F97: 大专 | G97: 职位描述1、热情接待进店用户，专业、准确地向用户讲解永达新能源所代理的品牌与产品；2、提供专业、完善的试驾体验，提高用户对产品的认可，建立并维系用户关系；3、向用户传递永达新能源的核心价值观，提高用户对永达新能源的品牌认可；4、认真学习了解代理品牌及产品的相关知识，完成各阶段成长任务；5、积极围绕用户需求，执行落地用户活动，根据业务发展需求，完成分配的其他相关职责。职位要求1、大专及以上学历，市场营销及汽车相关专业优先；2、形象气质佳，平易近人；3、热爱汽车与科技。 | H97: 日薪：150/天 | I97: =_xlfn.CONCAT(D97,"（学历：",F97," 专业要求：",IF(ISBLANK(M97),"无",M97),"）") -> 新能源汽车产品专家 - 上海（学历：大专 专业要求：无） | J97: =LEN(G97) -> 235 | K97: =_xlfn.XLOOKUP(A97,长度要求!A:A,长度要求!E:E) -> 500 | L97: =IF(J97<K97,G97,LEFT(G97,K97)&"……") -> 职位描述1、热情接待进店用户，专业、准确地向用户讲解永达新能源所代理的品牌与产品；2、提供专业、完善的试驾体验，提高用户对产品的认可，建立并维系用户关系；3、向用户传递永达新能源的核心价值观，提高用户对永达新能源的品牌认可；4、认真学习了解代理品牌及产品的相关知识，完成各阶段成长任务；5、积极围绕用户需求，执行落地用户活动，根据业务发展需求，完成分配的其他相关职责。职位要求1、大专及以上学历，市场营销及汽车相关专业优先；2、形象气质佳，平易近人；3、热爱汽车与科技。 | N97: =LEN(M97) -> 0 | O97: =IF(ISBLANK(M97),0,COUNTA(_xlfn.TEXTSPLIT(M97,","))) -> 0
A98: =COUNTIF(B:B,B98) -> 2 | B98: 上海迪麦科能源科技有限公司 | C98: 上海迪麦科能源科技有限公司是专业的暖通自控BA系统技术服务商，美国ALC公司（美国开利Carrier空调全资子公司）长期合作伙伴。专注于以中央空调系统为主的机电设备自控和节能管理，已经完成大量的T3、T4级别的大型数据中心项目。隶属于美国开利Carrier空调的ALC公司研发的WebCTRL系统是暖通自控BA行业最先进的系统之一，结合迪麦科公司多年的工程实践经验、强大的专业技术团队和大量数据中心案例，为各种类型数据中心用户提供设计完善、运行稳定、节能环保的BA系统的完整解决方案。上海迪麦科能源科技有限公司是万国数据、数据港、世纪互联等定制数据中心服务提供商的长期合作伙伴，为工商银行、阿里、微软、腾讯、百度和各地电信公司在北京、上海、深圳、广州、河源、杭州、南通、廊坊等地众多数据中心和云服务设施提供了完善的BA系统建设和技术服务。 | D98: 助理工程师 | E98: 3 | F98: 大专 | G98: 现招聘常驻上海、南通、杭州、广东河源、北京、河北廊坊等地的若干技术人员，要求如下：1)大专以上学历，智能化、自动化、机电一体化、暖通空调、制冷等相关专业毕业；2)有1~2年以上的实际工作经验（应届毕业生无工作经验要求）；3)熟练掌握CAD设计和Office办公软件的应用；4)有志向在大型数据中心行业长期发展；5)吃苦耐劳，有长时间在施工工地艰苦环境下工作和学习的心里准备；岗位职责：1、负责楼宇自控系统的安装、调试与维护工作；2、熟悉并能够处理常见的楼宇自控设备问题，确保系统稳定运行；3、参与楼宇自控项目的实施，提供技术支持和解决方案。 | H98: 月薪：4K-6K | I98: =_xlfn.CONCAT(D98,"（学历：",F98," 专业要求：",IF(ISBLANK(M98),"无",M98),"）") -> 助理工程师（学历：大专 专业要求：建筑电气与智能化,建筑智能化工程技术,供热通风与空调工程技术,制冷与空调技术） | J98: =LEN(G98) -> 270 | K98: =_xlfn.XLOOKUP(A98,长度要求!A:A,长度要求!E:E) -> 500 | L98: =IF(J98<K98,G98,LEFT(G98,K98)&"……") -> 现招聘常驻上海、南通、杭州、广东河源、北京、河北廊坊等地的若干技术人员，要求如下：1)大专以上学历，智能化、自动化、机电一体化、暖通空调、制冷等相关专业毕业；2)有1~2年以上的实际工作经验（应届毕业生无工作经验要求）；3)熟练掌握CAD设计和Office办公软件的应用；4)有志向在大型数据中心行业长期发展；5)吃苦耐劳，有长时间在施工工地艰苦环境下工作和学习的心里准备；岗位职责：1、负责楼宇自控系统的安装、调试与维护工作；2、熟悉并能够处理常见的楼宇自控设备问题，确保系统稳定运行；3、参与楼宇自控项目的实施，提供技术支持和解决方案。 | M98: 建筑电气与智能化,建筑智能化工程技术,供热通风与空调工程技术,制冷与空调技术 | N98: =LEN(M98) -> 38 | O98: =IF(ISBLANK(M98),0,COUNTA(_xlfn.TEXTSPLIT(M98,","))) -> 4
A99: =COUNTIF(B:B,B99) -> 2 | B99: 上海迪麦科能源科技有限公司 | C99: 上海迪麦科能源科技有限公司是专业的暖通自控BA系统技术服务商，美国ALC公司（美国开利Carrier空调全资子公司）长期合作伙伴。专注于以中央空调系统为主的机电设备自控和节能管理，已经完成大量的T3、T4级别的大型数据中心项目。隶属于美国开利Carrier空调的ALC公司研发的WebCTRL系统是暖通自控BA行业最先进的系统之一，结合迪麦科公司多年的工程实践经验、强大的专业技术团队和大量数据中心案例，为各种类型数据中心用户提供设计完善、运行稳定、节能环保的BA系统的完整解决方案。上海迪麦科能源科技有限公司是万国数据、数据港、世纪互联等定制数据中心服务提供商的长期合作伙伴，为工商银行、阿里、微软、腾讯、百度和各地电信公司在北京、上海、深圳、广州、河源、杭州、南通、廊坊等地众多数据中心和云服务设施提供了完善的BA系统建设和技术服务。 | D99: 助理工程师 | E99: 3 | F99: 大专 | G99: 现招聘常驻上海、南通、杭州、广东河源、北京、河北廊坊等地的若干技术人员，要求如下：1)大专以上学历，智能化、自动化、机电一体化、暖通空调、制冷等相关专业毕业；2)有1~2年以上的实际工作经验（应届毕业生无工作经验要求）；3)熟练掌握CAD设计和Office办公软件的应用；4)有志向在大型数据中心行业长期发展；5)吃苦耐劳，有长时间在施工工地艰苦环境下工作和学习的心里准备；岗位职责：1、负责楼宇自控系统的安装、调试与维护工作；2、熟悉并能够处理常见的楼宇自控设备问题，确保系统稳定运行；3、参与楼宇自控项目的实施，提供技术支持和解决方案。 | H99: 日薪：150-200/天 | I99: =_xlfn.CONCAT(D99,"（学历：",F99," 专业要求：",IF(ISBLANK(M99),"无",M99),"）") -> 助理工程师（学历：大专 专业要求：建筑电气与智能化,建筑智能化工程技术,制冷与空调技术,供热、供燃气、通风及空调工程） | J99: =LEN(G99) -> 270 | K99: =_xlfn.XLOOKUP(A99,长度要求!A:A,长度要求!E:E) -> 500 | L99: =IF(J99<K99,G99,LEFT(G99,K99)&"……") -> 现招聘常驻上海、南通、杭州、广东河源、北京、河北廊坊等地的若干技术人员，要求如下：1)大专以上学历，智能化、自动化、机电一体化、暖通空调、制冷等相关专业毕业；2)有1~2年以上的实际工作经验（应届毕业生无工作经验要求）；3)熟练掌握CAD设计和Office办公软件的应用；4)有志向在大型数据中心行业长期发展；5)吃苦耐劳，有长时间在施工工地艰苦环境下工作和学习的心里准备；岗位职责：1、负责楼宇自控系统的安装、调试与维护工作；2、熟悉并能够处理常见的楼宇自控设备问题，确保系统稳定运行；3、参与楼宇自控项目的实施，提供技术支持和解决方案。 | M99: 建筑电气与智能化,建筑智能化工程技术,制冷与空调技术,供热、供燃气、通风及空调工程 | N99: =LEN(M99) -> 41 | O99: =IF(ISBLANK(M99),0,COUNTA(_xlfn.TEXTSPLIT(M99,","))) -> 4
A100: =COUNTIF(B:B,B100) -> 3 | B100: 上海木圣网络科技有限公司 | C100: 木圣科技是一家从事3D虚拟现实的高新科技企业。主要是以3D制作，VR（虚拟现实），AR（增强现实）开发为核心业务。致力于国内外各个行业的虚拟现时内容定制服务和解决方案。 | D100: 项目经理助理 | E100: 3 | F100: 大专 | G100: 1、协助项目经理一起确认项目开发范围，协助项目经理撰写相关软件项目文档；2、协助项目经理确保项目进程与质量，并将项目阶段性成果反馈给相关项目干系人；3、项目内部协调，了解项目管理进度、项目风险等工作；4、领导安排的其他工作；任职资格：1、吃苦耐劳，责任心强，抗压能力强；2、良好的协调、沟通能力，强烈的团队意识和协作精神，主动性和执行力强；3、学习能力强，细心认真，有一定的分析和总结能力；4、熟练使用办公软件，如Excel、Word等；5、计算机专业、软件工程相关专业优先考虑； | H100: 月薪：4K-8K | I100: =_xlfn.CONCAT(D100,"（学历：",F100," 专业要求：",IF(ISBLANK(M100),"无",M100),"）") -> 项目经理助理（学历：大专 专业要求：项目管理） | J100: =LEN(G100) -> 240 | K100: =_xlfn.XLOOKUP(A100,长度要求!A:A,长度要求!E:E) -> 500 | L100: =IF(J100<K100,G100,LEFT(G100,K100)&"……") -> 1、协助项目经理一起确认项目开发范围，协助项目经理撰写相关软件项目文档；2、协助项目经理确保项目进程与质量，并将项目阶段性成果反馈给相关项目干系人；3、项目内部协调，了解项目管理进度、项目风险等工作；4、领导安排的其他工作；任职资格：1、吃苦耐劳，责任心强，抗压能力强；2、良好的协调、沟通能力，强烈的团队意识和协作精神，主动性和执行力强；3、学习能力强，细心认真，有一定的分析和总结能力；4、熟练使用办公软件，如Excel、Word等；5、计算机专业、软件工程相关专业优先考虑； | M100: 项目管理 | N100: =LEN(M100) -> 4 | O100: =IF(ISBLANK(M100),0,COUNTA(_xlfn.TEXTSPLIT(M100,","))) -> 1
...

Sheet 展区展位
A1: 名称 | B1: 展区 | C1: 展位
A2: 上海无线电设备研究所 | B2: A机械/制造/能源 | C2: A01
A3: 上海航天控制技术研究所 | B3: A机械/制造/能源 | C3: A02
A4: 上海航天电子通讯设备研究所 | B4: A机械/制造/能源 | C4: A03
A5: 上海卫星装备研究所 | B5: A机械/制造/能源 | C5: A04
A6: 上海航天精密机械研究所 | B6: A机械/制造/能源 | C6: A05
A7: 上海空间电源研究所 | B7: A机械/制造/能源 | C7: A06
A8: 上海新力动力设备研究所 | B8: A机械/制造/能源 | C8: A07
A9: 航天八院一四九厂 | B9: A机械/制造/能源 | C9: A08
A10: 上海中航光电子有限公司 | B10: A机械/制造/能源 | C10: A09
A11: 上海三菱电梯有限公司安装维修分公司 | B11: A机械/制造/能源 | C11: A10
A12: 上海飒智智能科技有限公司 | B12: A机械/制造/能源 | C12: A11
... A127: 上海笛申文化发展有限公司 | B127: F综合 | C127: F11

Sheet 长度要求
A1: 岗位数 | B1: 企业简介长度 | C1: 岗位介绍长度 | D1: 简介最长 | E1: 介绍最长
A2: 1 | B2: 200 | C2: 500 | D2: 200 | E2: 500
A3: 2 | B3: 200 | C3: 500 | D3: 200 | E3: 500
A4: 3 | B4: 200 | C4: 500 | D4: 200 | E4: 500
A5: 4 | B5: 200 | C5: 500 | D5: 200 | E5: 500
A6: 5 | B6: 200 | C6: 500 | D6: 200 | E6: 500
A7: 6 | B7: 200 | C7: 500 | D7: 200 | E7: 500
A8: 7 | B8: 200 | C8: 500 | D8: 200 | E8: 500
A9: 8 | B9: 200 | C9: 500 | D9: 200 | E9: 500
A10: 9 | B10: 200 | C10: 500 | D10: 200 | E10: 500
A11: 10 | B11: 200 | C11: 500 | D11: 200 | E11: 500
A12: 11 | B12: 200 | C12: 500 | D12: 200 | E12: 500
A13: 12 | B13: 200 | C13: 500 | D13: 200 | E13: 500
... A31: 30 | B31: 204 | C31: 500 | D31: 200 | E31: 500

Sheet 企业简介提取
A1: 岗位数量 | B1: 企业名称 | C1: 企业简介 | D1: 长度 | E1: 长度要求 | F1: 截取后内容
A2: =COUNTIF(B:B,B2) -> 4 | B2: 上海光通信有限公司 | C2: 上海光通信有限公司（英文名 Shanghai GTX Semiconductor Co., Ltd，下称“GTX”），成立于1988年，于2022年初转型进入集成电路制造领域。 | D2: =LEN(C2) -> 88 | E2: =_xlfn.XLOOKUP(A2,长度要求!A:A,长度要求!D:D) -> 200 | F2: =IF(D2<E2,C2,LEFT(C2,E2)&"……") -> 上海光通信有限公司（英文名 Shanghai GTX Semiconductor Co., Ltd，下称“GTX”），成立于1988年，于2022年初转型进入集成电路制造领域。
A3: =COUNTIF(B:B,B3) -> 6 | B3: 上海新皋实业有限公司 | C3: 新皋实业成立于2013年初，总部位于上海虹桥机场毗邻的明谷科技园，公司在智能家居领域率先投入智能家居控制系统的项目研发、生产及销售。获得软件专利著作权十多项，企业获得国家商标局认证商标： 《新皋》《XINGAO》《艾登堡》《ATNBO》等品牌，并推出真正适合国内外用户的智能影音系列产品。自主研发新皋XINGAO智能影院中控系统及艾登堡ATNBO家庭影院系列产品,深受行业专业人士好评。 新皋实业是上海闵行区就业促进中心审核认定的大学生实习基地，常年招收在校大学生实习实践，上海闵行地区户籍大学生或闵行地区高校学生优先录取，实习享受上海市闵行区人社局补贴。 | D3: =LEN(C3) -> 291 | E3: =_xlfn.XLOOKUP(A3,长度要求!A:A,长度要求!D:D) -> 200 | F3: =IF(D3<E3,C3,LEFT(C3,E3)&"……") -> 新皋实业成立于2013年初，总部位于上海虹桥机场毗邻的明谷科技园，公司在智能家居领域率先投入智能家居控制系统的项目研发、生产及销售。获得软件专利著作权十多项，企业获得国家商标局认证商标： 《新皋》《XINGAO》《艾登堡》《ATNBO》等品牌，并推出真正适合国内外用户的智能影音系列产品。自主研发新皋XINGAO智能影院中控系统及艾登堡ATNBO家庭影院系列产品,深受行业专业人士好评。……
A4: =COUNTIF(B:B,B4) -> 6 | B4: 上海新皋实业有限公司 | C4: 新皋实业成立于2013年初，总部位于上海虹桥机场毗邻的明谷科技园，公司在智能家居领域率先投入智能家居控制系统的项目研发、生产及销售。获得软件专利著作权十多项，企业获得国家商标局认证商标： 《新皋》《XINGAO》《艾登堡》《ATNBO》等品牌，并推出真正适合国内外用户的智能影音系列产品。自主研发新皋XINGAO智能影院中控系统及艾登堡ATNBO家庭影院系列产品,深受行业专业人士好评。 新皋实业是上海闵行区就业促进中心审核认定的大学生实习基地，常年招收在校大学生实习实践，上海闵行地区户籍大学生或闵行地区高校学生优先录取，实习享受上海市闵行区人社局补贴。 | D4: =LEN(C4) -> 291 | E4: =_xlfn.XLOOKUP(A4,长度要求!A:A,长度要求!D:D) -> 200 | F4: =IF(D4<E4,C4,LEFT(C4,E4)&"……") -> 新皋实业成立于2013年初，总部位于上海虹桥机场毗邻的明谷科技园，公司在智能家居领域率先投入智能家居控制系统的项目研发、生产及销售。获得软件专利著作权十多项，企业获得国家商标局认证商标： 《新皋》《XINGAO》《艾登堡》《ATNBO》等品牌，并推出真正适合国内外用户的智能影音系列产品。自主研发新皋XINGAO智能影院中控系统及艾登堡ATNBO家庭影院系列产品,深受行业专业人士好评。……
A5: =COUNTIF(B:B,B5) -> 2 | B5: 上海德辰汽车销售有限公司 | C5: 上海德辰汽车销售公司是北方一大型汽车经销商集团在上海新投资创立的 一汽大众奥迪品牌 4S 店。超越了传统豪华汽车 4S 店的概念，实际具备品牌体 验、车型展示、新车销售、售后服务、二手车置换等多种功能，完备的设施以 及周到的服务一应俱全，体现出国际豪华品牌全球统一的服务水准。 该城市展厅坐落于闵行区颛桥地区（颛兴东路 1280 弄 3 号）。地铁、轻轨 均可到达，交通便捷。地址：颛兴东路 1280 弄 3 号。总占地面积 11455 平方 米。上下共有三层，展厅面积 4168 平方米，销售展示分两层，有超过多个标准 汽车展位，大厅设有人性化的自动扶梯；屋顶设置顶楼停车厂，日接待能力超 过 100 台。简洁明快的建筑风格，落地玻璃和透明天窗的结合使整个展厅最大 限度地充满阳光和自然气息，充分体现了人性与科技的完美结合，展现奥迪品 牌的超凡卓越和豪华尊贵，修理车间面积 7287 平方米，共有多个汽车维修工 位，技术人员有 40 人，分为机修、电工、钣金、喷漆区，布局合理，设备先 进。突出强调“买车修车到德辰，诚信舒心更放心”的服务理念。也是每个德 辰员工的座右铭。我们以完善的硬件设施、周到的人性化服务迎接您的光临。 背景介绍 上海德辰的股东旗下共拥有多家 4S 店，其中在长春、嘉兴、宁波销售一汽 奥迪、一汽马自达、一汽丰田等知名品牌汽车。 企业文化 上海德辰奉行“务实、诚信、进取、激情、团队精神、服务意识”的企业 文化；在选人、用人、育人上：以具竞争力的薪酬吸引人才、以完善的培训体 系培养人才，以强烈的业绩导向、快速的晋升和广阔的发展空间开发人才。 | D5: =LEN(C5) -> 697 | E5: =_xlfn.XLOOKUP(A5,长度要求!A:A,长度要求!D:D) -> 200 | F5: =IF(D5<E5,C5,LEFT(C5,E5)&"……") -> 上海德辰汽车销售公司是北方一大型汽车经销商集团在上海新投资创立的 一汽大众奥迪品牌 4S 店。超越了传统豪华汽车 4S 店的概念，实际具备品牌体 验、车型展示、新车销售、售后服务、二手车置换等多种功能，完备的设施以 及周到的服务一应俱全，体现出国际豪华品牌全球统一的服务水准。 该城市展厅坐落于闵行区颛桥地区（颛兴东路 1280 弄 3 号）。地铁、轻轨 均可到达，交通便捷。地址：颛兴东路 ……
A6: =COUNTIF(B:B,B6) -> 1 | B6: 上海市黄浦区西凌第一幼儿园 | C6: 西凌第一幼儿园是一所上海市示范性幼儿园、上海市文明单位。地处黄浦区西藏南路，园内幼儿活动场地充裕，环境优美，四季绿化常青，阳光充足，是“上海市花园单位”。我园积极探索围棋与游戏融合的探索，秉持“以人为本，民主和谐，快乐发展”办园宗旨和 “以棋养德、以棋怡情、以棋明理、以棋启智”的教育理念，深受幼儿与家长的喜欢。西凌第一幼儿园已成为孩子们游戏、学习、生活的乐园。 | D6: =LEN(C6) -> 184 | E6: =_xlfn.XLOOKUP(A6,长度要求!A:A,长度要求!D:D) -> 200 | F6: =IF(D6<E6,C6,LEFT(C6,E6)&"……") -> 西凌第一幼儿园是一所上海市示范性幼儿园、上海市文明单位。地处黄浦区西藏南路，园内幼儿活动场地充裕，环境优美，四季绿化常青，阳光充足，是“上海市花园单位”。我园积极探索围棋与游戏融合的探索，秉持“以人为本，民主和谐，快乐发展”办园宗旨和 “以棋养德、以棋怡情、以棋明理、以棋启智”的教育理念，深受幼儿与家长的喜欢。西凌第一幼儿园已成为孩子们游戏、学习、生活的乐园。
A7: =COUNTIF(B:B,B7) -> 6 | B7: 上海新皋实业有限公司 | C7: 新皋实业成立于2013年初，总部位于上海虹桥机场毗邻的明谷科技园，公司在智能家居领域率先投入智能家居控制系统的项目研发、生产及销售。获得软件专利著作权十多项，企业获得国家商标局认证商标： 《新皋》《XINGAO》《艾登堡》《ATNBO》等品牌，并推出真正适合国内外用户的智能影音系列产品。自主研发新皋XINGAO智能影院中控系统及艾登堡ATNBO家庭影院系列产品,深受行业专业人士好评。 新皋实业是上海闵行区就业促进中心审核认定的大学生实习基地，常年招收在校大学生实习实践，上海闵行地区户籍大学生或闵行地区高校学生优先录取，实习享受上海市闵行区人社局补贴。 | D7: =LEN(C7) -> 291 | E7: =_xlfn.XLOOKUP(A7,长度要求!A:A,长度要求!D:D) -> 200 | F7: =IF(D7<E7,C7,LEFT(C7,E7)&"……") -> 新皋实业成立于2013年初，总部位于上海虹桥机场毗邻的明谷科技园，公司在智能家居领域率先投入智能家居控制系统的项目研发、生产及销售。获得软件专利著作权十多项，企业获得国家商标局认证商标： 《新皋》《XINGAO》《艾登堡》《ATNBO》等品牌，并推出真正适合国内外用户的智能影音系列产品。自主研发新皋XINGAO智能影院中控系统及艾登堡ATNBO家庭影院系列产品,深受行业专业人士好评。……
A8: =COUNTIF(B:B,B8) -> 6 | B8: 上海新皋实业有限公司 | C8: 新皋实业成立于2013年初，总部位于上海虹桥机场毗邻的明谷科技园，公司在智能家居领域率先投入智能家居控制系统的项目研发、生产及销售。获得软件专利著作权十多项，企业获得国家商标局认证商标： 《新皋》《XINGAO》《艾登堡》《ATNBO》等品牌，并推出真正适合国内外用户的智能影音系列产品。自主研发新皋XINGAO智能影院中控系统及艾登堡ATNBO家庭影院系列产品,深受行业专业人士好评。 新皋实业是上海闵行区就业促进中心审核认定的大学生实习基地，常年招收在校大学生实习实践，上海闵行地区户籍大学生或闵行地区高校学生优先录取，实习享受上海市闵行区人社局补贴。 | D8: =LEN(C8) -> 291 | E8: =_xlfn.XLOOKUP(A8,长度要求!A:A,长度要求!D:D) -> 200 | F8: =IF(D8<E8,C8,LEFT(C8,E8)&"……") -> 新皋实业成立于2013年初，总部位于上海虹桥机场毗邻的明谷科技园，公司在智能家居领域率先投入智能家居控制系统的项目研发、生产及销售。获得软件专利著作权十多项，企业获得国家商标局认证商标： 《新皋》《XINGAO》《艾登堡》《ATNBO》等品牌，并推出真正适合国内外用户的智能影音系列产品。自主研发新皋XINGAO智能影院中控系统及艾登堡ATNBO家庭影院系列产品,深受行业专业人士好评。……
A9: =COUNTIF(B:B,B9) -> 6 | B9: 上海新皋实业有限公司 | C9: 新皋实业成立于2013年初，总部位于上海虹桥机场毗邻的明谷科技园，公司在智能家居领域率先投入智能家居控制系统的项目研发、生产及销售。获得软件专利著作权十多项，企业获得国家商标局认证商标： 《新皋》《XINGAO》《艾登堡》《ATNBO》等品牌，并推出真正适合国内外用户的智能影音系列产品。自主研发新皋XINGAO智能影院中控系统及艾登堡ATNBO家庭影院系列产品,深受行业专业人士好评。 新皋实业是上海闵行区就业促进中心审核认定的大学生实习基地，常年招收在校大学生实习实践，上海闵行地区户籍大学生或闵行地区高校学生优先录取，实习享受上海市闵行区人社局补贴。 | D9: =LEN(C9) -> 291 | E9: =_xlfn.XLOOKUP(A9,长度要求!A:A,长度要求!D:D) -> 200 | F9: =IF(D9<E9,C9,LEFT(C9,E9)&"……") -> 新皋实业成立于2013年初，总部位于上海虹桥机场毗邻的明谷科技园，公司在智能家居领域率先投入智能家居控制系统的项目研发、生产及销售。获得软件专利著作权十多项，企业获得国家商标局认证商标： 《新皋》《XINGAO》《艾登堡》《ATNBO》等品牌，并推出真正适合国内外用户的智能影音系列产品。自主研发新皋XINGAO智能影院中控系统及艾登堡ATNBO家庭影院系列产品,深受行业专业人士好评。……
A10: =COUNTIF(B:B,B10) -> 6 | B10: 上海新皋实业有限公司 | C10: 新皋实业成立于2013年初，总部位于上海虹桥机场毗邻的明谷科技园，公司在智能家居领域率先投入智能家居控制系统的项目研发、生产及销售。获得软件专利著作权十多项，企业获得国家商标局认证商标： 《新皋》《XINGAO》《艾登堡》《ATNBO》等品牌，并推出真正适合国内外用户的智能影音系列产品。自主研发新皋XINGAO智能影院中控系统及艾登堡ATNBO家庭影院系列产品,深受行业专业人士好评。 新皋实业是上海闵行区就业促进中心审核认定的大学生实习基地，常年招收在校大学生实习实践，上海闵行地区户籍大学生或闵行地区高校学生优先录取，实习享受上海市闵行区人社局补贴。 | D10: =LEN(C10) -> 291 | E10: =_xlfn.XLOOKUP(A10,长度要求!A:A,长度要求!D:D) -> 200 | F10: =IF(D10<E10,C10,LEFT(C10,E10)&"……") -> 新皋实业成立于2013年初，总部位于上海虹桥机场毗邻的明谷科技园，公司在智能家居领域率先投入智能家居控制系统的项目研发、生产及销售。获得软件专利著作权十多项，企业获得国家商标局认证商标： 《新皋》《XINGAO》《艾登堡》《ATNBO》等品牌，并推出真正适合国内外用户的智能影音系列产品。自主研发新皋XINGAO智能影院中控系统及艾登堡ATNBO家庭影院系列产品,深受行业专业人士好评。……
A11: =COUNTIF(B:B,B11) -> 2 | B11: 上海网鱼酒店管理有限公司 | C11: 网鱼创始于1998年，从诞生之初就秉承不断创新的理念，致力于打造多人游戏空间。截至2020年12月31日，网鱼全球会员数超2000万，服务覆盖国内外106个城市。全球拥有超1000家门店，年服务人次超3000万，iG战队倾情代言，是深受全球玩家喜爱的聚玩圣地。2021年推出“网鱼电竞酒店”，正式进军电竞酒店行业，打造跨品类、跨业态、跨平台的综合娱乐型品牌，践行“给用户美好的体验”。 | D11: =LEN(C11) -> 192 | E11: =_xlfn.XLOOKUP(A11,长度要求!A:A,长度要求!D:D) -> 200 | F11: =IF(D11<E11,C11,LEFT(C11,E11)&"……") -> 网鱼创始于1998年，从诞生之初就秉承不断创新的理念，致力于打造多人游戏空间。截至2020年12月31日，网鱼全球会员数超2000万，服务覆盖国内外106个城市。全球拥有超1000家门店，年服务人次超3000万，iG战队倾情代言，是深受全球玩家喜爱的聚玩圣地。2021年推出“网鱼电竞酒店”，正式进军电竞酒店行业，打造跨品类、跨业态、跨平台的综合娱乐型品牌，践行“给用户美好的体验”。
A12: =COUNTIF(B:B,B12) -> 2 | B12: 上海网鱼酒店管理有限公司 | C12: 网鱼创始于1998年，从诞生之初就秉承不断创新的理念，致力于打造多人游戏空间。截至2020年12月31日，网鱼全球会员数超2000万，服务覆盖国内外106个城市。全球拥有超1000家门店，年服务人次超3000万，iG战队倾情代言，是深受全球玩家喜爱的聚玩圣地。2021年推出“网鱼电竞酒店”，正式进军电竞酒店行业，打造跨品类、跨业态、跨平台的综合娱乐型品牌，践行“给用户美好的体验”。 | D12: =LEN(C12) -> 192 | E12: =_xlfn.XLOOKUP(A12,长度要求!A:A,长度要求!D:D) -> 200 | F12: =IF(D12<E12,C12,LEFT(C12,E12)&"……") -> 网鱼创始于1998年，从诞生之初就秉承不断创新的理念，致力于打造多人游戏空间。截至2020年12月31日，网鱼全球会员数超2000万，服务覆盖国内外106个城市。全球拥有超1000家门店，年服务人次超3000万，iG战队倾情代言，是深受全球玩家喜爱的聚玩圣地。2021年推出“网鱼电竞酒店”，正式进军电竞酒店行业，打造跨品类、跨业态、跨平台的综合娱乐型品牌，践行“给用户美好的体验”。
A13: =COUNTIF(B:B,B13) -> 4 | B13: 珍岛信息技术（上海）股份有限公司 | C13: 珍岛信息技术（上海）股份有限公司（简称珍岛集团，股票代码02556.HK）是中国最大的营销及销售SaaS公司，也是最早推出 T-force 营销领域大模型的公司，最早推出 AI-Agentforce 中台的公司，聚焦数字化与智能化，基于人工智能、大数据技术，是专注数字化智能营销的SaaS服务提供商，于2024年在香港上市。 | D13: =LEN(C13) -> 162 | E13: =_xlfn.XLOOKUP(A13,长度要求!A:A,长度要求!D:D) -> 200 | F13: =IF(D13<E13,C13,LEFT(C13,E13)&"……") -> 珍岛信息技术（上海）股份有限公司（简称珍岛集团，股票代码02556.HK）是中国最大的营销及销售SaaS公司，也是最早推出 T-force 营销领域大模型的公司，最早推出 AI-Agentforce 中台的公司，聚焦数字化与智能化，基于人工智能、大数据技术，是专注数字化智能营销的SaaS服务提供商，于2024年在香港上市。
... A363: =COUNTIF(B:B,B363) -> 3 | B363: 中信泰富（上海）物业管理有限公司 | C363: 中信泰富（上海）物业管理有限公司于2004年在上海注册成立。中信泰富物业以中信集团创始人、前国家副主席荣毅仁先生所倡导的“遵纪守法、作风正派、实事求是、开拓创新、谦虚谨慎、团结互助、勤勉奋发、雷厉风行”三十二字作为企业文化建设的指导方针；以“品质源自于细节的关怀”作为作风特征，突出“规范、周到、务实、高效”的服务宗旨，努力创建具有“国际水准、中国特色”的一流物业管理企业。 | D363: =LEN(C363) -> 194 | E363: =_xlfn.XLOOKUP(A363,长度要求!A:A,长度要求!D:D) -> 200 | F363: =IF(D363<E363,C363,LEFT(C363,E363)&"……") -> 中信泰富（上海）物业管理有限公司于2004年在上海注册成立。中信泰富物业以中信集团创始人、前国家副主席荣毅仁先生所倡导的“遵纪守法、作风正派、实事求是、开拓创新、谦虚谨慎、团结互助、勤勉奋发、雷厉风行”三十二字作为企业文化建设的指导方针；以“品质源自于细节的关怀”作为作风特征，突出“规范、周到、务实、高效”的服务宗旨，努力创建具有“国际水准、中国特色”的一流物业管理企业。

Sheet 岗位1
A1: 展区 | B1: 展位 | C1: 单位名称 | D1: 单位简介 | E1: 职位1标题 | F1: 职位1jd | H1: 单位简介 | I1: 职位1jd
A2: =_xlfn.XLOOKUP(C2,展区展位!A:A,展区展位!B:B) -> D教育/传媒/电竞 | B2: =_xlfn.XLOOKUP(C2,展区展位!A:A,展区展位!C:C) -> D06 | C2: 上海市黄浦区西凌第一幼儿园 | D2: =_xlfn.XLOOKUP(C2,企业简介提取!B:B,企业简介提取!F:F) -> 西凌第一幼儿园是一所上海市示范性幼儿园、上海市文明单位。地处黄浦区西藏南路，园内幼儿活动场地充裕，环境优美，四季绿化常青，阳光充足，是“上海市花园单位”。我园积极探索围棋与游戏融合的探索，秉持“以人为本，民主和谐，快乐发展”办园宗旨和 “以棋养德、以棋怡情、以棋明理、以棋启智”的教育理念，深受幼儿与家长的喜欢。西凌第一幼儿园已成为孩子们游戏、学习、生活的乐园。 | E2: =INDEX(_xlfn._xlws.FILTER(报名明细!$I:$I,报名明细!$B:$B=$C2),1) -> 保育员（学历：初中及以下 专业要求：学前教育,卫生教育） | F2: =INDEX(_xlfn._xlws.FILTER(报名明细!$L:$L,报名明细!$B:$B=$C2),1) -> 具有良好师德，爱孩子，有正确的儿童观具备保育专业知识与技能 | H2: 西凌第一幼儿园是一所上海市示范性幼儿园、上海市文明单位。地处黄浦区西藏南路，园内幼儿活动场地充裕，环境优美，四季绿化常青，阳光充足，是“上海市花园单位”。我园积极探索围棋与游戏融合的探索，秉持“以人为本，民主和谐，快乐发展”办园宗旨和“以棋养德、以棋怡情、以棋明理、以棋启智”的教育理念，深受幼儿与家长的喜欢。西凌第一幼儿园已成为孩子们游戏、学习、生活的乐园。 | I2: 具有良好师德，爱孩子，有正确的儿童观具备保育专业知识与技能
A3: =_xlfn.XLOOKUP(C3,展区展位!A:A,展区展位!B:B) -> E城市运营与技术服务 | B3: =_xlfn.XLOOKUP(C3,展区展位!A:A,展区展位!C:C) -> E01 | C3: 上海世博中心有限公司 | D3: =_xlfn.XLOOKUP(C3,企业简介提取!B:B,企业简介提取!F:F) -> 上海世博中心，作为上海市机关事务管理局下属国有企业，同样具备了举办展览、会议、活动以及房屋租赁的功能，与上展中心在浦江两岸形成东西呼应的两座上海标志性建筑。上海世博中心以成为世界级的会议中心为目标。世博会期间，其承担了庆典、交流、贵宾接待、新闻发布和指挥运营等重要任务。世博会后，已转型成为大型高规格国际会议的重要场所，一方面承担政务服务功能，成为上海市“两会”及其他政务性会议的重要举办场所；另一方…… | E3: =INDEX(_xlfn._xlws.FILTER(报名明细!$I:$I,报名明细!$B:$B=$C3),1) -> 会展接待服务（学历：初中及以下 专业要求：无） | F3: =INDEX(_xlfn._xlws.FILTER(报名明细!$L:$L,报名明细!$B:$B=$C3),1) -> 1.女：身高1.65米以上，专业不限；2.品貌端正、无纹身、对工作有责任心，能吃苦耐劳；3.按照客户要求布置好会场，做好会前的准备工作；4.做好会中接待工作，确保会议有序进行；5.本岗位可招收实习生；6.完成上级安排的其他工作。 | H3: 上海世博中心，作为上海市机关事务管理局下属国有企业，同样具备了举办展览、会议、活动以及房屋租赁的功能，与上展中心在浦江两岸形成东西呼应的两座上海标志性建筑。上海世博中心以成为世界级的会议中心为目标。世博会期间，其承担了庆典、交流、贵宾接待、新闻发布和指挥运营等重要任务。世博会后，已转型成为大型高规格国际会议的重要场所，一方面承担政务服务功能，成为上海市“两会”及其他政务性会议的重要举办场所；另一方面还要承载社会功能，对市场和社会开放，以其会议、展览、活动（宴会）等专业功能形成核心竞争力，充分展示上海国际大都会形象，提升上海城市的综合竞争力。 | I3: 1.女：身高1.65米以上，专业不限；2.品貌端正、无纹身、对工作有责任心，能吃苦耐劳；3.按照客户要求布置好会场，做好会前的准备工作；4.做好会中接待工作，确保会议有序进行；5.本岗位可招收实习生；6.完成上级安排的其他工作。
A4: =_xlfn.XLOOKUP(C4,展区展位!A:A,展区展位!B:B) -> B互联网/电子/通信 | B4: =_xlfn.XLOOKUP(C4,展区展位!A:A,展区展位!C:C) -> B14 | C4: 上海特金信息科技有限公司 | D4: =_xlfn.XLOOKUP(C4,企业简介提取!B:B,企业简介提取!F:F) -> 上海特金创立于2003年，是国家级高新技术企业、国家级专精特新“小巨人”企业、上海市“专精特 新”企业，20余年深耕无线电感知和频谱大数据分析技术，致力于提供可信赖的低空安全管控解决方案， 在无人机预案、预警、识别、定位、追踪及处置方面处于业界领军地位，是国内将TDOA网格化无人机管控 技术进行产品化和大规模商用的发起者。 特金拥有一百多项核心知识产权，深度参与国标、行标、团标的标准制定，荣获国…… | E4: =INDEX(_xlfn._xlws.FILTER(报名明细!$I:$I,报名明细!$B:$B=$C4),1) -> 助理产品工程师（学历：大专 专业要求：无） | F4: =INDEX(_xlfn._xlws.FILTER(报名明细!$L:$L,报名明细!$B:$B=$C4),1) -> 岗位职责：1、通过相关培训能够快速适应生产作业，保证每个产品都是按照工艺要求生产；2、经过培训严格按照工艺要求熟练掌握产品组装、调试、测试；3、严格执行上级领导指派的工作任务；4、严格执行生产安全管理制度；5、遵守6S现场规章制度，保持生产线标准化工作环境；6、负责日常设备问题排查维修并输出维修报告。任职资格：1、机械，机电，电子，电气，通讯，无线电专业等工学专业；2、要求大专学历，应届毕业生或实习生；3、掌握基础电路、机械、钳工专业知识，会简单编程，熟练使用办公软件；4、能够接受不定时加班、户外测试，有驾驶证优先；5、有机械证书或者电工证优先；6、为人正直有较强的团队协助精神、勤奋好学、积极向上、有敬业精神，无不良嗜好。7、能尽快上岗者优先。 | H4: 上海特金创立于2003年，是国家级高新技术企业、国家级专精特新“小巨人”企业、上海市“专精特新”企业，20余年深耕无线电感知和频谱大数据分析技术，致力于提供可信赖的低空安全管控解决方案，在无人机预案、预警、识别、定位、追踪及处置方面处于业界领军地位，是国内将TDOA网格化无人机管控技术进行产品化和大规模商用的发起者。特金拥有一百多项核心知识产权，深度参与国标、行标、团标的标准制定，荣获国际电联ITUTelecomWorld全球最佳创新奖。特金无人机探测定位管制系统服务于建党百周年庆及70周年国庆首都核心区，杭州亚运会、成都大运会、央视春晚等大型活动低空安全保障，被誉为“低空防御专家，家国和平卫士”。 | I4: 岗位职责：1、通过相关培训能够快速适应生产作业，保证每个产品都是按照工艺要求生产；2、经过培训严格按照工艺要求熟练掌握产品组装、调试、测试；3、严格执行上级领导指派的工作任务；4、严格执行生产安全管理制度；5、遵守6S现场规章制度，保持生产线标准化工作环境；6、负责日常设备问题排查维修并输出维修报告。任职资格：1、机械，机电，电子，电气，通讯，无线电专业等工学专业；2、要求大专学历，应届毕业生或实习生；3、掌握基础电路、机械、钳工专业知识，会简单编程，熟练使用办公软件；4、能够接受不定时加班、户外测试，有驾驶证优先；5、有机械证书或者电工证优先；6、为人正直有较强的团队协助精神、勤奋好学、积极向上、有敬业精神，无不良嗜好。7、能尽快上岗者优先。
A5: =_xlfn.XLOOKUP(C5,展区展位!A:A,展区展位!B:B) -> D教育/传媒/电竞 | B5: =_xlfn.XLOOKUP(C5,展区展位!A:A,展区展位!C:C) -> D19 | C5: 上海积千理网络科技有限公司 | D5: =_xlfn.XLOOKUP(C5,企业简介提取!B:B,企业简介提取!F:F) -> 上海积千理网络科技有限公司成立于 2019 年 9 月 23 日，是一家专注游戏直播领域的小微企业，公司位于上海市闵行区禾谷文创园A213号，目前处于开业状态。公司经营范围广泛，涵盖数字文化创意内容应用、互联网数据服务、个人互联网直播服务等。自成立以来，公司凭借专业的团队和创新的理念，在游戏直播领域崭露头角，致力于为观众呈现精彩的游戏直播内容，为游戏爱好者搭建互动交流平台，在竞争激烈的游戏直播市场…… | E5: =INDEX(_xlfn._xlws.FILTER(报名明细!$I:$I,报名明细!$B:$B=$C5),1) -> 弹幕游戏互动主播（学历：初中及以下 专业要求：无） | F5: =INDEX(_xlfn._xlws.FILTER(报名明细!$L:$L,报名明细!$B:$B=$C5),1) -> 年满18岁，接受无经验从业者，新手小白，弹幕游戏就是抖音最新直播间弹幕游戏玩法，直播间可以不露脸露不露脸看自己个人意愿，主要就是烘托直播间PK赛况的气氛，拉动观众互动率，不用会玩游戏，不需要你上手操作，解说游戏赛况实时即可。岗位职责:1.负责直播抖音平台弹幕实时互动类游戏，直播游戏玩法2.正常上手后，开播六小时。配合公司运营下播复盘3.运营团队跟播，每日下播复盘，成熟话术提供，打造专属你个人的弹幕游戏直播间4.不需要你去维护大哥大姐，抖音平台自动分流，对新人流量扶持极大5.无任何培训费用，接受新手小白0经验，能快速上手6.公司提供专业电脑以及声卡设备，老人带播任职要求：1.公司可接受新手小白0经验新人从业者，应届生，在校大学生，有无经验均可，有直播行业从业经验优先考虑。2.零基础操作，无需懂太多游戏操作，只要你敢开口说话，性格外向活泼开朗，善于沟通，情商高。3.无任何形象上的要求，不需要才艺，年龄没有限制，学历没有要求，只需要你情商高会说话，敢说话，胆子大月入过万不再是梦想工作时间：每日工作六小时不加班，不需要一直坐班，稳定后可以自己挑选时间段播可以居家办公，节假日正常放假。薪资待遇：…… | H5: 上海积千理网络科技有限公司成立于2019年9月23日，是一家专注游戏直播领域的小微企业，公司位于上海市闵行区禾谷文创园A213号，目前处于开业状态。公司经营范围广泛，涵盖数字文化创意内容应用、互联网数据服务、个人互联网直播服务等。自成立以来，公司凭借专业的团队和创新的理念，在游戏直播领域崭露头角，致力于为观众呈现精彩的游戏直播内容，为游戏爱好者搭建互动交流平台，在竞争激烈的游戏直播市场中逐步站稳脚跟。 | I5: 年满18岁，接受无经验从业者，新手小白，弹幕游戏就是抖音最新直播间弹幕游戏玩法，直播间可以不露脸露不露脸看自己个人意愿，主要就是烘托直播间PK赛况的气氛，拉动观众互动率，不用会玩游戏，不需要你上手操作，解说游戏赛况实时即可。岗位职责:1.负责直播抖音平台弹幕实时互动类游戏，直播游戏玩法2.正常上手后，开播六小时。配合公司运营下播复盘3.运营团队跟播，每日下播复盘，成熟话术提供，打造专属你个人的弹幕游戏直播间4.不需要你去维护大哥大姐，抖音平台自动分流，对新人流量扶持极大5.无任何培训费用，接受新手小白0经验，能快速上手6.公司提供专业电脑以及声卡设备，老人带播任职要求：1.公司可接受新手小白0经验新人从业者，应届生，在校大学生，有无经验均可，有直播行业从业经验优先考虑。2.零基础操作，无需懂太多游戏操作，只要你敢开口说话，性格外向活泼开朗，善于沟通，情商高。3.无任何形象上的要求，不需要才艺，年龄没有限制，学历没有要求，只需要你情商高会说话，敢说话，胆子大月入过万不再是梦想工作时间：每日工作六小时不加班，不需要一直坐班，稳定后可以自己挑选时间段播可以居家办公，节假日正常放假。薪资待遇：……
A6: =_xlfn.XLOOKUP(C6,展区展位!A:A,展区展位!B:B) -> C汽车/服装/贸易 | B6: =_xlfn.XLOOKUP(C6,展区展位!A:A,展区展位!C:C) -> C14 | C6: 上海霈赞国际物流有限公司 | D6: =_xlfn.XLOOKUP(C6,企业简介提取!B:B,企业简介提取!F:F) -> 公司集国际货物贸易、报关、报检、货物运输代理等一体，主要承办货物的国际贸易代理、海运、空运进出口货物的国际运输及代理业务，是中国海关AEO高级认证企业，是诸多一线国际品牌合作伙伴。 | E6: =INDEX(_xlfn._xlws.FILTER(报名明细!$I:$I,报名明细!$B:$B=$C6),1) -> 物流单证报关实习生（学历：大专 专业要求：物流管理,报关与国际货运,国际贸易实务） | F6: =INDEX(_xlfn._xlws.FILTER(报名明细!$L:$L,报名明细!$B:$B=$C6),1) -> 物流单证报关实习生（浦东机场/双休/早9晚5）岗位职责：1、关务单证的收取、录入、整理、登记等；2、进出口报关输单、制单；3、操作文档的整理归档等；4、完成上级布置的其他任务。岗位要求：1、大专及以上学历，2026年毕业生；2、国际贸易、报关、物流管理专业优先；3、良好的学习能力，沟通能力，性格开朗，主动性强；4、word、excel软件操作熟练；5、家住上海浦东机场或祝桥镇周边地区。实习周期：周一—周五，结业完毕后依据实习期考核，表现优异者，进行正式录用及建立劳动关系；团队介绍：年轻活力的团队，专业资深的导师，舒适明亮的办公室；实习福利：实习160元/天，外加20元/天餐补。地址：浦东新区闻居路1333号A座608室闵行区莲花南路2288号杨浦区大连路688号 | H6: 公司集国际货物贸易、报关、报检、货物运输代理等一体，主要承办货物的国际贸易代理、海运、空运进出口货物的国际运输及代理业务，是中国海关AEO高级认证企业，是诸多一线国际品牌合作伙伴。 | I6: 物流单证报关实习生（浦东机场/双休/早9晚5）岗位职责：1、关务单证的收取、录入、整理、登记等；2、进出口报关输单、制单；3、操作文档的整理归档等；4、完成上级布置的其他任务。岗位要求：1、大专及以上学历，2026年毕业生；2、国际贸易、报关、物流管理专业优先；3、良好的学习能力，沟通能力，性格开朗，主动性强；4、word、excel软件操作熟练；5、家住上海浦东机场或祝桥镇周边地区。实习周期：周一—周五，结业完毕后依据实习期考核，表现优异者，进行正式录用及建立劳动关系；团队介绍：年轻活力的团队，专业资深的导师，舒适明亮的办公室；实习福利：实习160元/天，外加20元/天餐补。地址：浦东新区闻居路1333号A座608室闵行区莲花南路2288号杨浦区大连路688号
A7: =_xlfn.XLOOKUP(C7,展区展位!A:A,展区展位!B:B) -> B互联网/电子/通信 | B7: =_xlfn.XLOOKUP(C7,展区展位!A:A,展区展位!C:C) -> B05 | C7: 上海新致致远智能技术有限公司 | D7: =_xlfn.XLOOKUP(C7,企业简介提取!B:B,企业简介提取!F:F) -> 新致软件成立于1994年，总部坐落于上海，在北京、深圳、大连、重庆、成都、贵安、武汉、东京等多地设立了分支机构。新致软件专注于向保险公司、银行等金融机构及电信、汽车、医疗等其他行业终端客户提供IT解决方案、IT运维服务，以及向一级软件承包商提供软件项目分包服务。 上海新致致远智能公司致力于云计算、人工智能产品与解决方案。 | E7: =INDEX(_xlfn._xlws.FILTER(报名明细!$I:$I,报名明细!$B:$B=$C7),1) -> 云计算与AI算力运维工程师（学历：大专 专业要求：云计算技术与应用,人工智能技术服务） | F7: =INDEX(_xlfn._xlws.FILTER(报名明细!$L:$L,报名明细!$B:$B=$C7),1) -> 1.云架构设计与实施：参与设计高可用、高并发、可扩展的云基础架构方案（主要为IOT相关系统），参与人工智能算力架构设计，并负责将其落地实施。2.云计算与人工智能算力资源管理：管理和维护公司在公有云（如AWS、华为云、阿里云等）上的计算、存储、网络和安全资源。3.运维与监控：建立和完善监控、告警和日志系统，确保云上应用的稳定运行，并能快速定位并给出长期解决方案；对于中间件设定参数的确认，是否合理或者根据相关指标能及时调整。4.成本优化：监控和分析云资源使用情况，提出并实施成本优化方案，控制云支出。5.安全与合规：实施云安全最佳实践，负责网络访问控制、安全组策略、数据加密等，确保基础设施符合安全与合规要求。 | H7: 新致软件成立于1994年，总部坐落于上海，在北京、深圳、大连、重庆、成都、贵安、武汉、东京等多地设立了分支机构。新致软件专注于向保险公司、银行等金融机构及电信、汽车、医疗等其他行业终端客户提供IT解决方案、IT运维服务，以及向一级软件承包商提供软件项目分包服务。上海新致致远智能公司致力于云计算、人工智能产品与解决方案。 | I7: 1.云架构设计与实施：参与设计高可用、高并发、可扩展的云基础架构方案（主要为IOT相关系统），参与人工智能算力架构设计，并负责将其落地实施。2.云计算与人工智能算力资源管理：管理和维护公司在公有云（如AWS、华为云、阿里云等）上的计算、存储、网络和安全资源。3.运维与监控：建立和完善监控、告警和日志系统，确保云上应用的稳定运行，并能快速定位并给出长期解决方案；对于中间件设定参数的确认，是否合理或者根据相关指标能及时调整。4.成本优化：监控和分析云资源使用情况，提出并实施成本优化方案，控制云支出。5.安全与合规：实施云安全最佳实践，负责网络访问控制、安全组策略、数据加密等，确保基础设施符合安全与合规要求。
A8: =_xlfn.XLOOKUP(C8,展区展位!A:A,展区展位!B:B) -> B互联网/电子/通信 | B8: =_xlfn.XLOOKUP(C8,展区展位!A:A,展区展位!C:C) -> B12 | C8: 上海率震档案信息技术有限公司 | D8: =_xlfn.XLOOKUP(C8,企业简介提取!B:B,企业简介提取!F:F) -> 上海率震档案信息技术有限公司是一家专业为律师、律所、政法机关等提供现代化档案信息服务的科技型公司。现主营业务为档案软件开发，档案5A数字化建设、档案大规模扫描服务、文档追溯管理、档案图像识别、图像优化、档案寄存等。 2024年3月1日，《中华人民共和国档案法实施条例》正式施行。相较于此前的《档案法实施办法》，本次施行的《中华人民共和国档案法实施条例》无论是条款数量还是具体内容都有…… | E8: =INDEX(_xlfn._xlws.FILTER(报名明细!$I:$I,报名明细!$B:$B=$C8),1) -> 档案信息采集员（学历：大专 专业要求：档案学,图书档案管理） | F8: =INDEX(_xlfn._xlws.FILTER(报名明细!$L:$L,报名明细!$B:$B=$C8),1) -> 岗位名称及职责：整理员：将单位档案资料整理清楚，页码连贯、目录对应。扫描员：将单位档案资料通过扫描仪进行扫描处理，形成电子格式文档。质检员：检查扫描图像是否合格，并加以更正修改。录入员：将单位档案的封面信息、当事人信息、目录信息通过录入软件输入系统内。装订员：将数字化处理完的档案进行三孔一线的装订。岗位要求：1、大专及以上学历，专业不限；2、扫描员、质检员、录入员必须懂得电脑基本操作，熟练掌握OFFICE等办公软件。年龄18~35周岁，男女不限。扫描员要求动作迅速麻利，质检员要求认真仔细，录入员要求打字速度较快，五笔拼音皆可。整理员、装订员无需使用电脑，要求认真仔细，吃苦耐劳。3、入职需签署保密协议、提供无犯罪记录证明。4、着装得体，遵守单位和公司纪律。 | H8: 上海率震档案信息技术有限公司是一家专业为律师、律所、政法机关等提供现代化档案信息服务的科技型公司。现主营业务为档案软件开发，档案5A数字化建设、档案大规模扫描服务、文档追溯管理、档案图像识别、图像优化、档案寄存等。2024年3月1日，《中华人民共和国档案法实施条例》正式施行。相较于此前的《档案法实施办法》，本次施行的《中华人民共和国档案法实施条例》无论是条款数量还是具体内容都有较大变化，内容更加符合当下时代发展，反映时代特点，能够与1991年司法部、国家档案局颁布的《律师业务档案立卷归档办法》和《律师业务档案管理办法》紧密结合，为律师业务档案管理工作提供明确的法律依据和路线指导。上海率震档案信息技术有限公司公司秉承专业、可靠、高效的宗旨，为将律师及律师事务所从律师业务档案的繁重工作中彻底解放出来。现提供律师业务档案的整理、装订、数字化及保管等全流程的服务。 | I8: 岗位名称及职责：整理员：将单位档案资料整理清楚，页码连贯、目录对应。扫描员：将单位档案资料通过扫描仪进行扫描处理，形成电子格式文档。质检员：检查扫描图像是否合格，并加以更正修改。录入员：将单位档案的封面信息、当事人信息、目录信息通过录入软件输入系统内。装订员：将数字化处理完的档案进行三孔一线的装订。岗位要求：1、大专及以上学历，专业不限；2、扫描员、质检员、录入员必须懂得电脑基本操作，熟练掌握OFFICE等办公软件。年龄18~35周岁，男女不限。扫描员要求动作迅速麻利，质检员要求认真仔细，录入员要求打字速度较快，五笔拼音皆可。整理员、装订员无需使用电脑，要求认真仔细，吃苦耐劳。3、入职需签署保密协议、提供无犯罪记录证明。4、着装得体，遵守单位和公司纪律。
A9: =_xlfn.XLOOKUP(C9,展区展位!A:A,展区展位!B:B) -> F综合 | B9: =_xlfn.XLOOKUP(C9,展区展位!A:A,展区展位!C:C) -> F01 | C9: 上海久事公共交通集团有限公司 | D9: =_xlfn.XLOOKUP(C9,企业简介提取!B:B,企业简介提取!F:F) -> 上海久事公共交通集团有限公司是沪上大型城市公共交通国有企业。久事公交下属企业分为公交企业板块、保障类企业板块，及综合类企业板块。其中公交运营板块，主要负责上海浦西中心城区的公交运营以及相关车辆维修保障等工作。该板块由五家公交营运公司组成（上海巴士第一公共交通有限公司、上海巴士第二公共交通有限公司、上海巴士第三公共交通有限公司、上海巴士第四公共交通有限公司、上海巴士第五公共交通有限公司）久事公交共有…… | E9: =INDEX(_xlfn._xlws.FILTER(报名明细!$I:$I,报名明细!$B:$B=$C9),1) -> 公交车定向培训驾驶员（学历：大专 专业要求：交通运输类） | F9: =INDEX(_xlfn._xlws.FILTER(报名明细!$L:$L,报名明细!$B:$B=$C9),1) -> 1、具有本市户籍的，大专或以上应届毕业生。2、无不良社会记录，如拘留、劳改、判刑、吸毒史等。3、身体健康，有良好的反应能力及沟通能力。4、经用人单位面试、政审、体检合格后，签订“三方”（企业、驾校、个人）培训协议书（自费26000元），参加企业驾驶员定向培训。作为城市的名片及服务的窗口，公交车驾驶员需以热情饱满的精神面貌，良好的服务素养，独立担任线路车辆的营运，根据相关规定的线路与班式，保障公众出行的安全与便利。安全驾驶，维护公交车辆的车貌与车况，为广大乘客提供优质的服务。 | H9: 上海久事公共交通集团有限公司是沪上大型城市公共交通国有企业。久事公交下属企业分为公交企业板块、保障类企业板块，及综合类企业板块。其中公交运营板块，主要负责上海浦西中心城区的公交运营以及相关车辆维修保障等工作。该板块由五家公交营运公司组成（上海巴士第一公共交通有限公司、上海巴士第二公共交通有限公司、上海巴士第三公共交通有限公司、上海巴士第四公共交通有限公司、上海巴士第五公共交通有限公司）久事公交共有员工2.5万人左右。 | I9: 1、具有本市户籍的，大专或以上应届毕业生。2、无不良社会记录，如拘留、劳改、判刑、吸毒史等。3、身体健康，有良好的反应能力及沟通能力。4、经用人单位面试、政审、体检合格后，签订“三方”（企业、驾校、个人）培训协议书（自费26000元），参加企业驾驶员定向培训。作为城市的名片及服务的窗口，公交车驾驶员需以热情饱满的精神面貌，良好的服务素养，独立担任线路车辆的营运，根据相关规定的线路与班式，保障公众出行的安全与便利。安全驾驶，维护公交车辆的车貌与车况，为广大乘客提供优质的服务。
A10: =_xlfn.XLOOKUP(C10,展区展位!A:A,展区展位!B:B) -> F综合 | B10: =_xlfn.XLOOKUP(C10,展区展位!A:A,展区展位!C:C) -> F07 | C10: 上海慧之颜美容有限公司 | D10: =_xlfn.XLOOKUP(C10,企业简介提取!B:B,企业简介提取!F:F) -> 在上海市中心坐拥5家分店，主营品牌苗方清颜，主打祛痘及问题肌肤管理。开业14年以来，累计会员3000名以上。因为拓店需求，现招聘10名有工作经验的高级美容师及美容学徒，欢迎有志之士的加入。 | E10: =INDEX(_xlfn._xlws.FILTER(报名明细!$I:$I,报名明细!$B:$B=$C10),1) -> 美容师（学历：大专 专业要求：无） | F10: =INDEX(_xlfn._xlws.FILTER(报名明细!$L:$L,报名明细!$B:$B=$C10),1) -> 工作职责：1、为顾客提供皮肤护理、美容服务；2、安装美容仪器要求、程序、性能进行美容护理操作；3、保持工作环境的干净整洁；4、学习产品知识和专业技术，不断提高自身职业素质和技能。任职要求：1、形象好、气质佳，在20-40岁之间；2、有一年以上美容、仪器操作经验。有针清祛痘经验的优先3、沟通理解能力强、技术手法好，有服务意识；4、具有亲和力和团队精神，有上进心5、销售能力强的优先考虑薪资福利：1、试用期有保底工资2、转正后工资底薪+提成+奖金，具体详谈，薪资优厚，阶段性考核通过底薪提高3、提供宿舍4、完整的晋升通道：美容师-资深美容师-美容顾问-储备店长-店长5、带薪年假，生日福利，各种额外福利6、试用期过了享受员工福利价购买公司产品，以及免费做脱毛清洁等基础护理项目 | H10: 在上海市中心坐拥5家分店，主营品牌苗方清颜，主打祛痘及问题肌肤管理。开业14年以来，累计会员3000名以上。因为拓店需求，现招聘10名有工作经验的高级美容师及美容学徒，欢迎有志之士的加入。 | I10: 工作职责：1、为顾客提供皮肤护理、美容服务；2、安装美容仪器要求、程序、性能进行美容护理操作；3、保持工作环境的干净整洁；4、学习产品知识和专业技术，不断提高自身职业素质和技能。任职要求：1、形象好、气质佳，在20-40岁之间；2、有一年以上美容、仪器操作经验。有针清祛痘经验的优先3、沟通理解能力强、技术手法好，有服务意识；4、具有亲和力和团队精神，有上进心5、销售能力强的优先考虑薪资福利：1、试用期有保底工资2、转正后工资底薪+提成+奖金，具体详谈，薪资优厚，阶段性考核通过底薪提高3、提供宿舍4、完整的晋升通道：美容师-资深美容师-美容顾问-储备店长-店长5、带薪年假，生日福利，各种额外福利6、试用期过了享受员工福利价购买公司产品，以及免费做脱毛清洁等基础护理项目
A11: =_xlfn.XLOOKUP(C11,展区展位!A:A,展区展位!B:B) -> E城市运营与技术服务 | B11: =_xlfn.XLOOKUP(C11,展区展位!A:A,展区展位!C:C) -> E19 | C11: 上海墨刻景观工程有限公司 | D11: =_xlfn.XLOOKUP(C11,企业简介提取!B:B,企业简介提取!F:F) -> 上海墨刻景观工程有限公司是集设计与施工为一体的全程化景观服务咨询公司，同时也是最具设计魅力和施工表现的中国本土景观设计公司之一。我们致力于探索中国当代景观设计，继承本土设计的精华，同时力求创造中西文化艺术交融，强调将独到的创意与地域特征结合在一起，为不同客户创造不同的景观场所。 项目地点遍及上海、北京、天津、南京、成都、西安、银川、无锡、南昌、合肥、马鞍山、蚌埠、芜湖、武汉、大同，以及美国旧金山等…… | E11: =INDEX(_xlfn._xlws.FILTER(报名明细!$I:$I,报名明细!$B:$B=$C11),1) -> 设计助理（学历：大专 专业要求：建筑室内设计） | F11: =INDEX(_xlfn._xlws.FILTER(报名明细!$L:$L,报名明细!$B:$B=$C11),1) -> 1、艺术设计类相关专业，具有深厚的美术功底，有较强的艺术修养；2、掌握CAD、Coreldraw、Photoshop、SketchUp等设计软件；3、具备独特的设计理念，思维开阔、善于创意，具备丰富的空间想象力及创新能力，熟知商业美陈设计、商业空间设计、展览、展示设计及工艺结构和运作流程，能独立完成各种设计方案和施工图的制作； | H11: 上海墨刻景观工程有限公司是集设计与施工为一体的全程化景观服务咨询公司，同时也是最具设计魅力和施工表现的中国本土景观设计公司之一。我们致力于探索中国当代景观设计，继承本土设计的精华，同时力求创造中西文化艺术交融，强调将独到的创意与地域特征结合在一起，为不同客户创造不同的景观场所。项目地点遍及上海、北京、天津、南京、成都、西安、银川、无锡、南昌、合肥、马鞍山、蚌埠、芜湖、武汉、大同，以及美国旧金山等。项目内容包括高档住宅社区、高档酒店及旅游度假区、都市公园、郊野公园与市政广场、旅游风景区及主题公园、开发区及高科技园区等。我们与许多地方政府以及发展商建立了良好的合作关系。在项目发展过程中，我们始终充分理解业主的需求与意图，并积极寻求业主的充分参与。项目地点遍及上海、北京、天津、南京、成都、西安、银川、无锡、南昌、合肥、马鞍山、蚌埠、芜湖、武汉、大同，以及美国旧金山等。项目内容包括高档住宅社区、高档酒店及旅游度假区、都市公园、郊野公园与市政广场、旅游风景区及主题公园、开发区及高科技园区等。我们与许多地方政府以及发展商建立了良好的合作关系。在项目发展过程中，我们始终充分理解业主的需求与意图…… | I11: 1、艺术设计类相关专业，具有深厚的美术功底，有较强的艺术修养；2、掌握CAD、Coreldraw、Photoshop、SketchUp等设计软件；3、具备独特的设计理念，思维开阔、善于创意，具备丰富的空间想象力及创新能力，熟知商业美陈设计、商业空间设计、展览、展示设计及工艺结构和运作流程，能独立完成各种设计方案和施工图的制作；
A12: =_xlfn.XLOOKUP(C12,展区展位!A:A,展区展位!B:B) -> B互联网/电子/通信 | B12: =_xlfn.XLOOKUP(C12,展区展位!A:A,展区展位!C:C) -> B03 | C12: 中移铁通有限公司上海闵行分公司 | D12: =_xlfn.XLOOKUP(C12,企业简介提取!B:B,企业简介提取!F:F) -> 中移铁通为中国移动下属专业子公司，公司定位为“属地装维营销专业化支撑者”和“数智工程服务市场化拓展者”，重点聚焦家庭宽带安装维护、政企客户项目交付、DICT系统集成和工程项目建设维护等业务。 | E12: =INDEX(_xlfn._xlws.FILTER(报名明细!$I:$I,报名明细!$B:$B=$C12),1) -> 爱家工程师（学历：大专 专业要求：无） | F12: =INDEX(_xlfn._xlws.FILTER(报名明细!$L:$L,报名明细!$B:$B=$C12),1) -> 宽带、互联网电视、智能家居产品的安装调试，用户故障处理，移动业务随销等。 | H12: 中移铁通为中国移动下属专业子公司，公司定位为“属地装维营销专业化支撑者”和“数智工程服务市场化拓展者”，重点聚焦家庭宽带安装维护、政企客户项目交付、DICT系统集成和工程项目建设维护等业务。 | I12: 宽带、互联网电视、智能家居产品的安装调试，用户故障处理，移动业务随销等。
A13: =_xlfn.XLOOKUP(C13,展区展位!A:A,展区展位!B:B) -> C汽车/服装/贸易 | B13: =_xlfn.XLOOKUP(C13,展区展位!A:A,展区展位!C:C) -> C03 | C13: 上海世界联合服装有限公司 | D13: =_xlfn.XLOOKUP(C13,企业简介提取!B:B,企业简介提取!F:F) -> 上海世界联合服装有限公司 隶属ICCF之禾卡纷集团。 ICCF之禾卡纷集团是着重于可持续发展的全业务连高端时尚集团，致力于为世界提供基于优质原料的环境友好时装。 集团旗下目前的主要业务板块，包含中国品牌ICICLE之禾，法国品牌CARVEN卡纷，时装制造中心以及物流中心，从原料采购、产品开发、制造、销售和消费者体验的全业务连视角，寻求品牌发展与环境、社会的和谐共生。 我们的团队年轻有活力，乐…… | E13: =INDEX(_xlfn._xlws.FILTER(报名明细!$I:$I,报名明细!$B:$B=$C13),1) -> 生产培训生（毛衫方向）（学历：大专 专业要求：服装设计与工程,针织技术与针织服装,服装与服饰设计,服装设计与工艺,服装设计与工艺教育） | F13: =INDEX(_xlfn._xlws.FILTER(报名明细!$L:$L,报名明细!$B:$B=$C13),1) -> 招聘岗位：生产培训生（毛衫方向）培养方向：生产管理招聘人数：4人工作地点：上海市闵行区绿春路189号薪资：6000-8000元/月任职要求：1.专科及以上学历，服装相关专业（针织专业优先考虑）；2.应届毕业生或毕业三年以内；3.善于沟通表达；4.逻辑思维能力强，有进取心，职业发展规划清晰；5.热爱服装行业，愿意扎根工厂，热爱制造福利：包吃包住、带薪年假、节日福利、定期体检、六险一金（包含补充商业医疗保险）、交通补贴、团建活动。联系人：人事行政部 | H13: 上海世界联合服装有限公司隶属ICCF之禾卡纷集团。ICCF之禾卡纷集团是着重于可持续发展的全业务连高端时尚集团，致力于为世界提供基于优质原料的环境友好时装。集团旗下目前的主要业务板块，包含中国品牌ICICLE之禾，法国品牌CARVEN卡纷，时装制造中心以及物流中心，从原料采购、产品开发、制造、销售和消费者体验的全业务连视角，寻求品牌发展与环境、社会的和谐共生。我们的团队年轻有活力，乐意带教新人。我们诚挚的欢迎阳光，积极，进取的你。我们秉承集团追求天然，舒适，环保的理念，为员工提供良好的工作环境和氛围。 | I13: 招聘岗位：生产培训生（毛衫方向）培养方向：生产管理招聘人数：4人工作地点：上海市闵行区绿春路189号薪资：6000-8000元/月任职要求：1.专科及以上学历，服装相关专业（针织专业优先考虑）；2.应届毕业生或毕业三年以内；3.善于沟通表达；4.逻辑思维能力强，有进取心，职业发展规划清晰；5.热爱服装行业，愿意扎根工厂，热爱制造福利：包吃包住、带薪年假、节日福利、定期体检、六险一金（包含补充商业医疗保险）、交通补贴、团建活动。联系人：人事行政部
... A47: =_xlfn.XLOOKUP(C47,展区展位!A:A,展区展位!B:B) -> E城市运营与技术服务 | B47: =_xlfn.XLOOKUP(C47,展区展位!A:A,展区展位!C:C) -> E10 | C47: 上海格瑞特科技实业股份有限公司 | D47: =_xlfn.XLOOKUP(C47,企业简介提取!B:B,企业简介提取!F:F) -> 上海格瑞特科技实业股份有限公司，立于1994年； 中国楼控唯一新三板挂牌公司（证券代码：872532） 格瑞特是建筑智能化行业建筑设备安全运行解决方案的老牌设备制造商、服务商、解决方案提供商、设备能源服务运营商；中国楼控唯一新三板挂牌公司（证券代码872532）；系上海高新技术企业，软件企业，拥有50余项专利和软件著作权；系中国TC-100标准化委员会委员单位；多个行业协会副理事长和理事单位； …… | E47: =INDEX(_xlfn._xlws.FILTER(报名明细!$I:$I,报名明细!$B:$B=$C47),1) -> 助理调试工程师（学历：大专 专业要求：无） | F47: =INDEX(_xlfn._xlws.FILTER(报名明细!$L:$L,报名明细!$B:$B=$C47),1) -> 助理调试工程师1、岗位工作内容：（1）、学习楼宇自控、能源管理、智能照明等绿色建筑系统施工设计、现场指导、调试知识（2）、掌握楼宇自控系统软硬件操作、调试和现场问题解决能力2、岗位任职要求：（1）、大专及以上学历，自动化、信息工程、电子工程等工科专业（2）、有学习能力，已能够熟练CAD制图者优先。 | H47: 上海格瑞特科技实业股份有限公司，立于1994年；中国楼控唯一新三板挂牌公司（证券代码：872532）格瑞特是建筑智能化行业建筑设备安全运行解决方案的老牌设备制造商、服务商、解决方案提供商、设备能源服务运营商；中国楼控唯一新三板挂牌公司（证券代码872532）；系上海高新技术企业，软件企业，拥有50余项专利和软件著作权；系中国TC-100标准化委员会委员单位；多个行业协会副理事长和理事单位；建筑设备管理系统连续8年被多个专业机构评为中国十强品牌（含进口品牌）解决方案和产品遍布中国（大陆）所有省份；近2000用户数十万的终端运行中主要产品和解决方案：楼宇自控、能耗计量、空调计费、IBMS、智能照明、巡检系统等公司以用户和技术为导向，为用户提供易用的全生态全生命周期解决方案和产品；服务于新建筑和城市更新，及装配式建筑的精细化运营。 | I47: 助理调试工程师1、岗位工作内容：（1）、学习楼宇自控、能源管理、智能照明等绿色建筑系统施工设计、现场指导、调试知识（2）、掌握楼宇自控系统软硬件操作、调试和现场问题解决能力2、岗位任职要求：（1）、大专及以上学历，自动化、信息工程、电子工程等工科专业（2）、有学习能力，已能够熟练CAD制图者优先。

Sheet 岗位2
A1: 展区 | B1: 展位 | C1: 单位名称 | D1: 单位简介 | E1: 职位1标题 | F1: 职位1jd | G1: 职位2标题 | H1: 职位2jd
A2: =_xlfn.XLOOKUP(C2,展区展位!A:A,展区展位!B:B) -> C汽车/服装/贸易 | B2: =_xlfn.XLOOKUP(C2,展区展位!A:A,展区展位!C:C) -> C20 | C2: 上海德辰汽车销售有限公司 | D2: =_xlfn.XLOOKUP(C2,企业简介提取!B:B,企业简介提取!F:F) -> 上海德辰汽车销售公司是北方一大型汽车经销商集团在上海新投资创立的 一汽大众奥迪品牌 4S 店。超越了传统豪华汽车 4S 店的概念，实际具备品牌体 验、车型展示、新车销售、售后服务、二手车置换等多种功能，完备的设施以 及周到的服务一应俱全，体现出国际豪华品牌全球统一的服务水准。 该城市展厅坐落于闵行区颛桥地区（颛兴东路 1280 弄 3 号）。地铁、轻轨 均可到达，交通便捷。地址：颛兴东路 …… | E2: =INDEX(_xlfn._xlws.FILTER(报名明细!$I:$I,报名明细!$B:$B=$C2),1) -> 机电实习生（学历：中专/技校 专业要求：汽车检测与维修技术,新能源汽车技术,汽车运用与维修技术,汽车车身维修技术,新能源汽车运用与维修,汽车制造类,汽车服务工程,汽车维修工程教育,新能源汽车工程） | F2: =INDEX(_xlfn._xlws.FILTER(报名明细!$L:$L,报名明细!$B:$B=$C2),1) -> 具有一定的汽车理论知识和汽车维修知识，具有较强的动手能力、语言表达能力、独立解决问题的能力、汽车工艺学习及钻研能力 | G2: =INDEX(_xlfn._xlws.FILTER(报名明细!$I:$I,报名明细!$B:$B=$C2),2) -> 机电实习生（学历：中专/技校 专业要求：汽车运用与维修技术,汽车检测与维修技术,汽车服务工程） | H2: =INDEX(_xlfn._xlws.FILTER(报名明细!$L:$L,报名明细!$B:$B=$C2),2) -> 具有一定的汽车理论知识和汽车维修知识，具有较强的动手能力、语言表达能力、独立解决问题的能力、汽车工艺学习及钻研能力
A3: =_xlfn.XLOOKUP(C3,展区展位!A:A,展区展位!B:B) -> D教育/传媒/电竞 | B3: =_xlfn.XLOOKUP(C3,展区展位!A:A,展区展位!C:C) -> D16 | C3: 上海网鱼酒店管理有限公司 | D3: =_xlfn.XLOOKUP(C3,企业简介提取!B:B,企业简介提取!F:F) -> 网鱼创始于1998年，从诞生之初就秉承不断创新的理念，致力于打造多人游戏空间。截至2020年12月31日，网鱼全球会员数超2000万，服务覆盖国内外106个城市。全球拥有超1000家门店，年服务人次超3000万，iG战队倾情代言，是深受全球玩家喜爱的聚玩圣地。2021年推出“网鱼电竞酒店”，正式进军电竞酒店行业，打造跨品类、跨业态、跨平台的综合娱乐型品牌，践行“给用户美好的体验”。 | E3: =INDEX(_xlfn._xlws.FILTER(报名明细!$I:$I,报名明细!$B:$B=$C3),1) -> 门店管培生（学历：大专 专业要求：无） | F3: =INDEX(_xlfn._xlws.FILTER(报名明细!$L:$L,报名明细!$B:$B=$C3),1) -> 公司简介：网鱼创始于1998年，起源于上海松江，2015年获得上海市著名商标荣誉称号。作为国内电竞连锁的代表，从诞生之初就秉承不断创新的理念，致力于全球第一电竞社区的打造，为全球电竞玩家提供优质的电竞休闲娱乐服务。截至2021年12月31日，网鱼全球会员数超2000万，服务覆盖国内外82个城市，在美国、英国、加拿大、澳大利亚、新加坡等多个国家开设门店，全球拥有900多家门店，年服务人次超4000万。2021年，网鱼品牌创新升级为“网鱼电竞”，打造游戏玩家的电竞基地；探索多业态，推出“网鱼电竞酒店”，正式进军电竞酒店行业，打造跨品类、跨业态、跨平台的综合娱乐型品牌，践行“给用户美好的体验”。截至2023年12月，网鱼电竞酒店覆盖全国26个主要城市，在营门店数量超过200家。岗位介绍门店管培生（储备店长）：50名工作地点：全国（全国1700家门店，可根据意向城市分配工作城市）。工作职责:1、经营管理：从基层店员历练开始，协助酒店店长进行门店的运营管理，管理门店资产设备、现金、账务，薪资录入，奖金核算；2、学习管理：跟随导师学习门店人员的岗位落实及日常管理；3、品质管理：保证门店卫生品质，逐…… | G3: =INDEX(_xlfn._xlws.FILTER(报名明细!$I:$I,报名明细!$B:$B=$C3),2) -> 客户经理（学历：大专 专业要求：无） | H3: =INDEX(_xlfn._xlws.FILTER(报名明细!$L:$L,报名明细!$B:$B=$C3),2) -> 职责：1、导座服务：①严格执行门店导座SOP标准，提升顾客满意度；②主动观察顾客消费习惯，提供个性化服务；③工作时间需着JK制服，并保持整洁得体的妆容及精神面貌；2、抖音直播：①每日在门店非上客高峰期，使用门店抖音账号，完成2小时直播；②负责直播间的秩序维护和用户互动，积极解答用户问题；③发掘直播间内意向用户，吸引用户到店，提升门店新会员数量；④每日24点前，完成一条抖音视频发布。3、会员运营：①完成企业微信社群搭建、成员邀请及日常维护；②每日回访新客，定期收集top100顾客反馈建议；③每日邀请老顾客到店上网，并为顾客线上订座；4、线上平台维护：①每周按照店长要求，完成高德/百度/腾讯地图/美团平台的优质好评数。②100%邀请团购用户消费后评价。要求：1、性别：女2、年龄：18-24周岁3、学历：大专及以上学历4、形象：身高160CM以上，形象气质佳5、性格特质：活泼开朗，有服务意识，擅沟通喜交流6、经验能力：会端游、有直播或者游戏教练经验者优先薪资待遇1、薪资：月薪5000+；2、福利：每月免费上网时长60小时，免费饮品10杯，简餐半价券42张，其他福利均同门店其他员工；3、销售提……
A4: =_xlfn.XLOOKUP(C4,展区展位!A:A,展区展位!B:B) -> E城市运营与技术服务 | B4: =_xlfn.XLOOKUP(C4,展区展位!A:A,展区展位!C:C) -> E16 | C4: 上海万厦建筑装饰加固工程有限公司 | D4: =_xlfn.XLOOKUP(C4,企业简介提取!B:B,企业简介提取!F:F) -> 上海万厦建筑装饰加固工程有限公司是一家装饰加固的专业公司，影院建设的集成单位。公司专业配套、工种齐全。具有工艺设计、建声设计、装修设计、结构设计、机电设计以及工程管理与各施工项目经理部。在长期的工程实践中已取得了丰富的经验，形成了设计施工一体化的操作模式，取得了丰硕的业绩。 公司自上世纪九十年代至今已先后设计和施工了影剧院、演剧场、文化馆等几百项文化设施项目及公共商业设施项目，取得了良好的社会信誉…… | E4: =INDEX(_xlfn._xlws.FILTER(报名明细!$I:$I,报名明细!$B:$B=$C4),1) -> 软件开发设计师（学历：大专 专业要求：无） | F4: =INDEX(_xlfn._xlws.FILTER(报名明细!$L:$L,报名明细!$B:$B=$C4),1) -> 技术基础：掌握前端基础技术，包括HTML/CSS/JavaScript，了解ES6及以上语法；熟悉或初步了解小程序开发技术栈（WXML/WXSS），有使用微信开发者工具的基础经验；了解Vue、React等前端框架，或Python、Java等任一后端语言者优先。3.工具与能力：能使用微信开发者工具完成简单代码编写、调试与预览；具备基础的逻辑思维和问题排查能力，能理解简单业务需求并配合完成代码辅助工作；会使用Git等版本控制工具（如GitHub、GitLab）者加分。 | G4: =INDEX(_xlfn._xlws.FILTER(报名明细!$I:$I,报名明细!$B:$B=$C4),2) -> 装饰设计（学历：大专 专业要求：无） | H4: =INDEX(_xlfn._xlws.FILTER(报名明细!$L:$L,报名明细!$B:$B=$C4),2) -> 软件技能：熟练使用CAD（绘制平面图、施工图）、SketchUp（基础建模），掌握3DMax/Blender（建模）、Photoshop（效果图后期）者优先。具备基础的空间布局、色彩搭配审美；了解常见装饰材料（如板材、涂料）、施工工艺基础知识者。
A5: =_xlfn.XLOOKUP(C5,展区展位!A:A,展区展位!B:B) -> F综合 | B5: =_xlfn.XLOOKUP(C5,展区展位!A:A,展区展位!C:C) -> F09 | C5: 予童家庭服务（上海）有限公司 | D5: =_xlfn.XLOOKUP(C5,企业简介提取!B:B,企业简介提取!F:F) -> 予童家庭服务（BabyNanny），以“重塑美好育儿生态”为使命，专注为高净值家庭提供育婴照护、婴儿早教、孩童陪伴等服务。 作为高标准母婴护理及高质量家庭服务的坚定笃行者，予童为同样追求育儿品质的家庭，定制集育婴护理、入户指导和社群体验“三维一体”的婴童成长呵护方案，让育儿回归优雅和从容。以“百里挑一”的严苛标准遴选育婴师，打造迎合高端家庭需求的培塑实训，冀期予童的每一名育婴师，都能成为宝宝的温情…… | E5: =INDEX(_xlfn._xlws.FILTER(报名明细!$I:$I,报名明细!$B:$B=$C5),1) -> 家庭育婴师（学历：大专 专业要求：护理,学前教育,助产） | F5: =INDEX(_xlfn._xlws.FILTER(报名明细!$L:$L,报名明细!$B:$B=$C5),1) -> 一、工作地点上海全市二、岗位职责-全面负责新生儿的生活照料，涵盖喂养、洗澡、抚触、更换尿布等环节，保障宝宝的清洁与舒适。-密切留意宝宝的生长发育状况，诸如身高、体重、睡眠、大小便等方面，一旦察觉异常立即向家长或医生反馈。-依据宝宝的年龄及发展阶段，精心制定科学合理的喂养计划与作息时间表，悉心培养宝宝良好的生活习惯。-开展早期教育与启蒙工作，借助游戏、互动等多种方式，推动宝宝的认知、语言、运动以及社交能力的发展。-承担宝宝衣物、用品的清洗与消毒工作，确保宝宝生活环境的整洁与卫生。-与家长保持高效且良好的沟通，深入了解家长的需求与关注重点，给予专业的育婴建议和指导。-协助家长妥善处理宝宝的其他相关事务，像就医、接种疫苗等。三、任职要求需要会做饭。持有专业的育婴师资格证书，例如育婴员职业资格证书等优先。具有早教中心、托育园、幼儿园实习经验者优先。对婴幼儿事业充满热爱，拥有爱心、耐心和责任心，具备良好的职业道德和素养。具备出色的沟通能力和团队协作精神，能够与家长及其他工作人员构建起良好的关系。身体健康，拥有良好的心理素质和抗压能力。具有一定的学习和创新能力，能够持续更新育婴知识和技能。 | G5: =INDEX(_xlfn._xlws.FILTER(报名明细!$I:$I,报名明细!$B:$B=$C5),2) -> 家庭育婴师（学历：初中及以下 专业要求：学前教育,学前教育学,护理学,护理,护理学类,护理类,卫生教育,儿科学,妇幼保健医学,预防医学） | H5: =INDEX(_xlfn._xlws.FILTER(报名明细!$L:$L,报名明细!$B:$B=$C5),2) -> 可选择白班或住家1.全面负责新生儿的生活照料，涵盖喂养、洗澡、抚触、更换尿布等环节，保障宝宝的清洁与舒适。2.密切留意宝宝的生长发育状况，诸如身高、体重、睡眠、大小便等方面，一旦察觉异常立即向家长或医生反馈。3.依据宝宝的年龄及发展阶段，精心制定科学合理的喂养计划与作息时间表，悉心培养宝宝良好的生活习惯。4.开展早期教育与启蒙工作，借助游戏、互动等多种方式，推动宝宝的认知、语言、运动以及社交能力的发展。5.承担宝宝衣物、用品的清洗与消毒工作，确保宝宝生活环境的整洁与卫生。6.与家长保持高效且良好的沟通，深入了解家长的需求与关注重点，给予专业的育婴建议和指导。7.协助家长妥善处理宝宝的其他相关事务，像就医、接种疫苗等。任职要求对婴幼儿事业充满热爱，拥有爱心、耐心和责任心，具备良好的职业道德和素养。具备出色的沟通能力和团队协作精神，能够与家长及其他工作人员构建起良好的关系。身体健康，无传染性疾病，拥有良好的心理素质和抗压能力。具有一定的学习和创新能力，能够持续更新育婴知识和技能。有相关从业经验、实习经验者优先；护理专业、学前教育专业、婴幼儿托育专业优先；有乐器、舞蹈、声乐、英语、绘画等特长……
A6: =_xlfn.XLOOKUP(C6,展区展位!A:A,展区展位!B:B) -> B互联网/电子/通信 | B6: =_xlfn.XLOOKUP(C6,展区展位!A:A,展区展位!C:C) -> B02 | C6: 中国电信股份有限公司上海莘闵电信局 | D6: =_xlfn.XLOOKUP(C6,企业简介提取!B:B,企业简介提取!F:F) -> 中国电信股份有限公司上海莘闵电信局坐落于闵行区莘东路199号，简称莘闵电信局。前身为上海市电话局莘闵区局。2000年7月1日，中国电信集团上海市电信公司成立后，更名为上海市电信公司莘闵电信局； 2008年3月，更名为中国电信股份有限公司上海莘闵电信局。 中国电信股份有限公司上海莘闵电信局提供固定电话、移动通信、宽带互联网接入、互联网电视、卫星通信、信息化应用等泛在网络和综合智能信息服务能力，服务闵…… | E6: =INDEX(_xlfn._xlws.FILTER(报名明细!$I:$I,报名明细!$B:$B=$C6),1) -> 门店经理见习生（学历：大专 专业要求：无） | F6: =INDEX(_xlfn._xlws.FILTER(报名明细!$L:$L,报名明细!$B:$B=$C6),1) -> 电信门店的整体运营与业绩达成，核心涵盖经营指标、团队管理、客户服务、营销与渠道协同、合规与风险控制等关键模块。 | G6: =INDEX(_xlfn._xlws.FILTER(报名明细!$I:$I,报名明细!$B:$B=$C6),2) -> 装维见习生（学历：大专 专业要求：无） | H6: =INDEX(_xlfn._xlws.FILTER(报名明细!$L:$L,报名明细!$B:$B=$C6),2) -> 电信宽带、固定电话、IPTV等电信业务的安装与故障维修，同时承担客户沟通与网络简单维护任务。
A7: =_xlfn.XLOOKUP(C7,展区展位!A:A,展区展位!B:B) -> C汽车/服装/贸易 | B7: =_xlfn.XLOOKUP(C7,展区展位!A:A,展区展位!C:C) -> C22 | C7: 上海羊鑫布艺有限公司 | D7: =_xlfn.XLOOKUP(C7,企业简介提取!B:B,企业简介提取!F:F) -> 上海羊鑫布艺有限公司是海派旗袍与新中式文化创新的时尚企业作为上海海派旗袍文化促进会副会长单位,公司以"致知青花"系列为代表,融合传统制衣工艺与现代设计,打造独具东方韵味的高级定制服饰。产品屡获长三角旗袍设计大赛银奖等殊荣,创始人杨玉娟女士获“东方时尚工匠”称号。公司通过时尚闪秀、文化展览等多元化形式,致力于传承和发展海派旗袍文化,推动传统服饰艺术的现代表达与创新发展。 | E7: =INDEX(_xlfn._xlws.FILTER(报名明细!$I:$I,报名明细!$B:$B=$C7),1) -> 打样纸板师（学历：大专 专业要求：无） | F7: =INDEX(_xlfn._xlws.FILTER(报名明细!$L:$L,报名明细!$B:$B=$C7),1) -> 【岗位职责】负责服装款式的打板与制版工作：根据设计师提供的效果图、设计稿或样衣，精准制作纸样（含裁剪版、工艺版），确保版型符合设计风格与人体工学。样衣跟进与调整：配合样衣车间完成首件样衣制作，参与样衣试穿评审，根据试穿反馈（如尺寸偏差、版型舒适度）优化纸样，直至样衣合格。工艺文件输出：整理打板数据，制定详细的制版工艺说明（如缝份、缩率、面料特性适配方案），为生产车间提供清晰的技术指导。版型库管理：建立并维护公司版型数据库，分类归档不同款式、尺码的纸样文件，便于后续款式复用与优化。跨部门协作：与设计师、采购部（确认面料特性）、生产部（解决生产中的版型问题）高效配合，确保打板-制版-生产流程顺畅。【任职要求】学历与经验：中专及以上学历，服装相关专业（如服装工程、服装设计），1-3年及以上服装打板/制版经验（应届生可投递助理岗，需熟悉基础打板逻辑）。核心技能：熟练掌握手工打板技巧，能独立完成从净版到毛版的制作；精通制版软件（如富怡、ET、格柏Gerber等），可高效进行数字化制版与纸样修改；了解不同面料特性（如棉、丝、针织、弹力面料）对版型的影响，能针对性调整打板方案；熟悉服装号型标准（如G…… | G7: =INDEX(_xlfn._xlws.FILTER(报名明细!$I:$I,报名明细!$B:$B=$C7),2) -> 销售（学历：大专 专业要求：无） | H7: =INDEX(_xlfn._xlws.FILTER(报名明细!$L:$L,报名明细!$B:$B=$C7),2) -> 岗位职责：·顾客服务与销售：·热情接待每一位顾客，提供专业、耐心的咨询和穿搭建议。·洞察顾客需求，达成销售目标，并积极维护客户关系。·处理顾客的疑问和售后问题，提升顾客购物满意度。·店铺日常运营：·负责商品收货、盘点、陈列、补货和库存管理。·保持店铺环境整洁、美观，营造舒适的购物氛围。·熟练操作收银系统，完成每日销售结算工作。·团队协作：·与团队成员紧密合作，共同完成店铺销售目标和各项任务。·积极参与公司培训和团队会议，分享销售技巧和时尚资讯。·品牌形象维护：·以身作则，展现品牌的时尚形象和专业素养。·及时反馈市场信息和顾客意见，助力品牌成长。任职要求：·必备条件：·热爱时尚行业，对服装搭配有浓厚的兴趣和独特的见解。·性格开朗，具有良好的沟通表达能力和服务意识。·积极主动，有责任心，具备良好的团队合作精神。·能适应零售业周末、节假日的工作安排。·优先考虑：·有服装零售或相关销售工作经验者优先。·具备一定的抗压能力和目标导向思维。
A8: =_xlfn.XLOOKUP(C8,展区展位!A:A,展区展位!B:B) -> E城市运营与技术服务 | B8: =_xlfn.XLOOKUP(C8,展区展位!A:A,展区展位!C:C) -> E15 | C8: 上海科瑞物业管理发展有限公司 | D8: =_xlfn.XLOOKUP(C8,企业简介提取!B:B,企业简介提取!F:F) -> “和我们共创无限可能的未来” 上海科瑞物业管理发展有限公司，成立于2002年1月18日，注册资金5000万元。公司致力于成为“成为现代物业服务专业管家”品牌企业，服务于超高层建筑、城市综合体、办公楼、大型住宅、公众项目；以及提供大中小学校区管理、酒店管理和物业顾问等服务。科瑞物业崇尚现代物业管理理念，坚持以人为本、生态平衡的管理服务本质，追求高标准管理、细节化服务、规范化收费、可持续发展，以“一切…… | E8: =INDEX(_xlfn._xlws.FILTER(报名明细!$I:$I,报名明细!$B:$B=$C8),1) -> 智能建筑工程实习生（学历：大专 专业要求：建筑智能化工程技术） | F8: =INDEX(_xlfn._xlws.FILTER(报名明细!$L:$L,报名明细!$B:$B=$C8),1) -> 通过参与智能建筑工程全流程（设计辅助、现场实施、调试配合、文档整理等）工作，帮助实习生掌握智能建筑系统（如楼宇自控、安防监控、综合布线等）的基本原理与实际应用，熟悉工程现场管理流程，培养工程实践能力与问题解决意识，为未来从事智能建筑相关工作奠定基础。 | G8: =INDEX(_xlfn._xlws.FILTER(报名明细!$I:$I,报名明细!$B:$B=$C8),2) -> 管理培训生（学历：大专 专业要求：无） | H8: =INDEX(_xlfn._xlws.FILTER(报名明细!$L:$L,报名明细!$B:$B=$C8),2) -> 1、总部职能岗位管理培训生：服务管控中心、品质管控中心、企业发展中心、财务管理部、综合管理部和人力资源部管理培训生；2、运营岗位管理培训生：上海各项目基础管理岗位管理培训生即项目运营条线秩序维护、工程管理、客户服务、环境管理和综合管理岗位管理培训生。岗位需求：根据公司发展不断扩大，为了更好提升管理团队的综合素养，也为了更好的对职能和项目管理人员进行补充，特拟定自2022年10月起启动招聘“新瑞”计划，即招收20名应届毕业生，具体要求如下：1、有志于从事物业管理行业；2、男女不限、形象良好，较强的沟通和表达能力；思维活跃，有较强的创新意识；有责任心，适应能力和抗压性强，3、有一定的文书编写能力，熟练操作各类电脑软件如PPT、PHOTOSHOP等；4、专业不限、户籍不限，除工程类“新瑞”需要对口机电类、工程技术类专业外；5、本科以上，985，211院校可优先考虑，条件特别优秀者可放宽至应届大专毕业生。如经面试录取后实习期为2023年2月起至2023年6月30日，经实习期评估合格可签订正式劳动合同，签订正式劳动岗位职级不低于主管级。工作内容：通过在总部、区域、项目的轮岗学习，对职能人力行政、……
A9: =_xlfn.XLOOKUP(C9,展区展位!A:A,展区展位!B:B) -> B互联网/电子/通信 | B9: =_xlfn.XLOOKUP(C9,展区展位!A:A,展区展位!C:C) -> B16 | C9: 图萌（上海）科技有限公司 | D9: =_xlfn.XLOOKUP(C9,企业简介提取!B:B,企业简介提取!F:F) -> 图萌（上海）科技有限公司倡导“科技融合，创新共赢”的理念，专注于新媒体+XR领域的数字技术和内容研发，在人工智能时代背景下，致力于AIGC内容生成式人才的培养，涵盖虚拟现实、数字媒体技术、动漫设计、广播电视编导、节目制作、新闻采编与制作、新媒体艺术、艺术设计、广告学、计算机等领域。 作为长三角文旅产业联盟会员单位、教育部职教工场项目白名单企业，图萌科技拥有计算机软件著作权登记证书、上海电…… | E9: =INDEX(_xlfn._xlws.FILTER(报名明细!$I:$I,报名明细!$B:$B=$C9),1) -> 平面设计（学历：大专 专业要求：视觉传达设计） | F9: =INDEX(_xlfn._xlws.FILTER(报名明细!$L:$L,报名明细!$B:$B=$C9),1) -> 岗位职责1、负责公司宣传材料、册页等的设计与整合。2、精通PS、AI等设计软件。3、参与设计讨论，和业务团队共同创建用户界面，跟踪设计效果，提出设计优化方案。4、良好的团队精神，工作踏实稳定。岗位要求1、全日制大专或以上学历，艺术设计类相关专业毕业。2、有实习经验者优先，能独立完成设计方案。3、会使用CAD做平面布局图者优先。4、会渲染三维效果图者优先。 | G9: =INDEX(_xlfn._xlws.FILTER(报名明细!$I:$I,报名明细!$B:$B=$C9),2) -> AI虚拟数字人拍摄制作专员（学历：大专 专业要求：无） | H9: =INDEX(_xlfn._xlws.FILTER(报名明细!$L:$L,报名明细!$B:$B=$C9),2) -> 岗位职责:1、负责AI虚拟数字人的形象设计、动态捕捉及视频拍摄全流程制作，包括前期策划、场景搭建、灯光调试等。2、使用动作捕捉设备(如光学/惯性动捕系统)、面部表情捕捉技术等，完成数字人的高精度动作与表情数据采集。3、配合A|算法团队，优化数字人的语音、表情、肢体动作的同步性与自然度提升拟真效果。4、负责虚拟拍摄现场的设备调试(如摄像机追踪、虚拟引擎实时渲染等)，确保拍摄效率与质量。5、跟踪行业技术趋势，探索A数字人在直播、短视频、影视等领域的创新应用场景。岗位要求:1、熟悉虚拟制作流程，有动作捕捉(如Vicon、OptiTrack)、面部捕捉(如Faceware、iPhoneARKit)或影视拍摄经验。2、掌握至少一款3D制作工具(如Blender、Maya、UnrealEngine、Unity)能完成基础模型调整与场景搭建。3、了解A|数字人相关技术(如语音合成、TTS、NLP)，有AI工具(如D-D、Synthesia)使用经验者优先。4、具备良好的镜头语言和审美能力，能独立完成脚本分镜设计及后期剪辑(熟悉Premiere、DaVinci等)。
A10: =_xlfn.XLOOKUP(C10,展区展位!A:A,展区展位!B:B) -> A机械/制造/能源 | B10: =_xlfn.XLOOKUP(C10,展区展位!A:A,展区展位!C:C) -> A26 | C10: 上海味捷智朗科技发展有限公司 | D10: =_xlfn.XLOOKUP(C10,企业简介提取!B:B,企业简介提取!F:F) -> 上海味捷智朗科技发展有限公司是熙香科技集团重要子公司之一。集团始创于2014年，是国内领先的人工智能科技企业，国内首家落地的生活服务机器人系统解决方案的服务商，公司致力于借助人工智能、物联网、大数据等技术，激发出更具交互性、智能化和安全的生活服务新业态，通过将物AI+技术应用于生活服务领域，建立智能服务一体化、作业机械无人化、需求定制自动化的“两化一体”模式，实现数据驱动的的精细化运营。公司相关智…… | E10: =INDEX(_xlfn._xlws.FILTER(报名明细!$I:$I,报名明细!$B:$B=$C10),1) -> 机械电工（学历：大专 专业要求：机械工程,机械设计制造及其自动化,机械制造及其自动化,机械电子工程） | F10: =INDEX(_xlfn._xlws.FILTER(报名明细!$L:$L,报名明细!$B:$B=$C10),1) -> 本岗位要求:1、3年以上非标自动化设备电气装配，有低压电工证，2、能看懂图纸3、会布线排线，会对点4、熟悉电气控制柜排布、电气元器件功能;5、熟练掌握电工的基本操作技能和工具6、能接受加班，能接受短期、临时出差 | G10: =INDEX(_xlfn._xlws.FILTER(报名明细!$I:$I,报名明细!$B:$B=$C10),2) -> 高级java开发工程师（学历：大专 专业要求：计算机科学与技术,电子与计算机工程,计算机网络技术,计算机应用技术,计算机应用工程） | H10: =INDEX(_xlfn._xlws.FILTER(报名明细!$L:$L,报名明细!$B:$B=$C10),2) -> 岗位职责1.参与公司产品或项目的需求分析、设计与开发，根据业务需求完成高质量代码编写，实现系统功能模块；2.负责后端系统的架构设计、搭建与优化，确保系统的稳定性、性能和可扩展性，保障系统高效稳定运行；3.与前端开发团队紧密协作，定义数据接口规范，完成前后端数据交互开发，确保项目整体功能的完整性和流畅性；4.进行数据库设计、优化和维护，熟练编写SQL语句，处理复杂的数据操作和事务管理，保障数据的准确性和安全性；5.编写详细准确的技术文档，包括设计文档、接口文档、使用说明等，为团队协作和系统维护提供支持6.独立解决和处理所负责的项目的运维和监控，及时处理生产环境中的故障和问题，保障系统的可用性和稳定性；7.持续关注行业技术发展趋势，引入新技术、新工具，优化现有技术方案和开发流程，提升团队技术水平和开发效率。任职要求1.专科及以上学历，计算机科学与技术、软件工程、机械、自动化等相关专业优先。2.具有5年以上Java开发经验，有完整的项目开发经验，能够独立承担模块开发任务3.扎实的Java基础知识，熟悉常用设计模式，对多线程、并发编程、JVM原理及调优有深入理解。4.熟练掌握Spring、Sp……
A11: =_xlfn.XLOOKUP(C11,展区展位!A:A,展区展位!B:B) -> F综合 | B11: =_xlfn.XLOOKUP(C11,展区展位!A:A,展区展位!C:C) -> F03 | C11: 上海市闵行区医疗急救中心 | D11: =_xlfn.XLOOKUP(C11,企业简介提取!B:B,企业简介提取!F:F) -> 上海市闵行区医疗急救中心隶属于上海市闵行区卫生健康委员会，是区内唯一从事院前急救专业的公立医疗卫生事业单位。承担了闵行区内272万人口的院前急救、危急重病症初步诊治与抢救护理。职责还包括急救临床教学、急救医学科研、急救卫生技术人员培训和区域重特大事故现场紧急救援以及大型赛事活动现场医疗保障等工作。 | E11: =INDEX(_xlfn._xlws.FILTER(报名明细!$I:$I,报名明细!$B:$B=$C11),1) -> 院前急救辅助人员（学历：大专 专业要求：无） | F11: =INDEX(_xlfn._xlws.FILTER(报名明细!$L:$L,报名明细!$B:$B=$C11),1) -> 1.协助急救医生做好现场医疗急救工作；2.承担病人的抬抱转运工作；3.协助急救驾驶员做好安全行车、车辆卫生及其他辅助性工作。 | G11: =INDEX(_xlfn._xlws.FILTER(报名明细!$I:$I,报名明细!$B:$B=$C11),2) -> 急救医师（学历：本科 专业要求：临床医学） | H11: =INDEX(_xlfn._xlws.FILTER(报名明细!$L:$L,报名明细!$B:$B=$C11),2) -> 院前急救、危急重病症初步诊治与抢救护理
A12: =_xlfn.XLOOKUP(C12,展区展位!A:A,展区展位!B:B) -> B互联网/电子/通信 | B12: =_xlfn.XLOOKUP(C12,展区展位!A:A,展区展位!C:C) -> B10 | C12: 上海博赫尔科技集团有限公司 | D12: =_xlfn.XLOOKUP(C12,企业简介提取!B:B,企业简介提取!F:F) -> 博赫尔（POHIR）科技集团是一家全球智能化清洁清洗解决方案提供商和服 务商，POHIR博赫尔品牌起源于上个世纪90年代的德国，经过近20多年的发展 和不断创新，POHIR博赫尔在全球已覆盖了北美，欧洲，东南亚等全球50多个 国家或地区，并为全球30万+客户提供清洁清洗设备解决方案。 在欧洲，博赫尔（POHIR）分别在德国、法国等地设有2个仓储运营服务中 心和1个产品设计研发中心。在北美，博赫尔（…… | E12: =INDEX(_xlfn._xlws.FILTER(报名明细!$I:$I,报名明细!$B:$B=$C12),1) -> 电商客服（学历：大专 专业要求：电子商务类） | F12: =INDEX(_xlfn._xlws.FILTER(报名明细!$L:$L,报名明细!$B:$B=$C12),1) -> 岗位职责：1、通过聊天工具完成平台的售前客户咨询接待；2、负责跟进订单、异常件管理；3、服从安排，负责其它售后问题及突发事件。4、打字速度50字/分钟以上；岗位要求：1、经验不限；2、做6休1，国定假期正常放假。公司提供完善的培训、轮岗、转岗及晋升机会！ | G12: =INDEX(_xlfn._xlws.FILTER(报名明细!$I:$I,报名明细!$B:$B=$C12),2) -> 跨境电商运营助理（学历：本科 专业要求：跨境电子商务） | H12: =INDEX(_xlfn._xlws.FILTER(报名明细!$L:$L,报名明细!$B:$B=$C12),2) -> 岗位职责:1.参与跨境电商平台（亚马逊、eBay、独立站等）的运营活动，包括但不限于产品发布、活动策划与执行；2.进行市场数据分析，了解行业趋势，调整运营策略以满足市场需求；3.与团队协作，开发新的销售渠道，提升产品曝光率和销量；4.管理和优化产品列表，确保产品信息的准确性和吸引力；5.监控运营指标，及时调整运营计划以达到销售目标。任职要求：1.对跨境电商行业感兴趣，具备基本的市场分析能力；2.具备创新思维，能够不断提出和实施新的运营思路。3、大学本科在读学生，英语好.
A13: =_xlfn.XLOOKUP(C13,展区展位!A:A,展区展位!B:B) -> F综合 | B13: =_xlfn.XLOOKUP(C13,展区展位!A:A,展区展位!C:C) -> F02 | C13: 上海上勤高级楼宇管理有限公司 | D13: =_xlfn.XLOOKUP(C13,企业简介提取!B:B,企业简介提取!F:F) -> 上海上勤高级楼宇管理有限公司，隶属于上海市机关事务管理局委托管理的国有独资企业，一直从事市人大和市政府等机关后勤服务保障工作。 公司秉持“一流服务、领先水平”的服务理念，坚持“做优服务、做强保障、做实管理”的工作目标，坚持专业化、标准化、个性化、精细化的品质，形成了独特的服务理念以及管理模式。目前，公司在管项目服务总量占市级机关物业服务市场62%，并在服务过程中形成品牌…… | E13: =INDEX(_xlfn._xlws.FILTER(报名明细!$I:$I,报名明细!$B:$B=$C13),1) -> 工程助理（物业维修电工）（学历：中专/技校 专业要求：无） | F13: =INDEX(_xlfn._xlws.FILTER(报名明细!$L:$L,报名明细!$B:$B=$C13),1) -> 机关项目，做五休二（晚间有轮流安排夜值班）岗位要求：1、年龄50岁以下，经验丰富者可适当放宽。2、至少须持有低压电工证、职业资格证书（维修电工初级/五级），能独立动手操作。3、须有高度的工作责任心、良好的沟通能力、有较强的团队意识。4、有酒店、办公楼等物业工作经验优先。 | G13: =INDEX(_xlfn._xlws.FILTER(报名明细!$I:$I,报名明细!$B:$B=$C13),2) -> 会务助理（学历：中专/技校 专业要求：无） | H13: =INDEX(_xlfn._xlws.FILTER(报名明细!$L:$L,报名明细!$B:$B=$C13),2) -> 工作地址：浦东新区张江丹桂路999弄张江国创中心1期岗位职责1、负责前台接待，访客登记、快递收发等；2、负责会务保障，包括会前准备、会中续水、会后收尾工作等；3、其他相关事务性协助工作。任职资格1、中专以上学历；2、熟练使用Office办公软件及办公自动化设备，普通话标准，能听懂上海话；3、具有良好的沟通、协调、表达能力，性格沉稳、待人礼貌周到，服务意识强；4、女性，年龄：18-35，身高：165以上，身材匀称，面容较好。
... A25: =_xlfn.XLOOKUP(C25,展区展位!A:A,展区展位!B:B) -> A机械/制造/能源 | B25: =_xlfn.XLOOKUP(C25,展区展位!A:A,展区展位!C:C) -> A06 | C25: 上海空间电源研究所 | D25: =_xlfn.XLOOKUP(C25,企业简介提取!B:B,企业简介提取!F:F) -> 中国航天科技集团有限公司上海空间电源研究所，地处上海市闵行区东川园区，主要承担“星、箭、弹、船、（探测）器”及其它特殊设备用电源系统、控制设备、电源产品的研究、设计、制造和试验任务以及新能源产业孵化工作，是中国航天科技集团有限公司唯一的电源专业所。 现拥有国内唯一的空间电源全国重点实验室，建有电子电源、化学电源、物理电源等电源领域研发中心，获科技部批复建有空间电源技术国际科技合作基地。 2020年…… | E25: =INDEX(_xlfn._xlws.FILTER(报名明细!$I:$I,报名明细!$B:$B=$C25),1) -> 化学电源工程师（学历：本科 专业要求：化学,材料科学与工程） | F25: =INDEX(_xlfn._xlws.FILTER(报名明细!$L:$L,报名明细!$B:$B=$C25),1) -> 1、要求，电化学、应用化学、材料科学与工程等专业优先考虑；2、熟悉锂电池电化学原理、锂电池性能测试；3、熟悉锂离子电池国内外技术现状；4、具备基本的英语读、写、听、说能力；5、做事认真、态度诚恳、团队协作能力强；6、热爱航天事业、责任感强、能吃苦耐劳； | G25: =INDEX(_xlfn._xlws.FILTER(报名明细!$I:$I,报名明细!$B:$B=$C25),2) -> 设备工程师（学历：本科 专业要求：机械制造及其自动化,电气类） | H25: =INDEX(_xlfn._xlws.FILTER(报名明细!$L:$L,报名明细!$B:$B=$C25),2) -> 1、本科学历，机电一体化、电气工程等相关专业；2、3年以上锂电池生产制造自动化设备维护工作经验；3、熟悉工程机械、电气构造原理，有一定工程机械故障处理经验、机械设计和机械维护经验，熟知设备保养、维修流程及规范和标准；4、能够指导工程机械设备进行维修维护及故障排除；5、熟练使用CAD和其他现代化办公设备和软件（如Word,Excel等）；6、对工作有很强的责任心，做事积极主动、认真踏实，注重工作质量和效率；7、团队合作精神，良好的沟通能力。

Sheet 岗位3
A1: 展区 | B1: 展位 | C1: 单位名称 | D1: 单位简介 | E1: 职位1标题 | F1: 职位1jd | G1: 职位2标题 | H1: 职位2jd | I1: 职位3标题 | J1: 职位3jd
A2: =_xlfn.XLOOKUP(C2,展区展位!A:A,展区展位!B:B) -> B互联网/电子/通信 | B2: =_xlfn.XLOOKUP(C2,展区展位!A:A,展区展位!C:C) -> B01 | C2: 上海光通信有限公司 | D2: =_xlfn.XLOOKUP(C2,企业简介提取!B:B,企业简介提取!F:F) -> 上海光通信有限公司（英文名 Shanghai GTX Semiconductor Co., Ltd，下称“GTX”），成立于1988年，于2022年初转型进入集成电路制造领域。 | E2: =INDEX(_xlfn._xlws.FILTER(报名明细!$I:$I,报名明细!$B:$B=$C2),1) -> 仓储助理专员（学历：大专 专业要求：无） | F2: =INDEX(_xlfn._xlws.FILTER(报名明细!$L:$L,报名明细!$B:$B=$C2),1) -> 工作职责1)根据规程，执行公司各种物资运输安排、管理及监控；2)执行物资仓储管理，保证物资有序账目清晰。任职要求1)大专及以上学历，物流、仓储等相关专业；2)具备良好的沟通能力和团队合作精神，具备独立工作、分析和解决问题的能力，良好的中英文读写说能力。 | G2: =INDEX(_xlfn._xlws.FILTER(报名明细!$I:$I,报名明细!$B:$B=$C2),2) -> 良率提升助理技术员（学历：大专 专业要求：无） | H2: =INDEX(_xlfn._xlws.FILTER(报名明细!$L:$L,报名明细!$B:$B=$C2),2) -> 岗位描述：1）负责支持在线缺陷监控，处理产线检测的产品、设备，保证产品正常生产，设备正常运行。2）负责监控并处理检测及复检机台的异常运行状况，保证机台正常运行。3）协同工程师进行缺陷改善，建立合格的检测程式和复检程式，发现并通知产生缺陷的制程，减少缺陷的影响范围。4）负责简单的缺陷切片制样，跟进切片结果。任职要求：1）大专及以上学历，专业不限。2）具备良好的沟通能力，具备团队意识。3）倒班工作模式，接受无尘室工作环境。 | I2: =INDEX(_xlfn._xlws.FILTER(报名明细!$I:$I,报名明细!$B:$B=$C2),3) -> 实验室技术员（学历：大专 专业要求：无） | J2: =INDEX(_xlfn._xlws.FILTER(报名明细!$L:$L,报名明细!$B:$B=$C2),3) -> 岗位描述：1）按照规程和作业指导书，执行失效分析实验室/可靠性实验室/化学实验室内相关仪器的操作并按照求完成具体失效分析工作。2）按照规程和作业指导书，执行失效分析实验室/可靠性实验室/化学实验室的日常点检，协助处理机台的日常维护工作。任职要求：1）大专以上学历，理工科相关专业。2）接受倒班工作模式，接受无尘室工作环境。3）具备良好的沟通能力和团队合作精神，具备独立工作、分析和解决问题的能力，良好的中英文读写说能力。
A3: =_xlfn.XLOOKUP(C3,展区展位!A:A,展区展位!B:B) -> B互联网/电子/通信 | B3: =_xlfn.XLOOKUP(C3,展区展位!A:A,展区展位!C:C) -> B20 | C3: 上海新皋实业有限公司 | D3: =_xlfn.XLOOKUP(C3,企业简介提取!B:B,企业简介提取!F:F) -> 新皋实业成立于2013年初，总部位于上海虹桥机场毗邻的明谷科技园，公司在智能家居领域率先投入智能家居控制系统的项目研发、生产及销售。获得软件专利著作权十多项，企业获得国家商标局认证商标： 《新皋》《XINGAO》《艾登堡》《ATNBO》等品牌，并推出真正适合国内外用户的智能影音系列产品。自主研发新皋XINGAO智能影院中控系统及艾登堡ATNBO家庭影院系列产品,深受行业专业人士好评。…… | E3: =INDEX(_xlfn._xlws.FILTER(报名明细!$I:$I,报名明细!$B:$B=$C3),1) -> 设计，UI设计，效果图设计（学历：大专 专业要求：无） | F3: =INDEX(_xlfn._xlws.FILTER(报名明细!$L:$L,报名明细!$B:$B=$C3),1) -> 工作内容：企业设计类工作，主要内容协助领导UI设计工作。招聘条件：有相关工作经验者优先；1、熟悉办公软件操作，具备良好的文字表达能力；2、熟练UI设计软件。公司从事智能家居及智能私人影院技术研发及硬件生产，招聘在校大学生实习实践，对智能家居，私人影院设备产品感兴趣者，实习生学员公司各岗位培养。实习期间成绩优秀者，毕业学年转正为企业员工，签定劳动合同，享受企业员工一切待遇。上海新皋实业有限公司是上海闵行区人社局及财政局审核认定的大学生实习实训基地。 | G3: =INDEX(_xlfn._xlws.FILTER(报名明细!$I:$I,报名明细!$B:$B=$C3),2) -> 物联网技术助理（学历：初中及以下 专业要求：微电子技术,微电子学与固体电子学,微电子科学与工程） | H3: =INDEX(_xlfn._xlws.FILTER(报名明细!$L:$L,报名明细!$B:$B=$C3),2) -> 我司是上海市人社局批准大学生实习基地，闵行区户籍实习生可以享受政府津贴，名额有限。公司从事智能家居及智能私人影院技术研发及硬件设备调试，招聘智能家居行业相关专业的在校大学生实习实践，要求物联网技术或电子及机电专业学生，具备弱电接线动手能力，对智能家居，私人影院设备安装调试感兴趣者，实习生学员公司提供技术培训。实习期间成绩优秀者，毕业学年转正为企业员工，签定劳动合同，享受企业员工一切待遇。优秀学员企业另外增加岗位津贴。面试证件：身份证；学信网个人资料；公司地址：上海市闵行区中春路7001号（明谷科技园）B栋415。公交路线：地铁9号线中春路站（2号口）出来沿着中春路骑行（10分钟）到达明谷科技园东大门，公司在东门左边进口处。 | I3: =INDEX(_xlfn._xlws.FILTER(报名明细!$I:$I,报名明细!$B:$B=$C3),3) -> 新媒体运营（学历：初中及以下 专业要求：无） | J3: =INDEX(_xlfn._xlws.FILTER(报名明细!$L:$L,报名明细!$B:$B=$C3),3) -> 工作内容负责公司多媒体渠道（包括但不限于微信公众号、抖音、微博等）的运营管理和内容策划。通过策划和执行，提升公司多媒体渠道的曝光度和用户粘性。主要职责：1、负责公司多媒体渠道的运营管理和内容策划，包括但不限于制定并执行渠道内容计划、跟踪和优化渠道运营效果、策划并执行创意等；2、撰写、编辑、发布公司公众号多媒体内容，提升内容质量和创意，以满足用户需求和公司需求；3、根据公司业务需求，制定并执行多媒体渠道的定期更新和升级策略，提升公司多媒体品牌形象和用户黏性；4、定期汇报公司多媒体渠道运营效果，提供数据驱动的改进建议，以优化公司多媒体运营策略；5、与其他部门的沟通和协作，包括但不限于与视频拍摄团队、设计师等合作，提升公司多媒体内容质量和用户体验。招聘条件多媒体运营专业，大专及以上学历，具备较强的项目管理能力和团队协作能力；1、熟悉新媒体渠道，具有一定的内容策划和创意能力，善于分析数据驱动问题；2、具有较强的沟通协调能力，能够与不同部门进行有效沟通和协作；3、具有较强的逻辑思维能力，能够独立思考和解决问题；4、熟练掌握公司多媒体运营流程和方法，了解公司业务需求。具有视频拍摄剪辑编辑能力。熟练……
A4: =_xlfn.XLOOKUP(C4,展区展位!A:A,展区展位!B:B) -> B互联网/电子/通信 | B4: =_xlfn.XLOOKUP(C4,展区展位!A:A,展区展位!C:C) -> B09 | C4: 珍岛信息技术（上海）股份有限公司 | D4: =_xlfn.XLOOKUP(C4,企业简介提取!B:B,企业简介提取!F:F) -> 珍岛信息技术（上海）股份有限公司（简称珍岛集团，股票代码02556.HK）是中国最大的营销及销售SaaS公司，也是最早推出 T-force 营销领域大模型的公司，最早推出 AI-Agentforce 中台的公司，聚焦数字化与智能化，基于人工智能、大数据技术，是专注数字化智能营销的SaaS服务提供商，于2024年在香港上市。 | E4: =INDEX(_xlfn._xlws.FILTER(报名明细!$I:$I,报名明细!$B:$B=$C4),1) -> 校企合作经理（学历：大专 专业要求：无） | F4: =INDEX(_xlfn._xlws.FILTER(报名明细!$L:$L,报名明细!$B:$B=$C4),1) -> 岗位职责：1、负责面向全国本科、高职、中职、技师院校进行数字营销实训软件的销售工作；2、制定区域销售计划并保障计划有效完成，进行系统化成本风控；3、完成区域业务团队组建、培养和绩效管理；4、建立院校业务多元化合作伙伴架构和体系。任职要求：1、不限专业，金融、网络营销、电子商务为佳；2、做事严谨细致，有耐心，有责任心，具有优秀的表达能力与团队协作能力3、具备良好的学习力、承压能力及高度责任心。4、能接受出差 | G4: =INDEX(_xlfn._xlws.FILTER(报名明细!$I:$I,报名明细!$B:$B=$C4),2) -> 大学生营销储备干部 （学历：本科 专业要求：无） | H4: =INDEX(_xlfn._xlws.FILTER(报名明细!$L:$L,报名明细!$B:$B=$C4),2) -> 【公司简介】珍岛集团成立于2009年，聚焦企业数字化智能化，打造了全球领先的智能营销云平台Marketingforce.com，也是国内最大的营销及销售SaaS解决方案提供商。基于大数据、人工智能、云计算技术，现已形成IaaS（云计算）、PaaS(开放中台)、All-in-oneAISaaS等一站式智能营销云平台。总部位于上海市静安区大数据产业基地，第二总部位于武汉光谷，云计算机房设立于无锡基地，30+分支机构覆盖江苏、浙江、广东等省份。珍岛集团现有员工约4000人，累计申请软件著作权400余项，相关专利40余项。【营销储备干部】★岗位职责1.通过电话、陌生拜访、新媒体等渠道寻找潜在客户，邀约并拜访客户；2.与客户面谈，现场提供专业的产品演示和解决方案，完成销售；3.对老客户进行定期维护，及时了解客户需求售卖的是珍岛的明星产品“T-云”★岗位要求1.专业、性别不限；2.有无经验皆可（90%的伙伴都没有互联网行业经验，我们有完善的培训给你信心）；3.喜欢销售，能抗压抗挫，表达沟通能力强，有理想有抱负。★薪资待遇一线城市：上海保障薪资8000元，广州、深圳保障薪资7500元（含9%-29%…… | I4: =INDEX(_xlfn._xlws.FILTER(报名明细!$I:$I,报名明细!$B:$B=$C4),3) -> HD智能营销顾问（学历：本科 专业要求：经济与金融,国际经济与贸易,英语,计算机科学与技术,大数据管理与应用,工程造价,信息管理与信息系统,市场营销教育,行政管理,电子商务） | J4: =INDEX(_xlfn._xlws.FILTER(报名明细!$L:$L,报名明细!$B:$B=$C4),3) -> 工作内容：1、通过电话、陌生拜访、新媒体等渠道寻找潜在客户，邀约并拜访客户；2、与客户面谈，现场提供专业的产品演示和解决方案，完成销售（当你还不能独立面谈的时候，经理会手把手带着你并演示给你看如何和客户面谈）；3、对老客户进行定期维护，及时了解客户需求，把握客户心理，实现销售机会到销售产能的最大转化。岗位要求：4、全日制本科及以上学历，专业不限；5、对互联网行业有浓厚兴趣且考虑在营销领域发展；6、有较强的学习能力、沟通能力和适应能力；喜欢做与人打交道的工作薪资：上海：实习保障薪资8000元/月+提成9%-29%深圳、广州：实习保障薪资7500元/月+提成9%-29%杭州、苏州、宁波、南京：实习保障工资6000元/月+提成9%-29%无锡、武汉：实习保障保障工资5500元/月+提成9%-29%东莞、佛山、温州、台州、绍兴、金华、义务、成都、南通、常州：实习保障保障工资5000元/月+提成9%-29%惠州、中山、顺德、扬州：实习保障保障工资4500元/月+提成9%-29%1、以上工资为实习工资(即未拿到毕业证)；2、如已经拿到毕业证，保障薪资会在此薪资基础上高500~1000元/月。上海、……
A5: =_xlfn.XLOOKUP(C5,展区展位!A:A,展区展位!B:B) -> C汽车/服装/贸易 | B5: =_xlfn.XLOOKUP(C5,展区展位!A:A,展区展位!C:C) -> C16 | C5: 宁波革力物流有限公司上海分公司 | D5: =_xlfn.XLOOKUP(C5,企业简介提取!B:B,企业简介提取!F:F) -> 革力物流有限公司总部设在上海,并在深圳,广州,佛山,中山,以及宁波设有分公司, 在华北地区也有较好的代理网络。公司网址为：www.gclchina.net 公司的代理网络覆盖100多个国家,优势航线为欧洲,地中海,中东印巴,以及澳洲新西兰和东南亚国家 除基本海运空运以外， 公司还致力于发展进出口代理、清关、仓储、供应链管理等多元化主体化的国际物流服务。 主要合作船公司有:MAERSK、APL、EV…… | E5: =INDEX(_xlfn._xlws.FILTER(报名明细!$I:$I,报名明细!$B:$B=$C5),1) -> 会计助理（实习生）（学历：大专 专业要求：无） | F5: =INDEX(_xlfn._xlws.FILTER(报名明细!$L:$L,报名明细!$B:$B=$C5),1) -> 开票基础凭证录入及时完成领导交办的其他事项岗位要求：会计或财务相关专业工作认真、仔细、负责欢迎应届毕业生 | G5: =INDEX(_xlfn._xlws.FILTER(报名明细!$I:$I,报名明细!$B:$B=$C5),2) -> 单证员（学历：大专 专业要求：无） | H5: =INDEX(_xlfn._xlws.FILTER(报名明细!$L:$L,报名明细!$B:$B=$C5),2) -> 负责托书准确的录入负责MBL&HOUSEBILL的核对、更改、申领及签发；熟悉各个船公司、各航线的制单要求；负责费用的录入及确认工作；负责VGM的审核确认及系统导入工作；做好单证及文件的整理和归档任职要求：具有中专以上学历，同行业三个月以上工作经验；能熟练使用电脑，中英文打字速度快，能熟练运用OFFICE操作软件。较强的学习能力，肯吃苦耐劳，对本职工作有着强烈的责任心，耐心、细致、谨慎地对待日常单证工作；有良好的语言表达能力，善于沟通、交流，具有团队合作的精神； | I5: =INDEX(_xlfn._xlws.FILTER(报名明细!$I:$I,报名明细!$B:$B=$C5),3) -> 货代商务/市场专员（实习生）（学历：大专 专业要求：无） | J5: =INDEX(_xlfn._xlws.FILTER(报名明细!$L:$L,报名明细!$B:$B=$C5),3) -> 岗位职责：1、根据不同渠道维护已有船公司、庄家等供应商；2、根据不同渠道开发新的船公司、庄家等供应商；3、承接海外销售部及本地销售同事的询价；4、收集市场信息，负责航线价格体系的维护和完善，定期更新市场价格体系；5、及时在公司内部做市场信息公布，如航线运价走势，各船公司对于运价及载货方面的新规定；6、及时解决仓位，操作异常等突发事件；7、及时完成上级交办的其他工作。薪资待遇：1、合理优厚的薪金：基本工资+绩效奖金+补贴+年终奖等,2、完善的假期组合：带薪年假、带薪病假及法定假期；3、齐全的福利体系：养老保险、医疗保险+补充医疗保险、生育保险、工伤保险、失业保险及住房公积金；4、丰富多彩的员工活动：员工聚餐、节日晚会、旅游活动、优秀员工表彰活动等；5、多元化培训课程：带薪岗前培训，在职个人提升计划；6、良好晋升机会：内部转职（横向发展）、纵向提升；
A6: =_xlfn.XLOOKUP(C6,展区展位!A:A,展区展位!B:B) -> E城市运营与技术服务 | B6: =_xlfn.XLOOKUP(C6,展区展位!A:A,展区展位!C:C) -> E06 | C6: 上海地矿物业管理有限公司 | D6: =_xlfn.XLOOKUP(C6,企业简介提取!B:B,企业简介提取!F:F) -> 上海地矿物业管理有限公司隶属于上市市规划和自然资源局。上海地矿物业管理有限公司城市规划展示馆项目。上海城市规划展示馆市国内售价以展示城市规划与发展为主题专业性场馆。 | E6: =INDEX(_xlfn._xlws.FILTER(报名明细!$I:$I,报名明细!$B:$B=$C6),1) -> 展区管理员（学历：大专 专业要求：无） | F6: =INDEX(_xlfn._xlws.FILTER(报名明细!$L:$L,报名明细!$B:$B=$C6),1) -> 要求：（1）五官端正、形象气质号，女性165cm，男性175cm以上，年龄30岁以下。（2）语言表达能力强、善于沟通。普通话水平二级乙等以上或具备同等水平。（3）有较强的组织协调能力，团队协作能力，反应敏捷、能妥善处理游客的突发状况，且具备熟练的电脑操作知识。（4）具有一定的英语口语能力，能与外宾简单交流。薪资待遇：5000-6000元/月其他福利：早中餐、高温费、年终奖、大礼包等实习生3000元+500元全勤奖，国企，提供完善的培训，实习表现优秀者毕业后优先录用。录用后缴纳四金，提供年终奖、高温费、大礼包，详情面谈。 | G6: =INDEX(_xlfn._xlws.FILTER(报名明细!$I:$I,报名明细!$B:$B=$C6),2) -> 空调维修实习工程师（学历：大专 专业要求：制冷与空调技术） | H6: =INDEX(_xlfn._xlws.FILTER(报名明细!$L:$L,报名明细!$B:$B=$C6),2) -> 职位描述人员要求：(1)年龄在50周岁以下，具备高中以上学历。(2)专业资格要求：具有制冷设备维修工（中级）及以上证书。(3)经验要求：连续从事本职业满二年。岗位职责：(1)负责市政府新闻发布会会场温度适宜，确保与会人员的舒适度；(2)保障各级会务场地、大型参观接待活动的温度适宜；(3)负责开、闭馆时空调设备开启、关闭工作；(4)空调制冷热主机的巡视、调节、记录；(5)展区空调点位现场巡视、测温、记录；(6)办公区域的现场巡视、测温、调节、记录；(7)急报修工作的安排、修理。(8)完成上级领导及馆主管部门交办的其他工作任务。职位福利：五险一金、高温补贴、加班补助、绩效奖金、餐补、带薪年假、定期体检、周末双休 | I6: =INDEX(_xlfn._xlws.FILTER(报名明细!$I:$I,报名明细!$B:$B=$C6),3) -> 空调维修工程师（学历：大专 专业要求：制冷与空调技术） | J6: =INDEX(_xlfn._xlws.FILTER(报名明细!$L:$L,报名明细!$B:$B=$C6),3) -> 职位描述人员要求：(1)年龄在50周岁以下，具备高中以上学历。(2)专业资格要求：具有制冷设备维修工（中级）及以上证书。(3)经验要求：连续从事本职业满二年。岗位职责：(1)负责市政府新闻发布会会场温度适宜，确保与会人员的舒适度；(2)保障各级会务场地、大型参观接待活动的温度适宜；(3)负责开、闭馆时空调设备开启、关闭工作；(4)空调制冷热主机的巡视、调节、记录；(5)展区空调点位现场巡视、测温、记录；(6)办公区域的现场巡视、测温、调节、记录；(7)急报修工作的安排、修理。(8)完成上级领导及馆主管部门交办的其他工作任务。职位福利：五险一金、高温补贴、加班补助、绩效奖金、餐补、带薪年假、定期体检、周末双休该岗位招募实习生，实习期间月薪3000+500全勤奖+500饭贴。
A7: =_xlfn.XLOOKUP(C7,展区展位!A:A,展区展位!B:B) -> D教育/传媒/电竞 | B7: =_xlfn.XLOOKUP(C7,展区展位!A:A,展区展位!C:C) -> D17 | C7: 上海点晴信息科技有限公司 | D7: =_xlfn.XLOOKUP(C7,企业简介提取!B:B,企业简介提取!F:F) -> 上海点晴信息科技有限公司(ALCHEMYInformationtech-nology Co.,Ltd) 成立于2013年，是一家集独立游戏开发、高品质游戏美术制作服务及游戏美术赛事运营为一体的移动互联网公司。获高新技术企业，专精特新企业、科技小巨人企业、徐汇区企业技术中心、上海市设计创新中心等荣誉。 作为腾讯，网易，育碧，米哈游，拳头，电魂，英雄互娱等知名研发公司的核心供…… | E7: =INDEX(_xlfn._xlws.FILTER(报名明细!$I:$I,报名明细!$B:$B=$C7),1) -> 3D模型师/3D建模师（学历：大专 专业要求：无） | F7: =INDEX(_xlfn._xlws.FILTER(报名明细!$L:$L,报名明细!$B:$B=$C7),1) -> 负责制作游戏内相关道具场景的建模，熟练使用3Dmax，ps，maya，zb等软件，熟悉次世代制作流程者优先。 | G7: =INDEX(_xlfn._xlws.FILTER(报名明细!$I:$I,报名明细!$B:$B=$C7),2) -> PM（学历：本科 专业要求：应用韩语,日语,英语,商务英语） | H7: =INDEX(_xlfn._xlws.FILTER(报名明细!$L:$L,报名明细!$B:$B=$C7),2) -> 负责游戏美术项目管理工作，工作内容包括：1、负责与客户沟通与客户关系维护；2、制作资料整理，保障信息准确及时传达；3、及时发现并解决项目问题，有效预防及管理风险；5、制定有关计划，报告，时间表；6、协助领导做好项目统计工作；7、跟踪任务，及时解决问题保证产品顺利完成。任职要求：1、性格开朗，外向2、朝鲜族/日韩欧美留学经历为加分项；3、较强的沟通能力，并能够较好的协调各方面的关系；4、熟练运用办公软件；5、全日制本科及以上学历；6、接受热爱游戏，但没有相关工作经验的同学，会有专人带教的工作时间：9:30-18:00周末双休 | I7: =INDEX(_xlfn._xlws.FILTER(报名明细!$I:$I,报名明细!$B:$B=$C7),3) -> 游戏2D原画设计师（学历：大专 专业要求：无） | J7: =INDEX(_xlfn._xlws.FILTER(报名明细!$L:$L,报名明细!$B:$B=$C7),3) -> 1、有扎实的美术基础，能把控画面整体氛围,造型能力强、色感优越，有较强的风格适应能力和学习能力（对二次元文化有深入研究者优先考虑）；2、熟悉主流游戏美术风格，且有较强的原创、创意能力。3、有一定的软件基础，能进行数字绘画（数位板使用），如：Photoshop,C4D,3Dmax以及各类数字绘画及辅助软件。4、热爱绘画，对商业插画有一定程度的涉猎，参与过实习/有游戏插画绘画经验者优先考虑；5、热爱游戏行业，对游戏制作有热情，有良好的沟通能力和团队合作意识，有较强的责任感，有较强的抗压能力和学习能力。6、艺术设计、工业设计、视觉传达、动画、游戏国画、版画、游戏美术等相关专业优先。
A8: =_xlfn.XLOOKUP(C8,展区展位!A:A,展区展位!B:B) -> A机械/制造/能源 | B8: =_xlfn.XLOOKUP(C8,展区展位!A:A,展区展位!C:C) -> A23 | C8: 上海汇珏科技集团股份有限公司 | D8: =_xlfn.XLOOKUP(C8,企业简介提取!B:B,企业简介提取!F:F) -> 汇珏集团成立于2002年，是一家集能源系统集成解决方案与智能网络通信设备服务型制造的高新技术企业，公司致力于成为通信及能源行业的领跑者。总部位于上海自贸区临港新片区，注册资金10778万元，目前在全国拥有6家全资子公司。在上海奉贤、江苏海安建立了3大生产基地，总占地面积超20万余平方米，拥有员工超数千人，销售和服务网点遍布全国各个城市，产品远销欧洲、北美、东南亚等多个国家和地区。汇珏网络先后获得了…… | E8: =INDEX(_xlfn._xlws.FILTER(报名明细!$I:$I,报名明细!$B:$B=$C8),1) -> 外贸业务助理（学历：大专 专业要求：国际经济与贸易,国际贸易学,贸易经济） | F8: =INDEX(_xlfn._xlws.FILTER(报名明细!$L:$L,报名明细!$B:$B=$C8),1) -> 1.英语大学四级及以上，书面英语读写无障碍，口语交流流利。2.优秀的沟通表达能力与亲和力，有出色的组织协调能力与执行力。3.工作积极主动、认真负责，责任心强。4.善于组织策划活动，有服务意识。5.持有有效驾照，驾驶技术熟练者优先。(因工作经常会涉及到海外客户接待需求)。 | G8: =INDEX(_xlfn._xlws.FILTER(报名明细!$I:$I,报名明细!$B:$B=$C8),2) -> 主动营销（学历：大专 专业要求：电子商务,跨境电子商务,电子商务技术,电子商务类） | H8: =INDEX(_xlfn._xlws.FILTER(报名明细!$L:$L,报名明细!$B:$B=$C8),2) -> 要求：1：依托公司平台开发新客户，日常电话，邮件等多种方式开发及跟进海外客户。2：熟练运用各种搜索平台，能独立开发客户3：可熟练阅读和收发国外邮件，大专及以上学历，有较好的英文沟通能力4：良好的沟通，计划，执行及时间管理能力，具备较强的团队精神，工作认真，责任心强5：良好的文字功底，较强的网站专题策划和信息采编能力工作内容：1）社交媒体（FB,linkedin）新客户的开发2）老客户的维护 | I8: =INDEX(_xlfn._xlws.FILTER(报名明细!$I:$I,报名明细!$B:$B=$C8),3) -> 文案实习生/英语编辑实习（学历：大专 专业要求：汉语言文学,英语,商务英语,英语语言文学,编辑出版学,新媒体艺术,市场营销,广告学） | J8: =INDEX(_xlfn._xlws.FILTER(报名明细!$L:$L,报名明细!$B:$B=$C8),3) -> 要求：1：有扎实的文字功底，中文，英文，编辑，媒体，市场营销，广告，汉语言文学专业皆可2：英语四级以上3：电脑使用熟练，能熟练操作各类办公软件工作内容：1：社交媒体日常文章的更新2：SEO文章的更新需求人数：2-4人女生优先备注：一天至少要写2-6篇原创文章（非AI写的文章），不符合要求的会需要修改，接受不了要修改的不要投
A9: =_xlfn.XLOOKUP(C9,展区展位!A:A,展区展位!B:B) -> B互联网/电子/通信 | B9: =_xlfn.XLOOKUP(C9,展区展位!A:A,展区展位!C:C) -> B18 | C9: 上海云众名远信息技术有限公司 | D9: =_xlfn.XLOOKUP(C9,企业简介提取!B:B,企业简介提取!F:F) -> 上海云众专注于移动互联网整合营销，汇集了全国数家移动媒体，是360在上海地区的优秀代理商。为客户提供全渠道“一对一”顾问式的定制服务方案，利用深度数据分析挖掘工具、可视化报表处理功能、高精度的实时用户画像，先进的搜索引擎技术实施精准投放广告，从广告主企业实际需求的出发，实现企业网络营销效果，提高广告转化效果。基于360AI大模型，提供元宇宙定制、AI数字人智能化业务定制服务，致力于通过前沿科技为企…… | E9: =INDEX(_xlfn._xlws.FILTER(报名明细!$I:$I,报名明细!$B:$B=$C9),1) -> 广告运营专员（学历：大专 专业要求：无） | F9: =INDEX(_xlfn._xlws.FILTER(报名明细!$L:$L,报名明细!$B:$B=$C9),1) -> 岗位职责：1、与客户沟通，及时了解客户需求和广告投放计划；2、根据客户产品制定投放策略，指导客户有效执行；3、对广告投放进行效果监控，及时反馈，并定期制定数据分析报告；4、跟进续费事宜，维护客户关系，确保客户长期合作；5、定期拜访客户，了解需求和效果，以便做账户优化和调整。任职要求：1、专业不限，积极主动，执行力强，踏实稳定，有强烈责任心和沟通能力；2、能熟练运用excel、PPT等办公软件；3、实习生可免费提供住宿，可转正。 | G9: =INDEX(_xlfn._xlws.FILTER(报名明细!$I:$I,报名明细!$B:$B=$C9),2) -> 总经理助理（学历：本科 专业要求：法学,中国语言与文化,应用语言学,汉语言文学） | H9: =INDEX(_xlfn._xlws.FILTER(报名明细!$L:$L,报名明细!$B:$B=$C9),2) -> 职位描述1、学习互联网广告公司（抖音、必应等）产品的理念、功能、应用场景及落地；2、学习公司理念和团队管理，项目执行落地经验；3、总经理直接带教，出席各种商业谈判和沙龙，拓宽高端人脉；4、负责公司内部各部门负责人之间的沟通协调，以达到高效推进项目，解决问题；5、迅速从基层向中层管理岗蜕变，能独立承接业务并完成业务输出；6、关注客户的使用情况，为客户提供运营支持服务，提高客户组织的活跃度；7、完成上级领导交代的其他任务；职位要求1、统招一本本科学历，985/211院校，工作经验1年及以上，互联网广告行业经验优先；2、有非常强的学习能力，较强的文字功底，形象气质佳；3、价值观正向、开放热情，对商业、组织有强烈的好奇心；4、较强的思考及创造力，能够超出现有框架提出并落地增值建议；5、对为客户创造价值有浓厚的兴趣；6、喜欢接受挑战、喜欢创新与实践，勤于思考；7、有非常好的表达能力，逻辑清晰、语言干练，普通话标准；8、较强的资源协调能力、合作能力、善于沟通、自驱力强； | I9: =INDEX(_xlfn._xlws.FILTER(报名明细!$I:$I,报名明细!$B:$B=$C9),3) -> 360广告销售（学历：大专 专业要求：无） | J9: =INDEX(_xlfn._xlws.FILTER(报名明细!$L:$L,报名明细!$B:$B=$C9),3) -> 岗位职责：1、负责开发360搜索推广的B端广告客户的开拓；2、针对客户的常规和突发问题，有良好的分析、判断及独立解决问题的能力；3、对互联网行业新生产品或事物保持敏感度，时刻了解掌握全行业最新动态及竞品信息；4、具备良好的沟通表达能力、出色的公关客情的能力，并能对客户进行长期维护回访；5、与各团队保持良好沟通，建立深度关系，深度了解公司产业业务及相关知识。任职要求：1、学历不限，可接受优秀新人和实习生；2、性格开朗，愿意与人沟通交流，愿意挑战高薪；3、实习生可以提供免费住宿，正式工可酌情商量。
A10: =_xlfn.XLOOKUP(C10,展区展位!A:A,展区展位!B:B) -> D教育/传媒/电竞 | B10: =_xlfn.XLOOKUP(C10,展区展位!A:A,展区展位!C:C) -> D26 | C10: 上海三客友文化传播有限公司 | D10: =_xlfn.XLOOKUP(C10,企业简介提取!B:B,企业简介提取!F:F) -> 公司成立于2021年04月01日，其创始人以及各合伙人均在本行业耕耘十余年，具有相当的专业能力以及行业分析力。现主营业务为全国各大行业展会行业头部展商展台的现场运营和各大知名品牌的线下推广活动以及国企央企等上市企业宣传片拍摄、短视频制作及新媒体运营等。服务企业有中国铁路局上海工务段、中粮集团、龙湖地产、奔驰、北汽、吉利、极狐、松下、尼康、三菱电机、丰收日集团、花嫁丽舍、沙田物业、上海婚庆行业协会等…… | E10: =INDEX(_xlfn._xlws.FILTER(报名明细!$I:$I,报名明细!$B:$B=$C10),1) -> 会展项目执行及管理（学历：大专 专业要求：无） | F10: =INDEX(_xlfn._xlws.FILTER(报名明细!$L:$L,报名明细!$B:$B=$C10),1) -> 1.项目策划与执行：参与展会项目的策划，包括但不限于确定展会主题、制定展会流程、安排展会时间表等，确保项目从策划到执行的顺利进行。2.沟通协调：与各部门、参展商、供应商等建立有效的沟通机制，确保信息的准确传达和项目的顺利推进。3.现场管理：在展会期间，负责现场的协调与管理工作，确保展会现场的秩序和安全。4.数据分析与报告：收集展会相关数据，进行分析并撰写报告，为公司的决策提供有力支持。岗位要求：展会现场执行、并辅助项目经理做好向下内部管理工作，例如：各类人员招募、礼品物料整理、了解基础搭建及制作知识，简单制作统计表等；具有一定的社交能力。 | G10: =INDEX(_xlfn._xlws.FILTER(报名明细!$I:$I,报名明细!$B:$B=$C10),2) -> 总经理助理（学历：大专 专业要求：无） | H10: =INDEX(_xlfn._xlws.FILTER(报名明细!$L:$L,报名明细!$B:$B=$C10),2) -> 工作内容：1.负责公司推广、项目规划以及日常运营。2.制定公司激励制度以及奖惩制度，做好公司内部人员管理。3.协助项目经理做好成本控制以及公司整体运营成本。辅助总经理对外商务洽谈，对内人员管理以及项目管理与核查。任职要求：1.有团队管理经验，负责过企业或学校的团队管理。2.从事过广告或会展行业者优先。福利：一年20天以上带薪休假 | I10: =INDEX(_xlfn._xlws.FILTER(报名明细!$I:$I,报名明细!$B:$B=$C10),3) -> 广告设计（学历：大专 专业要求：无） | J10: =INDEX(_xlfn._xlws.FILTER(报名明细!$L:$L,报名明细!$B:$B=$C10),3) -> 工作内容：1、负责企业宣传资料（如画册、海报、易拉宝、展板）的平面设计，结合品牌定位进行视觉呈现。使用设计软件（AdobePhotoshop、AdobeIllustrator等）进行图片处理、排版设计等工作。2、负责协助短视频、宣传片、活动记录等内容的剪辑和后期制作，确保视频内容流程，视觉效果突出，协助团队完成视频创意策划。3、协助团队完成其他文化传播、活动策划相关的工作。任职要求：1、艺术设计、视觉传达、广告学等相关专业大专及以上学历。2、熟悉广告设计原理、印刷工艺及数字媒体特性3、精通Photoshop、Illustrator、CorelDRAW等平面设计工具，掌握AE/PR（视频剪辑）、InDesign（排版）者优先。福利：一年20天以上带薪休假
A11: =_xlfn.XLOOKUP(C11,展区展位!A:A,展区展位!B:B) -> E城市运营与技术服务 | B11: =_xlfn.XLOOKUP(C11,展区展位!A:A,展区展位!C:C) -> E13 | C11: 上海明华智慧城市运营管理有限公司 | D11: =_xlfn.XLOOKUP(C11,企业简介提取!B:B,企业简介提取!F:F) -> 上海明华智慧城市运营管理有限公司（简称明华）成立于1992年8月，为上海市最早获得国家物业管理一级资质企业之一。近三十年来，明华始终秉承“快乐服务，追求卓越”的服务理念，不走寻常路，差异发展、创新经营，先人一步走出了一条“公众物业管理”的探索之路；在个性化、人性化、国际化理念的指引下，通过量身定制的服务研发和产品输出，成为物业行业中公众物业管理领域的领先者。 在公众物业管理领域，明华在上海乃至国内…… | E11: =INDEX(_xlfn._xlws.FILTER(报名明细!$I:$I,报名明细!$B:$B=$C11),1) -> 展馆管理（学历：大专 专业要求：无） | F11: =INDEX(_xlfn._xlws.FILTER(报名明细!$L:$L,报名明细!$B:$B=$C11),1) -> 岗位职责1.学习了解场馆内容主题，整理讲解词，向游客进行解说工作；2.负责场馆内指引接待工作，维护参观秩序；3.协助做好团队的其他工作。任职资格1.有亲和力，形象气质佳；2.有较强的语言表达能力，普通话标准；3.熟练掌握办公软件操作能力。 | G11: =INDEX(_xlfn._xlws.FILTER(报名明细!$I:$I,报名明细!$B:$B=$C11),2) -> 行政助理（学历：大专 专业要求：无） | H11: =INDEX(_xlfn._xlws.FILTER(报名明细!$L:$L,报名明细!$B:$B=$C11),2) -> 岗位职责在带教人指导下，协助完成日常行政事务、文档处理、信息整理及基础沟通协调工作，同时熟悉办公流程与职场规范，提升基础办公技能。1.文档处理与资料管理-协助进行文档的录入、排版、打印、复印与装订，确保文档格式规范、内容准确。-参与资料的整理与归档，2.日常行政事务协助-负责办公区域的基础后勤支持，如整理办公环境、补充办公用品（笔、纸、打印机耗材等）、登记领用情况。-协助接待来访人员，做好引导、登记，通知相关同事对接；3.信息整理与数据统计-协助收集、整理各类基础信息，按照要求进行简单的分类与汇总。-及时更新基础信息台账，保证信息的时效性。4.沟通协调与事务跟进-协助在部门内部或跨部门间传递文件、传达简单通知，确保信息传递及时。-跟进简单事务的进展（如待办事项、任务反馈等），并向带教人或上级汇报进度。任职资格1.仔细认真，沟通协调能力较强；2.办公软件熟练；3.有意向在物业行业长期发展者优先。 | I11: =INDEX(_xlfn._xlws.FILTER(报名明细!$I:$I,报名明细!$B:$B=$C11),3) -> 工程技术（学历：初中及以下 专业要求：无） | J11: =INDEX(_xlfn._xlws.FILTER(报名明细!$L:$L,报名明细!$B:$B=$C11),3) -> 岗位职责协助完成水电设施的日常巡检、维护、简单安装及维修工作，同时学习并掌握水电系统的基础原理、安全规范和实操技能。1.协助日常巡检与维护-跟随带教人对建筑物内的水电设施，进行定期巡检，记录设备运行状态。-协助完成水电设施的日常保养工作，-发现水电设施异常时，及时向带教人或上级汇报，并协助做好问题记录。2.辅助维修与安装工作-在带教人指导下，协助完成简单的维修任务，-参与水电安装的辅助工作，-维修或安装完成后，协助清理现场，整理工具和剩余材料任职资格：1.持证上岗（高、低压证、空调证等均可）；2.认真负责，沟通协调能力强；3.有意向在物业行业长期发展；
A12: =_xlfn.XLOOKUP(C12,展区展位!A:A,展区展位!B:B) -> D教育/传媒/电竞 | B12: =_xlfn.XLOOKUP(C12,展区展位!A:A,展区展位!C:C) -> D20 | C12: 上海樱帆望文化传媒有限公司 | D12: =_xlfn.XLOOKUP(C12,企业简介提取!B:B,企业简介提取!F:F) -> 樱帆电竞成立于2015年8月， 以电竞赛事组织策划执行和直转播节目制 作为业务核心。赛事组织板块已经完成过2018年雅加达亚运会、2018-2019年WESG 全球总决赛、2019-2024OPL 职业联赛等各类国 内外高级别比赛的赛事组织工作，时至今日樱帆电竞已经完成超过500个 游戏项目赛事组织执行工作。2021年公司成立直转播节目制作业务板块，完成了征途全民争霸赛总决赛暨年终盛典、三届永…… | E12: =INDEX(_xlfn._xlws.FILTER(报名明细!$I:$I,报名明细!$B:$B=$C12),1) -> 电竞赛事直转播播控岗位实习生（学历：大专 专业要求：广播电视学,广播电视,广播影视节目制作,广播电视编导） | F12: =INDEX(_xlfn._xlws.FILTER(报名明细!$L:$L,报名明细!$B:$B=$C12),1) -> 一、职位概述参与电竞赛事直转播工作，协助专业团队确保赛事直播的顺利进行。二、主要职责1.直播协助●深度参与电竞赛事直转播过程中的播控操作工作，包括但不限于设备的开启与关闭、信号切换、画面调整等。●密切监控直播信号，及时发现并反馈直播中的异常情况，确保直播质量。2.学习提升●学习电竞赛事直转播的流程和技术，熟悉各类播控设备的使用。●参加内部培训，提升专业技能和对电竞行业的认知。3.资料整理●整理电竞赛事直转播相关的技术资料和数据记录。●协助撰写简单的直播报告。4.播控任务●完成上级交办的其他与电竞赛事直转播播控相关的工作。内容包含但不限于导播切台、VCR、字幕机等。三、任职要求1.专业背景●传媒、广播电视、数字媒体技术、电子竞技等相关专业优先。2.技能要求●具备一定的计算机操作能力，熟悉常用办公软件。●对电竞有浓厚兴趣，了解电竞赛事直播特点，需要有一定的相关经验(社团、兼职等均可)。3.态度品质●工作认真负责，细心耐心，有较强的学习能力和团队合作精神。4.学历要求●大专以上学历，26届27届毕业生优先。 | G12: =INDEX(_xlfn._xlws.FILTER(报名明细!$I:$I,报名明细!$B:$B=$C12),2) -> 电竞赛事实习导演（学历：大专 专业要求：影视编导,新闻传播学类,新闻与传播,新闻传播学） | H12: =INDEX(_xlfn._xlws.FILTER(报名明细!$L:$L,报名明细!$B:$B=$C12),2) -> 岗位概述：作为公司导演及创意方向的核心管培生，你将参与到行业细分领域最头部的各项电竞赛事及内容节目的全流程导演工作中。我们希望你具备自主学习、钻研创新、吃苦耐劳的优秀品质和能力，对游戏和电竞内容抱有浓厚兴趣与较高审美。公司会针对管培安排包含培训、考核、轮岗等多样化的培养计划，并对表现优秀者优先招聘录用。一、岗位职责：1.【创意策划】：协助总导演对接产品相关的线上线下活动的前期创意策划，能够根据客户的需求，协助分析赛事或活动举办的底层逻辑；2.【筹备推进】：根据策划方案，协助总导演深化产出流程RD、视觉包装设计等创意落地方案，协助并确保各项产出匹配预期规划，保证项目顺利完成；3.【沟通协作】：协助总导演做好内外部的沟通管理与协调工作。在跨部门协作中，能够帮助总导演做到及时高效精准的信息沟通，保持各部门之间良好持久的协作关系，有效帮助工作推进。熟练掌握英/日/韩等外语书面及口语沟通能力者加分；4.【落地执行】：赛事/活动执行的彩排与直播期间，协助总导演完成现场的执行导演工作；5【复盘总结】：协助总导演对完成项目进行总结复盘，系统化整理与分享经验。二、任职要求:1.大专及以上学历，影视编导、…… | I12: =INDEX(_xlfn._xlws.FILTER(报名明细!$I:$I,报名明细!$B:$B=$C12),3) -> 电竞赛事执行（学历：大专 专业要求：体育学类,广播影视节目制作,文化服务类,广告学） | J12: =INDEX(_xlfn._xlws.FILTER(报名明细!$L:$L,报名明细!$B:$B=$C12),3) -> 一、游戏硬性要求：包括但不限于以下两款游戏，可接受入职之后再熟悉拳皇KOF全系列【1、拳皇KOF全系列（97-15均可），街霸6，铁拳等游戏，以上游戏单产品游戏时长50小时以上】【2、瓦罗兰特，游戏段位要求达到超凡】二、岗位要求：1、有拳皇系列&街霸6等格斗游戏经验的优先；2、有国内城市办赛经验者优先；3、熟练excel、word、PPT等日常办公软件；4、熟悉市场主流游戏的游戏机制和赛事规则；5、具有一定沟通、抗压能力，擅长对接及协助工作；三、任职要求1.专业背景●传媒、广播电视、数字媒体技术、电子竞技等相关专业优先。2.技能要求●具备一定的计算机操作能力，熟悉常用办公软件。●对电竞有浓厚兴趣，了解电竞赛事直播特点。3.态度品质●工作认真负责，细心耐心，有较强的学习能力和团队合作精神。4.学历要求●大专以上学历，26届27届毕业生优先。小贴士：公司比较看重岗位匹配度，同时也致力于挖掘每一位求职者的潜在能力，让大家能在最适合的岗位上发光发热。
A13: =_xlfn.XLOOKUP(C13,展区展位!A:A,展区展位!B:B) -> A机械/制造/能源 | B13: =_xlfn.XLOOKUP(C13,展区展位!A:A,展区展位!C:C) -> A16 | C13: 上海天安轴承有限公司 | D13: =_xlfn.XLOOKUP(C13,企业简介提取!B:B,企业简介提取!F:F) -> 上海天安轴承有限公司为上海电气集团旗下上海集优机械有限公司的全资企业，位于上海市闵行区莘庄工业园区银都路4399号，具有60多年的生产历史。 公司专业生产具有高精度、高转速、高灵敏度、低噪音、长寿命的微型轴承，并对轴承产品进行技术开发和产品售后服务。产品广泛运用于航空航天、工业装备、汽车医疗等行业，性能达到国际领先水平。 近几年公司大力支持国家航天事业，已为“天…… | E13: =INDEX(_xlfn._xlws.FILTER(报名明细!$I:$I,报名明细!$B:$B=$C13),1) -> 数控操作（学历：大专 专业要求：无） | F13: =INDEX(_xlfn._xlws.FILTER(报名明细!$L:$L,报名明细!$B:$B=$C13),1) -> 1、按作业指导书及设备操作规程，正确操作和保养数控机床2、对数控机床进行加工编程、线切割3、做好加工零件的自查，确保加工产品合格率 | G13: =INDEX(_xlfn._xlws.FILTER(报名明细!$I:$I,报名明细!$B:$B=$C13),2) -> 电气维修（学历：大专 专业要求：无） | H13: =INDEX(_xlfn._xlws.FILTER(报名明细!$L:$L,报名明细!$B:$B=$C13),2) -> 负责公司电气故障的排除；对公司内用电的分配、设计及用电管理工作；监督检查变电所管理制度的执行情况及备件管理工作 | I13: =INDEX(_xlfn._xlws.FILTER(报名明细!$I:$I,报名明细!$B:$B=$C13),3) -> 设备维修（学历：大专 专业要求：无） | J13: =INDEX(_xlfn._xlws.FILTER(报名明细!$L:$L,报名明细!$B:$B=$C13),3) -> 对设备的机械、液压、气动系统的故障、磨损进行维修，确保生产；对设备进行点检、保养工作负责设备的日常报表填写
... A53: =_xlfn.XLOOKUP(C53,展区展位!A:A,展区展位!B:B) -> C汽车/服装/贸易 | B53: =_xlfn.XLOOKUP(C53,展区展位!A:A,展区展位!C:C) -> C02 | C53: 延锋国际汽车技术有限公司 | D53: =_xlfn.XLOOKUP(C53,企业简介提取!B:B,企业简介提取!F:F) -> 延锋是国际领先的汽车零部件供应商，专注于汽车内外饰、汽车座椅、座舱电子及被动安全领域，为全球客户提供全方位服务。同时聚焦智能座舱与轻量化技术，助力汽车制造商探索高级别驾乘场景下的智能化水平，并提供灵活可持续的产品解决方案。目前，延锋在全球20个国家已有超过建有240多个分支机构，约56,000名员工。 延锋国际技术中心是延锋集团的核心职能部门，目前全球人数5000多人，总部在上海，在…… | E53: =INDEX(_xlfn._xlws.FILTER(报名明细!$I:$I,报名明细!$B:$B=$C53),1) -> 财务文员（学历：本科 专业要求：无） | F53: =INDEX(_xlfn._xlws.FILTER(报名明细!$L:$L,报名明细!$B:$B=$C53),1) -> 工作职责:1.负责财务共享中心若干工厂的应收款项相关业务的审核以及入账2.定期联系跟踪逾期应收款项回款进度，编制月度科目余额调节表3.定期与客户核对发票及收款账务，反馈差异并跟踪解决4.负责配合工厂分析，总账及审计提供相关统计报表及凭证基本要求：1.学历不限，大专及以上优先，2.优先财经类专业毕业3.具备良好的沟通表达能力4.品行端正5.英语沟通能力良好或具相关工作经验的申请者优先考虑6.基本的office办公自动化能力 | G53: =INDEX(_xlfn._xlws.FILTER(报名明细!$I:$I,报名明细!$B:$B=$C53),2) -> 宣传文员（学历：本科 专业要求：无） | H53: =INDEX(_xlfn._xlws.FILTER(报名明细!$L:$L,报名明细!$B:$B=$C53),2) -> 岗位职责：1.参与企业微信号的日常运营工作。日常新闻稿的采、编，与基层宣传员的沟通，了解相关信息。2.负责企业文化工作推进，能策划、组织各类员工活动、文化活动。3.企业新闻、活动的摄影摄像，并进行视频编辑。4.能贯彻执行上级单位、本公司布置的各类工作。任职要求：1.有良好的文字功底。2.有较强的策划、组织各类型会议、企业文化活动的能力。3.有视频剪辑、绘图功底，会使用PR、PS、美图秀秀等设计软件；熟练运用办公软件。4.吃苦耐劳，执行力强，责任心强、服务意识，工作效率高；乐于沟通、乐于助人，具有积极的工作态度，有良好的团队精神和服务意识。 | I53: =INDEX(_xlfn._xlws.FILTER(报名明细!$I:$I,报名明细!$B:$B=$C53),3) -> 产品设计工程师（内饰/安全/座椅）（学历：本科 专业要求：无） | J53: =INDEX(_xlfn._xlws.FILTER(报名明细!$L:$L,报名明细!$B:$B=$C53),3) -> 主要任务和职责1.根据产品投产系统（PLUS）以及客户产品开发程序的要求，按时保质地进行产品开发。2.制定和优化设计方案，选择正确.合适的零部件和材料，力求在保证功能.外观要求的情况下成本最低；掌握项目工程开发费用的使用。3.完成产品数据.图纸和材料清单（BOM）表等工程技术文件。4.协助处理客户提出的问题并参与解决。5.负责协调样品制造，客户交样和文件准备。6.组织或参与各类工程会议，并落实和跟踪行动计划。7.及时总结座椅开发过程中发生的问题和经验。8.与供应商和部门工厂联系，提供技术支持。基本条件1.2022年应届毕业生（包含海外留学生）2.全国重点院校本科及以上学历；3.CET-4或其他同等级英语能力证书，听说读写流利；4.会德语.法语.日语.韩语者优先考虑；5.成绩优秀，有奖学金者优先考虑；6.有学生会工作及社会实践经历者优先考虑。

Sheet 2
A1: 展位 | B1: 单位名称 | C1: 单位简介 | D1: 职位1标题 | E1: 职位1jd | F1: 职位2标题 | G1: 职位2jd
A2: C20 | B2: 上海德辰汽车销售有限公司 | C2: 上海德辰汽车销售公司是北方一大型汽车经销商集团在上海新投资创立的一汽大众奥迪品牌4S店。超越了传统豪华汽车4S店的概念，实际具备品牌体验、车型展示、新车销售、售后服务、二手车置换等多种功能，完备的设施以及周到的服务一应俱全，体现出国际豪华品牌全球统一的服务水准。该城市展厅坐落于闵行区颛桥地区（颛兴东路1280弄3号）。地铁、轻轨均可到达，交通便捷。地址：颛兴东路…… | D2: 机电实习生（学历：中专/技校专业要求：汽车检测与维修技术,新能源汽车技术,汽车运用与维修技术,汽车车身维修技术,新能源汽车运用与维修,汽车制造类,汽车服务工程,汽车维修工程教育,新能源汽车工程） | E2: 具有一定的汽车理论知识和汽车维修知识，具有较强的动手能力、语言表达能力、独立解决问题的能力、汽车工艺学习及钻研能力 | F2: 机电实习生（学历：中专/技校专业要求：汽车运用与维修技术,汽车检测与维修技术,汽车服务工程） | G2: 具有一定的汽车理论知识和汽车维修知识，具有较强的动手能力、语言表达能力、独立解决问题的能力、汽车工艺学习及钻研能力
A3: D16 | B3: 上海网鱼酒店管理有限公司 | C3: 网鱼创始于1998年，从诞生之初就秉承不断创新的理念，致力于打造多人游戏空间。截至2020年12月31日，网鱼全球会员数超2000万，服务覆盖国内外106个城市。全球拥有超1000家门店，年服务人次超3000万，iG战队倾情代言，是深受全球玩家喜爱的聚玩圣地。2021年推出“网鱼电竞酒店”，正式进军电竞酒店行业，打造跨品类、跨业态、跨平台的综合娱乐型品牌，践行“给用户美好的体验”。 | D3: 门店管培生（学历：大专专业要求：无） | E3: 公司简介：网鱼创始于1998年，起源于上海松江，2015年获得上海市著名商标荣誉称号。作为国内电竞连锁的代表，从诞生之初就秉承不断创新的理念，致力于全球第一电竞社区的打造，为全球电竞玩家提供优质的电竞休闲娱乐服务。截至2021年12月31日，网鱼全球会员数超2000万，服务覆盖国内外82个城市，在美国、英国、加拿大、澳大利亚、新加坡等多个国家开设门店，全球拥有900多家门店，年服务人次超4000万。2021年，网鱼品牌创新升级为“网鱼电竞”，打造游戏玩家的电竞基地；探索多业态，推出“网鱼电竞酒店”，正式进军电竞酒店行业，打造跨品类、跨业态、跨平台的综合娱乐型品牌，践行“给用户美好的体验”。截至2023年12月，网鱼电竞酒店覆盖全国26个主要城市，在营门店数量超过200家。岗位介绍门店管培生（储备店长）：50名工作地点：全国（全国1700家门店，可根据意向城市分配工作城市）。工作职责:1、经营管理：从基层店员历练开始，协助酒店店长进行门店的运营管理，管理门店资产设备、现金、账务，薪资录入，奖金核算；2、学习管理：跟随导师学习门店人员的岗位落实及日常管理；3、品质管理：保证门店卫生品质，逐…… | F3: 客户经理（学历：大专专业要求：无） | G3: 职责：1、导座服务：①严格执行门店导座SOP标准，提升顾客满意度；②主动观察顾客消费习惯，提供个性化服务；③工作时间需着JK制服，并保持整洁得体的妆容及精神面貌；2、抖音直播：①每日在门店非上客高峰期，使用门店抖音账号，完成2小时直播；②负责直播间的秩序维护和用户互动，积极解答用户问题；③发掘直播间内意向用户，吸引用户到店，提升门店新会员数量；④每日24点前，完成一条抖音视频发布。3、会员运营：①完成企业微信社群搭建、成员邀请及日常维护；②每日回访新客，定期收集top100顾客反馈建议；③每日邀请老顾客到店上网，并为顾客线上订座；4、线上平台维护：①每周按照店长要求，完成高德/百度/腾讯地图/美团平台的优质好评数。②100%邀请团购用户消费后评价。要求：1、性别：女2、年龄：18-24周岁3、学历：大专及以上学历4、形象：身高160CM以上，形象气质佳5、性格特质：活泼开朗，有服务意识，擅沟通喜交流6、经验能力：会端游、有直播或者游戏教练经验者优先薪资待遇1、薪资：月薪5000+；2、福利：每月免费上网时长60小时，免费饮品10杯，简餐半价券42张，其他福利均同门店其他员工；3、销售提……
A4: E16 | B4: 上海万厦建筑装饰加固工程有限公司 | C4: 上海万厦建筑装饰加固工程有限公司是一家装饰加固的专业公司，影院建设的集成单位。公司专业配套、工种齐全。具有工艺设计、建声设计、装修设计、结构设计、机电设计以及工程管理与各施工项目经理部。在长期的工程实践中已取得了丰富的经验，形成了设计施工一体化的操作模式，取得了丰硕的业绩。公司自上世纪九十年代至今已先后设计和施工了影剧院、演剧场、文化馆等几百项文化设施项目及公共商业设施项目，取得了良好的社会信誉…… | D4: 软件开发设计师（学历：大专专业要求：无） | E4: 技术基础：掌握前端基础技术，包括HTML/CSS/JavaScript，了解ES6及以上语法；熟悉或初步了解小程序开发技术栈（WXML/WXSS），有使用微信开发者工具的基础经验；了解Vue、React等前端框架，或Python、Java等任一后端语言者优先。3.工具与能力：能使用微信开发者工具完成简单代码编写、调试与预览；具备基础的逻辑思维和问题排查能力，能理解简单业务需求并配合完成代码辅助工作；会使用Git等版本控制工具（如GitHub、GitLab）者加分。 | F4: 装饰设计（学历：大专专业要求：无） | G4: 软件技能：熟练使用CAD（绘制平面图、施工图）、SketchUp（基础建模），掌握3DMax/Blender（建模）、Photoshop（效果图后期）者优先。具备基础的空间布局、色彩搭配审美；了解常见装饰材料（如板材、涂料）、施工工艺基础知识者。
A5: F09 | B5: 予童家庭服务（上海）有限公司 | C5: 予童家庭服务（BabyNanny），以“重塑美好育儿生态”为使命，专注为高净值家庭提供育婴照护、婴儿早教、孩童陪伴等服务。作为高标准母婴护理及高质量家庭服务的坚定笃行者，予童为同样追求育儿品质的家庭，定制集育婴护理、入户指导和社群体验“三维一体”的婴童成长呵护方案，让育儿回归优雅和从容。以“百里挑一”的严苛标准遴选育婴师，打造迎合高端家庭需求的培塑实训，冀期予童的每一名育婴师，都能成为宝宝的温情…… | D5: 家庭育婴师（学历：大专专业要求：护理,学前教育,助产） | E5: 一、工作地点上海全市二、岗位职责-全面负责新生儿的生活照料，涵盖喂养、洗澡、抚触、更换尿布等环节，保障宝宝的清洁与舒适。-密切留意宝宝的生长发育状况，诸如身高、体重、睡眠、大小便等方面，一旦察觉异常立即向家长或医生反馈。-依据宝宝的年龄及发展阶段，精心制定科学合理的喂养计划与作息时间表，悉心培养宝宝良好的生活习惯。-开展早期教育与启蒙工作，借助游戏、互动等多种方式，推动宝宝的认知、语言、运动以及社交能力的发展。-承担宝宝衣物、用品的清洗与消毒工作，确保宝宝生活环境的整洁与卫生。-与家长保持高效且良好的沟通，深入了解家长的需求与关注重点，给予专业的育婴建议和指导。-协助家长妥善处理宝宝的其他相关事务，像就医、接种疫苗等。三、任职要求需要会做饭。持有专业的育婴师资格证书，例如育婴员职业资格证书等优先。具有早教中心、托育园、幼儿园实习经验者优先。对婴幼儿事业充满热爱，拥有爱心、耐心和责任心，具备良好的职业道德和素养。具备出色的沟通能力和团队协作精神，能够与家长及其他工作人员构建起良好的关系。身体健康，拥有良好的心理素质和抗压能力。具有一定的学习和创新能力，能够持续更新育婴知识和技能。 | F5: 家庭育婴师（学历：初中及以下专业要求：学前教育,学前教育学,护理学,护理,护理学类,护理类,卫生教育,儿科学,妇幼保健医学,预防医学） | G5: 可选择白班或住家1.全面负责新生儿的生活照料，涵盖喂养、洗澡、抚触、更换尿布等环节，保障宝宝的清洁与舒适。2.密切留意宝宝的生长发育状况，诸如身高、体重、睡眠、大小便等方面，一旦察觉异常立即向家长或医生反馈。3.依据宝宝的年龄及发展阶段，精心制定科学合理的喂养计划与作息时间表，悉心培养宝宝良好的生活习惯。4.开展早期教育与启蒙工作，借助游戏、互动等多种方式，推动宝宝的认知、语言、运动以及社交能力的发展。5.承担宝宝衣物、用品的清洗与消毒工作，确保宝宝生活环境的整洁与卫生。6.与家长保持高效且良好的沟通，深入了解家长的需求与关注重点，给予专业的育婴建议和指导。7.协助家长妥善处理宝宝的其他相关事务，像就医、接种疫苗等。任职要求对婴幼儿事业充满热爱，拥有爱心、耐心和责任心，具备良好的职业道德和素养。具备出色的沟通能力和团队协作精神，能够与家长及其他工作人员构建起良好的关系。身体健康，无传染性疾病，拥有良好的心理素质和抗压能力。具有一定的学习和创新能力，能够持续更新育婴知识和技能。有相关从业经验、实习经验者优先；护理专业、学前教育专业、婴幼儿托育专业优先；有乐器、舞蹈、声乐、英语、绘画等特长……
A6: B02 | B6: 中国电信股份有限公司上海莘闵电信局 | C6: 中国电信股份有限公司上海莘闵电信局坐落于闵行区莘东路199号，简称莘闵电信局。前身为上海市电话局莘闵区局。2000年7月1日，中国电信集团上海市电信公司成立后，更名为上海市电信公司莘闵电信局；2008年3月，更名为中国电信股份有限公司上海莘闵电信局。中国电信股份有限公司上海莘闵电信局提供固定电话、移动通信、宽带互联网接入、互联网电视、卫星通信、信息化应用等泛在网络和综合智能信息服务能力，服务闵…… | D6: 门店经理见习生（学历：大专专业要求：无） | E6: 电信门店的整体运营与业绩达成，核心涵盖经营指标、团队管理、客户服务、营销与渠道协同、合规与风险控制等关键模块。 | F6: 装维见习生（学历：大专专业要求：无） | G6: 电信宽带、固定电话、IPTV等电信业务的安装与故障维修，同时承担客户沟通与网络简单维护任务。
A7: C22 | B7: 上海羊鑫布艺有限公司 | C7: 上海羊鑫布艺有限公司是海派旗袍与新中式文化创新的时尚企业作为上海海派旗袍文化促进会副会长单位,公司以"致知青花"系列为代表,融合传统制衣工艺与现代设计,打造独具东方韵味的高级定制服饰。产品屡获长三角旗袍设计大赛银奖等殊荣,创始人杨玉娟女士获“东方时尚工匠”称号。公司通过时尚闪秀、文化展览等多元化形式,致力于传承和发展海派旗袍文化,推动传统服饰艺术的现代表达与创新发展。 | D7: 打样纸板师（学历：大专专业要求：无） | E7: 【岗位职责】负责服装款式的打板与制版工作：根据设计师提供的效果图、设计稿或样衣，精准制作纸样（含裁剪版、工艺版），确保版型符合设计风格与人体工学。样衣跟进与调整：配合样衣车间完成首件样衣制作，参与样衣试穿评审，根据试穿反馈（如尺寸偏差、版型舒适度）优化纸样，直至样衣合格。工艺文件输出：整理打板数据，制定详细的制版工艺说明（如缝份、缩率、面料特性适配方案），为生产车间提供清晰的技术指导。版型库管理：建立并维护公司版型数据库，分类归档不同款式、尺码的纸样文件，便于后续款式复用与优化。跨部门协作：与设计师、采购部（确认面料特性）、生产部（解决生产中的版型问题）高效配合，确保打板-制版-生产流程顺畅。【任职要求】学历与经验：中专及以上学历，服装相关专业（如服装工程、服装设计），1-3年及以上服装打板/制版经验（应届生可投递助理岗，需熟悉基础打板逻辑）。核心技能：熟练掌握手工打板技巧，能独立完成从净版到毛版的制作；精通制版软件（如富怡、ET、格柏Gerber等），可高效进行数字化制版与纸样修改；了解不同面料特性（如棉、丝、针织、弹力面料）对版型的影响，能针对性调整打板方案；熟悉服装号型标准（如G…… | F7: 销售（学历：大专专业要求：无） | G7: 岗位职责：·顾客服务与销售：·热情接待每一位顾客，提供专业、耐心的咨询和穿搭建议。·洞察顾客需求，达成销售目标，并积极维护客户关系。·处理顾客的疑问和售后问题，提升顾客购物满意度。·店铺日常运营：·负责商品收货、盘点、陈列、补货和库存管理。·保持店铺环境整洁、美观，营造舒适的购物氛围。·熟练操作收银系统，完成每日销售结算工作。·团队协作：·与团队成员紧密合作，共同完成店铺销售目标和各项任务。·积极参与公司培训和团队会议，分享销售技巧和时尚资讯。·品牌形象维护：·以身作则，展现品牌的时尚形象和专业素养。·及时反馈市场信息和顾客意见，助力品牌成长。任职要求：·必备条件：·热爱时尚行业，对服装搭配有浓厚的兴趣和独特的见解。·性格开朗，具有良好的沟通表达能力和服务意识。·积极主动，有责任心，具备良好的团队合作精神。·能适应零售业周末、节假日的工作安排。·优先考虑：·有服装零售或相关销售工作经验者优先。·具备一定的抗压能力和目标导向思维。
A8: E15 | B8: 上海科瑞物业管理发展有限公司 | C8: “和我们共创无限可能的未来”上海科瑞物业管理发展有限公司，成立于2002年1月18日，注册资金5000万元。公司致力于成为“成为现代物业服务专业管家”品牌企业，服务于超高层建筑、城市综合体、办公楼、大型住宅、公众项目；以及提供大中小学校区管理、酒店管理和物业顾问等服务。科瑞物业崇尚现代物业管理理念，坚持以人为本、生态平衡的管理服务本质，追求高标准管理、细节化服务、规范化收费、可持续发展，以“一切…… | D8: 智能建筑工程实习生（学历：大专专业要求：建筑智能化工程技术） | E8: 通过参与智能建筑工程全流程（设计辅助、现场实施、调试配合、文档整理等）工作，帮助实习生掌握智能建筑系统（如楼宇自控、安防监控、综合布线等）的基本原理与实际应用，熟悉工程现场管理流程，培养工程实践能力与问题解决意识，为未来从事智能建筑相关工作奠定基础。 | F8: 管理培训生（学历：大专专业要求：无） | G8: 1、总部职能岗位管理培训生：服务管控中心、品质管控中心、企业发展中心、财务管理部、综合管理部和人力资源部管理培训生；2、运营岗位管理培训生：上海各项目基础管理岗位管理培训生即项目运营条线秩序维护、工程管理、客户服务、环境管理和综合管理岗位管理培训生。岗位需求：根据公司发展不断扩大，为了更好提升管理团队的综合素养，也为了更好的对职能和项目管理人员进行补充，特拟定自2022年10月起启动招聘“新瑞”计划，即招收20名应届毕业生，具体要求如下：1、有志于从事物业管理行业；2、男女不限、形象良好，较强的沟通和表达能力；思维活跃，有较强的创新意识；有责任心，适应能力和抗压性强，3、有一定的文书编写能力，熟练操作各类电脑软件如PPT、PHOTOSHOP等；4、专业不限、户籍不限，除工程类“新瑞”需要对口机电类、工程技术类专业外；5、本科以上，985，211院校可优先考虑，条件特别优秀者可放宽至应届大专毕业生。如经面试录取后实习期为2023年2月起至2023年6月30日，经实习期评估合格可签订正式劳动合同，签订正式劳动岗位职级不低于主管级。工作内容：通过在总部、区域、项目的轮岗学习，对职能人力行政、……
A9: B16 | B9: 图萌（上海）科技有限公司 | C9: 图萌（上海）科技有限公司倡导“科技融合，创新共赢”的理念，专注于新媒体+XR领域的数字技术和内容研发，在人工智能时代背景下，致力于AIGC内容生成式人才的培养，涵盖虚拟现实、数字媒体技术、动漫设计、广播电视编导、节目制作、新闻采编与制作、新媒体艺术、艺术设计、广告学、计算机等领域。作为长三角文旅产业联盟会员单位、教育部职教工场项目白名单企业，图萌科技拥有计算机软件著作权登记证书、上海电…… | D9: 平面设计（学历：大专专业要求：视觉传达设计） | E9: 岗位职责1、负责公司宣传材料、册页等的设计与整合。2、精通PS、AI等设计软件。3、参与设计讨论，和业务团队共同创建用户界面，跟踪设计效果，提出设计优化方案。4、良好的团队精神，工作踏实稳定。岗位要求1、全日制大专或以上学历，艺术设计类相关专业毕业。2、有实习经验者优先，能独立完成设计方案。3、会使用CAD做平面布局图者优先。4、会渲染三维效果图者优先。 | F9: AI虚拟数字人拍摄制作专员（学历：大专专业要求：无） | G9: 岗位职责:1、负责AI虚拟数字人的形象设计、动态捕捉及视频拍摄全流程制作，包括前期策划、场景搭建、灯光调试等。2、使用动作捕捉设备(如光学/惯性动捕系统)、面部表情捕捉技术等，完成数字人的高精度动作与表情数据采集。3、配合A|算法团队，优化数字人的语音、表情、肢体动作的同步性与自然度提升拟真效果。4、负责虚拟拍摄现场的设备调试(如摄像机追踪、虚拟引擎实时渲染等)，确保拍摄效率与质量。5、跟踪行业技术趋势，探索A数字人在直播、短视频、影视等领域的创新应用场景。岗位要求:1、熟悉虚拟制作流程，有动作捕捉(如Vicon、OptiTrack)、面部捕捉(如Faceware、iPhoneARKit)或影视拍摄经验。2、掌握至少一款3D制作工具(如Blender、Maya、UnrealEngine、Unity)能完成基础模型调整与场景搭建。3、了解A|数字人相关技术(如语音合成、TTS、NLP)，有AI工具(如D-D、Synthesia)使用经验者优先。4、具备良好的镜头语言和审美能力，能独立完成脚本分镜设计及后期剪辑(熟悉Premiere、DaVinci等)。
A10: A26 | B10: 上海味捷智朗科技发展有限公司 | C10: 上海味捷智朗科技发展有限公司是熙香科技集团重要子公司之一。集团始创于2014年，是国内领先的人工智能科技企业，国内首家落地的生活服务机器人系统解决方案的服务商，公司致力于借助人工智能、物联网、大数据等技术，激发出更具交互性、智能化和安全的生活服务新业态，通过将物AI+技术应用于生活服务领域，建立智能服务一体化、作业机械无人化、需求定制自动化的“两化一体”模式，实现数据驱动的的精细化运营。公司相关智…… | D10: 机械电工（学历：大专专业要求：机械工程,机械设计制造及其自动化,机械制造及其自动化,机械电子工程） | E10: 本岗位要求:1、3年以上非标自动化设备电气装配，有低压电工证，2、能看懂图纸3、会布线排线，会对点4、熟悉电气控制柜排布、电气元器件功能;5、熟练掌握电工的基本操作技能和工具6、能接受加班，能接受短期、临时出差 | F10: 高级java开发工程师（学历：大专专业要求：计算机科学与技术,电子与计算机工程,计算机网络技术,计算机应用技术,计算机应用工程） | G10: 岗位职责1.参与公司产品或项目的需求分析、设计与开发，根据业务需求完成高质量代码编写，实现系统功能模块；2.负责后端系统的架构设计、搭建与优化，确保系统的稳定性、性能和可扩展性，保障系统高效稳定运行；3.与前端开发团队紧密协作，定义数据接口规范，完成前后端数据交互开发，确保项目整体功能的完整性和流畅性；4.进行数据库设计、优化和维护，熟练编写SQL语句，处理复杂的数据操作和事务管理，保障数据的准确性和安全性；5.编写详细准确的技术文档，包括设计文档、接口文档、使用说明等，为团队协作和系统维护提供支持6.独立解决和处理所负责的项目的运维和监控，及时处理生产环境中的故障和问题，保障系统的可用性和稳定性；7.持续关注行业技术发展趋势，引入新技术、新工具，优化现有技术方案和开发流程，提升团队技术水平和开发效率。任职要求1.专科及以上学历，计算机科学与技术、软件工程、机械、自动化等相关专业优先。2.具有5年以上Java开发经验，有完整的项目开发经验，能够独立承担模块开发任务3.扎实的Java基础知识，熟悉常用设计模式，对多线程、并发编程、JVM原理及调优有深入理解。4.熟练掌握Spring、Sp……
A11: F03 | B11: 上海市闵行区医疗急救中心 | C11: 上海市闵行区医疗急救中心隶属于上海市闵行区卫生健康委员会，是区内唯一从事院前急救专业的公立医疗卫生事业单位。承担了闵行区内272万人口的院前急救、危急重病症初步诊治与抢救护理。职责还包括急救临床教学、急救医学科研、急救卫生技术人员培训和区域重特大事故现场紧急救援以及大型赛事活动现场医疗保障等工作。 | D11: 院前急救辅助人员（学历：大专专业要求：无） | E11: 1.协助急救医生做好现场医疗急救工作；2.承担病人的抬抱转运工作；3.协助急救驾驶员做好安全行车、车辆卫生及其他辅助性工作。 | F11: 急救医师（学历：本科专业要求：临床医学） | G11: 院前急救、危急重病症初步诊治与抢救护理
A12: B10 | B12: 上海博赫尔科技集团有限公司 | C12: 博赫尔（POHIR）科技集团是一家全球智能化清洁清洗解决方案提供商和服务商，POHIR博赫尔品牌起源于上个世纪90年代的德国，经过近20多年的发展和不断创新，POHIR博赫尔在全球已覆盖了北美，欧洲，东南亚等全球50多个国家或地区，并为全球30万+客户提供清洁清洗设备解决方案。在欧洲，博赫尔（POHIR）分别在德国、法国等地设有2个仓储运营服务中心和1个产品设计研发中心。在北美，博赫尔（…… | D12: 电商客服（学历：大专专业要求：电子商务类） | E12: 岗位职责：1、通过聊天工具完成平台的售前客户咨询接待；2、负责跟进订单、异常件管理；3、服从安排，负责其它售后问题及突发事件。4、打字速度50字/分钟以上；岗位要求：1、经验不限；2、做6休1，国定假期正常放假。公司提供完善的培训、轮岗、转岗及晋升机会！ | F12: 跨境电商运营助理（学历：本科专业要求：跨境电子商务） | G12: 岗位职责:1.参与跨境电商平台（亚马逊、eBay、独立站等）的运营活动，包括但不限于产品发布、活动策划与执行；2.进行市场数据分析，了解行业趋势，调整运营策略以满足市场需求；3.与团队协作，开发新的销售渠道，提升产品曝光率和销量；4.管理和优化产品列表，确保产品信息的准确性和吸引力；5.监控运营指标，及时调整运营计划以达到销售目标。任职要求：1.对跨境电商行业感兴趣，具备基本的市场分析能力；2.具备创新思维，能够不断提出和实施新的运营思路。3、大学本科在读学生，英语好.
... A25: A06 | B25: 上海空间电源研究所 | C25: 中国航天科技集团有限公司上海空间电源研究所，地处上海市闵行区东川园区，主要承担“星、箭、弹、船、（探测）器”及其它特殊设备用电源系统、控制设备、电源产品的研究、设计、制造和试验任务以及新能源产业孵化工作，是中国航天科技集团有限公司唯一的电源专业所。现拥有国内唯一的空间电源全国重点实验室，建有电子电源、化学电源、物理电源等电源领域研发中心，获科技部批复建有空间电源技术国际科技合作基地。2020年…… | D25: 化学电源工程师（学历：本科专业要求：化学,材料科学与工程） | E25: 1、要求，电化学、应用化学、材料科学与工程等专业优先考虑；2、熟悉锂电池电化学原理、锂电池性能测试；3、熟悉锂离子电池国内外技术现状；4、具备基本的英语读、写、听、说能力；5、做事认真、态度诚恳、团队协作能力强；6、热爱航天事业、责任感强、能吃苦耐劳； | F25: 设备工程师（学历：本科专业要求：机械制造及其自动化,电气类） | G25: 1、本科学历，机电一体化、电气工程等相关专业；2、3年以上锂电池生产制造自动化设备维护工作经验；3、熟悉工程机械、电气构造原理，有一定工程机械故障处理经验、机械设计和机械维护经验，熟知设备保养、维修流程及规范和标准；4、能够指导工程机械设备进行维修维护及故障排除；5、熟练使用CAD和其他现代化办公设备和软件（如Word,Excel等）；6、对工作有很强的责任心，做事积极主动、认真踏实，注重工作质量和效率；7、团队合作精神，良好的沟通能力。

Sheet 3
A1: 展位 | B1: 单位名称 | C1: 单位简介 | D1: 职位1标题 | E1: 职位1jd | F1: 职位2标题 | G1: 职位2jd | H1: 职位3标题 | I1: 职位3jd
A2: B01 | B2: 上海光通信有限公司 | C2: 上海光通信有限公司（英文名ShanghaiGTXSemiconductorCo.,Ltd，下称“GTX”），成立于1988年，于2022年初转型进入集成电路制造领域。 | D2: 仓储助理专员（学历：大专专业要求：无） | E2: 工作职责1)根据规程，执行公司各种物资运输安排、管理及监控；2)执行物资仓储管理，保证物资有序账目清晰。任职要求1)大专及以上学历，物流、仓储等相关专业；2)具备良好的沟通能力和团队合作精神，具备独立工作、分析和解决问题的能力，良好的中英文读写说能力。 | F2: 良率提升助理技术员（学历：大专专业要求：无） | G2: 岗位描述：1）负责支持在线缺陷监控，处理产线检测的产品、设备，保证产品正常生产，设备正常运行。2）负责监控并处理检测及复检机台的异常运行状况，保证机台正常运行。3）协同工程师进行缺陷改善，建立合格的检测程式和复检程式，发现并通知产生缺陷的制程，减少缺陷的影响范围。4）负责简单的缺陷切片制样，跟进切片结果。任职要求：1）大专及以上学历，专业不限。2）具备良好的沟通能力，具备团队意识。3）倒班工作模式，接受无尘室工作环境。 | H2: 实验室技术员（学历：大专专业要求：无） | I2: 岗位描述：1）按照规程和作业指导书，执行失效分析实验室/可靠性实验室/化学实验室内相关仪器的操作并按照求完成具体失效分析工作。2）按照规程和作业指导书，执行失效分析实验室/可靠性实验室/化学实验室的日常点检，协助处理机台的日常维护工作。任职要求：1）大专以上学历，理工科相关专业。2）接受倒班工作模式，接受无尘室工作环境。3）具备良好的沟通能力和团队合作精神，具备独立工作、分析和解决问题的能力，良好的中英文读写说能力。
